Workbook

Sheet Summary
A2: Paper: | B2: Human oversight
A4: Human turns | B4: 90
A5: Turns with no substantive AI reply visible | B5: 12
J6: Expertise evidence
A7: Prompt (interaction) types | B7: Primary count | C7: Any occurrence | D7: Share of prompts | F7: Agency mode | G7: Turns | H7: Share | J7: Demonstrated human expertise types | K7: Turns | L7: Share
A8: Open delegation | B8: =COUNTIFS(Coding!$E$2:$E$91,A8) -> 0 | C8: =SUM(Coding!Q2:Q91) -> 3 | D8: =C8/$B$4 -> 0.033333333 | F8: Delegative | G8: =COUNTIFS(Coding!$G$2:$G$91,F8) -> 3 | H8: =G8/$B$4 -> 0.033333333 | J8: Domain correction | K8: =SUM(Coding!Z2:Z91) -> 0 | L8: =K8/$B$4 -> 0
A9: Directed delegation | B9: =COUNTIFS(Coding!$E$2:$E$91,A9) -> 29 | C9: =SUM(Coding!R2:R91) -> 58 | D9: =C9/$B$4 -> 0.64444444 | F9: Directive | G9: =COUNTIFS(Coding!$G$2:$G$91,F9) -> 47 | H9: =G9/$B$4 -> 0.52222222 | J9: Conceptual discrimination | K9: =SUM(Coding!AA2:AA91) -> 8 | L9: =K9/$B$4 -> 0.088888889
A10: Evaluation | B10: =COUNTIFS(Coding!$E$2:$E$91,A10) -> 14 | C10: =SUM(Coding!S2:S91) -> 19 | D10: =C10/$B$4 -> 0.21111111 | F10: Evaluative | G10: =COUNTIFS(Coding!$G$2:$G$91,F10) -> 15 | H10: =G10/$B$4 -> 0.16666667 | J10: Evidence judgment | K10: =SUM(Coding!AB2:AB91) -> 31 | L10: =K10/$B$4 -> 0.34444444
A11: Correction/Challenge | B11: =COUNTIFS(Coding!$E$2:$E$91,A11) -> 13 | C11: =SUM(Coding!T2:T91) -> 19 | D11: =C11/$B$4 -> 0.21111111 | F11: Critical | G11: =COUNTIFS(Coding!$G$2:$G$91,F11) -> 19 | H11: =G11/$B$4 -> 0.21111111 | J11: Methodological judgment | K11: =SUM(Coding!AC2:AC91) -> 12 | L11: =K11/$B$4 -> 0.13333333
A12: Redirection | B12: =COUNTIFS(Coding!$E$2:$E$91,A12) -> 6 | C12: =SUM(Coding!U2:U91) -> 16 | D12: =C12/$B$4 -> 0.17777778 | F12: Deliberative | G12: =COUNTIFS(Coding!$G$2:$G$91,F12) -> 6 | H12: =G12/$B$4 -> 0.066666667 | J12: Argumentative judgment | K12: =SUM(Coding!AD2:AD91) -> 34 | L12: =K12/$B$4 -> 0.37777778
A13: Knowledge injection | B13: =COUNTIFS(Coding!$E$2:$E$91,A13) -> 7 | C13: =SUM(Coding!V2:V91) -> 50 | D13: =C13/$B$4 -> 0.55555556 | J13: Genre/writing expertise | K13: =SUM(Coding!AE2:AE91) -> 44 | L13: =K13/$B$4 -> 0.48888889
A14: Selection/Rejection | B14: =COUNTIFS(Coding!$E$2:$E$91,A14) -> 12 | C14: =SUM(Coding!W2:W91) -> 29 | D14: =C14/$B$4 -> 0.32222222 | J14: None | K14: =SUM(Coding!AF2:AF91) -> 18 | L14: =K14/$B$4 -> 0.2
A15: Deliberation | B15: =COUNTIFS(Coding!$E$2:$E$91,A15) -> 6 | C15: =SUM(Coding!X2:X91) -> 6 | D15: =C15/$B$4 -> 0.066666667
A18: Phase | B18: First turn | C18: Last turn | D18: # of prompts (turns) | E18: Delegative | F18: Directive | G18: Evaluative | H18: Critical | I18: Deliberative
A19: Initial framing | B19: 1 | C19: 7 | D19: =C19-B19+1 -> 7 | E19: =COUNTIFS(Coding!$B$2:$B$91,">="&B19,Coding!$B$2:$B$91,"<="&C19,Coding!$G$2:$G$91,"Delegative") -> 1 | F19: =COUNTIFS(Coding!$B$2:$B$91,">="&B19,Coding!$B$2:$B$91,"<="&C19,Coding!$G$2:$G$91,"Directive") -> 4 | G19: =COUNTIFS(Coding!$B$2:$B$91,">="&B19,Coding!$B$2:$B$91,"<="&C19,Coding!$G$2:$G$91,"Evaluative") -> 1 | H19: =COUNTIFS(Coding!$B$2:$B$91,">="&B19,Coding!$B$2:$B$91,"<="&C19,Coding!$G$2:$G$91,"Critical") -> 1 | I19: =COUNTIFS(Coding!$B$2:$B$91,">="&B19,Coding!$B$2:$B$91,"<="&C19,Coding!$G$2:$G$91,"Deliberative") -> 0
A20: Source selection and citation repair | B20: 8 | C20: 19 | D20: =C20-B20+1 -> 12 | E20: =COUNTIFS(Coding!$B$2:$B$91,">="&B20,Coding!$B$2:$B$91,"<="&C20,Coding!$G$2:$G$91,"Delegative") -> 1 | F20: =COUNTIFS(Coding!$B$2:$B$91,">="&B20,Coding!$B$2:$B$91,"<="&C20,Coding!$G$2:$G$91,"Directive") -> 7 | G20: =COUNTIFS(Coding!$B$2:$B$91,">="&B20,Coding!$B$2:$B$91,"<="&C20,Coding!$G$2:$G$91,"Evaluative") -> 0 | H20: =COUNTIFS(Coding!$B$2:$B$91,">="&B20,Coding!$B$2:$B$91,"<="&C20,Coding!$G$2:$G$91,"Critical") -> 4 | I20: =COUNTIFS(Coding!$B$2:$B$91,">="&B20,Coding!$B$2:$B$91,"<="&C20,Coding!$G$2:$G$91,"Deliberative") -> 0
A21: Abstract and paper positioning | B21: 20 | C21: 36 | D21: =C21-B21+1 -> 17 | E21: =COUNTIFS(Coding!$B$2:$B$91,">="&B21,Coding!$B$2:$B$91,"<="&C21,Coding!$G$2:$G$91,"Delegative") -> 0 | F21: =COUNTIFS(Coding!$B$2:$B$91,">="&B21,Coding!$B$2:$B$91,"<="&C21,Coding!$G$2:$G$91,"Directive") -> 7 | G21: =COUNTIFS(Coding!$B$2:$B$91,">="&B21,Coding!$B$2:$B$91,"<="&C21,Coding!$G$2:$G$91,"Evaluative") -> 5 | H21: =COUNTIFS(Coding!$B$2:$B$91,">="&B21,Coding!$B$2:$B$91,"<="&C21,Coding!$G$2:$G$91,"Critical") -> 3 | I21: =COUNTIFS(Coding!$B$2:$B$91,">="&B21,Coding!$B$2:$B$91,"<="&C21,Coding!$G$2:$G$91,"Deliberative") -> 2
A22: Conceptual structure | B22: 37 | C22: 44 | D22: =C22-B22+1 -> 8 | E22: =COUNTIFS(Coding!$B$2:$B$91,">="&B22,Coding!$B$2:$B$91,"<="&C22,Coding!$G$2:$G$91,"Delegative") -> 0 | F22: =COUNTIFS(Coding!$B$2:$B$91,">="&B22,Coding!$B$2:$B$91,"<="&C22,Coding!$G$2:$G$91,"Directive") -> 6 | G22: =COUNTIFS(Coding!$B$2:$B$91,">="&B22,Coding!$B$2:$B$91,"<="&C22,Coding!$G$2:$G$91,"Evaluative") -> 0 | H22: =COUNTIFS(Coding!$B$2:$B$91,">="&B22,Coding!$B$2:$B$91,"<="&C22,Coding!$G$2:$G$91,"Critical") -> 0 | I22: =COUNTIFS(Coding!$B$2:$B$91,">="&B22,Coding!$B$2:$B$91,"<="&C22,Coding!$G$2:$G$91,"Deliberative") -> 2
A23: Supplement and section drafting | B23: 45 | C23: 59 | D23: =C23-B23+1 -> 15 | E23: =COUNTIFS(Coding!$B$2:$B$91,">="&B23,Coding!$B$2:$B$91,"<="&C23,Coding!$G$2:$G$91,"Delegative") -> 0 | F23: =COUNTIFS(Coding!$B$2:$B$91,">="&B23,Coding!$B$2:$B$91,"<="&C23,Coding!$G$2:$G$91,"Directive") -> 10 | G23: =COUNTIFS(Coding!$B$2:$B$91,">="&B23,Coding!$B$2:$B$91,"<="&C23,Coding!$G$2:$G$91,"Evaluative") -> 1 | H23: =COUNTIFS(Coding!$B$2:$B$91,">="&B23,Coding!$B$2:$B$91,"<="&C23,Coding!$G$2:$G$91,"Critical") -> 4 | I23: =COUNTIFS(Coding!$B$2:$B$91,">="&B23,Coding!$B$2:$B$91,"<="&C23,Coding!$G$2:$G$91,"Deliberative") -> 0
A24: Evidence audit and pool revision | B24: 60 | C24: 69 | D24: =C24-B24+1 -> 10 | E24: =COUNTIFS(Coding!$B$2:$B$91,">="&B24,Coding!$B$2:$B$91,"<="&C24,Coding!$G$2:$G$91,"Delegative") -> 0 | F24: =COUNTIFS(Coding!$B$2:$B$91,">="&B24,Coding!$B$2:$B$91,"<="&C24,Coding!$G$2:$G$91,"Directive") -> 3 | G24: =COUNTIFS(Coding!$B$2:$B$91,">="&B24,Coding!$B$2:$B$91,"<="&C24,Coding!$G$2:$G$91,"Evaluative") -> 4 | H24: =COUNTIFS(Coding!$B$2:$B$91,">="&B24,Coding!$B$2:$B$91,"<="&C24,Coding!$G$2:$G$91,"Critical") -> 3 | I24: =COUNTIFS(Coding!$B$2:$B$91,">="&B24,Coding!$B$2:$B$91,"<="&C24,Coding!$G$2:$G$91,"Deliberative") -> 0
A25: Completion and review requests | B25: 70 | C25: 78 | D25: =C25-B25+1 -> 9 | E25: =COUNTIFS(Coding!$B$2:$B$91,">="&B25,Coding!$B$2:$B$91,"<="&C25,Coding!$G$2:$G$91,"Delegative") -> 1 | F25: =COUNTIFS(Coding!$B$2:$B$91,">="&B25,Coding!$B$2:$B$91,"<="&C25,Coding!$G$2:$G$91,"Directive") -> 5 | G25: =COUNTIFS(Coding!$B$2:$B$91,">="&B25,Coding!$B$2:$B$91,"<="&C25,Coding!$G$2:$G$91,"Evaluative") -> 2 | H25: =COUNTIFS(Coding!$B$2:$B$91,">="&B25,Coding!$B$2:$B$91,"<="&C25,Coding!$G$2:$G$91,"Critical") -> 1 | I25: =COUNTIFS(Coding!$B$2:$B$91,">="&B25,Coding!$B$2:$B$91,"<="&C25,Coding!$G$2:$G$91,"Deliberative") -> 0
A26: Feedback and reframing | B26: 79 | C26: 90 | D26: =C26-B26+1 -> 12 | E26: =COUNTIFS(Coding!$B$2:$B$91,">="&B26,Coding!$B$2:$B$91,"<="&C26,Coding!$G$2:$G$91,"Delegative") -> 0 | F26: =COUNTIFS(Coding!$B$2:$B$91,">="&B26,Coding!$B$2:$B$91,"<="&C26,Coding!$G$2:$G$91,"Directive") -> 5 | G26: =COUNTIFS(Coding!$B$2:$B$91,">="&B26,Coding!$B$2:$B$91,"<="&C26,Coding!$G$2:$G$91,"Evaluative") -> 2 | H26: =COUNTIFS(Coding!$B$2:$B$91,">="&B26,Coding!$B$2:$B$91,"<="&C26,Coding!$G$2:$G$91,"Critical") -> 3 | I26: =COUNTIFS(Coding!$B$2:$B$91,">="&B26,Coding!$B$2:$B$91,"<="&C26,Coding!$G$2:$G$91,"Deliberative") -> 2
A29: Key patterns and limits
A30: Directive agency is most frequent: 47/90 turns (52.2%). Critical: 19 (21.1%); Evaluative: 15 (16.7%); Deliberative: 6 (6.7%); Delegative: 3 (3.3%).
A31: Drafting and scrutiny alternate. Human agency is visible through constraints, selection, verification and reframing, rather than a single linear shift toward deliberation.
A32: Citation repair: P2-013 rejects fake references; P2-014 challenges an entry still mislabeled after claimed verification; P2-018 supplies correct title and authors.
A33: Quotation audit: P2-060 to P2-065 check sources against burden categories. At P2-064, the assistant admits its earlier purported verbatim quotations are not in the source.
A34: Evidence control: P2-066 explicitly reduces ten sources to eight. P2-067 reports human-extracted quotes organized in table comments; actual comment access is unverified.
A35: Conceptual framing: P2-037 distinguishes IDE and chat-based tools. P2-042 merges overlapping cost categories. P2-050 removes a redundant category from the evidence table.
A36: Claim discipline: P2-006 and P2-025 moderate certainty. P2-073 labels the figure hypothetical. P2-083 to P2-090 negotiate column genre, evidence synthesis and voice.
A37: Turn-taking control: P2-083 asks AI to wait while the human develops responses; AI nevertheless drafts a reply. P2-084 reasserts human control over substantive replies.
A38: Twelve missing assistant replies limit outcome claims. The two identical review requests are retained. A visible yes approves only a contextual next step; P2-078 has no visible antecedent.
A39: Paper 1 has missing prompts, according to the user. The 22-versus-90 turn difference describes surviving records and cannot establish a difference in actual agency or expertise.
A40: Single-coder interpretive analysis. Source accuracy, final uptake and unseen attachments are not inferred. See Codebook for operational rules and ambiguous cases.

Sheet Coding
A1: Turn ID | B1: Sequence | C1: Phase | D1: Prompt excerpt | E1: Primary interaction type | F1: Additional interaction types | G1: Agency mode | H1: Expertise evidence | I1: Coding rationale | J1: Observed outcome / notes | K1: Prompt provenance | L1: Response provenance | M1: Attachment metadata | N1: Response availability | O1: Coding caution | P1: sum | Q1: Open Delegation | R1: Directed delegation | S1: Evaluation | T1: Correction/Challenge | U1: Redirection | V1: Knowledge injection | W1: Acceptance/ Rejection | X1: Deliberation | Y1: Expertise | Z1: Subject-matter correction | AA1: Conceptual differentiation | AB1: Evidence judgment | AC1: Methodological judgment | AD1: Argumentative judgment | AE1: Genre/ writing expertise | AF1: none
A2: P2-001 | B2: 1 | C2: Initial framing | D2: Hidden cost of AI-SE: Short opinion paper | E2: Delegation | G2: Delegative | H2: none | I2: Topic-only request for a short opinion paper, without substantive constraints. | J2: AI starts a short opinion draft and abstract. | K2: p4 L2-p4 L2 | L2: p4 L3-p4 L12 | N2: Visible substantive response | P2: =SUM(Paper2Coding[[#This Row],[Open Delegation]:[Expertise]]) -> 2 | Q2: =IF(OR(E2="Delegation",ISNUMBER(SEARCH("; Delegation; ","; "&F2&"; "))),1,0) -> 1 | R2: =IF(OR(E2="Directed delegation",ISNUMBER(SEARCH("; Directed delegation; ","; "&F2&"; "))),1,0) -> 0 | S2: =IF(OR(E2="Evaluation",ISNUMBER(SEARCH("; Evaluation; ","; "&F2&"; "))),1,0) -> 0 | T2: =IF(OR(E2="Correction/Challenge",ISNUMBER(SEARCH("; Correction/Challenge; ","; "&F2&"; "))),1,0) -> 0 | U2: =IF(OR(E2="Redirection",ISNUMBER(SEARCH("; Redirection; ","; "&F2&"; "))),1,0) -> 0 | V2: =IF(OR(E2="Knowledge injection",ISNUMBER(SEARCH("; Knowledge injection; ","; "&F2&"; "))),1,0) -> 0 | W2: =IF(OR(E2="Selection/Rejection",ISNUMBER(SEARCH("; Selection/Rejection; ","; "&F2&"; "))),1,0) -> 0 | X2: =IF(OR(E2="Deliberation",ISNUMBER(SEARCH("; Deliberation; ","; "&F2&"; "))),1,0) -> 0 | Y2: =SUM(Paper2Coding[[#This Row],[Subject-matter correction]:[none]]) -> 1 | Z2: =IF(ISNUMBER(SEARCH("; domain correction; ","; "&H2&"; ")),1,0) -> 0 | AA2: =IF(ISNUMBER(SEARCH("; conceptual discrimination; ","; "&H2&"; ")),1,0) -> 0 | AB2: =IF(ISNUMBER(SEARCH("; evidence judgment; ","; "&H2&"; ")),1,0) -> 0 | AC2: =IF(ISNUMBER(SEARCH("; methodological judgment; ","; "&H2&"; ")),1,0) -> 0 | AD2: =IF(ISNUMBER(SEARCH("; argumentative judgment; ","; "&H2&"; ")),1,0) -> 0 | AE2: =IF(ISNUMBER(SEARCH("; genre/writing expertise; ","; "&H2&"; ")),1,0) -> 0 | AF2: =IF(ISNUMBER(SEARCH("; none; ","; "&H2&"; ")),1,0) -> 1
A3: P2-002 | B3: 2 | C3: Initial framing | D3: I want to write a short "Opinion" paper for IEEE SW ... cannot present research findings ... first, suggest a clear title. | E3: Directed delegation | F3: Redirection; Knowledge injection | G3: Directive | H3: genre/writing expertise; argumentative judgment; methodological judgment | I3: Specifies venue, length, scope and objectives; explicitly rules out presenting original research findings. | J3: AI offers title options. The quantification objectives and opinion-only constraint create a tension, not resolved here. | K3: p4 L13-p4 L22 | L3: p4 L24-p4 L37 | N3: Visible substantive response | P3: =SUM(Paper2Coding[[#This Row],[Open Delegation]:[Expertise]]) -> 6 | Q3: =IF(OR(E3="Delegation",ISNUMBER(SEARCH("; Delegation; ","; "&F3&"; "))),1,0) -> 0 | R3: =IF(OR(E3="Directed delegation",ISNUMBER(SEARCH("; Directed delegation; ","; "&F3&"; "))),1,0) -> 1 | S3: =IF(OR(E3="Evaluation",ISNUMBER(SEARCH("; Evaluation; ","; "&F3&"; "))),1,0) -> 0 | T3: =IF(OR(E3="Correction/Challenge",ISNUMBER(SEARCH("; Correction/Challenge; ","; "&F3&"; "))),1,0) -> 0 | U3: =IF(OR(E3="Redirection",ISNUMBER(SEARCH("; Redirection; ","; "&F3&"; "))),1,0) -> 1 | V3: =IF(OR(E3="Knowledge injection",ISNUMBER(SEARCH("; Knowledge injection; ","; "&F3&"; "))),1,0) -> 1 | W3: =IF(OR(E3="Selection/Rejection",ISNUMBER(SEARCH("; Selection/Rejection; ","; "&F3&"; "))),1,0) -> 0 | X3: =IF(OR(E3="Deliberation",ISNUMBER(SEARCH("; Deliberation; ","; "&F3&"; "))),1,0) -> 0 | Y3: =SUM(Paper2Coding[[#This Row],[Subject-matter correction]:[none]]) -> 3 | Z3: =IF(ISNUMBER(SEARCH("; domain correction; ","; "&H3&"; ")),1,0) -> 0 | AA3: =IF(ISNUMBER(SEARCH("; conceptual discrimination; ","; "&H3&"; ")),1,0) -> 0 | AB3: =IF(ISNUMBER(SEARCH("; evidence judgment; ","; "&H3&"; ")),1,0) -> 0 | AC3: =IF(ISNUMBER(SEARCH("; methodological judgment; ","; "&H3&"; ")),1,0) -> 1 | AD3: =IF(ISNUMBER(SEARCH("; argumentative judgment; ","; "&H3&"; ")),1,0) -> 1 | AE3: =IF(ISNUMBER(SEARCH("; genre/writing expertise; ","; "&H3&"; ")),1,0) -> 1 | AF3: =IF(ISNUMBER(SEARCH("; none; ","; "&H3&"; ")),1,0) -> 0
A4: P2-003 | B4: 3 | C4: Initial framing | D4: make it shorter | E4: Directed delegation | G4: Directive | H4: genre/writing expertise | I4: Requests a shorter title, retaining control over brevity. | J4: AI offers shorter title options. | K4: p4 L38-p4 L38 | L4: p4 L39-p5 L6 | N4: Visible substantive response | P4: =SUM(Paper2Coding[[#This Row],[Open Delegation]:[Expertise]]) -> 2 | Q4: =IF(OR(E4="Delegation",ISNUMBER(SEARCH("; Delegation; ","; "&F4&"; "))),1,0) -> 0 | R4: =IF(OR(E4="Directed delegation",ISNUMBER(SEARCH("; Directed delegation; ","; "&F4&"; "))),1,0) -> 1 | S4: =IF(OR(E4="Evaluation",ISNUMBER(SEARCH("; Evaluation; ","; "&F4&"; "))),1,0) -> 0 | T4: =IF(OR(E4="Correction/Challenge",ISNUMBER(SEARCH("; Correction/Challenge; ","; "&F4&"; "))),1,0) -> 0 | U4: =IF(OR(E4="Redirection",ISNUMBER(SEARCH("; Redirection; ","; "&F4&"; "))),1,0) -> 0 | V4: =IF(OR(E4="Knowledge injection",ISNUMBER(SEARCH("; Knowledge injection; ","; "&F4&"; "))),1,0) -> 0 | W4: =IF(OR(E4="Selection/Rejection",ISNUMBER(SEARCH("; Selection/Rejection; ","; "&F4&"; "))),1,0) -> 0 | X4: =IF(OR(E4="Deliberation",ISNUMBER(SEARCH("; Deliberation; ","; "&F4&"; "))),1,0) -> 0 | Y4: =SUM(Paper2Coding[[#This Row],[Subject-matter correction]:[none]]) -> 1 | Z4: =IF(ISNUMBER(SEARCH("; domain correction; ","; "&H4&"; ")),1,0) -> 0 | AA4: =IF(ISNUMBER(SEARCH("; conceptual discrimination; ","; "&H4&"; ")),1,0) -> 0 | AB4: =IF(ISNUMBER(SEARCH("; evidence judgment; ","; "&H4&"; ")),1,0) -> 0 | AC4: =IF(ISNUMBER(SEARCH("; methodological judgment; ","; "&H4&"; ")),1,0) -> 0 | AD4: =IF(ISNUMBER(SEARCH("; argumentative judgment; ","; "&H4&"; ")),1,0) -> 0 | AE4: =IF(ISNUMBER(SEARCH("; genre/writing expertise; ","; "&H4&"; ")),1,0) -> 1 | AF4: =IF(ISNUMBER(SEARCH("; none; ","; "&H4&"; ")),1,0) -> 0
A5: P2-004 | B5: 4 | C5: Initial framing | D5: is rthis a good one: Hidden Cost of AI in Software Engineering: Efficiency versus Burden | E5: Evaluation | F5: Knowledge injection | G5: Evaluative | H5: genre/writing expertise; argumentative judgment | I5: Supplies a candidate title for assessment of its framing. | J5: AI endorses it and offers a slight refinement; no final choice yet. | K5: p5 L7-p5 L7 | L5: p5 L8-p5 L14 | N5: Visible substantive response | P5: =SUM(Paper2Coding[[#This Row],[Open Delegation]:[Expertise]]) -> 4 | Q5: =IF(OR(E5="Delegation",ISNUMBER(SEARCH("; Delegation; ","; "&F5&"; "))),1,0) -> 0 | R5: =IF(OR(E5="Directed delegation",ISNUMBER(SEARCH("; Directed delegation; ","; "&F5&"; "))),1,0) -> 0 | S5: =IF(OR(E5="Evaluation",ISNUMBER(SEARCH("; Evaluation; ","; "&F5&"; "))),1,0) -> 1 | T5: =IF(OR(E5="Correction/Challenge",ISNUMBER(SEARCH("; Correction/Challenge; ","; "&F5&"; "))),1,0) -> 0 | U5: =IF(OR(E5="Redirection",ISNUMBER(SEARCH("; Redirection; ","; "&F5&"; "))),1,0) -> 0 | V5: =IF(OR(E5="Knowledge injection",ISNUMBER(SEARCH("; Knowledge injection; ","; "&F5&"; "))),1,0) -> 1 | W5: =IF(OR(E5="Selection/Rejection",ISNUMBER(SEARCH("; Selection/Rejection; ","; "&F5&"; "))),1,0) -> 0 | X5: =IF(OR(E5="Deliberation",ISNUMBER(SEARCH("; Deliberation; ","; "&F5&"; "))),1,0) -> 0 | Y5: =SUM(Paper2Coding[[#This Row],[Subject-matter correction]:[none]]) -> 2 | Z5: =IF(ISNUMBER(SEARCH("; domain correction; ","; "&H5&"; ")),1,0) -> 0 | AA5: =IF(ISNUMBER(SEARCH("; conceptual discrimination; ","; "&H5&"; ")),1,0) -> 0 | AB5: =IF(ISNUMBER(SEARCH("; evidence judgment; ","; "&H5&"; ")),1,0) -> 0 | AC5: =IF(ISNUMBER(SEARCH("; methodological judgment; ","; "&H5&"; ")),1,0) -> 0 | AD5: =IF(ISNUMBER(SEARCH("; argumentative judgment; ","; "&H5&"; ")),1,0) -> 1 | AE5: =IF(ISNUMBER(SEARCH("; genre/writing expertise; ","; "&H5&"; ")),1,0) -> 1 | AF5: =IF(ISNUMBER(SEARCH("; none; ","; "&H5&"; ")),1,0) -> 0
A6: P2-005 | B6: 5 | C6: Initial framing | D6: give a short Abstract: and 5 Keywords | E6: Directed delegation | G6: Directive | H6: none | I6: Specifies short abstract and five keywords, without substantive argument constraints. | J6: AI provides an abstract and five keywords. | K6: p5 L15-p5 L16 | L6: p5 L17-p5 L22 | N6: Visible substantive response | P6: =SUM(Paper2Coding[[#This Row],[Open Delegation]:[Expertise]]) -> 2 | Q6: =IF(OR(E6="Delegation",ISNUMBER(SEARCH("; Delegation; ","; "&F6&"; "))),1,0) -> 0 | R6: =IF(OR(E6="Directed delegation",ISNUMBER(SEARCH("; Directed delegation; ","; "&F6&"; "))),1,0) -> 1 | S6: =IF(OR(E6="Evaluation",ISNUMBER(SEARCH("; Evaluation; ","; "&F6&"; "))),1,0) -> 0 | T6: =IF(OR(E6="Correction/Challenge",ISNUMBER(SEARCH("; Correction/Challenge; ","; "&F6&"; "))),1,0) -> 0 | U6: =IF(OR(E6="Redirection",ISNUMBER(SEARCH("; Redirection; ","; "&F6&"; "))),1,0) -> 0 | V6: =IF(OR(E6="Knowledge injection",ISNUMBER(SEARCH("; Knowledge injection; ","; "&F6&"; "))),1,0) -> 0 | W6: =IF(OR(E6="Selection/Rejection",ISNUMBER(SEARCH("; Selection/Rejection; ","; "&F6&"; "))),1,0) -> 0 | X6: =IF(OR(E6="Deliberation",ISNUMBER(SEARCH("; Deliberation; ","; "&F6&"; "))),1,0) -> 0 | Y6: =SUM(Paper2Coding[[#This Row],[Subject-matter correction]:[none]]) -> 1 | Z6: =IF(ISNUMBER(SEARCH("; domain correction; ","; "&H6&"; ")),1,0) -> 0 | AA6: =IF(ISNUMBER(SEARCH("; conceptual discrimination; ","; "&H6&"; ")),1,0) -> 0 | AB6: =IF(ISNUMBER(SEARCH("; evidence judgment; ","; "&H6&"; ")),1,0) -> 0 | AC6: =IF(ISNUMBER(SEARCH("; methodological judgment; ","; "&H6&"; ")),1,0) -> 0 | AD6: =IF(ISNUMBER(SEARCH("; argumentative judgment; ","; "&H6&"; ")),1,0) -> 0 | AE6: =IF(ISNUMBER(SEARCH("; genre/writing expertise; ","; "&H6&"; ")),1,0) -> 0 | AF6: =IF(ISNUMBER(SEARCH("; none; ","; "&H6&"; ")),1,0) -> 1
A7: P2-006 | B7: 6 | C7: Initial framing | D7: how about this: AI tools promise increased efficiency in software engineering (SE), yet their use can potentially introduce hidden costs. Software engineers must review, validate, and correct AI-generated SE artifacts—efforts that can potentially outweigh productivity gains. T... | E7: Correction/Challenge | F7: Evaluation; Knowledge injection; Redirection | G7: Critical | H7: evidence judgment; argumentative judgment; genre/writing expertise | I7: Adds potentially to moderate the strength of claims and requests assessment of the rewritten abstract. | J7: AI retains cautious claims while reducing repetition of potentially. | K7: p5 L23-p5 L27 | L7: p5 L29-p5 L36 | N7: Visible substantive response | P7: =SUM(Paper2Coding[[#This Row],[Open Delegation]:[Expertise]]) -> 7 | Q7: =IF(OR(E7="Delegation",ISNUMBER(SEARCH("; Delegation; ","; "&F7&"; "))),1,0) -> 0 | R7: =IF(OR(E7="Directed delegation",ISNUMBER(SEARCH("; Directed delegation; ","; "&F7&"; "))),1,0) -> 0 | S7: =IF(OR(E7="Evaluation",ISNUMBER(SEARCH("; Evaluation; ","; "&F7&"; "))),1,0) -> 1 | T7: =IF(OR(E7="Correction/Challenge",ISNUMBER(SEARCH("; Correction/Challenge; ","; "&F7&"; "))),1,0) -> 1 | U7: =IF(OR(E7="Redirection",ISNUMBER(SEARCH("; Redirection; ","; "&F7&"; "))),1,0) -> 1 | V7: =IF(OR(E7="Knowledge injection",ISNUMBER(SEARCH("; Knowledge injection; ","; "&F7&"; "))),1,0) -> 1 | W7: =IF(OR(E7="Selection/Rejection",ISNUMBER(SEARCH("; Selection/Rejection; ","; "&F7&"; "))),1,0) -> 0 | X7: =IF(OR(E7="Deliberation",ISNUMBER(SEARCH("; Deliberation; ","; "&F7&"; "))),1,0) -> 0 | Y7: =SUM(Paper2Coding[[#This Row],[Subject-matter correction]:[none]]) -> 3 | Z7: =IF(ISNUMBER(SEARCH("; domain correction; ","; "&H7&"; ")),1,0) -> 0 | AA7: =IF(ISNUMBER(SEARCH("; conceptual discrimination; ","; "&H7&"; ")),1,0) -> 0 | AB7: =IF(ISNUMBER(SEARCH("; evidence judgment; ","; "&H7&"; ")),1,0) -> 1 | AC7: =IF(ISNUMBER(SEARCH("; methodological judgment; ","; "&H7&"; ")),1,0) -> 0 | AD7: =IF(ISNUMBER(SEARCH("; argumentative judgment; ","; "&H7&"; ")),1,0) -> 1 | AE7: =IF(ISNUMBER(SEARCH("; genre/writing expertise; ","; "&H7&"; ")),1,0) -> 1 | AF7: =IF(ISNUMBER(SEARCH("; none; ","; "&H7&"; ")),1,0) -> 0
A8: P2-007 | B8: 7 | C8: Initial framing | D8: suggest the paper structure, recall: the MAX limit is 2600 words. consider adding two figures, each worth 250 words, thus leaving only 2100 words for text. suggest two figure topics. | E8: Directed delegation | G8: Directive | H8: genre/writing expertise | I8: Allocates a 2600-word budget, including two figures at 250 words each, and requests structure and figure topics. | J8: AI proposes sections, figure topics and word allocations using the stated budget. | K8: p5 L37-p5 L39 | L8: p5 L40-p6 L40 | N8: Visible substantive response | P8: =SUM(Paper2Coding[[#This Row],[Open Delegation]:[Expertise]]) -> 2 | Q8: =IF(OR(E8="Delegation",ISNUMBER(SEARCH("; Delegation; ","; "&F8&"; "))),1,0) -> 0 | R8: =IF(OR(E8="Directed delegation",ISNUMBER(SEARCH("; Directed delegation; ","; "&F8&"; "))),1,0) -> 1 | S8: =IF(OR(E8="Evaluation",ISNUMBER(SEARCH("; Evaluation; ","; "&F8&"; "))),1,0) -> 0 | T8: =IF(OR(E8="Correction/Challenge",ISNUMBER(SEARCH("; Correction/Challenge; ","; "&F8&"; "))),1,0) -> 0 | U8: =IF(OR(E8="Redirection",ISNUMBER(SEARCH("; Redirection; ","; "&F8&"; "))),1,0) -> 0 | V8: =IF(OR(E8="Knowledge injection",ISNUMBER(SEARCH("; Knowledge injection; ","; "&F8&"; "))),1,0) -> 0 | W8: =IF(OR(E8="Selection/Rejection",ISNUMBER(SEARCH("; Selection/Rejection; ","; "&F8&"; "))),1,0) -> 0 | X8: =IF(OR(E8="Deliberation",ISNUMBER(SEARCH("; Deliberation; ","; "&F8&"; "))),1,0) -> 0 | Y8: =SUM(Paper2Coding[[#This Row],[Subject-matter correction]:[none]]) -> 1 | Z8: =IF(ISNUMBER(SEARCH("; domain correction; ","; "&H8&"; ")),1,0) -> 0 | AA8: =IF(ISNUMBER(SEARCH("; conceptual discrimination; ","; "&H8&"; ")),1,0) -> 0 | AB8: =IF(ISNUMBER(SEARCH("; evidence judgment; ","; "&H8&"; ")),1,0) -> 0 | AC8: =IF(ISNUMBER(SEARCH("; methodological judgment; ","; "&H8&"; ")),1,0) -> 0 | AD8: =IF(ISNUMBER(SEARCH("; argumentative judgment; ","; "&H8&"; ")),1,0) -> 0 | AE8: =IF(ISNUMBER(SEARCH("; genre/writing expertise; ","; "&H8&"; ")),1,0) -> 1 | AF8: =IF(ISNUMBER(SEARCH("; none; ","; "&H8&"; ")),1,0) -> 0
A9: P2-008 | B9: 8 | C9: Source selection and citation repair | D9: search and show for me both academic and grey literature on the topic | E9: Directed delegation | G9: Directive | H9: evidence judgment | I9: Requests both academic and grey literature, specifying evidence types. | J9: AI reports an attempted search and partial progress, without a finished source list. | K9: p6 L41-p6 L41 | L9: p6 L42-p7 L28 | N9: Visible substantive response | P9: =SUM(Paper2Coding[[#This Row],[Open Delegation]:[Expertise]]) -> 2 | Q9: =IF(OR(E9="Delegation",ISNUMBER(SEARCH("; Delegation; ","; "&F9&"; "))),1,0) -> 0 | R9: =IF(OR(E9="Directed delegation",ISNUMBER(SEARCH("; Directed delegation; ","; "&F9&"; "))),1,0) -> 1 | S9: =IF(OR(E9="Evaluation",ISNUMBER(SEARCH("; Evaluation; ","; "&F9&"; "))),1,0) -> 0 | T9: =IF(OR(E9="Correction/Challenge",ISNUMBER(SEARCH("; Correction/Challenge; ","; "&F9&"; "))),1,0) -> 0 | U9: =IF(OR(E9="Redirection",ISNUMBER(SEARCH("; Redirection; ","; "&F9&"; "))),1,0) -> 0 | V9: =IF(OR(E9="Knowledge injection",ISNUMBER(SEARCH("; Knowledge injection; ","; "&F9&"; "))),1,0) -> 0 | W9: =IF(OR(E9="Selection/Rejection",ISNUMBER(SEARCH("; Selection/Rejection; ","; "&F9&"; "))),1,0) -> 0 | X9: =IF(OR(E9="Deliberation",ISNUMBER(SEARCH("; Deliberation; ","; "&F9&"; "))),1,0) -> 0 | Y9: =SUM(Paper2Coding[[#This Row],[Subject-matter correction]:[none]]) -> 1 | Z9: =IF(ISNUMBER(SEARCH("; domain correction; ","; "&H9&"; ")),1,0) -> 0 | AA9: =IF(ISNUMBER(SEARCH("; conceptual discrimination; ","; "&H9&"; ")),1,0) -> 0 | AB9: =IF(ISNUMBER(SEARCH("; evidence judgment; ","; "&H9&"; ")),1,0) -> 1 | AC9: =IF(ISNUMBER(SEARCH("; methodological judgment; ","; "&H9&"; ")),1,0) -> 0 | AD9: =IF(ISNUMBER(SEARCH("; argumentative judgment; ","; "&H9&"; ")),1,0) -> 0 | AE9: =IF(ISNUMBER(SEARCH("; genre/writing expertise; ","; "&H9&"; ")),1,0) -> 0 | AF9: =IF(ISNUMBER(SEARCH("; none; ","; "&H9&"; ")),1,0) -> 0
A10: P2-009 | B10: 9 | C10: Source selection and citation repair | D10: just list them in the chat | E10: Directed delegation | F10: Redirection | G10: Directive | H10: none | I10: Changes presentation to a direct list in chat. | J10: AI lists academic and grey sources. Later corrections establish that at least one citation was misidentified. | K10: p7 L29-p7 L29 | L10: p7 L30-p8 L14 | N10: Visible substantive response | P10: =SUM(Paper2Coding[[#This Row],[Open Delegation]:[Expertise]]) -> 3 | Q10: =IF(OR(E10="Delegation",ISNUMBER(SEARCH("; Delegation; ","; "&F10&"; "))),1,0) -> 0 | R10: =IF(OR(E10="Directed delegation",ISNUMBER(SEARCH("; Directed delegation; ","; "&F10&"; "))),1,0) -> 1 | S10: =IF(OR(E10="Evaluation",ISNUMBER(SEARCH("; Evaluation; ","; "&F10&"; "))),1,0) -> 0 | T10: =IF(OR(E10="Correction/Challenge",ISNUMBER(SEARCH("; Correction/Challenge; ","; "&F10&"; "))),1,0) -> 0 | U10: =IF(OR(E10="Redirection",ISNUMBER(SEARCH("; Redirection; ","; "&F10&"; "))),1,0) -> 1 | V10: =IF(OR(E10="Knowledge injection",ISNUMBER(SEARCH("; Knowledge injection; ","; "&F10&"; "))),1,0) -> 0 | W10: =IF(OR(E10="Selection/Rejection",ISNUMBER(SEARCH("; Selection/Rejection; ","; "&F10&"; "))),1,0) -> 0 | X10: =IF(OR(E10="Deliberation",ISNUMBER(SEARCH("; Deliberation; ","; "&F10&"; "))),1,0) -> 0 | Y10: =SUM(Paper2Coding[[#This Row],[Subject-matter correction]:[none]]) -> 1 | Z10: =IF(ISNUMBER(SEARCH("; domain correction; ","; "&H10&"; ")),1,0) -> 0 | AA10: =IF(ISNUMBER(SEARCH("; conceptual discrimination; ","; "&H10&"; ")),1,0) -> 0 | AB10: =IF(ISNUMBER(SEARCH("; evidence judgment; ","; "&H10&"; ")),1,0) -> 0 | AC10: =IF(ISNUMBER(SEARCH("; methodological judgment; ","; "&H10&"; ")),1,0) -> 0 | AD10: =IF(ISNUMBER(SEARCH("; argumentative judgment; ","; "&H10&"; ")),1,0) -> 0 | AE10: =IF(ISNUMBER(SEARCH("; genre/writing expertise; ","; "&H10&"; ")),1,0) -> 0 | AF10: =IF(ISNUMBER(SEARCH("; none; ","; "&H10&"; ")),1,0) -> 1
A11: P2-010 | B11: 10 | C11: Source selection and citation repair | D11: I found these: [seven source URLs] ... ensuring using ideas from them, mixi with my ideas, and citer them throught my paper | E11: Knowledge injection | F11: Directed delegation; Selection/Rejection | G11: Directive | H11: evidence judgment; argumentative judgment | I11: Supplies seven selected source URLs and instructs integration with the human's ideas throughout the paper. | J11: AI acknowledges the pool and intended integration; it does not draft a section in this response. | K11: p8 L15-p8 L22 | L11: p8 L24-p8 L25 | N11: Visible substantive response | P11: =SUM(Paper2Coding[[#This Row],[Open Delegation]:[Expertise]]) -> 5 | Q11: =IF(OR(E11="Delegation",ISNUMBER(SEARCH("; Delegation; ","; "&F11&"; "))),1,0) -> 0 | R11: =IF(OR(E11="Directed delegation",ISNUMBER(SEARCH("; Directed delegation; ","; "&F11&"; "))),1,0) -> 1 | S11: =IF(OR(E11="Evaluation",ISNUMBER(SEARCH("; Evaluation; ","; "&F11&"; "))),1,0) -> 0 | T11: =IF(OR(E11="Correction/Challenge",ISNUMBER(SEARCH("; Correction/Challenge; ","; "&F11&"; "))),1,0) -> 0 | U11: =IF(OR(E11="Redirection",ISNUMBER(SEARCH("; Redirection; ","; "&F11&"; "))),1,0) -> 0 | V11: =IF(OR(E11="Knowledge injection",ISNUMBER(SEARCH("; Knowledge injection; ","; "&F11&"; "))),1,0) -> 1 | W11: =IF(OR(E11="Selection/Rejection",ISNUMBER(SEARCH("; Selection/Rejection; ","; "&F11&"; "))),1,0) -> 1 | X11: =IF(OR(E11="Deliberation",ISNUMBER(SEARCH("; Deliberation; ","; "&F11&"; "))),1,0) -> 0 | Y11: =SUM(Paper2Coding[[#This Row],[Subject-matter correction]:[none]]) -> 2 | Z11: =IF(ISNUMBER(SEARCH("; domain correction; ","; "&H11&"; ")),1,0) -> 0 | AA11: =IF(ISNUMBER(SEARCH("; conceptual discrimination; ","; "&H11&"; ")),1,0) -> 0 | AB11: =IF(ISNUMBER(SEARCH("; evidence judgment; ","; "&H11&"; ")),1,0) -> 1 | AC11: =IF(ISNUMBER(SEARCH("; methodological judgment; ","; "&H11&"; ")),1,0) -> 0 | AD11: =IF(ISNUMBER(SEARCH("; argumentative judgment; ","; "&H11&"; ")),1,0) -> 1 | AE11: =IF(ISNUMBER(SEARCH("; genre/writing expertise; ","; "&H11&"; ")),1,0) -> 0 | AF11: =IF(ISNUMBER(SEARCH("; none; ","; "&H11&"; ")),1,0) -> 0
A12: P2-011 | B12: 11 | C12: Source selection and citation repair | D12: write section 1 | E12: Delegation | G12: Delegative | H12: none | I12: Requests Section 1 with no new substantive specification. Earlier constraints remain context. | J12: AI drafts an introduction using the supplied sources. | K12: p8 L26-p8 L26 | L12: p8 L27-p9 L5 | N12: Visible substantive response | P12: =SUM(Paper2Coding[[#This Row],[Open Delegation]:[Expertise]]) -> 2 | Q12: =IF(OR(E12="Delegation",ISNUMBER(SEARCH("; Delegation; ","; "&F12&"; "))),1,0) -> 1 | R12: =IF(OR(E12="Directed delegation",ISNUMBER(SEARCH("; Directed delegation; ","; "&F12&"; "))),1,0) -> 0 | S12: =IF(OR(E12="Evaluation",ISNUMBER(SEARCH("; Evaluation; ","; "&F12&"; "))),1,0) -> 0 | T12: =IF(OR(E12="Correction/Challenge",ISNUMBER(SEARCH("; Correction/Challenge; ","; "&F12&"; "))),1,0) -> 0 | U12: =IF(OR(E12="Redirection",ISNUMBER(SEARCH("; Redirection; ","; "&F12&"; "))),1,0) -> 0 | V12: =IF(OR(E12="Knowledge injection",ISNUMBER(SEARCH("; Knowledge injection; ","; "&F12&"; "))),1,0) -> 0 | W12: =IF(OR(E12="Selection/Rejection",ISNUMBER(SEARCH("; Selection/Rejection; ","; "&F12&"; "))),1,0) -> 0 | X12: =IF(OR(E12="Deliberation",ISNUMBER(SEARCH("; Deliberation; ","; "&F12&"; "))),1,0) -> 0 | Y12: =SUM(Paper2Coding[[#This Row],[Subject-matter correction]:[none]]) -> 1 | Z12: =IF(ISNUMBER(SEARCH("; domain correction; ","; "&H12&"; ")),1,0) -> 0 | AA12: =IF(ISNUMBER(SEARCH("; conceptual discrimination; ","; "&H12&"; ")),1,0) -> 0 | AB12: =IF(ISNUMBER(SEARCH("; evidence judgment; ","; "&H12&"; ")),1,0) -> 0 | AC12: =IF(ISNUMBER(SEARCH("; methodological judgment; ","; "&H12&"; ")),1,0) -> 0 | AD12: =IF(ISNUMBER(SEARCH("; argumentative judgment; ","; "&H12&"; ")),1,0) -> 0 | AE12: =IF(ISNUMBER(SEARCH("; genre/writing expertise; ","; "&H12&"; ")),1,0) -> 0 | AF12: =IF(ISNUMBER(SEARCH("; none; ","; "&H12&"; ")),1,0) -> 1
A13: P2-012 | B13: 12 | C13: Source selection and citation repair | D13: for each ref cited, give me their full list at end of each section | E13: Directed delegation | G13: Directive | H13: evidence judgment; genre/writing expertise | I13: Requires a full reference list at the end of every section for traceability. | J13: AI supplies the Section 1 list, including the subsequently challenged arXiv citation. | K13: p9 L6-p9 L6 | L13: p9 L7-p9 L21 | N13: Visible substantive response | P13: =SUM(Paper2Coding[[#This Row],[Open Delegation]:[Expertise]]) -> 3 | Q13: =IF(OR(E13="Delegation",ISNUMBER(SEARCH("; Delegation; ","; "&F13&"; "))),1,0) -> 0 | R13: =IF(OR(E13="Directed delegation",ISNUMBER(SEARCH("; Directed delegation; ","; "&F13&"; "))),1,0) -> 1 | S13: =IF(OR(E13="Evaluation",ISNUMBER(SEARCH("; Evaluation; ","; "&F13&"; "))),1,0) -> 0 | T13: =IF(OR(E13="Correction/Challenge",ISNUMBER(SEARCH("; Correction/Challenge; ","; "&F13&"; "))),1,0) -> 0 | U13: =IF(OR(E13="Redirection",ISNUMBER(SEARCH("; Redirection; ","; "&F13&"; "))),1,0) -> 0 | V13: =IF(OR(E13="Knowledge injection",ISNUMBER(SEARCH("; Knowledge injection; ","; "&F13&"; "))),1,0) -> 0 | W13: =IF(OR(E13="Selection/Rejection",ISNUMBER(SEARCH("; Selection/Rejection; ","; "&F13&"; "))),1,0) -> 0 | X13: =IF(OR(E13="Deliberation",ISNUMBER(SEARCH("; Deliberation; ","; "&F13&"; "))),1,0) -> 0 | Y13: =SUM(Paper2Coding[[#This Row],[Subject-matter correction]:[none]]) -> 2 | Z13: =IF(ISNUMBER(SEARCH("; domain correction; ","; "&H13&"; ")),1,0) -> 0 | AA13: =IF(ISNUMBER(SEARCH("; conceptual discrimination; ","; "&H13&"; ")),1,0) -> 0 | AB13: =IF(ISNUMBER(SEARCH("; evidence judgment; ","; "&H13&"; ")),1,0) -> 1 | AC13: =IF(ISNUMBER(SEARCH("; methodological judgment; ","; "&H13&"; ")),1,0) -> 0 | AD13: =IF(ISNUMBER(SEARCH("; argumentative judgment; ","; "&H13&"; ")),1,0) -> 0 | AE13: =IF(ISNUMBER(SEARCH("; genre/writing expertise; ","; "&H13&"; ")),1,0) -> 1 | AF13: =IF(ISNUMBER(SEARCH("; none; ","; "&H13&"; ")),1,0) -> 0
A14: P2-013 | B14: 13 | C14: Source selection and citation repair | D14: do not generate FAKE refernedces. verify each of the above and remove the FAKE ones | E14: Correction/Challenge | F14: Directed delegation; Selection/Rejection | G14: Critical | H14: evidence judgment; methodological judgment | I14: Explicitly challenges fake references and demands verification and removal. | J14: AI labels the list verified but repeats the misidentified arXiv citation challenged in the next turn. | K14: p9 L22-p9 L22 | L14: p9 L23-p9 L40 | N14: Visible substantive response | P14: =SUM(Paper2Coding[[#This Row],[Open Delegation]:[Expertise]]) -> 5 | Q14: =IF(OR(E14="Delegation",ISNUMBER(SEARCH("; Delegation; ","; "&F14&"; "))),1,0) -> 0 | R14: =IF(OR(E14="Directed delegation",ISNUMBER(SEARCH("; Directed delegation; ","; "&F14&"; "))),1,0) -> 1 | S14: =IF(OR(E14="Evaluation",ISNUMBER(SEARCH("; Evaluation; ","; "&F14&"; "))),1,0) -> 0 | T14: =IF(OR(E14="Correction/Challenge",ISNUMBER(SEARCH("; Correction/Challenge; ","; "&F14&"; "))),1,0) -> 1 | U14: =IF(OR(E14="Redirection",ISNUMBER(SEARCH("; Redirection; ","; "&F14&"; "))),1,0) -> 0 | V14: =IF(OR(E14="Knowledge injection",ISNUMBER(SEARCH("; Knowledge injection; ","; "&F14&"; "))),1,0) -> 0 | W14: =IF(OR(E14="Selection/Rejection",ISNUMBER(SEARCH("; Selection/Rejection; ","; "&F14&"; "))),1,0) -> 1 | X14: =IF(OR(E14="Deliberation",ISNUMBER(SEARCH("; Deliberation; ","; "&F14&"; "))),1,0) -> 0 | Y14: =SUM(Paper2Coding[[#This Row],[Subject-matter correction]:[none]]) -> 2 | Z14: =IF(ISNUMBER(SEARCH("; domain correction; ","; "&H14&"; ")),1,0) -> 0 | AA14: =IF(ISNUMBER(SEARCH("; conceptual discrimination; ","; "&H14&"; ")),1,0) -> 0 | AB14: =IF(ISNUMBER(SEARCH("; evidence judgment; ","; "&H14&"; ")),1,0) -> 1 | AC14: =IF(ISNUMBER(SEARCH("; methodological judgment; ","; "&H14&"; ")),1,0) -> 1 | AD14: =IF(ISNUMBER(SEARCH("; argumentative judgment; ","; "&H14&"; ")),1,0) -> 0 | AE14: =IF(ISNUMBER(SEARCH("; genre/writing expertise; ","; "&H14&"; ")),1,0) -> 0 | AF14: =IF(ISNUMBER(SEARCH("; none; ","; "&H14&"; ")),1,0) -> 0
A15: P2-014 | B15: 14 | C15: Source selection and citation repair | D15: A. Siddiq, A. Agashe, Y. Zhou, et al., _Evaluating Large Language Models for Code Quality: An Empirical Study_, arXiv preprint arXiv:2410.06992v1, 2024. \[Online\]. Available: [https://arxiv.org/html/2410.06992v1](https://arxiv.org/html/2410.06992v1) is still fake!! | E15: Correction/Challenge | G15: Critical | H15: evidence judgment | I15: Identifies the particular citation as still fake, challenging the earlier verification assurance. | J15: AI admits that title and authors do not match the identifier and advises removing the entry. | K15: p10 L1-p10 L3 | L15: p10 L4-p10 L19 | N15: Visible substantive response | P15: =SUM(Paper2Coding[[#This Row],[Open Delegation]:[Expertise]]) -> 2 | Q15: =IF(OR(E15="Delegation",ISNUMBER(SEARCH("; Delegation; ","; "&F15&"; "))),1,0) -> 0 | R15: =IF(OR(E15="Directed delegation",ISNUMBER(SEARCH("; Directed delegation; ","; "&F15&"; "))),1,0) -> 0 | S15: =IF(OR(E15="Evaluation",ISNUMBER(SEARCH("; Evaluation; ","; "&F15&"; "))),1,0) -> 0 | T15: =IF(OR(E15="Correction/Challenge",ISNUMBER(SEARCH("; Correction/Challenge; ","; "&F15&"; "))),1,0) -> 1 | U15: =IF(OR(E15="Redirection",ISNUMBER(SEARCH("; Redirection; ","; "&F15&"; "))),1,0) -> 0 | V15: =IF(OR(E15="Knowledge injection",ISNUMBER(SEARCH("; Knowledge injection; ","; "&F15&"; "))),1,0) -> 0 | W15: =IF(OR(E15="Selection/Rejection",ISNUMBER(SEARCH("; Selection/Rejection; ","; "&F15&"; "))),1,0) -> 0 | X15: =IF(OR(E15="Deliberation",ISNUMBER(SEARCH("; Deliberation; ","; "&F15&"; "))),1,0) -> 0 | Y15: =SUM(Paper2Coding[[#This Row],[Subject-matter correction]:[none]]) -> 1 | Z15: =IF(ISNUMBER(SEARCH("; domain correction; ","; "&H15&"; ")),1,0) -> 0 | AA15: =IF(ISNUMBER(SEARCH("; conceptual discrimination; ","; "&H15&"; ")),1,0) -> 0 | AB15: =IF(ISNUMBER(SEARCH("; evidence judgment; ","; "&H15&"; ")),1,0) -> 1 | AC15: =IF(ISNUMBER(SEARCH("; methodological judgment; ","; "&H15&"; ")),1,0) -> 0 | AD15: =IF(ISNUMBER(SEARCH("; argumentative judgment; ","; "&H15&"; ")),1,0) -> 0 | AE15: =IF(ISNUMBER(SEARCH("; genre/writing expertise; ","; "&H15&"; ")),1,0) -> 0 | AF15: =IF(ISNUMBER(SEARCH("; none; ","; "&H15&"; ")),1,0) -> 0
A16: P2-015 | B16: 15 | C16: Source selection and citation repair | D16: include also https://arxiv.org/html/2410.06992v1 | E16: Selection/Rejection | F16: Directed delegation | G16: Directive | H16: evidence judgment | I16: Retains the supplied arXiv URL despite rejecting its erroneous bibliographic description. | J16: AI agrees to include the URL; it does not establish correct metadata in this response. | K16: p10 L20-p10 L20 | L16: p10 L21-p10 L22 | N16: Visible substantive response | P16: =SUM(Paper2Coding[[#This Row],[Open Delegation]:[Expertise]]) -> 3 | Q16: =IF(OR(E16="Delegation",ISNUMBER(SEARCH("; Delegation; ","; "&F16&"; "))),1,0) -> 0 | R16: =IF(OR(E16="Directed delegation",ISNUMBER(SEARCH("; Directed delegation; ","; "&F16&"; "))),1,0) -> 1 | S16: =IF(OR(E16="Evaluation",ISNUMBER(SEARCH("; Evaluation; ","; "&F16&"; "))),1,0) -> 0 | T16: =IF(OR(E16="Correction/Challenge",ISNUMBER(SEARCH("; Correction/Challenge; ","; "&F16&"; "))),1,0) -> 0 | U16: =IF(OR(E16="Redirection",ISNUMBER(SEARCH("; Redirection; ","; "&F16&"; "))),1,0) -> 0 | V16: =IF(OR(E16="Knowledge injection",ISNUMBER(SEARCH("; Knowledge injection; ","; "&F16&"; "))),1,0) -> 0 | W16: =IF(OR(E16="Selection/Rejection",ISNUMBER(SEARCH("; Selection/Rejection; ","; "&F16&"; "))),1,0) -> 1 | X16: =IF(OR(E16="Deliberation",ISNUMBER(SEARCH("; Deliberation; ","; "&F16&"; "))),1,0) -> 0 | Y16: =SUM(Paper2Coding[[#This Row],[Subject-matter correction]:[none]]) -> 1 | Z16: =IF(ISNUMBER(SEARCH("; domain correction; ","; "&H16&"; ")),1,0) -> 0 | AA16: =IF(ISNUMBER(SEARCH("; conceptual discrimination; ","; "&H16&"; ")),1,0) -> 0 | AB16: =IF(ISNUMBER(SEARCH("; evidence judgment; ","; "&H16&"; ")),1,0) -> 1 | AC16: =IF(ISNUMBER(SEARCH("; methodological judgment; ","; "&H16&"; ")),1,0) -> 0 | AD16: =IF(ISNUMBER(SEARCH("; argumentative judgment; ","; "&H16&"; ")),1,0) -> 0 | AE16: =IF(ISNUMBER(SEARCH("; genre/writing expertise; ","; "&H16&"; ")),1,0) -> 0 | AF16: =IF(ISNUMBER(SEARCH("; none; ","; "&H16&"; ")),1,0) -> 0
A17: P2-016 | B17: 16 | C17: Source selection and citation repair | D17: give updated section 1 with citing all 7 sources | E17: Directed delegation | G17: Directive | H17: evidence judgment; genre/writing expertise | I17: Requires the revised introduction to cite all seven selected sources. | J17: AI supplies an updated introduction and reference list. | K17: p10 L23-p10 L23 | L17: p10 L24-p11 L22 | N17: Visible substantive response | P17: =SUM(Paper2Coding[[#This Row],[Open Delegation]:[Expertise]]) -> 3 | Q17: =IF(OR(E17="Delegation",ISNUMBER(SEARCH("; Delegation; ","; "&F17&"; "))),1,0) -> 0 | R17: =IF(OR(E17="Directed delegation",ISNUMBER(SEARCH("; Directed delegation; ","; "&F17&"; "))),1,0) -> 1 | S17: =IF(OR(E17="Evaluation",ISNUMBER(SEARCH("; Evaluation; ","; "&F17&"; "))),1,0) -> 0 | T17: =IF(OR(E17="Correction/Challenge",ISNUMBER(SEARCH("; Correction/Challenge; ","; "&F17&"; "))),1,0) -> 0 | U17: =IF(OR(E17="Redirection",ISNUMBER(SEARCH("; Redirection; ","; "&F17&"; "))),1,0) -> 0 | V17: =IF(OR(E17="Knowledge injection",ISNUMBER(SEARCH("; Knowledge injection; ","; "&F17&"; "))),1,0) -> 0 | W17: =IF(OR(E17="Selection/Rejection",ISNUMBER(SEARCH("; Selection/Rejection; ","; "&F17&"; "))),1,0) -> 0 | X17: =IF(OR(E17="Deliberation",ISNUMBER(SEARCH("; Deliberation; ","; "&F17&"; "))),1,0) -> 0 | Y17: =SUM(Paper2Coding[[#This Row],[Subject-matter correction]:[none]]) -> 2 | Z17: =IF(ISNUMBER(SEARCH("; domain correction; ","; "&H17&"; ")),1,0) -> 0 | AA17: =IF(ISNUMBER(SEARCH("; conceptual discrimination; ","; "&H17&"; ")),1,0) -> 0 | AB17: =IF(ISNUMBER(SEARCH("; evidence judgment; ","; "&H17&"; ")),1,0) -> 1 | AC17: =IF(ISNUMBER(SEARCH("; methodological judgment; ","; "&H17&"; ")),1,0) -> 0 | AD17: =IF(ISNUMBER(SEARCH("; argumentative judgment; ","; "&H17&"; ")),1,0) -> 0 | AE17: =IF(ISNUMBER(SEARCH("; genre/writing expertise; ","; "&H17&"; ")),1,0) -> 1 | AF17: =IF(ISNUMBER(SEARCH("; none; ","; "&H17&"; ")),1,0) -> 0
A18: P2-017 | B18: 17 | C18: Source selection and citation repair | D18: include this also: https://stackoverflow.blog/2024/12/31/generative-ai-is-not-going-to-build-your-engineering-team-for-you/ as the 8th citation | E18: Knowledge injection | F18: Directed delegation; Selection/Rejection | G18: Directive | H18: evidence judgment | I18: Adds a selected Stack Overflow source as the eighth citation. | J18: AI acknowledges the source and revises the introduction and references. | K18: p11 L23-p11 L23 | L18: p11 L24-p12 L23 | N18: Visible substantive response | P18: =SUM(Paper2Coding[[#This Row],[Open Delegation]:[Expertise]]) -> 4 | Q18: =IF(OR(E18="Delegation",ISNUMBER(SEARCH("; Delegation; ","; "&F18&"; "))),1,0) -> 0 | R18: =IF(OR(E18="Directed delegation",ISNUMBER(SEARCH("; Directed delegation; ","; "&F18&"; "))),1,0) -> 1 | S18: =IF(OR(E18="Evaluation",ISNUMBER(SEARCH("; Evaluation; ","; "&F18&"; "))),1,0) -> 0 | T18: =IF(OR(E18="Correction/Challenge",ISNUMBER(SEARCH("; Correction/Challenge; ","; "&F18&"; "))),1,0) -> 0 | U18: =IF(OR(E18="Redirection",ISNUMBER(SEARCH("; Redirection; ","; "&F18&"; "))),1,0) -> 0 | V18: =IF(OR(E18="Knowledge injection",ISNUMBER(SEARCH("; Knowledge injection; ","; "&F18&"; "))),1,0) -> 1 | W18: =IF(OR(E18="Selection/Rejection",ISNUMBER(SEARCH("; Selection/Rejection; ","; "&F18&"; "))),1,0) -> 1 | X18: =IF(OR(E18="Deliberation",ISNUMBER(SEARCH("; Deliberation; ","; "&F18&"; "))),1,0) -> 0 | Y18: =SUM(Paper2Coding[[#This Row],[Subject-matter correction]:[none]]) -> 1 | Z18: =IF(ISNUMBER(SEARCH("; domain correction; ","; "&H18&"; ")),1,0) -> 0 | AA18: =IF(ISNUMBER(SEARCH("; conceptual discrimination; ","; "&H18&"; ")),1,0) -> 0 | AB18: =IF(ISNUMBER(SEARCH("; evidence judgment; ","; "&H18&"; ")),1,0) -> 1 | AC18: =IF(ISNUMBER(SEARCH("; methodological judgment; ","; "&H18&"; ")),1,0) -> 0 | AD18: =IF(ISNUMBER(SEARCH("; argumentative judgment; ","; "&H18&"; ")),1,0) -> 0 | AE18: =IF(ISNUMBER(SEARCH("; genre/writing expertise; ","; "&H18&"; ")),1,0) -> 0 | AF18: =IF(ISNUMBER(SEARCH("; none; ","; "&H18&"; ")),1,0) -> 0
A19: P2-018 | B19: 18 | C19: Source selection and citation repair | D19: A. Siddiq, A. Agashe, Y. Zhou, et al., _Evaluating Large Language Models for Code Quality: An Empirical Study_ fix it. it is: SWE-Bench+: Enhanced Coding Benchmark for LLMs Reem Aleithan, Haoran Xue, Mohammad Mahdi Mohajer, Elijah Nnorom, Gias Uddin, Song Wang | E19: Correction/Challenge | F19: Knowledge injection; Directed delegation | G19: Critical | H19: evidence judgment | I19: Supplies the correct SWE-Bench+ title and six authors to replace the invented metadata. | J19: AI updates citation metadata. Its new claim about human repair is not independently verified here. | K19: p12 L24-p12 L26 | L19: p12 L27-p12 L34 | N19: Visible substantive response | P19: =SUM(Paper2Coding[[#This Row],[Open Delegation]:[Expertise]]) -> 4 | Q19: =IF(OR(E19="Delegation",ISNUMBER(SEARCH("; Delegation; ","; "&F19&"; "))),1,0) -> 0 | R19: =IF(OR(E19="Directed delegation",ISNUMBER(SEARCH("; Directed delegation; ","; "&F19&"; "))),1,0) -> 1 | S19: =IF(OR(E19="Evaluation",ISNUMBER(SEARCH("; Evaluation; ","; "&F19&"; "))),1,0) -> 0 | T19: =IF(OR(E19="Correction/Challenge",ISNUMBER(SEARCH("; Correction/Challenge; ","; "&F19&"; "))),1,0) -> 1 | U19: =IF(OR(E19="Redirection",ISNUMBER(SEARCH("; Redirection; ","; "&F19&"; "))),1,0) -> 0 | V19: =IF(OR(E19="Knowledge injection",ISNUMBER(SEARCH("; Knowledge injection; ","; "&F19&"; "))),1,0) -> 1 | W19: =IF(OR(E19="Selection/Rejection",ISNUMBER(SEARCH("; Selection/Rejection; ","; "&F19&"; "))),1,0) -> 0 | X19: =IF(OR(E19="Deliberation",ISNUMBER(SEARCH("; Deliberation; ","; "&F19&"; "))),1,0) -> 0 | Y19: =SUM(Paper2Coding[[#This Row],[Subject-matter correction]:[none]]) -> 1 | Z19: =IF(ISNUMBER(SEARCH("; domain correction; ","; "&H19&"; ")),1,0) -> 0 | AA19: =IF(ISNUMBER(SEARCH("; conceptual discrimination; ","; "&H19&"; ")),1,0) -> 0 | AB19: =IF(ISNUMBER(SEARCH("; evidence judgment; ","; "&H19&"; ")),1,0) -> 1 | AC19: =IF(ISNUMBER(SEARCH("; methodological judgment; ","; "&H19&"; ")),1,0) -> 0 | AD19: =IF(ISNUMBER(SEARCH("; argumentative judgment; ","; "&H19&"; ")),1,0) -> 0 | AE19: =IF(ISNUMBER(SEARCH("; genre/writing expertise; ","; "&H19&"; ")),1,0) -> 0 | AF19: =IF(ISNUMBER(SEARCH("; none; ","; "&H19&"; ")),1,0) -> 0
A20: P2-019 | B20: 19 | C20: Source selection and citation repair | D20: workflows I Do not like this term. do not use it in ANY of interactions with me. Insrtead, you can use: practices or processes | E20: Correction/Challenge | F20: Selection/Rejection; Directed delegation | G20: Critical | H20: genre/writing expertise | I20: Rejects a recurrent term and supplies preferred alternatives, asserting editorial control. | J20: AI acknowledges the wording preference. | K20: p12 L35-p12 L36 | L20: p12 L37-p12 L38 | N20: Visible substantive response | P20: =SUM(Paper2Coding[[#This Row],[Open Delegation]:[Expertise]]) -> 4 | Q20: =IF(OR(E20="Delegation",ISNUMBER(SEARCH("; Delegation; ","; "&F20&"; "))),1,0) -> 0 | R20: =IF(OR(E20="Directed delegation",ISNUMBER(SEARCH("; Directed delegation; ","; "&F20&"; "))),1,0) -> 1 | S20: =IF(OR(E20="Evaluation",ISNUMBER(SEARCH("; Evaluation; ","; "&F20&"; "))),1,0) -> 0 | T20: =IF(OR(E20="Correction/Challenge",ISNUMBER(SEARCH("; Correction/Challenge; ","; "&F20&"; "))),1,0) -> 1 | U20: =IF(OR(E20="Redirection",ISNUMBER(SEARCH("; Redirection; ","; "&F20&"; "))),1,0) -> 0 | V20: =IF(OR(E20="Knowledge injection",ISNUMBER(SEARCH("; Knowledge injection; ","; "&F20&"; "))),1,0) -> 0 | W20: =IF(OR(E20="Selection/Rejection",ISNUMBER(SEARCH("; Selection/Rejection; ","; "&F20&"; "))),1,0) -> 1 | X20: =IF(OR(E20="Deliberation",ISNUMBER(SEARCH("; Deliberation; ","; "&F20&"; "))),1,0) -> 0 | Y20: =SUM(Paper2Coding[[#This Row],[Subject-matter correction]:[none]]) -> 1 | Z20: =IF(ISNUMBER(SEARCH("; domain correction; ","; "&H20&"; ")),1,0) -> 0 | AA20: =IF(ISNUMBER(SEARCH("; conceptual discrimination; ","; "&H20&"; ")),1,0) -> 0 | AB20: =IF(ISNUMBER(SEARCH("; evidence judgment; ","; "&H20&"; ")),1,0) -> 0 | AC20: =IF(ISNUMBER(SEARCH("; methodological judgment; ","; "&H20&"; ")),1,0) -> 0 | AD20: =IF(ISNUMBER(SEARCH("; argumentative judgment; ","; "&H20&"; ")),1,0) -> 0 | AE20: =IF(ISNUMBER(SEARCH("; genre/writing expertise; ","; "&H20&"; ")),1,0) -> 1 | AF20: =IF(ISNUMBER(SEARCH("; none; ","; "&H20&"; ")),1,0) -> 0
A21: P2-020 | B21: 20 | C21: Abstract and paper positioning | D21: how about this title? Be aware of the Hidden Cost of using GenAI in Software Engineering: Efficiency or Burden . it's a bit long, can it be shortened? | E21: Evaluation | F21: Directed delegation; Knowledge injection | G21: Evaluative | H21: genre/writing expertise | I21: Proposes a title, identifies its length problem and requests shortening. | J21: AI gives shorter options without a recorded final choice. | K21: p12 L39-p12 L40 | L21: p12 L41-p13 L11 | N21: Visible substantive response | P21: =SUM(Paper2Coding[[#This Row],[Open Delegation]:[Expertise]]) -> 4 | Q21: =IF(OR(E21="Delegation",ISNUMBER(SEARCH("; Delegation; ","; "&F21&"; "))),1,0) -> 0 | R21: =IF(OR(E21="Directed delegation",ISNUMBER(SEARCH("; Directed delegation; ","; "&F21&"; "))),1,0) -> 1 | S21: =IF(OR(E21="Evaluation",ISNUMBER(SEARCH("; Evaluation; ","; "&F21&"; "))),1,0) -> 1 | T21: =IF(OR(E21="Correction/Challenge",ISNUMBER(SEARCH("; Correction/Challenge; ","; "&F21&"; "))),1,0) -> 0 | U21: =IF(OR(E21="Redirection",ISNUMBER(SEARCH("; Redirection; ","; "&F21&"; "))),1,0) -> 0 | V21: =IF(OR(E21="Knowledge injection",ISNUMBER(SEARCH("; Knowledge injection; ","; "&F21&"; "))),1,0) -> 1 | W21: =IF(OR(E21="Selection/Rejection",ISNUMBER(SEARCH("; Selection/Rejection; ","; "&F21&"; "))),1,0) -> 0 | X21: =IF(OR(E21="Deliberation",ISNUMBER(SEARCH("; Deliberation; ","; "&F21&"; "))),1,0) -> 0 | Y21: =SUM(Paper2Coding[[#This Row],[Subject-matter correction]:[none]]) -> 1 | Z21: =IF(ISNUMBER(SEARCH("; domain correction; ","; "&H21&"; ")),1,0) -> 0 | AA21: =IF(ISNUMBER(SEARCH("; conceptual discrimination; ","; "&H21&"; ")),1,0) -> 0 | AB21: =IF(ISNUMBER(SEARCH("; evidence judgment; ","; "&H21&"; ")),1,0) -> 0 | AC21: =IF(ISNUMBER(SEARCH("; methodological judgment; ","; "&H21&"; ")),1,0) -> 0 | AD21: =IF(ISNUMBER(SEARCH("; argumentative judgment; ","; "&H21&"; ")),1,0) -> 0 | AE21: =IF(ISNUMBER(SEARCH("; genre/writing expertise; ","; "&H21&"; ")),1,0) -> 1 | AF21: =IF(ISNUMBER(SEARCH("; none; ","; "&H21&"; ")),1,0) -> 0
A22: P2-021 | B22: 21 | C22: Abstract and paper positioning | D22: I slightly improved the abstract. proof read it: AI tools promise increased efficiency in software engineering (SE), yet their use can introduce hidden costs. Software engineers often need to review, validate, and correct AI-generated SE artifacts—efforts that may outweigh the... | E22: Directed delegation | F22: Knowledge injection | G22: Directive | H22: genre/writing expertise; argumentative judgment | I22: Supplies a revised abstract incorporating industrial experience and limits the task to proofreading. | J22: AI proofreads the abstract; no independent audit of the experience claim is visible. | K22: p13 L12-p13 L17 | L22: p13 L19-p13 L25 | N22: Visible substantive response | P22: =SUM(Paper2Coding[[#This Row],[Open Delegation]:[Expertise]]) -> 4 | Q22: =IF(OR(E22="Delegation",ISNUMBER(SEARCH("; Delegation; ","; "&F22&"; "))),1,0) -> 0 | R22: =IF(OR(E22="Directed delegation",ISNUMBER(SEARCH("; Directed delegation; ","; "&F22&"; "))),1,0) -> 1 | S22: =IF(OR(E22="Evaluation",ISNUMBER(SEARCH("; Evaluation; ","; "&F22&"; "))),1,0) -> 0 | T22: =IF(OR(E22="Correction/Challenge",ISNUMBER(SEARCH("; Correction/Challenge; ","; "&F22&"; "))),1,0) -> 0 | U22: =IF(OR(E22="Redirection",ISNUMBER(SEARCH("; Redirection; ","; "&F22&"; "))),1,0) -> 0 | V22: =IF(OR(E22="Knowledge injection",ISNUMBER(SEARCH("; Knowledge injection; ","; "&F22&"; "))),1,0) -> 1 | W22: =IF(OR(E22="Selection/Rejection",ISNUMBER(SEARCH("; Selection/Rejection; ","; "&F22&"; "))),1,0) -> 0 | X22: =IF(OR(E22="Deliberation",ISNUMBER(SEARCH("; Deliberation; ","; "&F22&"; "))),1,0) -> 0 | Y22: =SUM(Paper2Coding[[#This Row],[Subject-matter correction]:[none]]) -> 2 | Z22: =IF(ISNUMBER(SEARCH("; domain correction; ","; "&H22&"; ")),1,0) -> 0 | AA22: =IF(ISNUMBER(SEARCH("; conceptual discrimination; ","; "&H22&"; ")),1,0) -> 0 | AB22: =IF(ISNUMBER(SEARCH("; evidence judgment; ","; "&H22&"; ")),1,0) -> 0 | AC22: =IF(ISNUMBER(SEARCH("; methodological judgment; ","; "&H22&"; ")),1,0) -> 0 | AD22: =IF(ISNUMBER(SEARCH("; argumentative judgment; ","; "&H22&"; ")),1,0) -> 1 | AE22: =IF(ISNUMBER(SEARCH("; genre/writing expertise; ","; "&H22&"; ")),1,0) -> 1 | AF22: =IF(ISNUMBER(SEARCH("; none; ","; "&H22&"; ")),1,0) -> 0
A23: P2-022 | B23: 22 | C23: Abstract and paper positioning | D23: add that, to get productivity gains from AI in SE, it should be used in the right way, and other "right" factors | E23: Directed delegation | F23: Knowledge injection | G23: Directive | H23: argumentative judgment | I23: Adds the human's argument that productivity gains depend on appropriate AI use and other factors. | J23: AI adds engineering practice, human judgment and task-selection conditions. | K23: p13 L26-p13 L26 | L23: p13 L27-p13 L35 | N23: Visible substantive response | P23: =SUM(Paper2Coding[[#This Row],[Open Delegation]:[Expertise]]) -> 3 | Q23: =IF(OR(E23="Delegation",ISNUMBER(SEARCH("; Delegation; ","; "&F23&"; "))),1,0) -> 0 | R23: =IF(OR(E23="Directed delegation",ISNUMBER(SEARCH("; Directed delegation; ","; "&F23&"; "))),1,0) -> 1 | S23: =IF(OR(E23="Evaluation",ISNUMBER(SEARCH("; Evaluation; ","; "&F23&"; "))),1,0) -> 0 | T23: =IF(OR(E23="Correction/Challenge",ISNUMBER(SEARCH("; Correction/Challenge; ","; "&F23&"; "))),1,0) -> 0 | U23: =IF(OR(E23="Redirection",ISNUMBER(SEARCH("; Redirection; ","; "&F23&"; "))),1,0) -> 0 | V23: =IF(OR(E23="Knowledge injection",ISNUMBER(SEARCH("; Knowledge injection; ","; "&F23&"; "))),1,0) -> 1 | W23: =IF(OR(E23="Selection/Rejection",ISNUMBER(SEARCH("; Selection/Rejection; ","; "&F23&"; "))),1,0) -> 0 | X23: =IF(OR(E23="Deliberation",ISNUMBER(SEARCH("; Deliberation; ","; "&F23&"; "))),1,0) -> 0 | Y23: =SUM(Paper2Coding[[#This Row],[Subject-matter correction]:[none]]) -> 1 | Z23: =IF(ISNUMBER(SEARCH("; domain correction; ","; "&H23&"; ")),1,0) -> 0 | AA23: =IF(ISNUMBER(SEARCH("; conceptual discrimination; ","; "&H23&"; ")),1,0) -> 0 | AB23: =IF(ISNUMBER(SEARCH("; evidence judgment; ","; "&H23&"; ")),1,0) -> 0 | AC23: =IF(ISNUMBER(SEARCH("; methodological judgment; ","; "&H23&"; ")),1,0) -> 0 | AD23: =IF(ISNUMBER(SEARCH("; argumentative judgment; ","; "&H23&"; ")),1,0) -> 1 | AE23: =IF(ISNUMBER(SEARCH("; genre/writing expertise; ","; "&H23&"; ")),1,0) -> 0 | AF23: =IF(ISNUMBER(SEARCH("; none; ","; "&H23&"; ")),1,0) -> 0
A24: P2-023 | B24: 23 | C24: Abstract and paper positioning | D24: —guided by sound engineering practices, critical human judgment, and appropriate task selection good, but it is hard to read, sepaarate that sentence. also further disucss " appropriate task selection". I also like you use "right" as the adjective multiple time for those aspects | E24: Correction/Challenge | F24: Directed delegation; Selection/Rejection | G24: Critical | H24: genre/writing expertise; argumentative judgment | I24: Partly approves the idea but diagnoses poor readability, directs sentence separation and preferred wording, and requests elaboration. | J24: AI rewrites and expands task selection using the requested repeated adjective. | K24: p13 L36-p13 L38 | L24: p13 L39-p14 L10 | N24: Visible substantive response | P24: =SUM(Paper2Coding[[#This Row],[Open Delegation]:[Expertise]]) -> 5 | Q24: =IF(OR(E24="Delegation",ISNUMBER(SEARCH("; Delegation; ","; "&F24&"; "))),1,0) -> 0 | R24: =IF(OR(E24="Directed delegation",ISNUMBER(SEARCH("; Directed delegation; ","; "&F24&"; "))),1,0) -> 1 | S24: =IF(OR(E24="Evaluation",ISNUMBER(SEARCH("; Evaluation; ","; "&F24&"; "))),1,0) -> 0 | T24: =IF(OR(E24="Correction/Challenge",ISNUMBER(SEARCH("; Correction/Challenge; ","; "&F24&"; "))),1,0) -> 1 | U24: =IF(OR(E24="Redirection",ISNUMBER(SEARCH("; Redirection; ","; "&F24&"; "))),1,0) -> 0 | V24: =IF(OR(E24="Knowledge injection",ISNUMBER(SEARCH("; Knowledge injection; ","; "&F24&"; "))),1,0) -> 0 | W24: =IF(OR(E24="Selection/Rejection",ISNUMBER(SEARCH("; Selection/Rejection; ","; "&F24&"; "))),1,0) -> 1 | X24: =IF(OR(E24="Deliberation",ISNUMBER(SEARCH("; Deliberation; ","; "&F24&"; "))),1,0) -> 0 | Y24: =SUM(Paper2Coding[[#This Row],[Subject-matter correction]:[none]]) -> 2 | Z24: =IF(ISNUMBER(SEARCH("; domain correction; ","; "&H24&"; ")),1,0) -> 0 | AA24: =IF(ISNUMBER(SEARCH("; conceptual discrimination; ","; "&H24&"; ")),1,0) -> 0 | AB24: =IF(ISNUMBER(SEARCH("; evidence judgment; ","; "&H24&"; ")),1,0) -> 0 | AC24: =IF(ISNUMBER(SEARCH("; methodological judgment; ","; "&H24&"; ")),1,0) -> 0 | AD24: =IF(ISNUMBER(SEARCH("; argumentative judgment; ","; "&H24&"; ")),1,0) -> 1 | AE24: =IF(ISNUMBER(SEARCH("; genre/writing expertise; ","; "&H24&"; ")),1,0) -> 1 | AF24: =IF(ISNUMBER(SEARCH("; none; ","; "&H24&"; ")),1,0) -> 0
A25: P2-024 | B25: 24 | C25: Abstract and paper positioning | D25: yes | E25: Selection/Rejection | G25: Directive | H25: none | I25: Accepts the immediately preceding offer of an under-200-word abstract. Terse acceptance adds no independent expertise evidence. | J25: AI supplies a shorter abstract and reports 149 words. | K25: p14 L11-p14 L11 | L25: p14 L12-p14 L23 | N25: Visible substantive response | O25: Assent resolved from immediately preceding offer; not blanket approval | P25: =SUM(Paper2Coding[[#This Row],[Open Delegation]:[Expertise]]) -> 2 | Q25: =IF(OR(E25="Delegation",ISNUMBER(SEARCH("; Delegation; ","; "&F25&"; "))),1,0) -> 0 | R25: =IF(OR(E25="Directed delegation",ISNUMBER(SEARCH("; Directed delegation; ","; "&F25&"; "))),1,0) -> 0 | S25: =IF(OR(E25="Evaluation",ISNUMBER(SEARCH("; Evaluation; ","; "&F25&"; "))),1,0) -> 0 | T25: =IF(OR(E25="Correction/Challenge",ISNUMBER(SEARCH("; Correction/Challenge; ","; "&F25&"; "))),1,0) -> 0 | U25: =IF(OR(E25="Redirection",ISNUMBER(SEARCH("; Redirection; ","; "&F25&"; "))),1,0) -> 0 | V25: =IF(OR(E25="Knowledge injection",ISNUMBER(SEARCH("; Knowledge injection; ","; "&F25&"; "))),1,0) -> 0 | W25: =IF(OR(E25="Selection/Rejection",ISNUMBER(SEARCH("; Selection/Rejection; ","; "&F25&"; "))),1,0) -> 1 | X25: =IF(OR(E25="Deliberation",ISNUMBER(SEARCH("; Deliberation; ","; "&F25&"; "))),1,0) -> 0 | Y25: =SUM(Paper2Coding[[#This Row],[Subject-matter correction]:[none]]) -> 1 | Z25: =IF(ISNUMBER(SEARCH("; domain correction; ","; "&H25&"; ")),1,0) -> 0 | AA25: =IF(ISNUMBER(SEARCH("; conceptual discrimination; ","; "&H25&"; ")),1,0) -> 0 | AB25: =IF(ISNUMBER(SEARCH("; evidence judgment; ","; "&H25&"; ")),1,0) -> 0 | AC25: =IF(ISNUMBER(SEARCH("; methodological judgment; ","; "&H25&"; ")),1,0) -> 0 | AD25: =IF(ISNUMBER(SEARCH("; argumentative judgment; ","; "&H25&"; ")),1,0) -> 0 | AE25: =IF(ISNUMBER(SEARCH("; genre/writing expertise; ","; "&H25&"; ")),1,0) -> 0 | AF25: =IF(ISNUMBER(SEARCH("; none; ","; "&H25&"; ")),1,0) -> 1
A26: P2-025 | B26: 25 | C26: Abstract and paper positioning | D26: promise replace with: have the potential , or similar tone | E26: Correction/Challenge | F26: Directed delegation | G26: Critical | H26: evidence judgment; argumentative judgment; genre/writing expertise | I26: Replaces promise with have the potential, reducing unwarranted certainty. | J26: AI revises the abstract with the more cautious wording. | K26: p14 L24-p14 L25 | L26: p14 L26-p14 L36 | N26: Visible substantive response | P26: =SUM(Paper2Coding[[#This Row],[Open Delegation]:[Expertise]]) -> 5 | Q26: =IF(OR(E26="Delegation",ISNUMBER(SEARCH("; Delegation; ","; "&F26&"; "))),1,0) -> 0 | R26: =IF(OR(E26="Directed delegation",ISNUMBER(SEARCH("; Directed delegation; ","; "&F26&"; "))),1,0) -> 1 | S26: =IF(OR(E26="Evaluation",ISNUMBER(SEARCH("; Evaluation; ","; "&F26&"; "))),1,0) -> 0 | T26: =IF(OR(E26="Correction/Challenge",ISNUMBER(SEARCH("; Correction/Challenge; ","; "&F26&"; "))),1,0) -> 1 | U26: =IF(OR(E26="Redirection",ISNUMBER(SEARCH("; Redirection; ","; "&F26&"; "))),1,0) -> 0 | V26: =IF(OR(E26="Knowledge injection",ISNUMBER(SEARCH("; Knowledge injection; ","; "&F26&"; "))),1,0) -> 0 | W26: =IF(OR(E26="Selection/Rejection",ISNUMBER(SEARCH("; Selection/Rejection; ","; "&F26&"; "))),1,0) -> 0 | X26: =IF(OR(E26="Deliberation",ISNUMBER(SEARCH("; Deliberation; ","; "&F26&"; "))),1,0) -> 0 | Y26: =SUM(Paper2Coding[[#This Row],[Subject-matter correction]:[none]]) -> 3 | Z26: =IF(ISNUMBER(SEARCH("; domain correction; ","; "&H26&"; ")),1,0) -> 0 | AA26: =IF(ISNUMBER(SEARCH("; conceptual discrimination; ","; "&H26&"; ")),1,0) -> 0 | AB26: =IF(ISNUMBER(SEARCH("; evidence judgment; ","; "&H26&"; ")),1,0) -> 1 | AC26: =IF(ISNUMBER(SEARCH("; methodological judgment; ","; "&H26&"; ")),1,0) -> 0 | AD26: =IF(ISNUMBER(SEARCH("; argumentative judgment; ","; "&H26&"; ")),1,0) -> 1 | AE26: =IF(ISNUMBER(SEARCH("; genre/writing expertise; ","; "&H26&"; ")),1,0) -> 1 | AF26: =IF(ISNUMBER(SEARCH("; none; ","; "&H26&"; ")),1,0) -> 0
A27: P2-026 | B27: 26 | C27: Abstract and paper positioning | D27: note that I plan to write later a follow-up paper on when and how to use GenAI effectively in SE. DEcrease the focus on it, to a minimum: to make this paper focus clear (Hidden Cost of GenAI in Software Engineering: Efficiency or Burden ) and also to leave stuff for the next p... | E27: Redirection | F27: Directed delegation; Knowledge injection | G27: Directive | H27: argumentative judgment; genre/writing expertise | I27: Reserves effective-use guidance for a planned follow-up paper and narrows the current scope to hidden costs. | J27: AI reduces that discussion but adds an explicit future-scope sentence. | K27: p14 L37-p14 L38 | L27: p14 L39-p15 L6 | N27: Visible substantive response | P27: =SUM(Paper2Coding[[#This Row],[Open Delegation]:[Expertise]]) -> 5 | Q27: =IF(OR(E27="Delegation",ISNUMBER(SEARCH("; Delegation; ","; "&F27&"; "))),1,0) -> 0 | R27: =IF(OR(E27="Directed delegation",ISNUMBER(SEARCH("; Directed delegation; ","; "&F27&"; "))),1,0) -> 1 | S27: =IF(OR(E27="Evaluation",ISNUMBER(SEARCH("; Evaluation; ","; "&F27&"; "))),1,0) -> 0 | T27: =IF(OR(E27="Correction/Challenge",ISNUMBER(SEARCH("; Correction/Challenge; ","; "&F27&"; "))),1,0) -> 0 | U27: =IF(OR(E27="Redirection",ISNUMBER(SEARCH("; Redirection; ","; "&F27&"; "))),1,0) -> 1 | V27: =IF(OR(E27="Knowledge injection",ISNUMBER(SEARCH("; Knowledge injection; ","; "&F27&"; "))),1,0) -> 1 | W27: =IF(OR(E27="Selection/Rejection",ISNUMBER(SEARCH("; Selection/Rejection; ","; "&F27&"; "))),1,0) -> 0 | X27: =IF(OR(E27="Deliberation",ISNUMBER(SEARCH("; Deliberation; ","; "&F27&"; "))),1,0) -> 0 | Y27: =SUM(Paper2Coding[[#This Row],[Subject-matter correction]:[none]]) -> 2 | Z27: =IF(ISNUMBER(SEARCH("; domain correction; ","; "&H27&"; ")),1,0) -> 0 | AA27: =IF(ISNUMBER(SEARCH("; conceptual discrimination; ","; "&H27&"; ")),1,0) -> 0 | AB27: =IF(ISNUMBER(SEARCH("; evidence judgment; ","; "&H27&"; ")),1,0) -> 0 | AC27: =IF(ISNUMBER(SEARCH("; methodological judgment; ","; "&H27&"; ")),1,0) -> 0 | AD27: =IF(ISNUMBER(SEARCH("; argumentative judgment; ","; "&H27&"; ")),1,0) -> 1 | AE27: =IF(ISNUMBER(SEARCH("; genre/writing expertise; ","; "&H27&"; ")),1,0) -> 1 | AF27: =IF(ISNUMBER(SEARCH("; none; ","; "&H27&"; ")),1,0) -> 0
A28: P2-027 | B28: 27 | C28: Abstract and paper positioning | D28: Broader questions of when and how to use GenAI effectively are important but remain outside the scope of this work and are left for future discussion. not a good wording for abstract | E28: Correction/Challenge | F28: Selection/Rejection | G28: Critical | H28: genre/writing expertise | I28: Rejects the explicit future-scope wording as unsuitable for an abstract. | J28: AI revises the wording while retaining the limited focus. | K28: p15 L7-p15 L9 | L28: p15 L10-p15 L20 | N28: Visible substantive response | P28: =SUM(Paper2Coding[[#This Row],[Open Delegation]:[Expertise]]) -> 3 | Q28: =IF(OR(E28="Delegation",ISNUMBER(SEARCH("; Delegation; ","; "&F28&"; "))),1,0) -> 0 | R28: =IF(OR(E28="Directed delegation",ISNUMBER(SEARCH("; Directed delegation; ","; "&F28&"; "))),1,0) -> 0 | S28: =IF(OR(E28="Evaluation",ISNUMBER(SEARCH("; Evaluation; ","; "&F28&"; "))),1,0) -> 0 | T28: =IF(OR(E28="Correction/Challenge",ISNUMBER(SEARCH("; Correction/Challenge; ","; "&F28&"; "))),1,0) -> 1 | U28: =IF(OR(E28="Redirection",ISNUMBER(SEARCH("; Redirection; ","; "&F28&"; "))),1,0) -> 0 | V28: =IF(OR(E28="Knowledge injection",ISNUMBER(SEARCH("; Knowledge injection; ","; "&F28&"; "))),1,0) -> 0 | W28: =IF(OR(E28="Selection/Rejection",ISNUMBER(SEARCH("; Selection/Rejection; ","; "&F28&"; "))),1,0) -> 1 | X28: =IF(OR(E28="Deliberation",ISNUMBER(SEARCH("; Deliberation; ","; "&F28&"; "))),1,0) -> 0 | Y28: =SUM(Paper2Coding[[#This Row],[Subject-matter correction]:[none]]) -> 1 | Z28: =IF(ISNUMBER(SEARCH("; domain correction; ","; "&H28&"; ")),1,0) -> 0 | AA28: =IF(ISNUMBER(SEARCH("; conceptual discrimination; ","; "&H28&"; ")),1,0) -> 0 | AB28: =IF(ISNUMBER(SEARCH("; evidence judgment; ","; "&H28&"; ")),1,0) -> 0 | AC28: =IF(ISNUMBER(SEARCH("; methodological judgment; ","; "&H28&"; ")),1,0) -> 0 | AD28: =IF(ISNUMBER(SEARCH("; argumentative judgment; ","; "&H28&"; ")),1,0) -> 0 | AE28: =IF(ISNUMBER(SEARCH("; genre/writing expertise; ","; "&H28&"; ")),1,0) -> 1 | AF28: =IF(ISNUMBER(SEARCH("; none; ","; "&H28&"; ")),1,0) -> 0
A29: P2-028 | B29: 28 | C29: Abstract and paper positioning | D29: how human oversight, error correction, and information overload challenge the presumed benefits of AI-assisted SE. reaplce wtih: efforts spent by human for oversight, correction of errors made by AI , and information overload can challenge the presumed benefits of AI-assisted SE. | E29: Directed delegation | F29: Knowledge injection; Selection/Rejection | G29: Directive | H29: argumentative judgment; genre/writing expertise | I29: Provides replacement wording emphasizing human effort and errors made by AI. | J29: AI integrates the requested phrasing into the abstract. | K29: p15 L21-p15 L23 | L29: p15 L24-p15 L33 | N29: Visible substantive response | P29: =SUM(Paper2Coding[[#This Row],[Open Delegation]:[Expertise]]) -> 5 | Q29: =IF(OR(E29="Delegation",ISNUMBER(SEARCH("; Delegation; ","; "&F29&"; "))),1,0) -> 0 | R29: =IF(OR(E29="Directed delegation",ISNUMBER(SEARCH("; Directed delegation; ","; "&F29&"; "))),1,0) -> 1 | S29: =IF(OR(E29="Evaluation",ISNUMBER(SEARCH("; Evaluation; ","; "&F29&"; "))),1,0) -> 0 | T29: =IF(OR(E29="Correction/Challenge",ISNUMBER(SEARCH("; Correction/Challenge; ","; "&F29&"; "))),1,0) -> 0 | U29: =IF(OR(E29="Redirection",ISNUMBER(SEARCH("; Redirection; ","; "&F29&"; "))),1,0) -> 0 | V29: =IF(OR(E29="Knowledge injection",ISNUMBER(SEARCH("; Knowledge injection; ","; "&F29&"; "))),1,0) -> 1 | W29: =IF(OR(E29="Selection/Rejection",ISNUMBER(SEARCH("; Selection/Rejection; ","; "&F29&"; "))),1,0) -> 1 | X29: =IF(OR(E29="Deliberation",ISNUMBER(SEARCH("; Deliberation; ","; "&F29&"; "))),1,0) -> 0 | Y29: =SUM(Paper2Coding[[#This Row],[Subject-matter correction]:[none]]) -> 2 | Z29: =IF(ISNUMBER(SEARCH("; domain correction; ","; "&H29&"; ")),1,0) -> 0 | AA29: =IF(ISNUMBER(SEARCH("; conceptual discrimination; ","; "&H29&"; ")),1,0) -> 0 | AB29: =IF(ISNUMBER(SEARCH("; evidence judgment; ","; "&H29&"; ")),1,0) -> 0 | AC29: =IF(ISNUMBER(SEARCH("; methodological judgment; ","; "&H29&"; ")),1,0) -> 0 | AD29: =IF(ISNUMBER(SEARCH("; argumentative judgment; ","; "&H29&"; ")),1,0) -> 1 | AE29: =IF(ISNUMBER(SEARCH("; genre/writing expertise; ","; "&H29&"; ")),1,0) -> 1 | AF29: =IF(ISNUMBER(SEARCH("; none; ","; "&H29&"; ")),1,0) -> 0
A30: P2-029 | B30: 29 | C30: Abstract and paper positioning | D30: for title, how about; AI in Software Engineering: Efficiency, Hidden Cost or Burden? | E30: Evaluation | F30: Knowledge injection | G30: Evaluative | H30: genre/writing expertise; argumentative judgment | I30: Proposes another title for assessment. | J30: AI offers variants and recommends a lightly edited version. | K30: p15 L34-p15 L35 | L30: p15 L36-p16 L8 | N30: Visible substantive response | P30: =SUM(Paper2Coding[[#This Row],[Open Delegation]:[Expertise]]) -> 4 | Q30: =IF(OR(E30="Delegation",ISNUMBER(SEARCH("; Delegation; ","; "&F30&"; "))),1,0) -> 0 | R30: =IF(OR(E30="Directed delegation",ISNUMBER(SEARCH("; Directed delegation; ","; "&F30&"; "))),1,0) -> 0 | S30: =IF(OR(E30="Evaluation",ISNUMBER(SEARCH("; Evaluation; ","; "&F30&"; "))),1,0) -> 1 | T30: =IF(OR(E30="Correction/Challenge",ISNUMBER(SEARCH("; Correction/Challenge; ","; "&F30&"; "))),1,0) -> 0 | U30: =IF(OR(E30="Redirection",ISNUMBER(SEARCH("; Redirection; ","; "&F30&"; "))),1,0) -> 0 | V30: =IF(OR(E30="Knowledge injection",ISNUMBER(SEARCH("; Knowledge injection; ","; "&F30&"; "))),1,0) -> 1 | W30: =IF(OR(E30="Selection/Rejection",ISNUMBER(SEARCH("; Selection/Rejection; ","; "&F30&"; "))),1,0) -> 0 | X30: =IF(OR(E30="Deliberation",ISNUMBER(SEARCH("; Deliberation; ","; "&F30&"; "))),1,0) -> 0 | Y30: =SUM(Paper2Coding[[#This Row],[Subject-matter correction]:[none]]) -> 2 | Z30: =IF(ISNUMBER(SEARCH("; domain correction; ","; "&H30&"; ")),1,0) -> 0 | AA30: =IF(ISNUMBER(SEARCH("; conceptual discrimination; ","; "&H30&"; ")),1,0) -> 0 | AB30: =IF(ISNUMBER(SEARCH("; evidence judgment; ","; "&H30&"; ")),1,0) -> 0 | AC30: =IF(ISNUMBER(SEARCH("; methodological judgment; ","; "&H30&"; ")),1,0) -> 0 | AD30: =IF(ISNUMBER(SEARCH("; argumentative judgment; ","; "&H30&"; ")),1,0) -> 1 | AE30: =IF(ISNUMBER(SEARCH("; genre/writing expertise; ","; "&H30&"; ")),1,0) -> 1 | AF30: =IF(ISNUMBER(SEARCH("; none; ","; "&H30&"; ")),1,0) -> 0
A31: P2-030 | B31: 30 | C31: Abstract and paper positioning | D31: here are my final decsision: AI in Software Engineering: Efficiency, Hidden Cost, or Burden? ... update section 1 text, and use all 8 references | E31: Selection/Rejection | F31: Directed delegation; Knowledge injection | G31: Directive | H31: argumentative judgment; genre/writing expertise | I31: Explicitly finalizes title and abstract and requests an aligned introduction citing eight sources. | J31: AI supplies a new introduction aligned to the stated decisions; later changes mean this is a local finalization. | K31: p16 L9-p16 L21 | L31: p16 L23-p17 L2 | N31: Visible substantive response | P31: =SUM(Paper2Coding[[#This Row],[Open Delegation]:[Expertise]]) -> 5 | Q31: =IF(OR(E31="Delegation",ISNUMBER(SEARCH("; Delegation; ","; "&F31&"; "))),1,0) -> 0 | R31: =IF(OR(E31="Directed delegation",ISNUMBER(SEARCH("; Directed delegation; ","; "&F31&"; "))),1,0) -> 1 | S31: =IF(OR(E31="Evaluation",ISNUMBER(SEARCH("; Evaluation; ","; "&F31&"; "))),1,0) -> 0 | T31: =IF(OR(E31="Correction/Challenge",ISNUMBER(SEARCH("; Correction/Challenge; ","; "&F31&"; "))),1,0) -> 0 | U31: =IF(OR(E31="Redirection",ISNUMBER(SEARCH("; Redirection; ","; "&F31&"; "))),1,0) -> 0 | V31: =IF(OR(E31="Knowledge injection",ISNUMBER(SEARCH("; Knowledge injection; ","; "&F31&"; "))),1,0) -> 1 | W31: =IF(OR(E31="Selection/Rejection",ISNUMBER(SEARCH("; Selection/Rejection; ","; "&F31&"; "))),1,0) -> 1 | X31: =IF(OR(E31="Deliberation",ISNUMBER(SEARCH("; Deliberation; ","; "&F31&"; "))),1,0) -> 0 | Y31: =SUM(Paper2Coding[[#This Row],[Subject-matter correction]:[none]]) -> 2 | Z31: =IF(ISNUMBER(SEARCH("; domain correction; ","; "&H31&"; ")),1,0) -> 0 | AA31: =IF(ISNUMBER(SEARCH("; conceptual discrimination; ","; "&H31&"; ")),1,0) -> 0 | AB31: =IF(ISNUMBER(SEARCH("; evidence judgment; ","; "&H31&"; ")),1,0) -> 0 | AC31: =IF(ISNUMBER(SEARCH("; methodological judgment; ","; "&H31&"; ")),1,0) -> 0 | AD31: =IF(ISNUMBER(SEARCH("; argumentative judgment; ","; "&H31&"; ")),1,0) -> 1 | AE31: =IF(ISNUMBER(SEARCH("; genre/writing expertise; ","; "&H31&"; ")),1,0) -> 1 | AF31: =IF(ISNUMBER(SEARCH("; none; ","; "&H31&"; ")),1,0) -> 0
A32: P2-031 | B32: 31 | C32: Abstract and paper positioning | D32: remove "opinion" paper phrase from the paper | E32: Selection/Rejection | F32: Directed delegation | G32: Directive | H32: genre/writing expertise | I32: Removes the opinion paper label from manuscript wording. | J32: AI revises Section 1 and agrees to avoid the phrase. This does not itself change the underlying study design. | K32: p17 L3-p17 L3 | L32: p17 L4-p17 L35 | N32: Visible substantive response | P32: =SUM(Paper2Coding[[#This Row],[Open Delegation]:[Expertise]]) -> 3 | Q32: =IF(OR(E32="Delegation",ISNUMBER(SEARCH("; Delegation; ","; "&F32&"; "))),1,0) -> 0 | R32: =IF(OR(E32="Directed delegation",ISNUMBER(SEARCH("; Directed delegation; ","; "&F32&"; "))),1,0) -> 1 | S32: =IF(OR(E32="Evaluation",ISNUMBER(SEARCH("; Evaluation; ","; "&F32&"; "))),1,0) -> 0 | T32: =IF(OR(E32="Correction/Challenge",ISNUMBER(SEARCH("; Correction/Challenge; ","; "&F32&"; "))),1,0) -> 0 | U32: =IF(OR(E32="Redirection",ISNUMBER(SEARCH("; Redirection; ","; "&F32&"; "))),1,0) -> 0 | V32: =IF(OR(E32="Knowledge injection",ISNUMBER(SEARCH("; Knowledge injection; ","; "&F32&"; "))),1,0) -> 0 | W32: =IF(OR(E32="Selection/Rejection",ISNUMBER(SEARCH("; Selection/Rejection; ","; "&F32&"; "))),1,0) -> 1 | X32: =IF(OR(E32="Deliberation",ISNUMBER(SEARCH("; Deliberation; ","; "&F32&"; "))),1,0) -> 0 | Y32: =SUM(Paper2Coding[[#This Row],[Subject-matter correction]:[none]]) -> 1 | Z32: =IF(ISNUMBER(SEARCH("; domain correction; ","; "&H32&"; ")),1,0) -> 0 | AA32: =IF(ISNUMBER(SEARCH("; conceptual discrimination; ","; "&H32&"; ")),1,0) -> 0 | AB32: =IF(ISNUMBER(SEARCH("; evidence judgment; ","; "&H32&"; ")),1,0) -> 0 | AC32: =IF(ISNUMBER(SEARCH("; methodological judgment; ","; "&H32&"; ")),1,0) -> 0 | AD32: =IF(ISNUMBER(SEARCH("; argumentative judgment; ","; "&H32&"; ")),1,0) -> 0 | AE32: =IF(ISNUMBER(SEARCH("; genre/writing expertise; ","; "&H32&"; ")),1,0) -> 1 | AF32: =IF(ISNUMBER(SEARCH("; none; ","; "&H32&"; ")),1,0) -> 0
A33: P2-032 | B33: 32 | C33: Abstract and paper positioning | D33: so I have written and submitted this other work. review it. Then I have the current paper in progress (The Hidden Cost of AI-Assisted SE). As a next paper, I will focus on: When and how to use GenAI in SE effectively. position these papers properly w.r.t each other and suggest... | E33: Deliberation | F33: Evaluation; Directed delegation; Knowledge injection | G33: Deliberative | H33: argumentative judgment; conceptual discrimination; genre/writing expertise | I33: Asks to position submitted, current and planned papers relative to one another and limit overlap. | J33: No substantive assistant response is visible before the next human turn. | K33: p17 L38-p17 L41 | M33: AI-assisted SE process-IEEE Software.docx | N33: No substantive response visible | O33: Export gap: no assistant outcome can be inferred | P33: =SUM(Paper2Coding[[#This Row],[Open Delegation]:[Expertise]]) -> 7 | Q33: =IF(OR(E33="Delegation",ISNUMBER(SEARCH("; Delegation; ","; "&F33&"; "))),1,0) -> 0 | R33: =IF(OR(E33="Directed delegation",ISNUMBER(SEARCH("; Directed delegation; ","; "&F33&"; "))),1,0) -> 1 | S33: =IF(OR(E33="Evaluation",ISNUMBER(SEARCH("; Evaluation; ","; "&F33&"; "))),1,0) -> 1 | T33: =IF(OR(E33="Correction/Challenge",ISNUMBER(SEARCH("; Correction/Challenge; ","; "&F33&"; "))),1,0) -> 0 | U33: =IF(OR(E33="Redirection",ISNUMBER(SEARCH("; Redirection; ","; "&F33&"; "))),1,0) -> 0 | V33: =IF(OR(E33="Knowledge injection",ISNUMBER(SEARCH("; Knowledge injection; ","; "&F33&"; "))),1,0) -> 1 | W33: =IF(OR(E33="Selection/Rejection",ISNUMBER(SEARCH("; Selection/Rejection; ","; "&F33&"; "))),1,0) -> 0 | X33: =IF(OR(E33="Deliberation",ISNUMBER(SEARCH("; Deliberation; ","; "&F33&"; "))),1,0) -> 1 | Y33: =SUM(Paper2Coding[[#This Row],[Subject-matter correction]:[none]]) -> 3 | Z33: =IF(ISNUMBER(SEARCH("; domain correction; ","; "&H33&"; ")),1,0) -> 0 | AA33: =IF(ISNUMBER(SEARCH("; conceptual discrimination; ","; "&H33&"; ")),1,0) -> 1 | AB33: =IF(ISNUMBER(SEARCH("; evidence judgment; ","; "&H33&"; ")),1,0) -> 0 | AC33: =IF(ISNUMBER(SEARCH("; methodological judgment; ","; "&H33&"; ")),1,0) -> 0 | AD33: =IF(ISNUMBER(SEARCH("; argumentative judgment; ","; "&H33&"; ")),1,0) -> 1 | AE33: =IF(ISNUMBER(SEARCH("; genre/writing expertise; ","; "&H33&"; ")),1,0) -> 1 | AF33: =IF(ISNUMBER(SEARCH("; none; ","; "&H33&"; ")),1,0) -> 0
A34: P2-033 | B34: 33 | C34: Abstract and paper positioning | D34: read that paper again, and tell me in quotes where exactly it is related to my work | E34: Evaluation | F34: Directed delegation | G34: Evaluative | H34: evidence judgment | I34: Requests exact quotes showing relevance of that paper, rather than accepting a general relevance claim. | J34: AI responds about SWE-Bench+; the immediately preceding attachment is a different submitted paper. Referent and response alignment are uncertain. | K34: p17 L43-p17 L43 | L34: p18 L1-p18 L25 | N34: Visible substantive response | O34: Ambiguous paper referent / apparent response mismatch | P34: =SUM(Paper2Coding[[#This Row],[Open Delegation]:[Expertise]]) -> 3 | Q34: =IF(OR(E34="Delegation",ISNUMBER(SEARCH("; Delegation; ","; "&F34&"; "))),1,0) -> 0 | R34: =IF(OR(E34="Directed delegation",ISNUMBER(SEARCH("; Directed delegation; ","; "&F34&"; "))),1,0) -> 1 | S34: =IF(OR(E34="Evaluation",ISNUMBER(SEARCH("; Evaluation; ","; "&F34&"; "))),1,0) -> 1 | T34: =IF(OR(E34="Correction/Challenge",ISNUMBER(SEARCH("; Correction/Challenge; ","; "&F34&"; "))),1,0) -> 0 | U34: =IF(OR(E34="Redirection",ISNUMBER(SEARCH("; Redirection; ","; "&F34&"; "))),1,0) -> 0 | V34: =IF(OR(E34="Knowledge injection",ISNUMBER(SEARCH("; Knowledge injection; ","; "&F34&"; "))),1,0) -> 0 | W34: =IF(OR(E34="Selection/Rejection",ISNUMBER(SEARCH("; Selection/Rejection; ","; "&F34&"; "))),1,0) -> 0 | X34: =IF(OR(E34="Deliberation",ISNUMBER(SEARCH("; Deliberation; ","; "&F34&"; "))),1,0) -> 0 | Y34: =SUM(Paper2Coding[[#This Row],[Subject-matter correction]:[none]]) -> 1 | Z34: =IF(ISNUMBER(SEARCH("; domain correction; ","; "&H34&"; ")),1,0) -> 0 | AA34: =IF(ISNUMBER(SEARCH("; conceptual discrimination; ","; "&H34&"; ")),1,0) -> 0 | AB34: =IF(ISNUMBER(SEARCH("; evidence judgment; ","; "&H34&"; ")),1,0) -> 1 | AC34: =IF(ISNUMBER(SEARCH("; methodological judgment; ","; "&H34&"; ")),1,0) -> 0 | AD34: =IF(ISNUMBER(SEARCH("; argumentative judgment; ","; "&H34&"; ")),1,0) -> 0 | AE34: =IF(ISNUMBER(SEARCH("; genre/writing expertise; ","; "&H34&"; ")),1,0) -> 0 | AF34: =IF(ISNUMBER(SEARCH("; none; ","; "&H34&"; ")),1,0) -> 0
A35: P2-034 | B35: 34 | C35: Abstract and paper positioning | D35: I want to add this last phrase to my title: Hidden Cost of AI in Software Engineering: Efficiency or Burden? And how to find the right balance? --- is thart a good idea? | E35: Deliberation | F35: Evaluation; Knowledge injection | G35: Deliberative | H35: argumentative judgment; genre/writing expertise | I35: Tests whether adding a balance question improves the title despite the current paper's narrower purpose. | J35: AI recommends keeping balance strategies for the planned follow-up and retaining the narrower title. | K35: p18 L26-p18 L27 | L35: p18 L28-p18 L35 | N35: Visible substantive response | P35: =SUM(Paper2Coding[[#This Row],[Open Delegation]:[Expertise]]) -> 5 | Q35: =IF(OR(E35="Delegation",ISNUMBER(SEARCH("; Delegation; ","; "&F35&"; "))),1,0) -> 0 | R35: =IF(OR(E35="Directed delegation",ISNUMBER(SEARCH("; Directed delegation; ","; "&F35&"; "))),1,0) -> 0 | S35: =IF(OR(E35="Evaluation",ISNUMBER(SEARCH("; Evaluation; ","; "&F35&"; "))),1,0) -> 1 | T35: =IF(OR(E35="Correction/Challenge",ISNUMBER(SEARCH("; Correction/Challenge; ","; "&F35&"; "))),1,0) -> 0 | U35: =IF(OR(E35="Redirection",ISNUMBER(SEARCH("; Redirection; ","; "&F35&"; "))),1,0) -> 0 | V35: =IF(OR(E35="Knowledge injection",ISNUMBER(SEARCH("; Knowledge injection; ","; "&F35&"; "))),1,0) -> 1 | W35: =IF(OR(E35="Selection/Rejection",ISNUMBER(SEARCH("; Selection/Rejection; ","; "&F35&"; "))),1,0) -> 0 | X35: =IF(OR(E35="Deliberation",ISNUMBER(SEARCH("; Deliberation; ","; "&F35&"; "))),1,0) -> 1 | Y35: =SUM(Paper2Coding[[#This Row],[Subject-matter correction]:[none]]) -> 2 | Z35: =IF(ISNUMBER(SEARCH("; domain correction; ","; "&H35&"; ")),1,0) -> 0 | AA35: =IF(ISNUMBER(SEARCH("; conceptual discrimination; ","; "&H35&"; ")),1,0) -> 0 | AB35: =IF(ISNUMBER(SEARCH("; evidence judgment; ","; "&H35&"; ")),1,0) -> 0 | AC35: =IF(ISNUMBER(SEARCH("; methodological judgment; ","; "&H35&"; ")),1,0) -> 0 | AD35: =IF(ISNUMBER(SEARCH("; argumentative judgment; ","; "&H35&"; ")),1,0) -> 1 | AE35: =IF(ISNUMBER(SEARCH("; genre/writing expertise; ","; "&H35&"; ")),1,0) -> 1 | AF35: =IF(ISNUMBER(SEARCH("; none; ","; "&H35&"; ")),1,0) -> 0
A36: P2-035 | B36: 35 | C36: Abstract and paper positioning | D36: was this reallty mentioned in that source: As discussed in SecureFlag’s analysis, this overproduction may reduce clarity and introduce decision fatigue, especially for complex or high-stakes SE tasks ?? | E36: Evaluation | G36: Evaluative | H36: evidence judgment | I36: Questions whether a particular claim really appears in SecureFlag. A verification request is coded Evaluation unless an error is explicitly diagnosed. | J36: AI says the exact wording is absent and attributes overproduction and decision fatigue to synthesis rather than a verbatim source claim. | K36: p18 L36-p18 L37 | L36: p19 L1-p19 L25 | N36: Visible substantive response | P36: =SUM(Paper2Coding[[#This Row],[Open Delegation]:[Expertise]]) -> 2 | Q36: =IF(OR(E36="Delegation",ISNUMBER(SEARCH("; Delegation; ","; "&F36&"; "))),1,0) -> 0 | R36: =IF(OR(E36="Directed delegation",ISNUMBER(SEARCH("; Directed delegation; ","; "&F36&"; "))),1,0) -> 0 | S36: =IF(OR(E36="Evaluation",ISNUMBER(SEARCH("; Evaluation; ","; "&F36&"; "))),1,0) -> 1 | T36: =IF(OR(E36="Correction/Challenge",ISNUMBER(SEARCH("; Correction/Challenge; ","; "&F36&"; "))),1,0) -> 0 | U36: =IF(OR(E36="Redirection",ISNUMBER(SEARCH("; Redirection; ","; "&F36&"; "))),1,0) -> 0 | V36: =IF(OR(E36="Knowledge injection",ISNUMBER(SEARCH("; Knowledge injection; ","; "&F36&"; "))),1,0) -> 0 | W36: =IF(OR(E36="Selection/Rejection",ISNUMBER(SEARCH("; Selection/Rejection; ","; "&F36&"; "))),1,0) -> 0 | X36: =IF(OR(E36="Deliberation",ISNUMBER(SEARCH("; Deliberation; ","; "&F36&"; "))),1,0) -> 0 | Y36: =SUM(Paper2Coding[[#This Row],[Subject-matter correction]:[none]]) -> 1 | Z36: =IF(ISNUMBER(SEARCH("; domain correction; ","; "&H36&"; ")),1,0) -> 0 | AA36: =IF(ISNUMBER(SEARCH("; conceptual discrimination; ","; "&H36&"; ")),1,0) -> 0 | AB36: =IF(ISNUMBER(SEARCH("; evidence judgment; ","; "&H36&"; ")),1,0) -> 1 | AC36: =IF(ISNUMBER(SEARCH("; methodological judgment; ","; "&H36&"; ")),1,0) -> 0 | AD36: =IF(ISNUMBER(SEARCH("; argumentative judgment; ","; "&H36&"; ")),1,0) -> 0 | AE36: =IF(ISNUMBER(SEARCH("; genre/writing expertise; ","; "&H36&"; ")),1,0) -> 0 | AF36: =IF(ISNUMBER(SEARCH("; none; ","; "&H36&"; ")),1,0) -> 0
A37: P2-036 | B37: 36 | C37: Abstract and paper positioning | D37: does this blog post related to my work https://research.google/blog/ai-in-software-engineering-at-google-progress-and-the-path-ahead/? | E37: Evaluation | F37: Knowledge injection | G37: Evaluative | H37: evidence judgment | I37: Supplies a Google Research link and asks about its relevance. | J37: AI assesses it as a contrasting account of benefits and human involvement. The source is not independently checked here. | K37: p19 L26-p19 L26 | L37: p19 L27-p20 L6 | N37: Visible substantive response | P37: =SUM(Paper2Coding[[#This Row],[Open Delegation]:[Expertise]]) -> 3 | Q37: =IF(OR(E37="Delegation",ISNUMBER(SEARCH("; Delegation; ","; "&F37&"; "))),1,0) -> 0 | R37: =IF(OR(E37="Directed delegation",ISNUMBER(SEARCH("; Directed delegation; ","; "&F37&"; "))),1,0) -> 0 | S37: =IF(OR(E37="Evaluation",ISNUMBER(SEARCH("; Evaluation; ","; "&F37&"; "))),1,0) -> 1 | T37: =IF(OR(E37="Correction/Challenge",ISNUMBER(SEARCH("; Correction/Challenge; ","; "&F37&"; "))),1,0) -> 0 | U37: =IF(OR(E37="Redirection",ISNUMBER(SEARCH("; Redirection; ","; "&F37&"; "))),1,0) -> 0 | V37: =IF(OR(E37="Knowledge injection",ISNUMBER(SEARCH("; Knowledge injection; ","; "&F37&"; "))),1,0) -> 1 | W37: =IF(OR(E37="Selection/Rejection",ISNUMBER(SEARCH("; Selection/Rejection; ","; "&F37&"; "))),1,0) -> 0 | X37: =IF(OR(E37="Deliberation",ISNUMBER(SEARCH("; Deliberation; ","; "&F37&"; "))),1,0) -> 0 | Y37: =SUM(Paper2Coding[[#This Row],[Subject-matter correction]:[none]]) -> 1 | Z37: =IF(ISNUMBER(SEARCH("; domain correction; ","; "&H37&"; ")),1,0) -> 0 | AA37: =IF(ISNUMBER(SEARCH("; conceptual discrimination; ","; "&H37&"; ")),1,0) -> 0 | AB37: =IF(ISNUMBER(SEARCH("; evidence judgment; ","; "&H37&"; ")),1,0) -> 1 | AC37: =IF(ISNUMBER(SEARCH("; methodological judgment; ","; "&H37&"; ")),1,0) -> 0 | AD37: =IF(ISNUMBER(SEARCH("; argumentative judgment; ","; "&H37&"; ")),1,0) -> 0 | AE37: =IF(ISNUMBER(SEARCH("; genre/writing expertise; ","; "&H37&"; ")),1,0) -> 0 | AF37: =IF(ISNUMBER(SEARCH("; none; ","; "&H37&"; ")),1,0) -> 0
A38: P2-037 | B38: 37 | C38: Conceptual structure | D38: never mind this. back to our paper: I think in our paper, we need to differentiative for AI support in IDE, like code completion as one writes code, vs chat-based AI tools, like GPT. | E38: Knowledge injection | F38: Redirection; Directed delegation | G38: Directive | H38: conceptual discrimination; argumentative judgment | I38: Introduces a distinction between IDE completion and chat-based tools and returns the discussion to the current paper. | J38: AI agrees to distinguish the tool classes and describes implications for oversight. | K38: p20 L7-p20 L8 | L38: p20 L9-p20 L11 | N38: Visible substantive response | P38: =SUM(Paper2Coding[[#This Row],[Open Delegation]:[Expertise]]) -> 5 | Q38: =IF(OR(E38="Delegation",ISNUMBER(SEARCH("; Delegation; ","; "&F38&"; "))),1,0) -> 0 | R38: =IF(OR(E38="Directed delegation",ISNUMBER(SEARCH("; Directed delegation; ","; "&F38&"; "))),1,0) -> 1 | S38: =IF(OR(E38="Evaluation",ISNUMBER(SEARCH("; Evaluation; ","; "&F38&"; "))),1,0) -> 0 | T38: =IF(OR(E38="Correction/Challenge",ISNUMBER(SEARCH("; Correction/Challenge; ","; "&F38&"; "))),1,0) -> 0 | U38: =IF(OR(E38="Redirection",ISNUMBER(SEARCH("; Redirection; ","; "&F38&"; "))),1,0) -> 1 | V38: =IF(OR(E38="Knowledge injection",ISNUMBER(SEARCH("; Knowledge injection; ","; "&F38&"; "))),1,0) -> 1 | W38: =IF(OR(E38="Selection/Rejection",ISNUMBER(SEARCH("; Selection/Rejection; ","; "&F38&"; "))),1,0) -> 0 | X38: =IF(OR(E38="Deliberation",ISNUMBER(SEARCH("; Deliberation; ","; "&F38&"; "))),1,0) -> 0 | Y38: =SUM(Paper2Coding[[#This Row],[Subject-matter correction]:[none]]) -> 2 | Z38: =IF(ISNUMBER(SEARCH("; domain correction; ","; "&H38&"; ")),1,0) -> 0 | AA38: =IF(ISNUMBER(SEARCH("; conceptual discrimination; ","; "&H38&"; ")),1,0) -> 1 | AB38: =IF(ISNUMBER(SEARCH("; evidence judgment; ","; "&H38&"; ")),1,0) -> 0 | AC38: =IF(ISNUMBER(SEARCH("; methodological judgment; ","; "&H38&"; ")),1,0) -> 0 | AD38: =IF(ISNUMBER(SEARCH("; argumentative judgment; ","; "&H38&"; ")),1,0) -> 1 | AE38: =IF(ISNUMBER(SEARCH("; genre/writing expertise; ","; "&H38&"; ")),1,0) -> 0 | AF38: =IF(ISNUMBER(SEARCH("; none; ","; "&H38&"; ")),1,0) -> 0
A39: P2-038 | B39: 38 | C39: Conceptual structure | D39: elabroate why this differentiation is important | E39: Deliberation | F39: Directed delegation | G39: Deliberative | H39: conceptual discrimination; argumentative judgment | I39: Requests reasoned explanation of why the two tool classes need distinguishing, developing a comparative conceptual argument. | J39: AI elaborates differences in interaction, context and cognitive burden. | K39: p20 L12-p20 L12 | L39: p20 L13-p21 L3 | N39: Visible substantive response | O39: Comparative elaboration coded Deliberation; borderline with Directed delegation | P39: =SUM(Paper2Coding[[#This Row],[Open Delegation]:[Expertise]]) -> 4 | Q39: =IF(OR(E39="Delegation",ISNUMBER(SEARCH("; Delegation; ","; "&F39&"; "))),1,0) -> 0 | R39: =IF(OR(E39="Directed delegation",ISNUMBER(SEARCH("; Directed delegation; ","; "&F39&"; "))),1,0) -> 1 | S39: =IF(OR(E39="Evaluation",ISNUMBER(SEARCH("; Evaluation; ","; "&F39&"; "))),1,0) -> 0 | T39: =IF(OR(E39="Correction/Challenge",ISNUMBER(SEARCH("; Correction/Challenge; ","; "&F39&"; "))),1,0) -> 0 | U39: =IF(OR(E39="Redirection",ISNUMBER(SEARCH("; Redirection; ","; "&F39&"; "))),1,0) -> 0 | V39: =IF(OR(E39="Knowledge injection",ISNUMBER(SEARCH("; Knowledge injection; ","; "&F39&"; "))),1,0) -> 0 | W39: =IF(OR(E39="Selection/Rejection",ISNUMBER(SEARCH("; Selection/Rejection; ","; "&F39&"; "))),1,0) -> 0 | X39: =IF(OR(E39="Deliberation",ISNUMBER(SEARCH("; Deliberation; ","; "&F39&"; "))),1,0) -> 1 | Y39: =SUM(Paper2Coding[[#This Row],[Subject-matter correction]:[none]]) -> 2 | Z39: =IF(ISNUMBER(SEARCH("; domain correction; ","; "&H39&"; ")),1,0) -> 0 | AA39: =IF(ISNUMBER(SEARCH("; conceptual discrimination; ","; "&H39&"; ")),1,0) -> 1 | AB39: =IF(ISNUMBER(SEARCH("; evidence judgment; ","; "&H39&"; ")),1,0) -> 0 | AC39: =IF(ISNUMBER(SEARCH("; methodological judgment; ","; "&H39&"; ")),1,0) -> 0 | AD39: =IF(ISNUMBER(SEARCH("; argumentative judgment; ","; "&H39&"; ")),1,0) -> 1 | AE39: =IF(ISNUMBER(SEARCH("; genre/writing expertise; ","; "&H39&"; ")),1,0) -> 0 | AF39: =IF(ISNUMBER(SEARCH("; none; ","; "&H39&"; ")),1,0) -> 0
A40: P2-039 | B40: 39 | C40: Conceptual structure | D40: sure, generate sec 2 | E40: Directed delegation | F40: Selection/Rejection | G40: Directive | H40: none | I40: Approves drafting the previously discussed Section 2, inheriting that contextual scope. | J40: AI drafts a section comparing inline and chat-based assistance. | K40: p21 L4-p21 L4 | L40: p21 L5-p21 L40 | N40: Visible substantive response | P40: =SUM(Paper2Coding[[#This Row],[Open Delegation]:[Expertise]]) -> 3 | Q40: =IF(OR(E40="Delegation",ISNUMBER(SEARCH("; Delegation; ","; "&F40&"; "))),1,0) -> 0 | R40: =IF(OR(E40="Directed delegation",ISNUMBER(SEARCH("; Directed delegation; ","; "&F40&"; "))),1,0) -> 1 | S40: =IF(OR(E40="Evaluation",ISNUMBER(SEARCH("; Evaluation; ","; "&F40&"; "))),1,0) -> 0 | T40: =IF(OR(E40="Correction/Challenge",ISNUMBER(SEARCH("; Correction/Challenge; ","; "&F40&"; "))),1,0) -> 0 | U40: =IF(OR(E40="Redirection",ISNUMBER(SEARCH("; Redirection; ","; "&F40&"; "))),1,0) -> 0 | V40: =IF(OR(E40="Knowledge injection",ISNUMBER(SEARCH("; Knowledge injection; ","; "&F40&"; "))),1,0) -> 0 | W40: =IF(OR(E40="Selection/Rejection",ISNUMBER(SEARCH("; Selection/Rejection; ","; "&F40&"; "))),1,0) -> 1 | X40: =IF(OR(E40="Deliberation",ISNUMBER(SEARCH("; Deliberation; ","; "&F40&"; "))),1,0) -> 0 | Y40: =SUM(Paper2Coding[[#This Row],[Subject-matter correction]:[none]]) -> 1 | Z40: =IF(ISNUMBER(SEARCH("; domain correction; ","; "&H40&"; ")),1,0) -> 0 | AA40: =IF(ISNUMBER(SEARCH("; conceptual discrimination; ","; "&H40&"; ")),1,0) -> 0 | AB40: =IF(ISNUMBER(SEARCH("; evidence judgment; ","; "&H40&"; ")),1,0) -> 0 | AC40: =IF(ISNUMBER(SEARCH("; methodological judgment; ","; "&H40&"; ")),1,0) -> 0 | AD40: =IF(ISNUMBER(SEARCH("; argumentative judgment; ","; "&H40&"; ")),1,0) -> 0 | AE40: =IF(ISNUMBER(SEARCH("; genre/writing expertise; ","; "&H40&"; ")),1,0) -> 0 | AF40: =IF(ISNUMBER(SEARCH("; none; ","; "&H40&"; ")),1,0) -> 1
A41: P2-040 | B41: 40 | C41: Conceptual structure | D41: I found a 9th good resource: https://www.linkedin.com/pulse/reality-ai-assisted-coding-why-vibe-more-challenging-than-frank-wang-qszkc/ - review and use it for our paper. among other interesting issues, it discusses information (cognitive) overload | E41: Knowledge injection | F41: Directed delegation; Selection/Rejection | G41: Directive | H41: evidence judgment | I41: Adds a ninth source and identifies cognitive overload as its intended evidential contribution. | J41: AI acknowledges the selected source and intended integration. | K41: p21 L41-p22 L1 | L41: p22 L2-p22 L4 | N41: Visible substantive response | P41: =SUM(Paper2Coding[[#This Row],[Open Delegation]:[Expertise]]) -> 4 | Q41: =IF(OR(E41="Delegation",ISNUMBER(SEARCH("; Delegation; ","; "&F41&"; "))),1,0) -> 0 | R41: =IF(OR(E41="Directed delegation",ISNUMBER(SEARCH("; Directed delegation; ","; "&F41&"; "))),1,0) -> 1 | S41: =IF(OR(E41="Evaluation",ISNUMBER(SEARCH("; Evaluation; ","; "&F41&"; "))),1,0) -> 0 | T41: =IF(OR(E41="Correction/Challenge",ISNUMBER(SEARCH("; Correction/Challenge; ","; "&F41&"; "))),1,0) -> 0 | U41: =IF(OR(E41="Redirection",ISNUMBER(SEARCH("; Redirection; ","; "&F41&"; "))),1,0) -> 0 | V41: =IF(OR(E41="Knowledge injection",ISNUMBER(SEARCH("; Knowledge injection; ","; "&F41&"; "))),1,0) -> 1 | W41: =IF(OR(E41="Selection/Rejection",ISNUMBER(SEARCH("; Selection/Rejection; ","; "&F41&"; "))),1,0) -> 1 | X41: =IF(OR(E41="Deliberation",ISNUMBER(SEARCH("; Deliberation; ","; "&F41&"; "))),1,0) -> 0 | Y41: =SUM(Paper2Coding[[#This Row],[Subject-matter correction]:[none]]) -> 1 | Z41: =IF(ISNUMBER(SEARCH("; domain correction; ","; "&H41&"; ")),1,0) -> 0 | AA41: =IF(ISNUMBER(SEARCH("; conceptual discrimination; ","; "&H41&"; ")),1,0) -> 0 | AB41: =IF(ISNUMBER(SEARCH("; evidence judgment; ","; "&H41&"; ")),1,0) -> 1 | AC41: =IF(ISNUMBER(SEARCH("; methodological judgment; ","; "&H41&"; ")),1,0) -> 0 | AD41: =IF(ISNUMBER(SEARCH("; argumentative judgment; ","; "&H41&"; ")),1,0) -> 0 | AE41: =IF(ISNUMBER(SEARCH("; genre/writing expertise; ","; "&H41&"; ")),1,0) -> 0 | AF41: =IF(ISNUMBER(SEARCH("; none; ","; "&H41&"; ")),1,0) -> 0
A42: P2-041 | B42: 41 | C42: Conceptual structure | D42: and I found the 10th good resource: https://pmc.ncbi.nlm.nih.gov/articles/PMC12191316/ - review and use it for our paper. among other interesting issues, it discusses information (cognitive) overload | E42: Knowledge injection | F42: Directed delegation; Selection/Rejection | G42: Directive | H42: evidence judgment | I42: Adds a tenth source and identifies its relevance to cognitive overload. | J42: AI acknowledges the new source and intended integration. | K42: p22 L5-p22 L6 | L42: p22 L7-p22 L8 | N42: Visible substantive response | P42: =SUM(Paper2Coding[[#This Row],[Open Delegation]:[Expertise]]) -> 4 | Q42: =IF(OR(E42="Delegation",ISNUMBER(SEARCH("; Delegation; ","; "&F42&"; "))),1,0) -> 0 | R42: =IF(OR(E42="Directed delegation",ISNUMBER(SEARCH("; Directed delegation; ","; "&F42&"; "))),1,0) -> 1 | S42: =IF(OR(E42="Evaluation",ISNUMBER(SEARCH("; Evaluation; ","; "&F42&"; "))),1,0) -> 0 | T42: =IF(OR(E42="Correction/Challenge",ISNUMBER(SEARCH("; Correction/Challenge; ","; "&F42&"; "))),1,0) -> 0 | U42: =IF(OR(E42="Redirection",ISNUMBER(SEARCH("; Redirection; ","; "&F42&"; "))),1,0) -> 0 | V42: =IF(OR(E42="Knowledge injection",ISNUMBER(SEARCH("; Knowledge injection; ","; "&F42&"; "))),1,0) -> 1 | W42: =IF(OR(E42="Selection/Rejection",ISNUMBER(SEARCH("; Selection/Rejection; ","; "&F42&"; "))),1,0) -> 1 | X42: =IF(OR(E42="Deliberation",ISNUMBER(SEARCH("; Deliberation; ","; "&F42&"; "))),1,0) -> 0 | Y42: =SUM(Paper2Coding[[#This Row],[Subject-matter correction]:[none]]) -> 1 | Z42: =IF(ISNUMBER(SEARCH("; domain correction; ","; "&H42&"; ")),1,0) -> 0 | AA42: =IF(ISNUMBER(SEARCH("; conceptual discrimination; ","; "&H42&"; ")),1,0) -> 0 | AB42: =IF(ISNUMBER(SEARCH("; evidence judgment; ","; "&H42&"; ")),1,0) -> 1 | AC42: =IF(ISNUMBER(SEARCH("; methodological judgment; ","; "&H42&"; ")),1,0) -> 0 | AD42: =IF(ISNUMBER(SEARCH("; argumentative judgment; ","; "&H42&"; ")),1,0) -> 0 | AE42: =IF(ISNUMBER(SEARCH("; genre/writing expertise; ","; "&H42&"; ")),1,0) -> 0 | AF42: =IF(ISNUMBER(SEARCH("; none; ","; "&H42&"; ")),1,0) -> 0
A43: P2-042 | B43: 42 | C43: Conceptual structure | D43: I merged them into two ... human oversight effort ... detecting and fixing defects ... information and cognitive overload ... is that a good idea? | E43: Deliberation | F43: Evaluation; Knowledge injection; Redirection | G43: Deliberative | H43: conceptual discrimination; methodological judgment; argumentative judgment | I43: Proposes merging error correction into oversight, comparing a three-category and two-category structure to avoid overlap. | J43: AI endorses the merge and reformulates two cost categories. | K43: p22 L9-p22 L15 | L43: p22 L17-p22 L24 | N43: Visible substantive response | P43: =SUM(Paper2Coding[[#This Row],[Open Delegation]:[Expertise]]) -> 7 | Q43: =IF(OR(E43="Delegation",ISNUMBER(SEARCH("; Delegation; ","; "&F43&"; "))),1,0) -> 0 | R43: =IF(OR(E43="Directed delegation",ISNUMBER(SEARCH("; Directed delegation; ","; "&F43&"; "))),1,0) -> 0 | S43: =IF(OR(E43="Evaluation",ISNUMBER(SEARCH("; Evaluation; ","; "&F43&"; "))),1,0) -> 1 | T43: =IF(OR(E43="Correction/Challenge",ISNUMBER(SEARCH("; Correction/Challenge; ","; "&F43&"; "))),1,0) -> 0 | U43: =IF(OR(E43="Redirection",ISNUMBER(SEARCH("; Redirection; ","; "&F43&"; "))),1,0) -> 1 | V43: =IF(OR(E43="Knowledge injection",ISNUMBER(SEARCH("; Knowledge injection; ","; "&F43&"; "))),1,0) -> 1 | W43: =IF(OR(E43="Selection/Rejection",ISNUMBER(SEARCH("; Selection/Rejection; ","; "&F43&"; "))),1,0) -> 0 | X43: =IF(OR(E43="Deliberation",ISNUMBER(SEARCH("; Deliberation; ","; "&F43&"; "))),1,0) -> 1 | Y43: =SUM(Paper2Coding[[#This Row],[Subject-matter correction]:[none]]) -> 3 | Z43: =IF(ISNUMBER(SEARCH("; domain correction; ","; "&H43&"; ")),1,0) -> 0 | AA43: =IF(ISNUMBER(SEARCH("; conceptual discrimination; ","; "&H43&"; ")),1,0) -> 1 | AB43: =IF(ISNUMBER(SEARCH("; evidence judgment; ","; "&H43&"; ")),1,0) -> 0 | AC43: =IF(ISNUMBER(SEARCH("; methodological judgment; ","; "&H43&"; ")),1,0) -> 1 | AD43: =IF(ISNUMBER(SEARCH("; argumentative judgment; ","; "&H43&"; ")),1,0) -> 1 | AE43: =IF(ISNUMBER(SEARCH("; genre/writing expertise; ","; "&H43&"; ")),1,0) -> 0 | AF43: =IF(ISNUMBER(SEARCH("; none; ","; "&H43&"; ")),1,0) -> 0
A44: P2-043 | B44: 43 | C44: Conceptual structure | D44: generate a short para about that differentiation for end of sec 1 | E44: Directed delegation | G44: Directive | H44: genre/writing expertise; argumentative judgment | I44: Specifies a short bridging paragraph about the tool distinction at the end of Section 1. | J44: AI drafts the bridge and points ahead to Section 2. | K44: p22 L25-p22 L25 | L44: p22 L26-p22 L30 | N44: Visible substantive response | P44: =SUM(Paper2Coding[[#This Row],[Open Delegation]:[Expertise]]) -> 3 | Q44: =IF(OR(E44="Delegation",ISNUMBER(SEARCH("; Delegation; ","; "&F44&"; "))),1,0) -> 0 | R44: =IF(OR(E44="Directed delegation",ISNUMBER(SEARCH("; Directed delegation; ","; "&F44&"; "))),1,0) -> 1 | S44: =IF(OR(E44="Evaluation",ISNUMBER(SEARCH("; Evaluation; ","; "&F44&"; "))),1,0) -> 0 | T44: =IF(OR(E44="Correction/Challenge",ISNUMBER(SEARCH("; Correction/Challenge; ","; "&F44&"; "))),1,0) -> 0 | U44: =IF(OR(E44="Redirection",ISNUMBER(SEARCH("; Redirection; ","; "&F44&"; "))),1,0) -> 0 | V44: =IF(OR(E44="Knowledge injection",ISNUMBER(SEARCH("; Knowledge injection; ","; "&F44&"; "))),1,0) -> 0 | W44: =IF(OR(E44="Selection/Rejection",ISNUMBER(SEARCH("; Selection/Rejection; ","; "&F44&"; "))),1,0) -> 0 | X44: =IF(OR(E44="Deliberation",ISNUMBER(SEARCH("; Deliberation; ","; "&F44&"; "))),1,0) -> 0 | Y44: =SUM(Paper2Coding[[#This Row],[Subject-matter correction]:[none]]) -> 2 | Z44: =IF(ISNUMBER(SEARCH("; domain correction; ","; "&H44&"; ")),1,0) -> 0 | AA44: =IF(ISNUMBER(SEARCH("; conceptual discrimination; ","; "&H44&"; ")),1,0) -> 0 | AB44: =IF(ISNUMBER(SEARCH("; evidence judgment; ","; "&H44&"; ")),1,0) -> 0 | AC44: =IF(ISNUMBER(SEARCH("; methodological judgment; ","; "&H44&"; ")),1,0) -> 0 | AD44: =IF(ISNUMBER(SEARCH("; argumentative judgment; ","; "&H44&"; ")),1,0) -> 1 | AE44: =IF(ISNUMBER(SEARCH("; genre/writing expertise; ","; "&H44&"; ")),1,0) -> 1 | AF44: =IF(ISNUMBER(SEARCH("; none; ","; "&H44&"; ")),1,0) -> 0
A45: P2-044 | B45: 44 | C45: Conceptual structure | D45: I changed it to "..,, This distinction is discussed further in the following sections to clarify how each tool class contributes differently to human oversight burden and cognitive overload." ,, also, I wanrt to use this structure. geneerate sec 2 text | E45: Directed delegation | F45: Selection/Rejection; Knowledge injection | G45: Directive | H45: genre/writing expertise; argumentative judgment | I45: Reports a revised bridge, selects a structure and delegates Section 2 drafting within it. | J45: AI drafts The Oversight Burden, reflecting a changed Section 2 role. | K45: p22 L31-p22 L32 | L45: p22 L33-p23 L26 | N45: Visible substantive response | P45: =SUM(Paper2Coding[[#This Row],[Open Delegation]:[Expertise]]) -> 5 | Q45: =IF(OR(E45="Delegation",ISNUMBER(SEARCH("; Delegation; ","; "&F45&"; "))),1,0) -> 0 | R45: =IF(OR(E45="Directed delegation",ISNUMBER(SEARCH("; Directed delegation; ","; "&F45&"; "))),1,0) -> 1 | S45: =IF(OR(E45="Evaluation",ISNUMBER(SEARCH("; Evaluation; ","; "&F45&"; "))),1,0) -> 0 | T45: =IF(OR(E45="Correction/Challenge",ISNUMBER(SEARCH("; Correction/Challenge; ","; "&F45&"; "))),1,0) -> 0 | U45: =IF(OR(E45="Redirection",ISNUMBER(SEARCH("; Redirection; ","; "&F45&"; "))),1,0) -> 0 | V45: =IF(OR(E45="Knowledge injection",ISNUMBER(SEARCH("; Knowledge injection; ","; "&F45&"; "))),1,0) -> 1 | W45: =IF(OR(E45="Selection/Rejection",ISNUMBER(SEARCH("; Selection/Rejection; ","; "&F45&"; "))),1,0) -> 1 | X45: =IF(OR(E45="Deliberation",ISNUMBER(SEARCH("; Deliberation; ","; "&F45&"; "))),1,0) -> 0 | Y45: =SUM(Paper2Coding[[#This Row],[Subject-matter correction]:[none]]) -> 2 | Z45: =IF(ISNUMBER(SEARCH("; domain correction; ","; "&H45&"; ")),1,0) -> 0 | AA45: =IF(ISNUMBER(SEARCH("; conceptual discrimination; ","; "&H45&"; ")),1,0) -> 0 | AB45: =IF(ISNUMBER(SEARCH("; evidence judgment; ","; "&H45&"; ")),1,0) -> 0 | AC45: =IF(ISNUMBER(SEARCH("; methodological judgment; ","; "&H45&"; ")),1,0) -> 0 | AD45: =IF(ISNUMBER(SEARCH("; argumentative judgment; ","; "&H45&"; ")),1,0) -> 1 | AE45: =IF(ISNUMBER(SEARCH("; genre/writing expertise; ","; "&H45&"; ")),1,0) -> 1 | AF45: =IF(ISNUMBER(SEARCH("; none; ","; "&H45&"; ")),1,0) -> 0
A46: P2-045 | B46: 45 | C46: Supplement and section drafting | D46: let's resume work on this paper. latest draft is attached. first space constraints: Length: each figure = 250 words max 2500 words (including figures) We have two figures, thus 500 words --> Max text Length = 2000 words -------------- we will have a Supplementary material (doc... | E46: Directed delegation | F46: Knowledge injection | G46: Directive | H46: genre/writing expertise | I46: Updates the length limit to 2500 words including figures, leaving 2000 text words, and allocates extra material to a supplement. | J46: No substantive assistant response is visible before the next human turn. | K46: p23 L29-p23 L34 | M46: Hidden Cost of AI-assisted SE-IEEE SW.docx | N46: No substantive response visible | O46: Export gap: no assistant outcome can be inferred | P46: =SUM(Paper2Coding[[#This Row],[Open Delegation]:[Expertise]]) -> 3 | Q46: =IF(OR(E46="Delegation",ISNUMBER(SEARCH("; Delegation; ","; "&F46&"; "))),1,0) -> 0 | R46: =IF(OR(E46="Directed delegation",ISNUMBER(SEARCH("; Directed delegation; ","; "&F46&"; "))),1,0) -> 1 | S46: =IF(OR(E46="Evaluation",ISNUMBER(SEARCH("; Evaluation; ","; "&F46&"; "))),1,0) -> 0 | T46: =IF(OR(E46="Correction/Challenge",ISNUMBER(SEARCH("; Correction/Challenge; ","; "&F46&"; "))),1,0) -> 0 | U46: =IF(OR(E46="Redirection",ISNUMBER(SEARCH("; Redirection; ","; "&F46&"; "))),1,0) -> 0 | V46: =IF(OR(E46="Knowledge injection",ISNUMBER(SEARCH("; Knowledge injection; ","; "&F46&"; "))),1,0) -> 1 | W46: =IF(OR(E46="Selection/Rejection",ISNUMBER(SEARCH("; Selection/Rejection; ","; "&F46&"; "))),1,0) -> 0 | X46: =IF(OR(E46="Deliberation",ISNUMBER(SEARCH("; Deliberation; ","; "&F46&"; "))),1,0) -> 0 | Y46: =SUM(Paper2Coding[[#This Row],[Subject-matter correction]:[none]]) -> 1 | Z46: =IF(ISNUMBER(SEARCH("; domain correction; ","; "&H46&"; ")),1,0) -> 0 | AA46: =IF(ISNUMBER(SEARCH("; conceptual discrimination; ","; "&H46&"; ")),1,0) -> 0 | AB46: =IF(ISNUMBER(SEARCH("; evidence judgment; ","; "&H46&"; ")),1,0) -> 0 | AC46: =IF(ISNUMBER(SEARCH("; methodological judgment; ","; "&H46&"; ")),1,0) -> 0 | AD46: =IF(ISNUMBER(SEARCH("; argumentative judgment; ","; "&H46&"; ")),1,0) -> 0 | AE46: =IF(ISNUMBER(SEARCH("; genre/writing expertise; ","; "&H46&"; ")),1,0) -> 1 | AF46: =IF(ISNUMBER(SEARCH("; none; ","; "&H46&"; ")),1,0) -> 0
A47: P2-046 | B47: 46 | C47: Supplement and section drafting | D47: We will have two parts ... Rapid Review ... Field Observations ... Türkiye (5 engineers) ... Azerbaijan (2 engineers) ... gather some metrics ... prepare the Supplementary material doc first | E47: Directed delegation | F47: Knowledge injection | G47: Directive | H47: methodological judgment; evidence judgment | I47: Defines supplementary sections, fixes a ten-source pool and proposes quantitative field observations involving five and two engineers in two companies. | J47: No substantive assistant response is visible. This is a proposed observation plan, not evidence that observations were conducted. | K47: p23 L38-p24 L4 | M47: Supplementary material (document).docx | N47: No substantive response visible | O47: Export gap: no assistant outcome can be inferred; Planned observations; no completed data collection inferred | P47: =SUM(Paper2Coding[[#This Row],[Open Delegation]:[Expertise]]) -> 4 | Q47: =IF(OR(E47="Delegation",ISNUMBER(SEARCH("; Delegation; ","; "&F47&"; "))),1,0) -> 0 | R47: =IF(OR(E47="Directed delegation",ISNUMBER(SEARCH("; Directed delegation; ","; "&F47&"; "))),1,0) -> 1 | S47: =IF(OR(E47="Evaluation",ISNUMBER(SEARCH("; Evaluation; ","; "&F47&"; "))),1,0) -> 0 | T47: =IF(OR(E47="Correction/Challenge",ISNUMBER(SEARCH("; Correction/Challenge; ","; "&F47&"; "))),1,0) -> 0 | U47: =IF(OR(E47="Redirection",ISNUMBER(SEARCH("; Redirection; ","; "&F47&"; "))),1,0) -> 0 | V47: =IF(OR(E47="Knowledge injection",ISNUMBER(SEARCH("; Knowledge injection; ","; "&F47&"; "))),1,0) -> 1 | W47: =IF(OR(E47="Selection/Rejection",ISNUMBER(SEARCH("; Selection/Rejection; ","; "&F47&"; "))),1,0) -> 0 | X47: =IF(OR(E47="Deliberation",ISNUMBER(SEARCH("; Deliberation; ","; "&F47&"; "))),1,0) -> 0 | Y47: =SUM(Paper2Coding[[#This Row],[Subject-matter correction]:[none]]) -> 2 | Z47: =IF(ISNUMBER(SEARCH("; domain correction; ","; "&H47&"; ")),1,0) -> 0 | AA47: =IF(ISNUMBER(SEARCH("; conceptual discrimination; ","; "&H47&"; ")),1,0) -> 0 | AB47: =IF(ISNUMBER(SEARCH("; evidence judgment; ","; "&H47&"; ")),1,0) -> 1 | AC47: =IF(ISNUMBER(SEARCH("; methodological judgment; ","; "&H47&"; ")),1,0) -> 1 | AD47: =IF(ISNUMBER(SEARCH("; argumentative judgment; ","; "&H47&"; ")),1,0) -> 0 | AE47: =IF(ISNUMBER(SEARCH("; genre/writing expertise; ","; "&H47&"; ")),1,0) -> 0 | AF47: =IF(ISNUMBER(SEARCH("; none; ","; "&H47&"; ")),1,0) -> 0
A48: P2-047 | B48: 47 | C48: Supplement and section drafting | D48: latest draft of the Supplementary material (document) is attached. review sec 1-A Review of the Relevant Grey Literature | E48: Evaluation | F48: Knowledge injection | G48: Evaluative | H48: none | I48: Provides a supplementary draft for review of its literature-review section; attachment provision alone does not prove expertise. | J48: No substantive assistant response is visible before the next human turn. | K48: p24 L8-p24 L8 | M48: Supplementary material (document).docx | N48: No substantive response visible | O48: Export gap: no assistant outcome can be inferred | P48: =SUM(Paper2Coding[[#This Row],[Open Delegation]:[Expertise]]) -> 3 | Q48: =IF(OR(E48="Delegation",ISNUMBER(SEARCH("; Delegation; ","; "&F48&"; "))),1,0) -> 0 | R48: =IF(OR(E48="Directed delegation",ISNUMBER(SEARCH("; Directed delegation; ","; "&F48&"; "))),1,0) -> 0 | S48: =IF(OR(E48="Evaluation",ISNUMBER(SEARCH("; Evaluation; ","; "&F48&"; "))),1,0) -> 1 | T48: =IF(OR(E48="Correction/Challenge",ISNUMBER(SEARCH("; Correction/Challenge; ","; "&F48&"; "))),1,0) -> 0 | U48: =IF(OR(E48="Redirection",ISNUMBER(SEARCH("; Redirection; ","; "&F48&"; "))),1,0) -> 0 | V48: =IF(OR(E48="Knowledge injection",ISNUMBER(SEARCH("; Knowledge injection; ","; "&F48&"; "))),1,0) -> 1 | W48: =IF(OR(E48="Selection/Rejection",ISNUMBER(SEARCH("; Selection/Rejection; ","; "&F48&"; "))),1,0) -> 0 | X48: =IF(OR(E48="Deliberation",ISNUMBER(SEARCH("; Deliberation; ","; "&F48&"; "))),1,0) -> 0 | Y48: =SUM(Paper2Coding[[#This Row],[Subject-matter correction]:[none]]) -> 1 | Z48: =IF(ISNUMBER(SEARCH("; domain correction; ","; "&H48&"; ")),1,0) -> 0 | AA48: =IF(ISNUMBER(SEARCH("; conceptual discrimination; ","; "&H48&"; ")),1,0) -> 0 | AB48: =IF(ISNUMBER(SEARCH("; evidence judgment; ","; "&H48&"; ")),1,0) -> 0 | AC48: =IF(ISNUMBER(SEARCH("; methodological judgment; ","; "&H48&"; ")),1,0) -> 0 | AD48: =IF(ISNUMBER(SEARCH("; argumentative judgment; ","; "&H48&"; ")),1,0) -> 0 | AE48: =IF(ISNUMBER(SEARCH("; genre/writing expertise; ","; "&H48&"; ")),1,0) -> 0 | AF48: =IF(ISNUMBER(SEARCH("; none; ","; "&H48&"; ")),1,0) -> 1
A49: P2-048 | B49: 48 | C49: Supplement and section drafting | D49: redo the Rapid Review synthesis . I have attached all the 10 sources for you, so you can carefully review and synthesize them. important: only synthesize these points, since only they are our focus in this work: Need for and cost of human oversight, Cognitive overload of AI, a... | E49: Directed delegation | F49: Knowledge injection; Redirection | G49: Directive | H49: evidence judgment; methodological judgment | I49: Supplies ten PDFs and confines synthesis to specified burden categories, conditional on actual source coverage. | J49: No substantive assistant response is visible. The instruction is not proof that a source-grounded synthesis was completed. | K49: p24 L27-p24 L29 | L49: p24 L31-p24 L31 | M49: 10-The neurophysiological paradox of AI-induced frustration.pdf 1-AI in software development-Productivity gains, but at what cost.pdf 2-AI is shifting engineering burden and bottlenecks from code authors to code reviewers.pdf 3-The risks of generative AI coding in software development.pdf 4-SWE-Bench+ Enhanced coding benchmark for LLMs.pdf 5-The Hidden Cost of AI Software Engineers-Why LLMs Are a Financial Black Hole.pdf 6-The Hidden Cost of AI Code Assistants.pdf 7-The Hidden Cost Of Code And Generative AI.pdf 8-Generative AI is not going to build your engineering team for you.pdf 9-The Reality of AI-Assisted Coding Why Vibe Coding Is More Challenging Than It.pdf | N49: No substantive response visible | O49: Export gap: no assistant outcome can be inferred | P49: =SUM(Paper2Coding[[#This Row],[Open Delegation]:[Expertise]]) -> 5 | Q49: =IF(OR(E49="Delegation",ISNUMBER(SEARCH("; Delegation; ","; "&F49&"; "))),1,0) -> 0 | R49: =IF(OR(E49="Directed delegation",ISNUMBER(SEARCH("; Directed delegation; ","; "&F49&"; "))),1,0) -> 1 | S49: =IF(OR(E49="Evaluation",ISNUMBER(SEARCH("; Evaluation; ","; "&F49&"; "))),1,0) -> 0 | T49: =IF(OR(E49="Correction/Challenge",ISNUMBER(SEARCH("; Correction/Challenge; ","; "&F49&"; "))),1,0) -> 0 | U49: =IF(OR(E49="Redirection",ISNUMBER(SEARCH("; Redirection; ","; "&F49&"; "))),1,0) -> 1 | V49: =IF(OR(E49="Knowledge injection",ISNUMBER(SEARCH("; Knowledge injection; ","; "&F49&"; "))),1,0) -> 1 | W49: =IF(OR(E49="Selection/Rejection",ISNUMBER(SEARCH("; Selection/Rejection; ","; "&F49&"; "))),1,0) -> 0 | X49: =IF(OR(E49="Deliberation",ISNUMBER(SEARCH("; Deliberation; ","; "&F49&"; "))),1,0) -> 0 | Y49: =SUM(Paper2Coding[[#This Row],[Subject-matter correction]:[none]]) -> 2 | Z49: =IF(ISNUMBER(SEARCH("; domain correction; ","; "&H49&"; ")),1,0) -> 0 | AA49: =IF(ISNUMBER(SEARCH("; conceptual discrimination; ","; "&H49&"; ")),1,0) -> 0 | AB49: =IF(ISNUMBER(SEARCH("; evidence judgment; ","; "&H49&"; ")),1,0) -> 1 | AC49: =IF(ISNUMBER(SEARCH("; methodological judgment; ","; "&H49&"; ")),1,0) -> 1 | AD49: =IF(ISNUMBER(SEARCH("; argumentative judgment; ","; "&H49&"; ")),1,0) -> 0 | AE49: =IF(ISNUMBER(SEARCH("; genre/writing expertise; ","; "&H49&"; ")),1,0) -> 0 | AF49: =IF(ISNUMBER(SEARCH("; none; ","; "&H49&"; ")),1,0) -> 0
A50: P2-049 | B50: 49 | C50: Supplement and section drafting | D50: I consider Supplementary Material (Document) done, see attached. it is short to the point. no need to put the synthesis in it, as we will discuss in the paper itself | E50: Selection/Rejection | F50: Redirection; Knowledge injection | G50: Directive | H50: genre/writing expertise; argumentative judgment | I50: Declares the supplement sufficient and excludes synthesis from it because synthesis belongs in the main paper. | J50: No substantive assistant response is visible; completion is explicitly the human's local decision. | K50: p24 L34-p24 L35 | M50: Supplementary material (document).docx | N50: No substantive response visible | O50: Export gap: no assistant outcome can be inferred | P50: =SUM(Paper2Coding[[#This Row],[Open Delegation]:[Expertise]]) -> 5 | Q50: =IF(OR(E50="Delegation",ISNUMBER(SEARCH("; Delegation; ","; "&F50&"; "))),1,0) -> 0 | R50: =IF(OR(E50="Directed delegation",ISNUMBER(SEARCH("; Directed delegation; ","; "&F50&"; "))),1,0) -> 0 | S50: =IF(OR(E50="Evaluation",ISNUMBER(SEARCH("; Evaluation; ","; "&F50&"; "))),1,0) -> 0 | T50: =IF(OR(E50="Correction/Challenge",ISNUMBER(SEARCH("; Correction/Challenge; ","; "&F50&"; "))),1,0) -> 0 | U50: =IF(OR(E50="Redirection",ISNUMBER(SEARCH("; Redirection; ","; "&F50&"; "))),1,0) -> 1 | V50: =IF(OR(E50="Knowledge injection",ISNUMBER(SEARCH("; Knowledge injection; ","; "&F50&"; "))),1,0) -> 1 | W50: =IF(OR(E50="Selection/Rejection",ISNUMBER(SEARCH("; Selection/Rejection; ","; "&F50&"; "))),1,0) -> 1 | X50: =IF(OR(E50="Deliberation",ISNUMBER(SEARCH("; Deliberation; ","; "&F50&"; "))),1,0) -> 0 | Y50: =SUM(Paper2Coding[[#This Row],[Subject-matter correction]:[none]]) -> 2 | Z50: =IF(ISNUMBER(SEARCH("; domain correction; ","; "&H50&"; ")),1,0) -> 0 | AA50: =IF(ISNUMBER(SEARCH("; conceptual discrimination; ","; "&H50&"; ")),1,0) -> 0 | AB50: =IF(ISNUMBER(SEARCH("; evidence judgment; ","; "&H50&"; ")),1,0) -> 0 | AC50: =IF(ISNUMBER(SEARCH("; methodological judgment; ","; "&H50&"; ")),1,0) -> 0 | AD50: =IF(ISNUMBER(SEARCH("; argumentative judgment; ","; "&H50&"; ")),1,0) -> 1 | AE50: =IF(ISNUMBER(SEARCH("; genre/writing expertise; ","; "&H50&"; ")),1,0) -> 1 | AF50: =IF(ISNUMBER(SEARCH("; none; ","; "&H50&"; ")),1,0) -> 0
A51: P2-050 | B51: 50 | C51: Supplement and section drafting | D51: low-quality output findings i removed this from Table 1 in Supplementary Material (Document), as it would confuse the reader. low-quality output findings of AI is related to "Need for and cost of human oversight" already | E51: Selection/Rejection | F51: Correction/Challenge; Knowledge injection | G51: Critical | H51: conceptual discrimination; methodological judgment | I51: Reports deleting a redundant low-quality-output category because it overlaps with oversight and could confuse readers. | J51: No substantive assistant response is visible. The deletion and rationale are explicit human actions. | K51: p24 L36-p24 L40 | M51: Supplementary material (document).docx | N51: No substantive response visible | O51: Export gap: no assistant outcome can be inferred | P51: =SUM(Paper2Coding[[#This Row],[Open Delegation]:[Expertise]]) -> 5 | Q51: =IF(OR(E51="Delegation",ISNUMBER(SEARCH("; Delegation; ","; "&F51&"; "))),1,0) -> 0 | R51: =IF(OR(E51="Directed delegation",ISNUMBER(SEARCH("; Directed delegation; ","; "&F51&"; "))),1,0) -> 0 | S51: =IF(OR(E51="Evaluation",ISNUMBER(SEARCH("; Evaluation; ","; "&F51&"; "))),1,0) -> 0 | T51: =IF(OR(E51="Correction/Challenge",ISNUMBER(SEARCH("; Correction/Challenge; ","; "&F51&"; "))),1,0) -> 1 | U51: =IF(OR(E51="Redirection",ISNUMBER(SEARCH("; Redirection; ","; "&F51&"; "))),1,0) -> 0 | V51: =IF(OR(E51="Knowledge injection",ISNUMBER(SEARCH("; Knowledge injection; ","; "&F51&"; "))),1,0) -> 1 | W51: =IF(OR(E51="Selection/Rejection",ISNUMBER(SEARCH("; Selection/Rejection; ","; "&F51&"; "))),1,0) -> 1 | X51: =IF(OR(E51="Deliberation",ISNUMBER(SEARCH("; Deliberation; ","; "&F51&"; "))),1,0) -> 0 | Y51: =SUM(Paper2Coding[[#This Row],[Subject-matter correction]:[none]]) -> 2 | Z51: =IF(ISNUMBER(SEARCH("; domain correction; ","; "&H51&"; ")),1,0) -> 0 | AA51: =IF(ISNUMBER(SEARCH("; conceptual discrimination; ","; "&H51&"; ")),1,0) -> 1 | AB51: =IF(ISNUMBER(SEARCH("; evidence judgment; ","; "&H51&"; ")),1,0) -> 0 | AC51: =IF(ISNUMBER(SEARCH("; methodological judgment; ","; "&H51&"; ")),1,0) -> 1 | AD51: =IF(ISNUMBER(SEARCH("; argumentative judgment; ","; "&H51&"; ")),1,0) -> 0 | AE51: =IF(ISNUMBER(SEARCH("; genre/writing expertise; ","; "&H51&"; ")),1,0) -> 0 | AF51: =IF(ISNUMBER(SEARCH("; none; ","; "&H51&"; ")),1,0) -> 0
A52: P2-051 | B52: 51 | C52: Supplement and section drafting | D52: latest paper draft is attached. let's write it from sec 1 in shortest form, and highest quailty. use the 10 sources that we found and listed in Supplementary material (document). I also gave you their PDFs, right? | E52: Directed delegation | F52: Knowledge injection | G52: Directive | H52: genre/writing expertise; evidence judgment | I52: Requests the shortest high-quality introduction using the ten selected sources and existing draft. | J52: No substantive assistant response is visible before the next human turn. | K52: p25 L3-p25 L4 | M52: Hidden Cost of AI-assisted SE-IEEE SW.docx | N52: No substantive response visible | O52: Export gap: no assistant outcome can be inferred | P52: =SUM(Paper2Coding[[#This Row],[Open Delegation]:[Expertise]]) -> 4 | Q52: =IF(OR(E52="Delegation",ISNUMBER(SEARCH("; Delegation; ","; "&F52&"; "))),1,0) -> 0 | R52: =IF(OR(E52="Directed delegation",ISNUMBER(SEARCH("; Directed delegation; ","; "&F52&"; "))),1,0) -> 1 | S52: =IF(OR(E52="Evaluation",ISNUMBER(SEARCH("; Evaluation; ","; "&F52&"; "))),1,0) -> 0 | T52: =IF(OR(E52="Correction/Challenge",ISNUMBER(SEARCH("; Correction/Challenge; ","; "&F52&"; "))),1,0) -> 0 | U52: =IF(OR(E52="Redirection",ISNUMBER(SEARCH("; Redirection; ","; "&F52&"; "))),1,0) -> 0 | V52: =IF(OR(E52="Knowledge injection",ISNUMBER(SEARCH("; Knowledge injection; ","; "&F52&"; "))),1,0) -> 1 | W52: =IF(OR(E52="Selection/Rejection",ISNUMBER(SEARCH("; Selection/Rejection; ","; "&F52&"; "))),1,0) -> 0 | X52: =IF(OR(E52="Deliberation",ISNUMBER(SEARCH("; Deliberation; ","; "&F52&"; "))),1,0) -> 0 | Y52: =SUM(Paper2Coding[[#This Row],[Subject-matter correction]:[none]]) -> 2 | Z52: =IF(ISNUMBER(SEARCH("; domain correction; ","; "&H52&"; ")),1,0) -> 0 | AA52: =IF(ISNUMBER(SEARCH("; conceptual discrimination; ","; "&H52&"; ")),1,0) -> 0 | AB52: =IF(ISNUMBER(SEARCH("; evidence judgment; ","; "&H52&"; ")),1,0) -> 1 | AC52: =IF(ISNUMBER(SEARCH("; methodological judgment; ","; "&H52&"; ")),1,0) -> 0 | AD52: =IF(ISNUMBER(SEARCH("; argumentative judgment; ","; "&H52&"; ")),1,0) -> 0 | AE52: =IF(ISNUMBER(SEARCH("; genre/writing expertise; ","; "&H52&"; ")),1,0) -> 1 | AF52: =IF(ISNUMBER(SEARCH("; none; ","; "&H52&"; ")),1,0) -> 0
A53: P2-052 | B53: 52 | C53: Supplement and section drafting | D53: While AI in SE is often treated as a single category, we differentiate between **inline AI assistants** (e.g., IDE completions) and **chat-based AI tools** (e.g., ChatGPT). Each class differs in interaction style, output scale, and the types of hidden costs it generates, a dis... | E53: Redirection | F53: Correction/Challenge; Selection/Rejection; Directed delegation | G53: Critical | H53: genre/writing expertise; argumentative judgment | I53: Moves the tool-class distinction out of the introduction to prevent scattered framing and requests a transition to the next section. | J53: No substantive assistant response is visible. The referenced image is identified as an attachment, not transcribed as prose. | K53: p25 L5-p25 L10 | M53: f661f767-4928-45d2-ac72-b2e18d8fa503.png | N53: No substantive response visible | O53: Export gap: no assistant outcome can be inferred | P53: =SUM(Paper2Coding[[#This Row],[Open Delegation]:[Expertise]]) -> 6 | Q53: =IF(OR(E53="Delegation",ISNUMBER(SEARCH("; Delegation; ","; "&F53&"; "))),1,0) -> 0 | R53: =IF(OR(E53="Directed delegation",ISNUMBER(SEARCH("; Directed delegation; ","; "&F53&"; "))),1,0) -> 1 | S53: =IF(OR(E53="Evaluation",ISNUMBER(SEARCH("; Evaluation; ","; "&F53&"; "))),1,0) -> 0 | T53: =IF(OR(E53="Correction/Challenge",ISNUMBER(SEARCH("; Correction/Challenge; ","; "&F53&"; "))),1,0) -> 1 | U53: =IF(OR(E53="Redirection",ISNUMBER(SEARCH("; Redirection; ","; "&F53&"; "))),1,0) -> 1 | V53: =IF(OR(E53="Knowledge injection",ISNUMBER(SEARCH("; Knowledge injection; ","; "&F53&"; "))),1,0) -> 0 | W53: =IF(OR(E53="Selection/Rejection",ISNUMBER(SEARCH("; Selection/Rejection; ","; "&F53&"; "))),1,0) -> 1 | X53: =IF(OR(E53="Deliberation",ISNUMBER(SEARCH("; Deliberation; ","; "&F53&"; "))),1,0) -> 0 | Y53: =SUM(Paper2Coding[[#This Row],[Subject-matter correction]:[none]]) -> 2 | Z53: =IF(ISNUMBER(SEARCH("; domain correction; ","; "&H53&"; ")),1,0) -> 0 | AA53: =IF(ISNUMBER(SEARCH("; conceptual discrimination; ","; "&H53&"; ")),1,0) -> 0 | AB53: =IF(ISNUMBER(SEARCH("; evidence judgment; ","; "&H53&"; ")),1,0) -> 0 | AC53: =IF(ISNUMBER(SEARCH("; methodological judgment; ","; "&H53&"; ")),1,0) -> 0 | AD53: =IF(ISNUMBER(SEARCH("; argumentative judgment; ","; "&H53&"; ")),1,0) -> 1 | AE53: =IF(ISNUMBER(SEARCH("; genre/writing expertise; ","; "&H53&"; ")),1,0) -> 1 | AF53: =IF(ISNUMBER(SEARCH("; none; ","; "&H53&"; ")),1,0) -> 0
A54: P2-053 | B54: 53 | C54: Supplement and section drafting | D54: latest paper draft is attached. write sec 2 in shortest form, and highest quality. use my existing text there. at the end of sec 2, discuss Fig 1. | E54: Directed delegation | F54: Knowledge injection | G54: Directive | H54: genre/writing expertise; argumentative judgment | I54: Constrains Section 2 drafting to existing text, brevity and a figure discussion. | J54: AI drafts an evidence-base section and a Table 1 discussion. The request names Fig 1; exact compliance is not established. | K54: p25 L13-p25 L15 | L54: p25 L16-p25 L30 | M54: Hidden Cost of AI-assisted SE-IEEE SW.docx | N54: Visible substantive response | P54: =SUM(Paper2Coding[[#This Row],[Open Delegation]:[Expertise]]) -> 4 | Q54: =IF(OR(E54="Delegation",ISNUMBER(SEARCH("; Delegation; ","; "&F54&"; "))),1,0) -> 0 | R54: =IF(OR(E54="Directed delegation",ISNUMBER(SEARCH("; Directed delegation; ","; "&F54&"; "))),1,0) -> 1 | S54: =IF(OR(E54="Evaluation",ISNUMBER(SEARCH("; Evaluation; ","; "&F54&"; "))),1,0) -> 0 | T54: =IF(OR(E54="Correction/Challenge",ISNUMBER(SEARCH("; Correction/Challenge; ","; "&F54&"; "))),1,0) -> 0 | U54: =IF(OR(E54="Redirection",ISNUMBER(SEARCH("; Redirection; ","; "&F54&"; "))),1,0) -> 0 | V54: =IF(OR(E54="Knowledge injection",ISNUMBER(SEARCH("; Knowledge injection; ","; "&F54&"; "))),1,0) -> 1 | W54: =IF(OR(E54="Selection/Rejection",ISNUMBER(SEARCH("; Selection/Rejection; ","; "&F54&"; "))),1,0) -> 0 | X54: =IF(OR(E54="Deliberation",ISNUMBER(SEARCH("; Deliberation; ","; "&F54&"; "))),1,0) -> 0 | Y54: =SUM(Paper2Coding[[#This Row],[Subject-matter correction]:[none]]) -> 2 | Z54: =IF(ISNUMBER(SEARCH("; domain correction; ","; "&H54&"; ")),1,0) -> 0 | AA54: =IF(ISNUMBER(SEARCH("; conceptual discrimination; ","; "&H54&"; ")),1,0) -> 0 | AB54: =IF(ISNUMBER(SEARCH("; evidence judgment; ","; "&H54&"; ")),1,0) -> 0 | AC54: =IF(ISNUMBER(SEARCH("; methodological judgment; ","; "&H54&"; ")),1,0) -> 0 | AD54: =IF(ISNUMBER(SEARCH("; argumentative judgment; ","; "&H54&"; ")),1,0) -> 1 | AE54: =IF(ISNUMBER(SEARCH("; genre/writing expertise; ","; "&H54&"; ")),1,0) -> 1 | AF54: =IF(ISNUMBER(SEARCH("; none; ","; "&H54&"; ")),1,0) -> 0
A55: P2-054 | B55: 54 | C55: Supplement and section drafting | D55: yes | E55: Selection/Rejection | G55: Directive | H55: none | I55: Accepts the prior offer to polish the Table 1 caption. | J55: AI supplies the caption; acceptance of all preceding section content is not inferred. | K55: p25 L31-p25 L31 | L55: p25 L32-p25 L35 | N55: Visible substantive response | O55: Assent resolved from immediately preceding offer; not blanket approval | P55: =SUM(Paper2Coding[[#This Row],[Open Delegation]:[Expertise]]) -> 2 | Q55: =IF(OR(E55="Delegation",ISNUMBER(SEARCH("; Delegation; ","; "&F55&"; "))),1,0) -> 0 | R55: =IF(OR(E55="Directed delegation",ISNUMBER(SEARCH("; Directed delegation; ","; "&F55&"; "))),1,0) -> 0 | S55: =IF(OR(E55="Evaluation",ISNUMBER(SEARCH("; Evaluation; ","; "&F55&"; "))),1,0) -> 0 | T55: =IF(OR(E55="Correction/Challenge",ISNUMBER(SEARCH("; Correction/Challenge; ","; "&F55&"; "))),1,0) -> 0 | U55: =IF(OR(E55="Redirection",ISNUMBER(SEARCH("; Redirection; ","; "&F55&"; "))),1,0) -> 0 | V55: =IF(OR(E55="Knowledge injection",ISNUMBER(SEARCH("; Knowledge injection; ","; "&F55&"; "))),1,0) -> 0 | W55: =IF(OR(E55="Selection/Rejection",ISNUMBER(SEARCH("; Selection/Rejection; ","; "&F55&"; "))),1,0) -> 1 | X55: =IF(OR(E55="Deliberation",ISNUMBER(SEARCH("; Deliberation; ","; "&F55&"; "))),1,0) -> 0 | Y55: =SUM(Paper2Coding[[#This Row],[Subject-matter correction]:[none]]) -> 1 | Z55: =IF(ISNUMBER(SEARCH("; domain correction; ","; "&H55&"; ")),1,0) -> 0 | AA55: =IF(ISNUMBER(SEARCH("; conceptual discrimination; ","; "&H55&"; ")),1,0) -> 0 | AB55: =IF(ISNUMBER(SEARCH("; evidence judgment; ","; "&H55&"; ")),1,0) -> 0 | AC55: =IF(ISNUMBER(SEARCH("; methodological judgment; ","; "&H55&"; ")),1,0) -> 0 | AD55: =IF(ISNUMBER(SEARCH("; argumentative judgment; ","; "&H55&"; ")),1,0) -> 0 | AE55: =IF(ISNUMBER(SEARCH("; genre/writing expertise; ","; "&H55&"; ")),1,0) -> 0 | AF55: =IF(ISNUMBER(SEARCH("; none; ","; "&H55&"; ")),1,0) -> 1
A56: P2-055 | B56: 55 | C56: Supplement and section drafting | D56: latest paper draft is attached. since we have a new sec 2, give the updated sec 1 | E56: Directed delegation | F56: Knowledge injection | G56: Directive | H56: genre/writing expertise; argumentative judgment | I56: Requires the introduction to be updated to fit the newly drafted Section 2. | J56: AI drafts a revised introduction and links it to the evidence-base section. | K56: p25 L38-p25 L38 | L56: p26 L1-p26 L17 | M56: Hidden Cost of AI-assisted SE-IEEE SW.docx | N56: Visible substantive response | P56: =SUM(Paper2Coding[[#This Row],[Open Delegation]:[Expertise]]) -> 4 | Q56: =IF(OR(E56="Delegation",ISNUMBER(SEARCH("; Delegation; ","; "&F56&"; "))),1,0) -> 0 | R56: =IF(OR(E56="Directed delegation",ISNUMBER(SEARCH("; Directed delegation; ","; "&F56&"; "))),1,0) -> 1 | S56: =IF(OR(E56="Evaluation",ISNUMBER(SEARCH("; Evaluation; ","; "&F56&"; "))),1,0) -> 0 | T56: =IF(OR(E56="Correction/Challenge",ISNUMBER(SEARCH("; Correction/Challenge; ","; "&F56&"; "))),1,0) -> 0 | U56: =IF(OR(E56="Redirection",ISNUMBER(SEARCH("; Redirection; ","; "&F56&"; "))),1,0) -> 0 | V56: =IF(OR(E56="Knowledge injection",ISNUMBER(SEARCH("; Knowledge injection; ","; "&F56&"; "))),1,0) -> 1 | W56: =IF(OR(E56="Selection/Rejection",ISNUMBER(SEARCH("; Selection/Rejection; ","; "&F56&"; "))),1,0) -> 0 | X56: =IF(OR(E56="Deliberation",ISNUMBER(SEARCH("; Deliberation; ","; "&F56&"; "))),1,0) -> 0 | Y56: =SUM(Paper2Coding[[#This Row],[Subject-matter correction]:[none]]) -> 2 | Z56: =IF(ISNUMBER(SEARCH("; domain correction; ","; "&H56&"; ")),1,0) -> 0 | AA56: =IF(ISNUMBER(SEARCH("; conceptual discrimination; ","; "&H56&"; ")),1,0) -> 0 | AB56: =IF(ISNUMBER(SEARCH("; evidence judgment; ","; "&H56&"; ")),1,0) -> 0 | AC56: =IF(ISNUMBER(SEARCH("; methodological judgment; ","; "&H56&"; ")),1,0) -> 0 | AD56: =IF(ISNUMBER(SEARCH("; argumentative judgment; ","; "&H56&"; ")),1,0) -> 1 | AE56: =IF(ISNUMBER(SEARCH("; genre/writing expertise; ","; "&H56&"; ")),1,0) -> 1 | AF56: =IF(ISNUMBER(SEARCH("; none; ","; "&H56&"; ")),1,0) -> 0
A57: P2-056 | B57: 56 | C57: Supplement and section drafting | D57: write sec 3 in shortest form, and highest quality. use my existing text there. as per our table 1, pool papers [1-9[ discuss Oversight Burden. ensuring citing and discussing them all in sec 3, but very short. at the end of sec 3, discuss Fig 1. | E57: Directed delegation | F57: Knowledge injection | G57: Directive | H57: evidence judgment; genre/writing expertise; argumentative judgment | I57: Directs a brief Section 3 using existing text, all nine oversight sources and Figure 1. | J57: AI drafts Section 3 with source claims and a figure discussion. Quotations and interpretations are not independently checked here. | K57: p26 L20-p26 L22 | L57: p26 L23-p26 L40 | M57: Hidden Cost of AI-assisted SE-IEEE SW.docx | N57: Visible substantive response | P57: =SUM(Paper2Coding[[#This Row],[Open Delegation]:[Expertise]]) -> 5 | Q57: =IF(OR(E57="Delegation",ISNUMBER(SEARCH("; Delegation; ","; "&F57&"; "))),1,0) -> 0 | R57: =IF(OR(E57="Directed delegation",ISNUMBER(SEARCH("; Directed delegation; ","; "&F57&"; "))),1,0) -> 1 | S57: =IF(OR(E57="Evaluation",ISNUMBER(SEARCH("; Evaluation; ","; "&F57&"; "))),1,0) -> 0 | T57: =IF(OR(E57="Correction/Challenge",ISNUMBER(SEARCH("; Correction/Challenge; ","; "&F57&"; "))),1,0) -> 0 | U57: =IF(OR(E57="Redirection",ISNUMBER(SEARCH("; Redirection; ","; "&F57&"; "))),1,0) -> 0 | V57: =IF(OR(E57="Knowledge injection",ISNUMBER(SEARCH("; Knowledge injection; ","; "&F57&"; "))),1,0) -> 1 | W57: =IF(OR(E57="Selection/Rejection",ISNUMBER(SEARCH("; Selection/Rejection; ","; "&F57&"; "))),1,0) -> 0 | X57: =IF(OR(E57="Deliberation",ISNUMBER(SEARCH("; Deliberation; ","; "&F57&"; "))),1,0) -> 0 | Y57: =SUM(Paper2Coding[[#This Row],[Subject-matter correction]:[none]]) -> 3 | Z57: =IF(ISNUMBER(SEARCH("; domain correction; ","; "&H57&"; ")),1,0) -> 0 | AA57: =IF(ISNUMBER(SEARCH("; conceptual discrimination; ","; "&H57&"; ")),1,0) -> 0 | AB57: =IF(ISNUMBER(SEARCH("; evidence judgment; ","; "&H57&"; ")),1,0) -> 1 | AC57: =IF(ISNUMBER(SEARCH("; methodological judgment; ","; "&H57&"; ")),1,0) -> 0 | AD57: =IF(ISNUMBER(SEARCH("; argumentative judgment; ","; "&H57&"; ")),1,0) -> 1 | AE57: =IF(ISNUMBER(SEARCH("; genre/writing expertise; ","; "&H57&"; ")),1,0) -> 1 | AF57: =IF(ISNUMBER(SEARCH("; none; ","; "&H57&"; ")),1,0) -> 0
A58: P2-057 | B58: 57 | C58: Supplement and section drafting | D58: erode I do not like the word "erode ", replace it | E58: Correction/Challenge | F58: Selection/Rejection | G58: Critical | H58: genre/writing expertise | I58: Rejects erode and requests a replacement. | J58: AI suggests alternatives and demonstrates offset; no global manuscript replacement is confirmed. | K58: p26 L41-p26 L42 | L58: p26 L43-p27 L3 | N58: Visible substantive response | P58: =SUM(Paper2Coding[[#This Row],[Open Delegation]:[Expertise]]) -> 3 | Q58: =IF(OR(E58="Delegation",ISNUMBER(SEARCH("; Delegation; ","; "&F58&"; "))),1,0) -> 0 | R58: =IF(OR(E58="Directed delegation",ISNUMBER(SEARCH("; Directed delegation; ","; "&F58&"; "))),1,0) -> 0 | S58: =IF(OR(E58="Evaluation",ISNUMBER(SEARCH("; Evaluation; ","; "&F58&"; "))),1,0) -> 0 | T58: =IF(OR(E58="Correction/Challenge",ISNUMBER(SEARCH("; Correction/Challenge; ","; "&F58&"; "))),1,0) -> 1 | U58: =IF(OR(E58="Redirection",ISNUMBER(SEARCH("; Redirection; ","; "&F58&"; "))),1,0) -> 0 | V58: =IF(OR(E58="Knowledge injection",ISNUMBER(SEARCH("; Knowledge injection; ","; "&F58&"; "))),1,0) -> 0 | W58: =IF(OR(E58="Selection/Rejection",ISNUMBER(SEARCH("; Selection/Rejection; ","; "&F58&"; "))),1,0) -> 1 | X58: =IF(OR(E58="Deliberation",ISNUMBER(SEARCH("; Deliberation; ","; "&F58&"; "))),1,0) -> 0 | Y58: =SUM(Paper2Coding[[#This Row],[Subject-matter correction]:[none]]) -> 1 | Z58: =IF(ISNUMBER(SEARCH("; domain correction; ","; "&H58&"; ")),1,0) -> 0 | AA58: =IF(ISNUMBER(SEARCH("; conceptual discrimination; ","; "&H58&"; ")),1,0) -> 0 | AB58: =IF(ISNUMBER(SEARCH("; evidence judgment; ","; "&H58&"; ")),1,0) -> 0 | AC58: =IF(ISNUMBER(SEARCH("; methodological judgment; ","; "&H58&"; ")),1,0) -> 0 | AD58: =IF(ISNUMBER(SEARCH("; argumentative judgment; ","; "&H58&"; ")),1,0) -> 0 | AE58: =IF(ISNUMBER(SEARCH("; genre/writing expertise; ","; "&H58&"; ")),1,0) -> 1 | AF58: =IF(ISNUMBER(SEARCH("; none; ","; "&H58&"; ")),1,0) -> 0
A59: P2-058 | B59: 58 | C59: Supplement and section drafting | D59: I do not like the phrase "Industry accounts ", replace it | E59: Correction/Challenge | F59: Selection/Rejection | G59: Critical | H59: genre/writing expertise | I59: Rejects Industry accounts as wording. | J59: AI substitutes Practitioner reports and offers a wider consistency edit. | K59: p27 L4-p27 L4 | L59: p27 L5-p27 L10 | N59: Visible substantive response | P59: =SUM(Paper2Coding[[#This Row],[Open Delegation]:[Expertise]]) -> 3 | Q59: =IF(OR(E59="Delegation",ISNUMBER(SEARCH("; Delegation; ","; "&F59&"; "))),1,0) -> 0 | R59: =IF(OR(E59="Directed delegation",ISNUMBER(SEARCH("; Directed delegation; ","; "&F59&"; "))),1,0) -> 0 | S59: =IF(OR(E59="Evaluation",ISNUMBER(SEARCH("; Evaluation; ","; "&F59&"; "))),1,0) -> 0 | T59: =IF(OR(E59="Correction/Challenge",ISNUMBER(SEARCH("; Correction/Challenge; ","; "&F59&"; "))),1,0) -> 1 | U59: =IF(OR(E59="Redirection",ISNUMBER(SEARCH("; Redirection; ","; "&F59&"; "))),1,0) -> 0 | V59: =IF(OR(E59="Knowledge injection",ISNUMBER(SEARCH("; Knowledge injection; ","; "&F59&"; "))),1,0) -> 0 | W59: =IF(OR(E59="Selection/Rejection",ISNUMBER(SEARCH("; Selection/Rejection; ","; "&F59&"; "))),1,0) -> 1 | X59: =IF(OR(E59="Deliberation",ISNUMBER(SEARCH("; Deliberation; ","; "&F59&"; "))),1,0) -> 0 | Y59: =SUM(Paper2Coding[[#This Row],[Subject-matter correction]:[none]]) -> 1 | Z59: =IF(ISNUMBER(SEARCH("; domain correction; ","; "&H59&"; ")),1,0) -> 0 | AA59: =IF(ISNUMBER(SEARCH("; conceptual discrimination; ","; "&H59&"; ")),1,0) -> 0 | AB59: =IF(ISNUMBER(SEARCH("; evidence judgment; ","; "&H59&"; ")),1,0) -> 0 | AC59: =IF(ISNUMBER(SEARCH("; methodological judgment; ","; "&H59&"; ")),1,0) -> 0 | AD59: =IF(ISNUMBER(SEARCH("; argumentative judgment; ","; "&H59&"; ")),1,0) -> 0 | AE59: =IF(ISNUMBER(SEARCH("; genre/writing expertise; ","; "&H59&"; ")),1,0) -> 1 | AF59: =IF(ISNUMBER(SEARCH("; none; ","; "&H59&"; ")),1,0) -> 0
A60: P2-059 | B60: 59 | C60: Supplement and section drafting | D60: give the minimum sec 4. as I have in the draft, ensure citing and discussing my pre-print: "As observed in recent field studies [x], engineers often receive overly general or inconsistent outputs when prompting AI for complex artifacts. In many cases, they must deconstruct the... | E60: Directed delegation | F60: Knowledge injection | G60: Directive | H60: evidence judgment; argumentative judgment | I60: Supplies a preprint passage and citation, and specifies the two cognitive-overload sources for a minimal Section 4. | J60: AI drafts Section 4 using the specified material; the preprint metadata and claims are not independently verified. | K60: p27 L11-p27 L19 | L60: p27 L21-p27 L32 | N60: Visible substantive response | P60: =SUM(Paper2Coding[[#This Row],[Open Delegation]:[Expertise]]) -> 4 | Q60: =IF(OR(E60="Delegation",ISNUMBER(SEARCH("; Delegation; ","; "&F60&"; "))),1,0) -> 0 | R60: =IF(OR(E60="Directed delegation",ISNUMBER(SEARCH("; Directed delegation; ","; "&F60&"; "))),1,0) -> 1 | S60: =IF(OR(E60="Evaluation",ISNUMBER(SEARCH("; Evaluation; ","; "&F60&"; "))),1,0) -> 0 | T60: =IF(OR(E60="Correction/Challenge",ISNUMBER(SEARCH("; Correction/Challenge; ","; "&F60&"; "))),1,0) -> 0 | U60: =IF(OR(E60="Redirection",ISNUMBER(SEARCH("; Redirection; ","; "&F60&"; "))),1,0) -> 0 | V60: =IF(OR(E60="Knowledge injection",ISNUMBER(SEARCH("; Knowledge injection; ","; "&F60&"; "))),1,0) -> 1 | W60: =IF(OR(E60="Selection/Rejection",ISNUMBER(SEARCH("; Selection/Rejection; ","; "&F60&"; "))),1,0) -> 0 | X60: =IF(OR(E60="Deliberation",ISNUMBER(SEARCH("; Deliberation; ","; "&F60&"; "))),1,0) -> 0 | Y60: =SUM(Paper2Coding[[#This Row],[Subject-matter correction]:[none]]) -> 2 | Z60: =IF(ISNUMBER(SEARCH("; domain correction; ","; "&H60&"; ")),1,0) -> 0 | AA60: =IF(ISNUMBER(SEARCH("; conceptual discrimination; ","; "&H60&"; ")),1,0) -> 0 | AB60: =IF(ISNUMBER(SEARCH("; evidence judgment; ","; "&H60&"; ")),1,0) -> 1 | AC60: =IF(ISNUMBER(SEARCH("; methodological judgment; ","; "&H60&"; ")),1,0) -> 0 | AD60: =IF(ISNUMBER(SEARCH("; argumentative judgment; ","; "&H60&"; ")),1,0) -> 1 | AE60: =IF(ISNUMBER(SEARCH("; genre/writing expertise; ","; "&H60&"; ")),1,0) -> 0 | AF60: =IF(ISNUMBER(SEARCH("; none; ","; "&H60&"; ")),1,0) -> 0
A61: P2-060 | B61: 60 | C61: Evidence audit and pool revision | D61: you have the 10 sources PDF. in [4]: 4-SWE-Bench+ Enhanced coding benchmark for LLMs, tell me which parts of it discuss either of the costs: Need for and cost of human oversight , Cognitive overload of AI | E61: Evaluation | F61: Directed delegation | G61: Evaluative | H61: evidence judgment; methodological judgment | I61: Audits SWE-Bench+ against the two burden categories by requesting relevant parts. | J61: AI provides apparent quote examples and says there is no direct cognitive-overload discussion, then offers exact extraction. | K61: p27 L33-p27 L34 | L61: p27 L35-p28 L4 | N61: Visible substantive response | P61: =SUM(Paper2Coding[[#This Row],[Open Delegation]:[Expertise]]) -> 4 | Q61: =IF(OR(E61="Delegation",ISNUMBER(SEARCH("; Delegation; ","; "&F61&"; "))),1,0) -> 0 | R61: =IF(OR(E61="Directed delegation",ISNUMBER(SEARCH("; Directed delegation; ","; "&F61&"; "))),1,0) -> 1 | S61: =IF(OR(E61="Evaluation",ISNUMBER(SEARCH("; Evaluation; ","; "&F61&"; "))),1,0) -> 1 | T61: =IF(OR(E61="Correction/Challenge",ISNUMBER(SEARCH("; Correction/Challenge; ","; "&F61&"; "))),1,0) -> 0 | U61: =IF(OR(E61="Redirection",ISNUMBER(SEARCH("; Redirection; ","; "&F61&"; "))),1,0) -> 0 | V61: =IF(OR(E61="Knowledge injection",ISNUMBER(SEARCH("; Knowledge injection; ","; "&F61&"; "))),1,0) -> 0 | W61: =IF(OR(E61="Selection/Rejection",ISNUMBER(SEARCH("; Selection/Rejection; ","; "&F61&"; "))),1,0) -> 0 | X61: =IF(OR(E61="Deliberation",ISNUMBER(SEARCH("; Deliberation; ","; "&F61&"; "))),1,0) -> 0 | Y61: =SUM(Paper2Coding[[#This Row],[Subject-matter correction]:[none]]) -> 2 | Z61: =IF(ISNUMBER(SEARCH("; domain correction; ","; "&H61&"; ")),1,0) -> 0 | AA61: =IF(ISNUMBER(SEARCH("; conceptual discrimination; ","; "&H61&"; ")),1,0) -> 0 | AB61: =IF(ISNUMBER(SEARCH("; evidence judgment; ","; "&H61&"; ")),1,0) -> 1 | AC61: =IF(ISNUMBER(SEARCH("; methodological judgment; ","; "&H61&"; ")),1,0) -> 1 | AD61: =IF(ISNUMBER(SEARCH("; argumentative judgment; ","; "&H61&"; ")),1,0) -> 0 | AE61: =IF(ISNUMBER(SEARCH("; genre/writing expertise; ","; "&H61&"; ")),1,0) -> 0 | AF61: =IF(ISNUMBER(SEARCH("; none; ","; "&H61&"; ")),1,0) -> 0
A62: P2-061 | B62: 61 | C62: Evidence audit and pool revision | D62: , tell me which parts of source [7] discusses either of the costs: Need for and cost of human oversight , Cognitive overload of AI | E62: Evaluation | F62: Directed delegation; Knowledge injection | G62: Evaluative | H62: evidence judgment | I62: Supplies the Forbes PDF and asks which parts support either burden. | J62: AI says oversight relevance is indirect through maintenance and that cognitive overload is not directly discussed. | K62: p28 L7-p28 L7 | L62: p28 L8-p28 L19 | M62: 7-The Hidden Cost Of Code And Generative AI.pdf | N62: Visible substantive response | P62: =SUM(Paper2Coding[[#This Row],[Open Delegation]:[Expertise]]) -> 4 | Q62: =IF(OR(E62="Delegation",ISNUMBER(SEARCH("; Delegation; ","; "&F62&"; "))),1,0) -> 0 | R62: =IF(OR(E62="Directed delegation",ISNUMBER(SEARCH("; Directed delegation; ","; "&F62&"; "))),1,0) -> 1 | S62: =IF(OR(E62="Evaluation",ISNUMBER(SEARCH("; Evaluation; ","; "&F62&"; "))),1,0) -> 1 | T62: =IF(OR(E62="Correction/Challenge",ISNUMBER(SEARCH("; Correction/Challenge; ","; "&F62&"; "))),1,0) -> 0 | U62: =IF(OR(E62="Redirection",ISNUMBER(SEARCH("; Redirection; ","; "&F62&"; "))),1,0) -> 0 | V62: =IF(OR(E62="Knowledge injection",ISNUMBER(SEARCH("; Knowledge injection; ","; "&F62&"; "))),1,0) -> 1 | W62: =IF(OR(E62="Selection/Rejection",ISNUMBER(SEARCH("; Selection/Rejection; ","; "&F62&"; "))),1,0) -> 0 | X62: =IF(OR(E62="Deliberation",ISNUMBER(SEARCH("; Deliberation; ","; "&F62&"; "))),1,0) -> 0 | Y62: =SUM(Paper2Coding[[#This Row],[Subject-matter correction]:[none]]) -> 1 | Z62: =IF(ISNUMBER(SEARCH("; domain correction; ","; "&H62&"; ")),1,0) -> 0 | AA62: =IF(ISNUMBER(SEARCH("; conceptual discrimination; ","; "&H62&"; ")),1,0) -> 0 | AB62: =IF(ISNUMBER(SEARCH("; evidence judgment; ","; "&H62&"; ")),1,0) -> 1 | AC62: =IF(ISNUMBER(SEARCH("; methodological judgment; ","; "&H62&"; ")),1,0) -> 0 | AD62: =IF(ISNUMBER(SEARCH("; argumentative judgment; ","; "&H62&"; ")),1,0) -> 0 | AE62: =IF(ISNUMBER(SEARCH("; genre/writing expertise; ","; "&H62&"; ")),1,0) -> 0 | AF62: =IF(ISNUMBER(SEARCH("; none; ","; "&H62&"; ")),1,0) -> 0
A63: P2-062 | B63: 62 | C63: Evidence audit and pool revision | D63: , tell me which parts of this source discusses either of the costs: Need for and cost of human oversight , Cognitive overload of AI | E63: Evaluation | F63: Directed delegation; Knowledge injection | G63: Evaluative | H63: evidence judgment | I63: Supplies the Stack Overflow PDF and requests support for the two categories. | J63: AI claims oversight support and supplies a supposed quotation, offering exact extraction next. | K63: p28 L22-p28 L22 | L63: p28 L23-p28 L32 | M63: 8-Generative AI is not going to build your engineering team for you.pdf | N63: Visible substantive response | P63: =SUM(Paper2Coding[[#This Row],[Open Delegation]:[Expertise]]) -> 4 | Q63: =IF(OR(E63="Delegation",ISNUMBER(SEARCH("; Delegation; ","; "&F63&"; "))),1,0) -> 0 | R63: =IF(OR(E63="Directed delegation",ISNUMBER(SEARCH("; Directed delegation; ","; "&F63&"; "))),1,0) -> 1 | S63: =IF(OR(E63="Evaluation",ISNUMBER(SEARCH("; Evaluation; ","; "&F63&"; "))),1,0) -> 1 | T63: =IF(OR(E63="Correction/Challenge",ISNUMBER(SEARCH("; Correction/Challenge; ","; "&F63&"; "))),1,0) -> 0 | U63: =IF(OR(E63="Redirection",ISNUMBER(SEARCH("; Redirection; ","; "&F63&"; "))),1,0) -> 0 | V63: =IF(OR(E63="Knowledge injection",ISNUMBER(SEARCH("; Knowledge injection; ","; "&F63&"; "))),1,0) -> 1 | W63: =IF(OR(E63="Selection/Rejection",ISNUMBER(SEARCH("; Selection/Rejection; ","; "&F63&"; "))),1,0) -> 0 | X63: =IF(OR(E63="Deliberation",ISNUMBER(SEARCH("; Deliberation; ","; "&F63&"; "))),1,0) -> 0 | Y63: =SUM(Paper2Coding[[#This Row],[Subject-matter correction]:[none]]) -> 1 | Z63: =IF(ISNUMBER(SEARCH("; domain correction; ","; "&H63&"; ")),1,0) -> 0 | AA63: =IF(ISNUMBER(SEARCH("; conceptual discrimination; ","; "&H63&"; ")),1,0) -> 0 | AB63: =IF(ISNUMBER(SEARCH("; evidence judgment; ","; "&H63&"; ")),1,0) -> 1 | AC63: =IF(ISNUMBER(SEARCH("; methodological judgment; ","; "&H63&"; ")),1,0) -> 0 | AD63: =IF(ISNUMBER(SEARCH("; argumentative judgment; ","; "&H63&"; ")),1,0) -> 0 | AE63: =IF(ISNUMBER(SEARCH("; genre/writing expertise; ","; "&H63&"; ")),1,0) -> 0 | AF63: =IF(ISNUMBER(SEARCH("; none; ","; "&H63&"; ")),1,0) -> 0
A64: P2-063 | B64: 63 | C64: Evidence audit and pool revision | D64: yes | E64: Selection/Rejection | F64: Directed delegation | G64: Directive | H64: none | I64: Accepts the immediately preceding offer of exact quotations. A brief assent does not demonstrate source validation. | J64: AI presents sentences as verbatim; the next human challenge leads it to admit they are not verbatim. | K64: p28 L33-p28 L33 | L64: p28 L34-p29 L1 | N64: Visible substantive response | O64: Assent resolved from immediately preceding offer; not blanket approval | P64: =SUM(Paper2Coding[[#This Row],[Open Delegation]:[Expertise]]) -> 3 | Q64: =IF(OR(E64="Delegation",ISNUMBER(SEARCH("; Delegation; ","; "&F64&"; "))),1,0) -> 0 | R64: =IF(OR(E64="Directed delegation",ISNUMBER(SEARCH("; Directed delegation; ","; "&F64&"; "))),1,0) -> 1 | S64: =IF(OR(E64="Evaluation",ISNUMBER(SEARCH("; Evaluation; ","; "&F64&"; "))),1,0) -> 0 | T64: =IF(OR(E64="Correction/Challenge",ISNUMBER(SEARCH("; Correction/Challenge; ","; "&F64&"; "))),1,0) -> 0 | U64: =IF(OR(E64="Redirection",ISNUMBER(SEARCH("; Redirection; ","; "&F64&"; "))),1,0) -> 0 | V64: =IF(OR(E64="Knowledge injection",ISNUMBER(SEARCH("; Knowledge injection; ","; "&F64&"; "))),1,0) -> 0 | W64: =IF(OR(E64="Selection/Rejection",ISNUMBER(SEARCH("; Selection/Rejection; ","; "&F64&"; "))),1,0) -> 1 | X64: =IF(OR(E64="Deliberation",ISNUMBER(SEARCH("; Deliberation; ","; "&F64&"; "))),1,0) -> 0 | Y64: =SUM(Paper2Coding[[#This Row],[Subject-matter correction]:[none]]) -> 1 | Z64: =IF(ISNUMBER(SEARCH("; domain correction; ","; "&H64&"; ")),1,0) -> 0 | AA64: =IF(ISNUMBER(SEARCH("; conceptual discrimination; ","; "&H64&"; ")),1,0) -> 0 | AB64: =IF(ISNUMBER(SEARCH("; evidence judgment; ","; "&H64&"; ")),1,0) -> 0 | AC64: =IF(ISNUMBER(SEARCH("; methodological judgment; ","; "&H64&"; ")),1,0) -> 0 | AD64: =IF(ISNUMBER(SEARCH("; argumentative judgment; ","; "&H64&"; ")),1,0) -> 0 | AE64: =IF(ISNUMBER(SEARCH("; genre/writing expertise; ","; "&H64&"; ")),1,0) -> 0 | AF64: =IF(ISNUMBER(SEARCH("; none; ","; "&H64&"; ")),1,0) -> 1
A65: P2-064 | B65: 64 | C65: Evidence audit and pool revision | D65: you fabricated these???? | E65: Correction/Challenge | G65: Critical | H65: evidence judgment | I65: Directly challenges fabrication of the supposed verbatim quotations. | J65: AI admits those exact sentences do not appear and says it had presented summaries as quotations. | K65: p29 L2-p29 L2 | L65: p29 L3-p29 L10 | N65: Visible substantive response | P65: =SUM(Paper2Coding[[#This Row],[Open Delegation]:[Expertise]]) -> 2 | Q65: =IF(OR(E65="Delegation",ISNUMBER(SEARCH("; Delegation; ","; "&F65&"; "))),1,0) -> 0 | R65: =IF(OR(E65="Directed delegation",ISNUMBER(SEARCH("; Directed delegation; ","; "&F65&"; "))),1,0) -> 0 | S65: =IF(OR(E65="Evaluation",ISNUMBER(SEARCH("; Evaluation; ","; "&F65&"; "))),1,0) -> 0 | T65: =IF(OR(E65="Correction/Challenge",ISNUMBER(SEARCH("; Correction/Challenge; ","; "&F65&"; "))),1,0) -> 1 | U65: =IF(OR(E65="Redirection",ISNUMBER(SEARCH("; Redirection; ","; "&F65&"; "))),1,0) -> 0 | V65: =IF(OR(E65="Knowledge injection",ISNUMBER(SEARCH("; Knowledge injection; ","; "&F65&"; "))),1,0) -> 0 | W65: =IF(OR(E65="Selection/Rejection",ISNUMBER(SEARCH("; Selection/Rejection; ","; "&F65&"; "))),1,0) -> 0 | X65: =IF(OR(E65="Deliberation",ISNUMBER(SEARCH("; Deliberation; ","; "&F65&"; "))),1,0) -> 0 | Y65: =SUM(Paper2Coding[[#This Row],[Subject-matter correction]:[none]]) -> 1 | Z65: =IF(ISNUMBER(SEARCH("; domain correction; ","; "&H65&"; ")),1,0) -> 0 | AA65: =IF(ISNUMBER(SEARCH("; conceptual discrimination; ","; "&H65&"; ")),1,0) -> 0 | AB65: =IF(ISNUMBER(SEARCH("; evidence judgment; ","; "&H65&"; ")),1,0) -> 1 | AC65: =IF(ISNUMBER(SEARCH("; methodological judgment; ","; "&H65&"; ")),1,0) -> 0 | AD65: =IF(ISNUMBER(SEARCH("; argumentative judgment; ","; "&H65&"; ")),1,0) -> 0 | AE65: =IF(ISNUMBER(SEARCH("; genre/writing expertise; ","; "&H65&"; ")),1,0) -> 0 | AF65: =IF(ISNUMBER(SEARCH("; none; ","; "&H65&"; ")),1,0) -> 0
A66: P2-065 | B66: 65 | C66: Evidence audit and pool revision | D66: yes | E66: Selection/Rejection | F66: Directed delegation | G66: Directive | H66: none | I66: Accepts the offer to redo the source using direct quotes. | J66: AI supplies replacement excerpts and distinguishes direct oversight support from lack of direct cognitive-overload coverage; replacements are not independently verified here. | K66: p29 L11-p29 L11 | L66: p29 L12-p29 L20 | N66: Visible substantive response | O66: Assent resolved from immediately preceding offer; not blanket approval | P66: =SUM(Paper2Coding[[#This Row],[Open Delegation]:[Expertise]]) -> 3 | Q66: =IF(OR(E66="Delegation",ISNUMBER(SEARCH("; Delegation; ","; "&F66&"; "))),1,0) -> 0 | R66: =IF(OR(E66="Directed delegation",ISNUMBER(SEARCH("; Directed delegation; ","; "&F66&"; "))),1,0) -> 1 | S66: =IF(OR(E66="Evaluation",ISNUMBER(SEARCH("; Evaluation; ","; "&F66&"; "))),1,0) -> 0 | T66: =IF(OR(E66="Correction/Challenge",ISNUMBER(SEARCH("; Correction/Challenge; ","; "&F66&"; "))),1,0) -> 0 | U66: =IF(OR(E66="Redirection",ISNUMBER(SEARCH("; Redirection; ","; "&F66&"; "))),1,0) -> 0 | V66: =IF(OR(E66="Knowledge injection",ISNUMBER(SEARCH("; Knowledge injection; ","; "&F66&"; "))),1,0) -> 0 | W66: =IF(OR(E66="Selection/Rejection",ISNUMBER(SEARCH("; Selection/Rejection; ","; "&F66&"; "))),1,0) -> 1 | X66: =IF(OR(E66="Deliberation",ISNUMBER(SEARCH("; Deliberation; ","; "&F66&"; "))),1,0) -> 0 | Y66: =SUM(Paper2Coding[[#This Row],[Subject-matter correction]:[none]]) -> 1 | Z66: =IF(ISNUMBER(SEARCH("; domain correction; ","; "&H66&"; ")),1,0) -> 0 | AA66: =IF(ISNUMBER(SEARCH("; conceptual discrimination; ","; "&H66&"; ")),1,0) -> 0 | AB66: =IF(ISNUMBER(SEARCH("; evidence judgment; ","; "&H66&"; ")),1,0) -> 0 | AC66: =IF(ISNUMBER(SEARCH("; methodological judgment; ","; "&H66&"; ")),1,0) -> 0 | AD66: =IF(ISNUMBER(SEARCH("; argumentative judgment; ","; "&H66&"; ")),1,0) -> 0 | AE66: =IF(ISNUMBER(SEARCH("; genre/writing expertise; ","; "&H66&"; ")),1,0) -> 0 | AF66: =IF(ISNUMBER(SEARCH("; none; ","; "&H66&"; ")),1,0) -> 1
A67: P2-066 | B67: 66 | C67: Evidence audit and pool revision | D67: I removed two of the sources, due to above. the final pool have 8 papers: [eight source titles] | E67: Selection/Rejection | F67: Redirection; Knowledge injection | G67: Critical | H67: evidence judgment; methodological judgment | I67: Explicitly removes two sources after the preceding audit and specifies a final eight-source pool. | J67: AI acknowledges the eight-source pool. Comparing lists identifies SWE-Bench+ and Forbes as removed; the prompt does not name them separately. | K67: p29 L21-p29 L36 | L67: p29 L38-p30 L5 | N67: Visible substantive response | P67: =SUM(Paper2Coding[[#This Row],[Open Delegation]:[Expertise]]) -> 5 | Q67: =IF(OR(E67="Delegation",ISNUMBER(SEARCH("; Delegation; ","; "&F67&"; "))),1,0) -> 0 | R67: =IF(OR(E67="Directed delegation",ISNUMBER(SEARCH("; Directed delegation; ","; "&F67&"; "))),1,0) -> 0 | S67: =IF(OR(E67="Evaluation",ISNUMBER(SEARCH("; Evaluation; ","; "&F67&"; "))),1,0) -> 0 | T67: =IF(OR(E67="Correction/Challenge",ISNUMBER(SEARCH("; Correction/Challenge; ","; "&F67&"; "))),1,0) -> 0 | U67: =IF(OR(E67="Redirection",ISNUMBER(SEARCH("; Redirection; ","; "&F67&"; "))),1,0) -> 1 | V67: =IF(OR(E67="Knowledge injection",ISNUMBER(SEARCH("; Knowledge injection; ","; "&F67&"; "))),1,0) -> 1 | W67: =IF(OR(E67="Selection/Rejection",ISNUMBER(SEARCH("; Selection/Rejection; ","; "&F67&"; "))),1,0) -> 1 | X67: =IF(OR(E67="Deliberation",ISNUMBER(SEARCH("; Deliberation; ","; "&F67&"; "))),1,0) -> 0 | Y67: =SUM(Paper2Coding[[#This Row],[Subject-matter correction]:[none]]) -> 2 | Z67: =IF(ISNUMBER(SEARCH("; domain correction; ","; "&H67&"; ")),1,0) -> 0 | AA67: =IF(ISNUMBER(SEARCH("; conceptual discrimination; ","; "&H67&"; ")),1,0) -> 0 | AB67: =IF(ISNUMBER(SEARCH("; evidence judgment; ","; "&H67&"; ")),1,0) -> 1 | AC67: =IF(ISNUMBER(SEARCH("; methodological judgment; ","; "&H67&"; ")),1,0) -> 1 | AD67: =IF(ISNUMBER(SEARCH("; argumentative judgment; ","; "&H67&"; ")),1,0) -> 0 | AE67: =IF(ISNUMBER(SEARCH("; genre/writing expertise; ","; "&H67&"; ")),1,0) -> 0 | AF67: =IF(ISNUMBER(SEARCH("; none; ","; "&H67&"; ")),1,0) -> 0
A68: P2-067 | B68: 67 | C68: Evidence audit and pool revision | D68: I have taken the quotes from each of the 8 sources, related to the two cost issues and have put them as comments on the cells of the Table 1 attached, can you see them? | E68: Evaluation | F68: Knowledge injection | G68: Evaluative | H68: evidence judgment; methodological judgment | I68: Reports personally extracting quotes and organizing them in table comments, then checks whether AI can access them. | J68: AI claims it can see the comments. The attachment comments are not reproduced in this export, so access cannot be confirmed from the log. | K68: p30 L8-p30 L9 | L68: p30 L10-p30 L16 | M68: Supplementary material (document).docx | N68: Visible substantive response | O68: Document comments unavailable for independent access check | P68: =SUM(Paper2Coding[[#This Row],[Open Delegation]:[Expertise]]) -> 4 | Q68: =IF(OR(E68="Delegation",ISNUMBER(SEARCH("; Delegation; ","; "&F68&"; "))),1,0) -> 0 | R68: =IF(OR(E68="Directed delegation",ISNUMBER(SEARCH("; Directed delegation; ","; "&F68&"; "))),1,0) -> 0 | S68: =IF(OR(E68="Evaluation",ISNUMBER(SEARCH("; Evaluation; ","; "&F68&"; "))),1,0) -> 1 | T68: =IF(OR(E68="Correction/Challenge",ISNUMBER(SEARCH("; Correction/Challenge; ","; "&F68&"; "))),1,0) -> 0 | U68: =IF(OR(E68="Redirection",ISNUMBER(SEARCH("; Redirection; ","; "&F68&"; "))),1,0) -> 0 | V68: =IF(OR(E68="Knowledge injection",ISNUMBER(SEARCH("; Knowledge injection; ","; "&F68&"; "))),1,0) -> 1 | W68: =IF(OR(E68="Selection/Rejection",ISNUMBER(SEARCH("; Selection/Rejection; ","; "&F68&"; "))),1,0) -> 0 | X68: =IF(OR(E68="Deliberation",ISNUMBER(SEARCH("; Deliberation; ","; "&F68&"; "))),1,0) -> 0 | Y68: =SUM(Paper2Coding[[#This Row],[Subject-matter correction]:[none]]) -> 2 | Z68: =IF(ISNUMBER(SEARCH("; domain correction; ","; "&H68&"; ")),1,0) -> 0 | AA68: =IF(ISNUMBER(SEARCH("; conceptual discrimination; ","; "&H68&"; ")),1,0) -> 0 | AB68: =IF(ISNUMBER(SEARCH("; evidence judgment; ","; "&H68&"; ")),1,0) -> 1 | AC68: =IF(ISNUMBER(SEARCH("; methodological judgment; ","; "&H68&"; ")),1,0) -> 1 | AD68: =IF(ISNUMBER(SEARCH("; argumentative judgment; ","; "&H68&"; ")),1,0) -> 0 | AE68: =IF(ISNUMBER(SEARCH("; genre/writing expertise; ","; "&H68&"; ")),1,0) -> 0 | AF68: =IF(ISNUMBER(SEARCH("; none; ","; "&H68&"; ")),1,0) -> 0
A69: P2-068 | B69: 68 | C69: Evidence audit and pool revision | D69: give the sec 3 again, with a few quotes | E69: Directed delegation | G69: Directive | H69: evidence judgment; genre/writing expertise | I69: Requests a revised Section 3 containing a few quotations from the revised evidence base. | J69: AI drafts Section 3 and attributes quotations to the table comments; quotation accuracy is not independently established. | K69: p30 L17-p30 L17 | L69: p30 L18-p30 L31 | N69: Visible substantive response | P69: =SUM(Paper2Coding[[#This Row],[Open Delegation]:[Expertise]]) -> 3 | Q69: =IF(OR(E69="Delegation",ISNUMBER(SEARCH("; Delegation; ","; "&F69&"; "))),1,0) -> 0 | R69: =IF(OR(E69="Directed delegation",ISNUMBER(SEARCH("; Directed delegation; ","; "&F69&"; "))),1,0) -> 1 | S69: =IF(OR(E69="Evaluation",ISNUMBER(SEARCH("; Evaluation; ","; "&F69&"; "))),1,0) -> 0 | T69: =IF(OR(E69="Correction/Challenge",ISNUMBER(SEARCH("; Correction/Challenge; ","; "&F69&"; "))),1,0) -> 0 | U69: =IF(OR(E69="Redirection",ISNUMBER(SEARCH("; Redirection; ","; "&F69&"; "))),1,0) -> 0 | V69: =IF(OR(E69="Knowledge injection",ISNUMBER(SEARCH("; Knowledge injection; ","; "&F69&"; "))),1,0) -> 0 | W69: =IF(OR(E69="Selection/Rejection",ISNUMBER(SEARCH("; Selection/Rejection; ","; "&F69&"; "))),1,0) -> 0 | X69: =IF(OR(E69="Deliberation",ISNUMBER(SEARCH("; Deliberation; ","; "&F69&"; "))),1,0) -> 0 | Y69: =SUM(Paper2Coding[[#This Row],[Subject-matter correction]:[none]]) -> 2 | Z69: =IF(ISNUMBER(SEARCH("; domain correction; ","; "&H69&"; ")),1,0) -> 0 | AA69: =IF(ISNUMBER(SEARCH("; conceptual discrimination; ","; "&H69&"; ")),1,0) -> 0 | AB69: =IF(ISNUMBER(SEARCH("; evidence judgment; ","; "&H69&"; ")),1,0) -> 1 | AC69: =IF(ISNUMBER(SEARCH("; methodological judgment; ","; "&H69&"; ")),1,0) -> 0 | AD69: =IF(ISNUMBER(SEARCH("; argumentative judgment; ","; "&H69&"; ")),1,0) -> 0 | AE69: =IF(ISNUMBER(SEARCH("; genre/writing expertise; ","; "&H69&"; ")),1,0) -> 1 | AF69: =IF(ISNUMBER(SEARCH("; none; ","; "&H69&"; ")),1,0) -> 0
A70: P2-069 | B70: 69 | C70: Evidence audit and pool revision | D70: Practitioner evidence \[9\] but we now have 8 sources in the pool?? | E70: Correction/Challenge | F70: Knowledge injection | G70: Critical | H70: evidence judgment | I70: Detects an apparent reference [9] inconsistency after reducing the pool to eight. | J70: AI interprets this as incomplete pool coverage and rewrites across all eight sources rather than explicitly explaining the stray reference. | K70: p30 L32-p30 L33 | L70: p30 L34-p31 L11 | N70: Visible substantive response | P70: =SUM(Paper2Coding[[#This Row],[Open Delegation]:[Expertise]]) -> 3 | Q70: =IF(OR(E70="Delegation",ISNUMBER(SEARCH("; Delegation; ","; "&F70&"; "))),1,0) -> 0 | R70: =IF(OR(E70="Directed delegation",ISNUMBER(SEARCH("; Directed delegation; ","; "&F70&"; "))),1,0) -> 0 | S70: =IF(OR(E70="Evaluation",ISNUMBER(SEARCH("; Evaluation; ","; "&F70&"; "))),1,0) -> 0 | T70: =IF(OR(E70="Correction/Challenge",ISNUMBER(SEARCH("; Correction/Challenge; ","; "&F70&"; "))),1,0) -> 1 | U70: =IF(OR(E70="Redirection",ISNUMBER(SEARCH("; Redirection; ","; "&F70&"; "))),1,0) -> 0 | V70: =IF(OR(E70="Knowledge injection",ISNUMBER(SEARCH("; Knowledge injection; ","; "&F70&"; "))),1,0) -> 1 | W70: =IF(OR(E70="Selection/Rejection",ISNUMBER(SEARCH("; Selection/Rejection; ","; "&F70&"; "))),1,0) -> 0 | X70: =IF(OR(E70="Deliberation",ISNUMBER(SEARCH("; Deliberation; ","; "&F70&"; "))),1,0) -> 0 | Y70: =SUM(Paper2Coding[[#This Row],[Subject-matter correction]:[none]]) -> 1 | Z70: =IF(ISNUMBER(SEARCH("; domain correction; ","; "&H70&"; ")),1,0) -> 0 | AA70: =IF(ISNUMBER(SEARCH("; conceptual discrimination; ","; "&H70&"; ")),1,0) -> 0 | AB70: =IF(ISNUMBER(SEARCH("; evidence judgment; ","; "&H70&"; ")),1,0) -> 1 | AC70: =IF(ISNUMBER(SEARCH("; methodological judgment; ","; "&H70&"; ")),1,0) -> 0 | AD70: =IF(ISNUMBER(SEARCH("; argumentative judgment; ","; "&H70&"; ")),1,0) -> 0 | AE70: =IF(ISNUMBER(SEARCH("; genre/writing expertise; ","; "&H70&"; ")),1,0) -> 0 | AF70: =IF(ISNUMBER(SEARCH("; none; ","; "&H70&"; ")),1,0) -> 0
A71: P2-070 | B71: 70 | C71: Completion and review requests | D71: give me sec 4 | E71: Delegation | G71: Delegative | H71: none | I71: Requests Section 4 with no new substantive constraints; prior evidence context remains relevant. | J71: AI drafts cognitive-overload text using the eight-source pool and claimed table-comment quotations. | K71: p31 L12-p31 L12 | L71: p31 L13-p31 L29 | N71: Visible substantive response | P71: =SUM(Paper2Coding[[#This Row],[Open Delegation]:[Expertise]]) -> 2 | Q71: =IF(OR(E71="Delegation",ISNUMBER(SEARCH("; Delegation; ","; "&F71&"; "))),1,0) -> 1 | R71: =IF(OR(E71="Directed delegation",ISNUMBER(SEARCH("; Directed delegation; ","; "&F71&"; "))),1,0) -> 0 | S71: =IF(OR(E71="Evaluation",ISNUMBER(SEARCH("; Evaluation; ","; "&F71&"; "))),1,0) -> 0 | T71: =IF(OR(E71="Correction/Challenge",ISNUMBER(SEARCH("; Correction/Challenge; ","; "&F71&"; "))),1,0) -> 0 | U71: =IF(OR(E71="Redirection",ISNUMBER(SEARCH("; Redirection; ","; "&F71&"; "))),1,0) -> 0 | V71: =IF(OR(E71="Knowledge injection",ISNUMBER(SEARCH("; Knowledge injection; ","; "&F71&"; "))),1,0) -> 0 | W71: =IF(OR(E71="Selection/Rejection",ISNUMBER(SEARCH("; Selection/Rejection; ","; "&F71&"; "))),1,0) -> 0 | X71: =IF(OR(E71="Deliberation",ISNUMBER(SEARCH("; Deliberation; ","; "&F71&"; "))),1,0) -> 0 | Y71: =SUM(Paper2Coding[[#This Row],[Subject-matter correction]:[none]]) -> 1 | Z71: =IF(ISNUMBER(SEARCH("; domain correction; ","; "&H71&"; ")),1,0) -> 0 | AA71: =IF(ISNUMBER(SEARCH("; conceptual discrimination; ","; "&H71&"; ")),1,0) -> 0 | AB71: =IF(ISNUMBER(SEARCH("; evidence judgment; ","; "&H71&"; ")),1,0) -> 0 | AC71: =IF(ISNUMBER(SEARCH("; methodological judgment; ","; "&H71&"; ")),1,0) -> 0 | AD71: =IF(ISNUMBER(SEARCH("; argumentative judgment; ","; "&H71&"; ")),1,0) -> 0 | AE71: =IF(ISNUMBER(SEARCH("; genre/writing expertise; ","; "&H71&"; ")),1,0) -> 0 | AF71: =IF(ISNUMBER(SEARCH("; none; ","; "&H71&"; ")),1,0) -> 1
A72: P2-071 | B72: 71 | C72: Completion and review requests | D72: we have 1669 words, and max is 2000. we shall have have two more sections. give me their titles | E72: Directed delegation | F72: Knowledge injection | G72: Directive | H72: genre/writing expertise; argumentative judgment | I72: Reports 1669 words used out of 2000 and plans two remaining sections, requesting their titles. | J72: AI proposes balance and conclusion sections and offers to draft Section 5. | K72: p31 L30-p31 L30 | L72: p31 L31-p31 L38 | N72: Visible substantive response | P72: =SUM(Paper2Coding[[#This Row],[Open Delegation]:[Expertise]]) -> 4 | Q72: =IF(OR(E72="Delegation",ISNUMBER(SEARCH("; Delegation; ","; "&F72&"; "))),1,0) -> 0 | R72: =IF(OR(E72="Directed delegation",ISNUMBER(SEARCH("; Directed delegation; ","; "&F72&"; "))),1,0) -> 1 | S72: =IF(OR(E72="Evaluation",ISNUMBER(SEARCH("; Evaluation; ","; "&F72&"; "))),1,0) -> 0 | T72: =IF(OR(E72="Correction/Challenge",ISNUMBER(SEARCH("; Correction/Challenge; ","; "&F72&"; "))),1,0) -> 0 | U72: =IF(OR(E72="Redirection",ISNUMBER(SEARCH("; Redirection; ","; "&F72&"; "))),1,0) -> 0 | V72: =IF(OR(E72="Knowledge injection",ISNUMBER(SEARCH("; Knowledge injection; ","; "&F72&"; "))),1,0) -> 1 | W72: =IF(OR(E72="Selection/Rejection",ISNUMBER(SEARCH("; Selection/Rejection; ","; "&F72&"; "))),1,0) -> 0 | X72: =IF(OR(E72="Deliberation",ISNUMBER(SEARCH("; Deliberation; ","; "&F72&"; "))),1,0) -> 0 | Y72: =SUM(Paper2Coding[[#This Row],[Subject-matter correction]:[none]]) -> 2 | Z72: =IF(ISNUMBER(SEARCH("; domain correction; ","; "&H72&"; ")),1,0) -> 0 | AA72: =IF(ISNUMBER(SEARCH("; conceptual discrimination; ","; "&H72&"; ")),1,0) -> 0 | AB72: =IF(ISNUMBER(SEARCH("; evidence judgment; ","; "&H72&"; ")),1,0) -> 0 | AC72: =IF(ISNUMBER(SEARCH("; methodological judgment; ","; "&H72&"; ")),1,0) -> 0 | AD72: =IF(ISNUMBER(SEARCH("; argumentative judgment; ","; "&H72&"; ")),1,0) -> 1 | AE72: =IF(ISNUMBER(SEARCH("; genre/writing expertise; ","; "&H72&"; ")),1,0) -> 1 | AF72: =IF(ISNUMBER(SEARCH("; none; ","; "&H72&"; ")),1,0) -> 0
A73: P2-072 | B73: 72 | C73: Completion and review requests | D73: in sec 5, you should also discuss my Figure 2- Efficiency vs. hidden cost (burden) of using AI in SE | E73: Directed delegation | F73: Knowledge injection | G73: Directive | H73: argumentative judgment; genre/writing expertise | I73: Requires Section 5 to discuss the human's Figure 2 and its efficiency-burden relation. | J73: AI drafts Section 5 and describes trade-off curves; the actual figure is not independently reconstructed from the log. | K73: p31 L39-p31 L39 | L73: p31 L40-p32 L13 | N73: Visible substantive response | P73: =SUM(Paper2Coding[[#This Row],[Open Delegation]:[Expertise]]) -> 4 | Q73: =IF(OR(E73="Delegation",ISNUMBER(SEARCH("; Delegation; ","; "&F73&"; "))),1,0) -> 0 | R73: =IF(OR(E73="Directed delegation",ISNUMBER(SEARCH("; Directed delegation; ","; "&F73&"; "))),1,0) -> 1 | S73: =IF(OR(E73="Evaluation",ISNUMBER(SEARCH("; Evaluation; ","; "&F73&"; "))),1,0) -> 0 | T73: =IF(OR(E73="Correction/Challenge",ISNUMBER(SEARCH("; Correction/Challenge; ","; "&F73&"; "))),1,0) -> 0 | U73: =IF(OR(E73="Redirection",ISNUMBER(SEARCH("; Redirection; ","; "&F73&"; "))),1,0) -> 0 | V73: =IF(OR(E73="Knowledge injection",ISNUMBER(SEARCH("; Knowledge injection; ","; "&F73&"; "))),1,0) -> 1 | W73: =IF(OR(E73="Selection/Rejection",ISNUMBER(SEARCH("; Selection/Rejection; ","; "&F73&"; "))),1,0) -> 0 | X73: =IF(OR(E73="Deliberation",ISNUMBER(SEARCH("; Deliberation; ","; "&F73&"; "))),1,0) -> 0 | Y73: =SUM(Paper2Coding[[#This Row],[Subject-matter correction]:[none]]) -> 2 | Z73: =IF(ISNUMBER(SEARCH("; domain correction; ","; "&H73&"; ")),1,0) -> 0 | AA73: =IF(ISNUMBER(SEARCH("; conceptual discrimination; ","; "&H73&"; ")),1,0) -> 0 | AB73: =IF(ISNUMBER(SEARCH("; evidence judgment; ","; "&H73&"; ")),1,0) -> 0 | AC73: =IF(ISNUMBER(SEARCH("; methodological judgment; ","; "&H73&"; ")),1,0) -> 0 | AD73: =IF(ISNUMBER(SEARCH("; argumentative judgment; ","; "&H73&"; ")),1,0) -> 1 | AE73: =IF(ISNUMBER(SEARCH("; genre/writing expertise; ","; "&H73&"; ")),1,0) -> 1 | AF73: =IF(ISNUMBER(SEARCH("; none; ","; "&H73&"; ")),1,0) -> 0
A74: P2-073 | B74: 73 | C74: Completion and review requests | D74: I changed Figure 2 caption to Efficiency vs. hidden cost (burden) of using AI in SE (two hypothetical scenarios) | E74: Knowledge injection | F74: Directed delegation | G74: Directive | H74: conceptual discrimination; evidence judgment | I74: Explicitly labels the figure scenarios hypothetical, clarifying their evidential status. | J74: AI revises the discussion to align with the caption; this does not establish that every surrounding empirical-sounding claim was qualified. | K74: p32 L14-p32 L14 | L74: p32 L15-p32 L28 | N74: Visible substantive response | P74: =SUM(Paper2Coding[[#This Row],[Open Delegation]:[Expertise]]) -> 4 | Q74: =IF(OR(E74="Delegation",ISNUMBER(SEARCH("; Delegation; ","; "&F74&"; "))),1,0) -> 0 | R74: =IF(OR(E74="Directed delegation",ISNUMBER(SEARCH("; Directed delegation; ","; "&F74&"; "))),1,0) -> 1 | S74: =IF(OR(E74="Evaluation",ISNUMBER(SEARCH("; Evaluation; ","; "&F74&"; "))),1,0) -> 0 | T74: =IF(OR(E74="Correction/Challenge",ISNUMBER(SEARCH("; Correction/Challenge; ","; "&F74&"; "))),1,0) -> 0 | U74: =IF(OR(E74="Redirection",ISNUMBER(SEARCH("; Redirection; ","; "&F74&"; "))),1,0) -> 0 | V74: =IF(OR(E74="Knowledge injection",ISNUMBER(SEARCH("; Knowledge injection; ","; "&F74&"; "))),1,0) -> 1 | W74: =IF(OR(E74="Selection/Rejection",ISNUMBER(SEARCH("; Selection/Rejection; ","; "&F74&"; "))),1,0) -> 0 | X74: =IF(OR(E74="Deliberation",ISNUMBER(SEARCH("; Deliberation; ","; "&F74&"; "))),1,0) -> 0 | Y74: =SUM(Paper2Coding[[#This Row],[Subject-matter correction]:[none]]) -> 2 | Z74: =IF(ISNUMBER(SEARCH("; domain correction; ","; "&H74&"; ")),1,0) -> 0 | AA74: =IF(ISNUMBER(SEARCH("; conceptual discrimination; ","; "&H74&"; ")),1,0) -> 1 | AB74: =IF(ISNUMBER(SEARCH("; evidence judgment; ","; "&H74&"; ")),1,0) -> 1 | AC74: =IF(ISNUMBER(SEARCH("; methodological judgment; ","; "&H74&"; ")),1,0) -> 0 | AD74: =IF(ISNUMBER(SEARCH("; argumentative judgment; ","; "&H74&"; ")),1,0) -> 0 | AE74: =IF(ISNUMBER(SEARCH("; genre/writing expertise; ","; "&H74&"; ")),1,0) -> 0 | AF74: =IF(ISNUMBER(SEARCH("; none; ","; "&H74&"; ")),1,0) -> 0
A75: P2-074 | B75: 74 | C75: Completion and review requests | D75: yes | E75: Selection/Rejection | G75: Directive | H75: none | I75: Accepts the immediately preceding offer to draft Section 6 within the word limit. | J75: AI drafts a conclusion and call for action; total length is claimed, not independently demonstrated in the log. | K75: p32 L29-p32 L29 | L75: p32 L30-p33 L3 | N75: Visible substantive response | O75: Assent resolved from immediately preceding offer; not blanket approval | P75: =SUM(Paper2Coding[[#This Row],[Open Delegation]:[Expertise]]) -> 2 | Q75: =IF(OR(E75="Delegation",ISNUMBER(SEARCH("; Delegation; ","; "&F75&"; "))),1,0) -> 0 | R75: =IF(OR(E75="Directed delegation",ISNUMBER(SEARCH("; Directed delegation; ","; "&F75&"; "))),1,0) -> 0 | S75: =IF(OR(E75="Evaluation",ISNUMBER(SEARCH("; Evaluation; ","; "&F75&"; "))),1,0) -> 0 | T75: =IF(OR(E75="Correction/Challenge",ISNUMBER(SEARCH("; Correction/Challenge; ","; "&F75&"; "))),1,0) -> 0 | U75: =IF(OR(E75="Redirection",ISNUMBER(SEARCH("; Redirection; ","; "&F75&"; "))),1,0) -> 0 | V75: =IF(OR(E75="Knowledge injection",ISNUMBER(SEARCH("; Knowledge injection; ","; "&F75&"; "))),1,0) -> 0 | W75: =IF(OR(E75="Selection/Rejection",ISNUMBER(SEARCH("; Selection/Rejection; ","; "&F75&"; "))),1,0) -> 1 | X75: =IF(OR(E75="Deliberation",ISNUMBER(SEARCH("; Deliberation; ","; "&F75&"; "))),1,0) -> 0 | Y75: =SUM(Paper2Coding[[#This Row],[Subject-matter correction]:[none]]) -> 1 | Z75: =IF(ISNUMBER(SEARCH("; domain correction; ","; "&H75&"; ")),1,0) -> 0 | AA75: =IF(ISNUMBER(SEARCH("; conceptual discrimination; ","; "&H75&"; ")),1,0) -> 0 | AB75: =IF(ISNUMBER(SEARCH("; evidence judgment; ","; "&H75&"; ")),1,0) -> 0 | AC75: =IF(ISNUMBER(SEARCH("; methodological judgment; ","; "&H75&"; ")),1,0) -> 0 | AD75: =IF(ISNUMBER(SEARCH("; argumentative judgment; ","; "&H75&"; ")),1,0) -> 0 | AE75: =IF(ISNUMBER(SEARCH("; genre/writing expertise; ","; "&H75&"; ")),1,0) -> 0 | AF75: =IF(ISNUMBER(SEARCH("; none; ","; "&H75&"; ")),1,0) -> 1
A76: P2-075 | B76: 75 | C76: Completion and review requests | D76: the call to action is clear: tone it down | E76: Correction/Challenge | F76: Directed delegation | G76: Critical | H76: genre/writing expertise; argumentative judgment | I76: Requests a less forceful call to action, exercising control over claim tone and recommendations. | J76: AI supplies a more neutral conclusion. | K76: p33 L4-p33 L5 | L76: p33 L6-p33 L17 | N76: Visible substantive response | P76: =SUM(Paper2Coding[[#This Row],[Open Delegation]:[Expertise]]) -> 4 | Q76: =IF(OR(E76="Delegation",ISNUMBER(SEARCH("; Delegation; ","; "&F76&"; "))),1,0) -> 0 | R76: =IF(OR(E76="Directed delegation",ISNUMBER(SEARCH("; Directed delegation; ","; "&F76&"; "))),1,0) -> 1 | S76: =IF(OR(E76="Evaluation",ISNUMBER(SEARCH("; Evaluation; ","; "&F76&"; "))),1,0) -> 0 | T76: =IF(OR(E76="Correction/Challenge",ISNUMBER(SEARCH("; Correction/Challenge; ","; "&F76&"; "))),1,0) -> 1 | U76: =IF(OR(E76="Redirection",ISNUMBER(SEARCH("; Redirection; ","; "&F76&"; "))),1,0) -> 0 | V76: =IF(OR(E76="Knowledge injection",ISNUMBER(SEARCH("; Knowledge injection; ","; "&F76&"; "))),1,0) -> 0 | W76: =IF(OR(E76="Selection/Rejection",ISNUMBER(SEARCH("; Selection/Rejection; ","; "&F76&"; "))),1,0) -> 0 | X76: =IF(OR(E76="Deliberation",ISNUMBER(SEARCH("; Deliberation; ","; "&F76&"; "))),1,0) -> 0 | Y76: =SUM(Paper2Coding[[#This Row],[Subject-matter correction]:[none]]) -> 2 | Z76: =IF(ISNUMBER(SEARCH("; domain correction; ","; "&H76&"; ")),1,0) -> 0 | AA76: =IF(ISNUMBER(SEARCH("; conceptual discrimination; ","; "&H76&"; ")),1,0) -> 0 | AB76: =IF(ISNUMBER(SEARCH("; evidence judgment; ","; "&H76&"; ")),1,0) -> 0 | AC76: =IF(ISNUMBER(SEARCH("; methodological judgment; ","; "&H76&"; ")),1,0) -> 0 | AD76: =IF(ISNUMBER(SEARCH("; argumentative judgment; ","; "&H76&"; ")),1,0) -> 1 | AE76: =IF(ISNUMBER(SEARCH("; genre/writing expertise; ","; "&H76&"; ")),1,0) -> 1 | AF76: =IF(ISNUMBER(SEARCH("; none; ","; "&H76&"; ")),1,0) -> 0
A77: P2-076 | B77: 76 | C77: Completion and review requests | D77: latest paper draft is attached. do a critical review | E77: Evaluation | F77: Knowledge injection | G77: Evaluative | H77: none | I77: Requests a critical review of the supplied draft, without specifying substantive evaluation criteria. | J77: No substantive assistant response is visible before the next human turn. | K77: p33 L20-p33 L20 | M77: Hidden Cost of AI-assisted SE-IEEE SW.docx | N77: No substantive response visible | O77: Export gap: no assistant outcome can be inferred; Repeated request retained as a separate turn | P77: =SUM(Paper2Coding[[#This Row],[Open Delegation]:[Expertise]]) -> 3 | Q77: =IF(OR(E77="Delegation",ISNUMBER(SEARCH("; Delegation; ","; "&F77&"; "))),1,0) -> 0 | R77: =IF(OR(E77="Directed delegation",ISNUMBER(SEARCH("; Directed delegation; ","; "&F77&"; "))),1,0) -> 0 | S77: =IF(OR(E77="Evaluation",ISNUMBER(SEARCH("; Evaluation; ","; "&F77&"; "))),1,0) -> 1 | T77: =IF(OR(E77="Correction/Challenge",ISNUMBER(SEARCH("; Correction/Challenge; ","; "&F77&"; "))),1,0) -> 0 | U77: =IF(OR(E77="Redirection",ISNUMBER(SEARCH("; Redirection; ","; "&F77&"; "))),1,0) -> 0 | V77: =IF(OR(E77="Knowledge injection",ISNUMBER(SEARCH("; Knowledge injection; ","; "&F77&"; "))),1,0) -> 1 | W77: =IF(OR(E77="Selection/Rejection",ISNUMBER(SEARCH("; Selection/Rejection; ","; "&F77&"; "))),1,0) -> 0 | X77: =IF(OR(E77="Deliberation",ISNUMBER(SEARCH("; Deliberation; ","; "&F77&"; "))),1,0) -> 0 | Y77: =SUM(Paper2Coding[[#This Row],[Subject-matter correction]:[none]]) -> 1 | Z77: =IF(ISNUMBER(SEARCH("; domain correction; ","; "&H77&"; ")),1,0) -> 0 | AA77: =IF(ISNUMBER(SEARCH("; conceptual discrimination; ","; "&H77&"; ")),1,0) -> 0 | AB77: =IF(ISNUMBER(SEARCH("; evidence judgment; ","; "&H77&"; ")),1,0) -> 0 | AC77: =IF(ISNUMBER(SEARCH("; methodological judgment; ","; "&H77&"; ")),1,0) -> 0 | AD77: =IF(ISNUMBER(SEARCH("; argumentative judgment; ","; "&H77&"; ")),1,0) -> 0 | AE77: =IF(ISNUMBER(SEARCH("; genre/writing expertise; ","; "&H77&"; ")),1,0) -> 0 | AF77: =IF(ISNUMBER(SEARCH("; none; ","; "&H77&"; ")),1,0) -> 1
A78: P2-077 | B78: 77 | C78: Completion and review requests | D78: latest paper draft is attached. do a critical review | E78: Evaluation | F78: Knowledge injection | G78: Evaluative | H78: none | I78: Repeats the same critical-review request as a distinct visible message. | J78: No substantive assistant response is visible. The repetition is retained, not deduplicated. | K78: p33 L23-p33 L23 | M78: Hidden Cost of AI-assisted SE-IEEE SW.docx | N78: No substantive response visible | O78: Export gap: no assistant outcome can be inferred; Repeated request retained as a separate turn | P78: =SUM(Paper2Coding[[#This Row],[Open Delegation]:[Expertise]]) -> 3 | Q78: =IF(OR(E78="Delegation",ISNUMBER(SEARCH("; Delegation; ","; "&F78&"; "))),1,0) -> 0 | R78: =IF(OR(E78="Directed delegation",ISNUMBER(SEARCH("; Directed delegation; ","; "&F78&"; "))),1,0) -> 0 | S78: =IF(OR(E78="Evaluation",ISNUMBER(SEARCH("; Evaluation; ","; "&F78&"; "))),1,0) -> 1 | T78: =IF(OR(E78="Correction/Challenge",ISNUMBER(SEARCH("; Correction/Challenge; ","; "&F78&"; "))),1,0) -> 0 | U78: =IF(OR(E78="Redirection",ISNUMBER(SEARCH("; Redirection; ","; "&F78&"; "))),1,0) -> 0 | V78: =IF(OR(E78="Knowledge injection",ISNUMBER(SEARCH("; Knowledge injection; ","; "&F78&"; "))),1,0) -> 1 | W78: =IF(OR(E78="Selection/Rejection",ISNUMBER(SEARCH("; Selection/Rejection; ","; "&F78&"; "))),1,0) -> 0 | X78: =IF(OR(E78="Deliberation",ISNUMBER(SEARCH("; Deliberation; ","; "&F78&"; "))),1,0) -> 0 | Y78: =SUM(Paper2Coding[[#This Row],[Subject-matter correction]:[none]]) -> 1 | Z78: =IF(ISNUMBER(SEARCH("; domain correction; ","; "&H78&"; ")),1,0) -> 0 | AA78: =IF(ISNUMBER(SEARCH("; conceptual discrimination; ","; "&H78&"; ")),1,0) -> 0 | AB78: =IF(ISNUMBER(SEARCH("; evidence judgment; ","; "&H78&"; ")),1,0) -> 0 | AC78: =IF(ISNUMBER(SEARCH("; methodological judgment; ","; "&H78&"; ")),1,0) -> 0 | AD78: =IF(ISNUMBER(SEARCH("; argumentative judgment; ","; "&H78&"; ")),1,0) -> 0 | AE78: =IF(ISNUMBER(SEARCH("; genre/writing expertise; ","; "&H78&"; ")),1,0) -> 0 | AF78: =IF(ISNUMBER(SEARCH("; none; ","; "&H78&"; ")),1,0) -> 1
A79: P2-078 | B79: 78 | C79: Completion and review requests | D79: yes | E79: Selection/Rejection | G79: Directive | H79: none | I79: Terse assent with no preceding offer visible; its intended target cannot be established. | J79: AI offers academically toned sentence alternatives. This response does not resolve what the assent originally accepted. | K79: p33 L24-p33 L24 | L79: p33 L25-p33 L31 | N79: Visible substantive response | O79: Assent referent unavailable | P79: =SUM(Paper2Coding[[#This Row],[Open Delegation]:[Expertise]]) -> 2 | Q79: =IF(OR(E79="Delegation",ISNUMBER(SEARCH("; Delegation; ","; "&F79&"; "))),1,0) -> 0 | R79: =IF(OR(E79="Directed delegation",ISNUMBER(SEARCH("; Directed delegation; ","; "&F79&"; "))),1,0) -> 0 | S79: =IF(OR(E79="Evaluation",ISNUMBER(SEARCH("; Evaluation; ","; "&F79&"; "))),1,0) -> 0 | T79: =IF(OR(E79="Correction/Challenge",ISNUMBER(SEARCH("; Correction/Challenge; ","; "&F79&"; "))),1,0) -> 0 | U79: =IF(OR(E79="Redirection",ISNUMBER(SEARCH("; Redirection; ","; "&F79&"; "))),1,0) -> 0 | V79: =IF(OR(E79="Knowledge injection",ISNUMBER(SEARCH("; Knowledge injection; ","; "&F79&"; "))),1,0) -> 0 | W79: =IF(OR(E79="Selection/Rejection",ISNUMBER(SEARCH("; Selection/Rejection; ","; "&F79&"; "))),1,0) -> 1 | X79: =IF(OR(E79="Deliberation",ISNUMBER(SEARCH("; Deliberation; ","; "&F79&"; "))),1,0) -> 0 | Y79: =SUM(Paper2Coding[[#This Row],[Subject-matter correction]:[none]]) -> 1 | Z79: =IF(ISNUMBER(SEARCH("; domain correction; ","; "&H79&"; ")),1,0) -> 0 | AA79: =IF(ISNUMBER(SEARCH("; conceptual discrimination; ","; "&H79&"; ")),1,0) -> 0 | AB79: =IF(ISNUMBER(SEARCH("; evidence judgment; ","; "&H79&"; ")),1,0) -> 0 | AC79: =IF(ISNUMBER(SEARCH("; methodological judgment; ","; "&H79&"; ")),1,0) -> 0 | AD79: =IF(ISNUMBER(SEARCH("; argumentative judgment; ","; "&H79&"; ")),1,0) -> 0 | AE79: =IF(ISNUMBER(SEARCH("; genre/writing expertise; ","; "&H79&"; ")),1,0) -> 0 | AF79: =IF(ISNUMBER(SEARCH("; none; ","; "&H79&"; ")),1,0) -> 1
A80: P2-079 | B80: 79 | C80: Feedback and reframing | D80: so I got this feedback ... not a department column opinion piece ... research not fully explored ... so many OTHER hidden costs ... suggest a title change | E80: Knowledge injection | F80: Evaluation | G80: Evaluative | H80: none | I80: Supplies extensive external feedback. The criticism is the reviewer's, not automatically evidence of the author's expertise; a request to consider it is implicit. | J80: AI analyzes genre, evidential framing, scope and revision strategy. | K80: p33 L32-p34 L26 | L80: p34 L28-p35 L14 | N80: Visible substantive response | O80: External feedback distinguished from author judgment; implicit evaluation request | P80: =SUM(Paper2Coding[[#This Row],[Open Delegation]:[Expertise]]) -> 3 | Q80: =IF(OR(E80="Delegation",ISNUMBER(SEARCH("; Delegation; ","; "&F80&"; "))),1,0) -> 0 | R80: =IF(OR(E80="Directed delegation",ISNUMBER(SEARCH("; Directed delegation; ","; "&F80&"; "))),1,0) -> 0 | S80: =IF(OR(E80="Evaluation",ISNUMBER(SEARCH("; Evaluation; ","; "&F80&"; "))),1,0) -> 1 | T80: =IF(OR(E80="Correction/Challenge",ISNUMBER(SEARCH("; Correction/Challenge; ","; "&F80&"; "))),1,0) -> 0 | U80: =IF(OR(E80="Redirection",ISNUMBER(SEARCH("; Redirection; ","; "&F80&"; "))),1,0) -> 0 | V80: =IF(OR(E80="Knowledge injection",ISNUMBER(SEARCH("; Knowledge injection; ","; "&F80&"; "))),1,0) -> 1 | W80: =IF(OR(E80="Selection/Rejection",ISNUMBER(SEARCH("; Selection/Rejection; ","; "&F80&"; "))),1,0) -> 0 | X80: =IF(OR(E80="Deliberation",ISNUMBER(SEARCH("; Deliberation; ","; "&F80&"; "))),1,0) -> 0 | Y80: =SUM(Paper2Coding[[#This Row],[Subject-matter correction]:[none]]) -> 1 | Z80: =IF(ISNUMBER(SEARCH("; domain correction; ","; "&H80&"; ")),1,0) -> 0 | AA80: =IF(ISNUMBER(SEARCH("; conceptual discrimination; ","; "&H80&"; ")),1,0) -> 0 | AB80: =IF(ISNUMBER(SEARCH("; evidence judgment; ","; "&H80&"; ")),1,0) -> 0 | AC80: =IF(ISNUMBER(SEARCH("; methodological judgment; ","; "&H80&"; ")),1,0) -> 0 | AD80: =IF(ISNUMBER(SEARCH("; argumentative judgment; ","; "&H80&"; ")),1,0) -> 0 | AE80: =IF(ISNUMBER(SEARCH("; genre/writing expertise; ","; "&H80&"; ")),1,0) -> 0 | AF80: =IF(ISNUMBER(SEARCH("; none; ","; "&H80&"; ")),1,0) -> 1
A81: P2-080 | B81: 80 | C81: Feedback and reframing | D81: BTW, she (the provider of the feedback is a good friend of mine, Sigrid Eldh). summarize her points for in bullets | E81: Directed delegation | F81: Knowledge injection | G81: Directive | H81: none | I81: Identifies the feedback provider and requests a bullet summary. | J81: AI summarizes her concerns about genre, evidence, scope, human factors and audience. | K81: p35 L15-p35 L15 | L81: p35 L16-p35 L30 | N81: Visible substantive response | P81: =SUM(Paper2Coding[[#This Row],[Open Delegation]:[Expertise]]) -> 3 | Q81: =IF(OR(E81="Delegation",ISNUMBER(SEARCH("; Delegation; ","; "&F81&"; "))),1,0) -> 0 | R81: =IF(OR(E81="Directed delegation",ISNUMBER(SEARCH("; Directed delegation; ","; "&F81&"; "))),1,0) -> 1 | S81: =IF(OR(E81="Evaluation",ISNUMBER(SEARCH("; Evaluation; ","; "&F81&"; "))),1,0) -> 0 | T81: =IF(OR(E81="Correction/Challenge",ISNUMBER(SEARCH("; Correction/Challenge; ","; "&F81&"; "))),1,0) -> 0 | U81: =IF(OR(E81="Redirection",ISNUMBER(SEARCH("; Redirection; ","; "&F81&"; "))),1,0) -> 0 | V81: =IF(OR(E81="Knowledge injection",ISNUMBER(SEARCH("; Knowledge injection; ","; "&F81&"; "))),1,0) -> 1 | W81: =IF(OR(E81="Selection/Rejection",ISNUMBER(SEARCH("; Selection/Rejection; ","; "&F81&"; "))),1,0) -> 0 | X81: =IF(OR(E81="Deliberation",ISNUMBER(SEARCH("; Deliberation; ","; "&F81&"; "))),1,0) -> 0 | Y81: =SUM(Paper2Coding[[#This Row],[Subject-matter correction]:[none]]) -> 1 | Z81: =IF(ISNUMBER(SEARCH("; domain correction; ","; "&H81&"; ")),1,0) -> 0 | AA81: =IF(ISNUMBER(SEARCH("; conceptual discrimination; ","; "&H81&"; ")),1,0) -> 0 | AB81: =IF(ISNUMBER(SEARCH("; evidence judgment; ","; "&H81&"; ")),1,0) -> 0 | AC81: =IF(ISNUMBER(SEARCH("; methodological judgment; ","; "&H81&"; ")),1,0) -> 0 | AD81: =IF(ISNUMBER(SEARCH("; argumentative judgment; ","; "&H81&"; ")),1,0) -> 0 | AE81: =IF(ISNUMBER(SEARCH("; genre/writing expertise; ","; "&H81&"; ")),1,0) -> 0 | AF81: =IF(ISNUMBER(SEARCH("; none; ","; "&H81&"; ")),1,0) -> 1
A82: P2-081 | B82: 81 | C82: Feedback and reframing | D82: put the summarized points in a tone, which I could include in an email reply to her...like , instead of "She is interested in the human aspect (onboarding, learning, “right” use, efficiency in practice)." , say: "Covering also the human aspects (onboarding, learning, “right” u... | E82: Directed delegation | G82: Directive | H82: genre/writing expertise | I82: Specifies reply-ready phrasing and provides a tonal example for summarizing feedback. | J82: AI drafts an email-style response. No sending action is recorded. | K82: p35 L31-p35 L33 | L82: p35 L35-p36 L17 | N82: Visible substantive response | P82: =SUM(Paper2Coding[[#This Row],[Open Delegation]:[Expertise]]) -> 2 | Q82: =IF(OR(E82="Delegation",ISNUMBER(SEARCH("; Delegation; ","; "&F82&"; "))),1,0) -> 0 | R82: =IF(OR(E82="Directed delegation",ISNUMBER(SEARCH("; Directed delegation; ","; "&F82&"; "))),1,0) -> 1 | S82: =IF(OR(E82="Evaluation",ISNUMBER(SEARCH("; Evaluation; ","; "&F82&"; "))),1,0) -> 0 | T82: =IF(OR(E82="Correction/Challenge",ISNUMBER(SEARCH("; Correction/Challenge; ","; "&F82&"; "))),1,0) -> 0 | U82: =IF(OR(E82="Redirection",ISNUMBER(SEARCH("; Redirection; ","; "&F82&"; "))),1,0) -> 0 | V82: =IF(OR(E82="Knowledge injection",ISNUMBER(SEARCH("; Knowledge injection; ","; "&F82&"; "))),1,0) -> 0 | W82: =IF(OR(E82="Selection/Rejection",ISNUMBER(SEARCH("; Selection/Rejection; ","; "&F82&"; "))),1,0) -> 0 | X82: =IF(OR(E82="Deliberation",ISNUMBER(SEARCH("; Deliberation; ","; "&F82&"; "))),1,0) -> 0 | Y82: =SUM(Paper2Coding[[#This Row],[Subject-matter correction]:[none]]) -> 1 | Z82: =IF(ISNUMBER(SEARCH("; domain correction; ","; "&H82&"; ")),1,0) -> 0 | AA82: =IF(ISNUMBER(SEARCH("; conceptual discrimination; ","; "&H82&"; ")),1,0) -> 0 | AB82: =IF(ISNUMBER(SEARCH("; evidence judgment; ","; "&H82&"; ")),1,0) -> 0 | AC82: =IF(ISNUMBER(SEARCH("; methodological judgment; ","; "&H82&"; ")),1,0) -> 0 | AD82: =IF(ISNUMBER(SEARCH("; argumentative judgment; ","; "&H82&"; ")),1,0) -> 0 | AE82: =IF(ISNUMBER(SEARCH("; genre/writing expertise; ","; "&H82&"; ")),1,0) -> 1 | AF82: =IF(ISNUMBER(SEARCH("; none; ","; "&H82&"; ")),1,0) -> 0
A83: P2-082 | B83: 82 | C83: Feedback and reframing | D83: Now for each of the comments for each of the points I'm going to tell you what my ideas are to address each of them okay so let's start from the first one which is the following. | E83: Redirection | G83: Directive | H83: none | I83: Sets a turn-taking plan in which the human will provide responses to each feedback point. | J83: No substantive assistant response is visible before the next human turn. | K83: p36 L18-p36 L19 | N83: No substantive response visible | O83: Export gap: no assistant outcome can be inferred | P83: =SUM(Paper2Coding[[#This Row],[Open Delegation]:[Expertise]]) -> 2 | Q83: =IF(OR(E83="Delegation",ISNUMBER(SEARCH("; Delegation; ","; "&F83&"; "))),1,0) -> 0 | R83: =IF(OR(E83="Directed delegation",ISNUMBER(SEARCH("; Directed delegation; ","; "&F83&"; "))),1,0) -> 0 | S83: =IF(OR(E83="Evaluation",ISNUMBER(SEARCH("; Evaluation; ","; "&F83&"; "))),1,0) -> 0 | T83: =IF(OR(E83="Correction/Challenge",ISNUMBER(SEARCH("; Correction/Challenge; ","; "&F83&"; "))),1,0) -> 0 | U83: =IF(OR(E83="Redirection",ISNUMBER(SEARCH("; Redirection; ","; "&F83&"; "))),1,0) -> 1 | V83: =IF(OR(E83="Knowledge injection",ISNUMBER(SEARCH("; Knowledge injection; ","; "&F83&"; "))),1,0) -> 0 | W83: =IF(OR(E83="Selection/Rejection",ISNUMBER(SEARCH("; Selection/Rejection; ","; "&F83&"; "))),1,0) -> 0 | X83: =IF(OR(E83="Deliberation",ISNUMBER(SEARCH("; Deliberation; ","; "&F83&"; "))),1,0) -> 0 | Y83: =SUM(Paper2Coding[[#This Row],[Subject-matter correction]:[none]]) -> 1 | Z83: =IF(ISNUMBER(SEARCH("; domain correction; ","; "&H83&"; ")),1,0) -> 0 | AA83: =IF(ISNUMBER(SEARCH("; conceptual discrimination; ","; "&H83&"; ")),1,0) -> 0 | AB83: =IF(ISNUMBER(SEARCH("; evidence judgment; ","; "&H83&"; ")),1,0) -> 0 | AC83: =IF(ISNUMBER(SEARCH("; methodological judgment; ","; "&H83&"; ")),1,0) -> 0 | AD83: =IF(ISNUMBER(SEARCH("; argumentative judgment; ","; "&H83&"; ")),1,0) -> 0 | AE83: =IF(ISNUMBER(SEARCH("; genre/writing expertise; ","; "&H83&"; ")),1,0) -> 0 | AF83: =IF(ISNUMBER(SEARCH("; none; ","; "&H83&"; ")),1,0) -> 1
A84: P2-083 | B84: 83 | C84: Feedback and reframing | D84: You don't have to provide any reply ... a paper sitting between an opinion and a full research paper is okay ... multivocal rapid review ... opinion of the community | E84: Deliberation | F84: Knowledge injection; Redirection | G84: Deliberative | H84: methodological judgment; argumentative judgment; genre/writing expertise | I84: Defends an evidence-backed column between anecdotal opinion and full research, supplying a methodological argument and asking AI to wait. | J84: AI summarizes and drafts a reply despite the explicit request not to reply yet. | K84: p36 L20-p36 L28 | L84: p36 L30-p36 L44 | N84: Visible substantive response | P84: =SUM(Paper2Coding[[#This Row],[Open Delegation]:[Expertise]]) -> 6 | Q84: =IF(OR(E84="Delegation",ISNUMBER(SEARCH("; Delegation; ","; "&F84&"; "))),1,0) -> 0 | R84: =IF(OR(E84="Directed delegation",ISNUMBER(SEARCH("; Directed delegation; ","; "&F84&"; "))),1,0) -> 0 | S84: =IF(OR(E84="Evaluation",ISNUMBER(SEARCH("; Evaluation; ","; "&F84&"; "))),1,0) -> 0 | T84: =IF(OR(E84="Correction/Challenge",ISNUMBER(SEARCH("; Correction/Challenge; ","; "&F84&"; "))),1,0) -> 0 | U84: =IF(OR(E84="Redirection",ISNUMBER(SEARCH("; Redirection; ","; "&F84&"; "))),1,0) -> 1 | V84: =IF(OR(E84="Knowledge injection",ISNUMBER(SEARCH("; Knowledge injection; ","; "&F84&"; "))),1,0) -> 1 | W84: =IF(OR(E84="Selection/Rejection",ISNUMBER(SEARCH("; Selection/Rejection; ","; "&F84&"; "))),1,0) -> 0 | X84: =IF(OR(E84="Deliberation",ISNUMBER(SEARCH("; Deliberation; ","; "&F84&"; "))),1,0) -> 1 | Y84: =SUM(Paper2Coding[[#This Row],[Subject-matter correction]:[none]]) -> 3 | Z84: =IF(ISNUMBER(SEARCH("; domain correction; ","; "&H84&"; ")),1,0) -> 0 | AA84: =IF(ISNUMBER(SEARCH("; conceptual discrimination; ","; "&H84&"; ")),1,0) -> 0 | AB84: =IF(ISNUMBER(SEARCH("; evidence judgment; ","; "&H84&"; ")),1,0) -> 0 | AC84: =IF(ISNUMBER(SEARCH("; methodological judgment; ","; "&H84&"; ")),1,0) -> 1 | AD84: =IF(ISNUMBER(SEARCH("; argumentative judgment; ","; "&H84&"; ")),1,0) -> 1 | AE84: =IF(ISNUMBER(SEARCH("; genre/writing expertise; ","; "&H84&"; ")),1,0) -> 1 | AF84: =IF(ISNUMBER(SEARCH("; none; ","; "&H84&"; ")),1,0) -> 0
A85: P2-084 | B85: 84 | C85: Feedback and reframing | D85: Do not provide a reply for all of them yourself ... MY idea ... not frame it as research ... structured synthesis of practitioner evidence and opinions ... extended version ... research paper | E85: Redirection | F85: Correction/Challenge; Knowledge injection; Selection/Rejection | G85: Critical | H85: methodological judgment; evidence judgment; argumentative judgment; genre/writing expertise | I85: Reasserts control over reply generation, agrees to reframe evidence as synthesis rather than research, and reserves a fuller study for later. | J85: AI records the position and asks to move to the next point; the human remains the source of the substantive reply strategy. | K85: p36 L45-p37 L6 | L85: p37 L8-p37 L15 | N85: Visible substantive response | P85: =SUM(Paper2Coding[[#This Row],[Open Delegation]:[Expertise]]) -> 8 | Q85: =IF(OR(E85="Delegation",ISNUMBER(SEARCH("; Delegation; ","; "&F85&"; "))),1,0) -> 0 | R85: =IF(OR(E85="Directed delegation",ISNUMBER(SEARCH("; Directed delegation; ","; "&F85&"; "))),1,0) -> 0 | S85: =IF(OR(E85="Evaluation",ISNUMBER(SEARCH("; Evaluation; ","; "&F85&"; "))),1,0) -> 0 | T85: =IF(OR(E85="Correction/Challenge",ISNUMBER(SEARCH("; Correction/Challenge; ","; "&F85&"; "))),1,0) -> 1 | U85: =IF(OR(E85="Redirection",ISNUMBER(SEARCH("; Redirection; ","; "&F85&"; "))),1,0) -> 1 | V85: =IF(OR(E85="Knowledge injection",ISNUMBER(SEARCH("; Knowledge injection; ","; "&F85&"; "))),1,0) -> 1 | W85: =IF(OR(E85="Selection/Rejection",ISNUMBER(SEARCH("; Selection/Rejection; ","; "&F85&"; "))),1,0) -> 1 | X85: =IF(OR(E85="Deliberation",ISNUMBER(SEARCH("; Deliberation; ","; "&F85&"; "))),1,0) -> 0 | Y85: =SUM(Paper2Coding[[#This Row],[Subject-matter correction]:[none]]) -> 4 | Z85: =IF(ISNUMBER(SEARCH("; domain correction; ","; "&H85&"; ")),1,0) -> 0 | AA85: =IF(ISNUMBER(SEARCH("; conceptual discrimination; ","; "&H85&"; ")),1,0) -> 0 | AB85: =IF(ISNUMBER(SEARCH("; evidence judgment; ","; "&H85&"; ")),1,0) -> 1 | AC85: =IF(ISNUMBER(SEARCH("; methodological judgment; ","; "&H85&"; ")),1,0) -> 1 | AD85: =IF(ISNUMBER(SEARCH("; argumentative judgment; ","; "&H85&"; ")),1,0) -> 1 | AE85: =IF(ISNUMBER(SEARCH("; genre/writing expertise; ","; "&H85&"; ")),1,0) -> 1 | AF85: =IF(ISNUMBER(SEARCH("; none; ","; "&H85&"; ")),1,0) -> 0
A86: P2-085 | B86: 85 | C86: Feedback and reframing | D86: NEXT point: The current title “Hidden Costs of AI” feels too broad, since the paper only covers two key issues (oversight and cognitive overload), while practitioners might expect other costs to be included (energy consumption, onboarding, security, tool updating, etc.). MY id... | E86: Deliberation | F86: Correction/Challenge; Selection/Rejection; Knowledge injection | G86: Deliberative | H86: conceptual discrimination; argumentative judgment; genre/writing expertise | I86: Accepts the scope criticism, proposes human costs as a narrower framing and compares it with the reviewer's less precise alternative. | J86: AI acknowledges the revised framing and deferred other costs; no final title choice is logged here. | K86: p37 L16-p37 L21 | L86: p37 L23-p37 L32 | N86: Visible substantive response | P86: =SUM(Paper2Coding[[#This Row],[Open Delegation]:[Expertise]]) -> 7 | Q86: =IF(OR(E86="Delegation",ISNUMBER(SEARCH("; Delegation; ","; "&F86&"; "))),1,0) -> 0 | R86: =IF(OR(E86="Directed delegation",ISNUMBER(SEARCH("; Directed delegation; ","; "&F86&"; "))),1,0) -> 0 | S86: =IF(OR(E86="Evaluation",ISNUMBER(SEARCH("; Evaluation; ","; "&F86&"; "))),1,0) -> 0 | T86: =IF(OR(E86="Correction/Challenge",ISNUMBER(SEARCH("; Correction/Challenge; ","; "&F86&"; "))),1,0) -> 1 | U86: =IF(OR(E86="Redirection",ISNUMBER(SEARCH("; Redirection; ","; "&F86&"; "))),1,0) -> 0 | V86: =IF(OR(E86="Knowledge injection",ISNUMBER(SEARCH("; Knowledge injection; ","; "&F86&"; "))),1,0) -> 1 | W86: =IF(OR(E86="Selection/Rejection",ISNUMBER(SEARCH("; Selection/Rejection; ","; "&F86&"; "))),1,0) -> 1 | X86: =IF(OR(E86="Deliberation",ISNUMBER(SEARCH("; Deliberation; ","; "&F86&"; "))),1,0) -> 1 | Y86: =SUM(Paper2Coding[[#This Row],[Subject-matter correction]:[none]]) -> 3 | Z86: =IF(ISNUMBER(SEARCH("; domain correction; ","; "&H86&"; ")),1,0) -> 0 | AA86: =IF(ISNUMBER(SEARCH("; conceptual discrimination; ","; "&H86&"; ")),1,0) -> 1 | AB86: =IF(ISNUMBER(SEARCH("; evidence judgment; ","; "&H86&"; ")),1,0) -> 0 | AC86: =IF(ISNUMBER(SEARCH("; methodological judgment; ","; "&H86&"; ")),1,0) -> 0 | AD86: =IF(ISNUMBER(SEARCH("; argumentative judgment; ","; "&H86&"; ")),1,0) -> 1 | AE86: =IF(ISNUMBER(SEARCH("; genre/writing expertise; ","; "&H86&"; ")),1,0) -> 1 | AF86: =IF(ISNUMBER(SEARCH("; none; ","; "&H86&"; ")),1,0) -> 0
A87: P2-086 | B87: 86 | C87: Feedback and reframing | D87: NEXT point: Clarifying that the focus is specifically on two hidden costs, rather than all, would avoid misleading expectations. suggest a few title options including terms: oversight and cognitive overload | E87: Directed delegation | F87: Redirection | G87: Directive | H87: genre/writing expertise; argumentative judgment | I87: Constrains title alternatives to explicitly naming oversight and cognitive overload. | J87: AI supplies five title options. | K87: p37 L33-p37 L34 | L87: p37 L35-p37 L42 | N87: Visible substantive response | P87: =SUM(Paper2Coding[[#This Row],[Open Delegation]:[Expertise]]) -> 4 | Q87: =IF(OR(E87="Delegation",ISNUMBER(SEARCH("; Delegation; ","; "&F87&"; "))),1,0) -> 0 | R87: =IF(OR(E87="Directed delegation",ISNUMBER(SEARCH("; Directed delegation; ","; "&F87&"; "))),1,0) -> 1 | S87: =IF(OR(E87="Evaluation",ISNUMBER(SEARCH("; Evaluation; ","; "&F87&"; "))),1,0) -> 0 | T87: =IF(OR(E87="Correction/Challenge",ISNUMBER(SEARCH("; Correction/Challenge; ","; "&F87&"; "))),1,0) -> 0 | U87: =IF(OR(E87="Redirection",ISNUMBER(SEARCH("; Redirection; ","; "&F87&"; "))),1,0) -> 1 | V87: =IF(OR(E87="Knowledge injection",ISNUMBER(SEARCH("; Knowledge injection; ","; "&F87&"; "))),1,0) -> 0 | W87: =IF(OR(E87="Selection/Rejection",ISNUMBER(SEARCH("; Selection/Rejection; ","; "&F87&"; "))),1,0) -> 0 | X87: =IF(OR(E87="Deliberation",ISNUMBER(SEARCH("; Deliberation; ","; "&F87&"; "))),1,0) -> 0 | Y87: =SUM(Paper2Coding[[#This Row],[Subject-matter correction]:[none]]) -> 2 | Z87: =IF(ISNUMBER(SEARCH("; domain correction; ","; "&H87&"; ")),1,0) -> 0 | AA87: =IF(ISNUMBER(SEARCH("; conceptual discrimination; ","; "&H87&"; ")),1,0) -> 0 | AB87: =IF(ISNUMBER(SEARCH("; evidence judgment; ","; "&H87&"; ")),1,0) -> 0 | AC87: =IF(ISNUMBER(SEARCH("; methodological judgment; ","; "&H87&"; ")),1,0) -> 0 | AD87: =IF(ISNUMBER(SEARCH("; argumentative judgment; ","; "&H87&"; ")),1,0) -> 1 | AE87: =IF(ISNUMBER(SEARCH("; genre/writing expertise; ","; "&H87&"; ")),1,0) -> 1 | AF87: =IF(ISNUMBER(SEARCH("; none; ","; "&H87&"; ")),1,0) -> 0
A88: P2-087 | B88: 87 | C88: Feedback and reframing | D88: Hidden Human Costs of other ways to saying this phrase? what about this style --> Need for human Oversight and their Cognitive Overload by AI: Cost efficiency of using AI in Software Engineering | E88: Evaluation | F88: Directed delegation; Knowledge injection | G88: Evaluative | H88: genre/writing expertise; argumentative judgment | I88: Tests an alternative title style and requests paraphrases rather than committing to a final version. | J88: AI offers variants; this remains title evaluation, not a substantive deliberation over the cost model. | K88: p38 L1-p38 L3 | L88: p38 L4-p38 L13 | N88: Visible substantive response | P88: =SUM(Paper2Coding[[#This Row],[Open Delegation]:[Expertise]]) -> 5 | Q88: =IF(OR(E88="Delegation",ISNUMBER(SEARCH("; Delegation; ","; "&F88&"; "))),1,0) -> 0 | R88: =IF(OR(E88="Directed delegation",ISNUMBER(SEARCH("; Directed delegation; ","; "&F88&"; "))),1,0) -> 1 | S88: =IF(OR(E88="Evaluation",ISNUMBER(SEARCH("; Evaluation; ","; "&F88&"; "))),1,0) -> 1 | T88: =IF(OR(E88="Correction/Challenge",ISNUMBER(SEARCH("; Correction/Challenge; ","; "&F88&"; "))),1,0) -> 0 | U88: =IF(OR(E88="Redirection",ISNUMBER(SEARCH("; Redirection; ","; "&F88&"; "))),1,0) -> 0 | V88: =IF(OR(E88="Knowledge injection",ISNUMBER(SEARCH("; Knowledge injection; ","; "&F88&"; "))),1,0) -> 1 | W88: =IF(OR(E88="Selection/Rejection",ISNUMBER(SEARCH("; Selection/Rejection; ","; "&F88&"; "))),1,0) -> 0 | X88: =IF(OR(E88="Deliberation",ISNUMBER(SEARCH("; Deliberation; ","; "&F88&"; "))),1,0) -> 0 | Y88: =SUM(Paper2Coding[[#This Row],[Subject-matter correction]:[none]]) -> 2 | Z88: =IF(ISNUMBER(SEARCH("; domain correction; ","; "&H88&"; ")),1,0) -> 0 | AA88: =IF(ISNUMBER(SEARCH("; conceptual discrimination; ","; "&H88&"; ")),1,0) -> 0 | AB88: =IF(ISNUMBER(SEARCH("; evidence judgment; ","; "&H88&"; ")),1,0) -> 0 | AC88: =IF(ISNUMBER(SEARCH("; methodological judgment; ","; "&H88&"; ")),1,0) -> 0 | AD88: =IF(ISNUMBER(SEARCH("; argumentative judgment; ","; "&H88&"; ")),1,0) -> 1 | AE88: =IF(ISNUMBER(SEARCH("; genre/writing expertise; ","; "&H88&"; ")),1,0) -> 1 | AF88: =IF(ISNUMBER(SEARCH("; none; ","; "&H88&"; ")),1,0) -> 0
A89: P2-088 | B89: 88 | C89: Feedback and reframing | D89: So I'm attaching the last version of the paper and the improvement plans that I have in mind. So help me one by one, please go through the improvement ideas one by one, and we also discuss them, you have it in the chat about, and tell me, give me exact ideas, exact places to i... | E89: Directed delegation | F89: Knowledge injection | G89: Directive | H89: genre/writing expertise; argumentative judgment | I89: Supplies manuscript and improvement plans, requiring sequential discussion, exact locations and copy-ready revision text. | J89: AI starts with evidence-framing revisions and suggests locations and replacement text. | K89: p38 L16-p38 L18 | L89: p38 L20-p39 L3 | M89: improvement.docx Hidden Burdens of AI SE-IEEE SW-Sept 11.docx | N89: Visible substantive response | P89: =SUM(Paper2Coding[[#This Row],[Open Delegation]:[Expertise]]) -> 4 | Q89: =IF(OR(E89="Delegation",ISNUMBER(SEARCH("; Delegation; ","; "&F89&"; "))),1,0) -> 0 | R89: =IF(OR(E89="Directed delegation",ISNUMBER(SEARCH("; Directed delegation; ","; "&F89&"; "))),1,0) -> 1 | S89: =IF(OR(E89="Evaluation",ISNUMBER(SEARCH("; Evaluation; ","; "&F89&"; "))),1,0) -> 0 | T89: =IF(OR(E89="Correction/Challenge",ISNUMBER(SEARCH("; Correction/Challenge; ","; "&F89&"; "))),1,0) -> 0 | U89: =IF(OR(E89="Redirection",ISNUMBER(SEARCH("; Redirection; ","; "&F89&"; "))),1,0) -> 0 | V89: =IF(OR(E89="Knowledge injection",ISNUMBER(SEARCH("; Knowledge injection; ","; "&F89&"; "))),1,0) -> 1 | W89: =IF(OR(E89="Selection/Rejection",ISNUMBER(SEARCH("; Selection/Rejection; ","; "&F89&"; "))),1,0) -> 0 | X89: =IF(OR(E89="Deliberation",ISNUMBER(SEARCH("; Deliberation; ","; "&F89&"; "))),1,0) -> 0 | Y89: =SUM(Paper2Coding[[#This Row],[Subject-matter correction]:[none]]) -> 2 | Z89: =IF(ISNUMBER(SEARCH("; domain correction; ","; "&H89&"; ")),1,0) -> 0 | AA89: =IF(ISNUMBER(SEARCH("; conceptual discrimination; ","; "&H89&"; ")),1,0) -> 0 | AB89: =IF(ISNUMBER(SEARCH("; evidence judgment; ","; "&H89&"; ")),1,0) -> 0 | AC89: =IF(ISNUMBER(SEARCH("; methodological judgment; ","; "&H89&"; ")),1,0) -> 0 | AD89: =IF(ISNUMBER(SEARCH("; argumentative judgment; ","; "&H89&"; ")),1,0) -> 1 | AE89: =IF(ISNUMBER(SEARCH("; genre/writing expertise; ","; "&H89&"; ")),1,0) -> 1 | AF89: =IF(ISNUMBER(SEARCH("; none; ","; "&H89&"; ")),1,0) -> 0
