Workbook

Sheet Summary
A2: Diagnosing quality of higher education
A3: Human–AI interaction coding • single first-pass analysis • counts reflect category presence
A5: Human prompts | B5: 119 | D5: Count revised: 122 → 119 after joining continuation fragments.
A6: No next AI response | B6: 1 | D6: Expertise “none” = no explicit evidence in that prompt.
A8: Interaction type | B8: Primary count | C8: Any occurrence | D8: Share of prompts | F8: Agency mode | G8: Prompts | H8: Share | J8: Expertise evidence | K8: Prompts | L8: Share
A9: Open Delegation | B9: =COUNTIFS(Coding!$E$2:$E$120,A9) -> 0 | C9: =SUM(Coding!Q2:Q120) -> 2 | D9: =C9/$B$5 -> 0.016806723 | F9: Delegative | G9: =COUNTIFS(Coding!$G$2:$G$120,F9) -> 2 | H9: =G9/$B$5 -> 0.016806723 | J9: domain correction | K9: =SUM(Coding!Z2:Z120) -> 10 | L9: =K9/$B$5 -> 0.084033613
A10: Directed delegation | B10: =COUNTIFS(Coding!$E$2:$E$120,A10) -> 40 | C10: =SUM(Coding!R2:R120) -> 81 | D10: =C10/$B$5 -> 0.68067227 | F10: Directive | G10: =COUNTIFS(Coding!$G$2:$G$120,F10) -> 69 | H10: =G10/$B$5 -> 0.57983193 | J10: conceptual discrimination | K10: =SUM(Coding!AA2:AA120) -> 28 | L10: =K10/$B$5 -> 0.23529412
A11: Evaluation | B11: =COUNTIFS(Coding!$E$2:$E$120,A11) -> 17 | C11: =SUM(Coding!S2:S120) -> 23 | D11: =C11/$B$5 -> 0.19327731 | F11: Evaluative | G11: =COUNTIFS(Coding!$G$2:$G$120,F11) -> 18 | H11: =G11/$B$5 -> 0.1512605 | J11: evidence judgment | K11: =SUM(Coding!AB2:AB120) -> 29 | L11: =K11/$B$5 -> 0.24369748
A12: Correction/Challenge | B12: =COUNTIFS(Coding!$E$2:$E$120,A12) -> 26 | C12: =SUM(Coding!T2:T120) -> 27 | D12: =C12/$B$5 -> 0.22689076 | F12: Critical | G12: =COUNTIFS(Coding!$G$2:$G$120,F12) -> 26 | H12: =G12/$B$5 -> 0.21848739 | J12: methodological judgment | K12: =SUM(Coding!AC2:AC120) -> 23 | L12: =K12/$B$5 -> 0.19327731
A13: Redirection | B13: =COUNTIFS(Coding!$E$2:$E$120,A13) -> 10 | C13: =SUM(Coding!U2:U120) -> 26 | D13: =C13/$B$5 -> 0.21848739 | F13: Deliberative | G13: =COUNTIFS(Coding!$G$2:$G$120,F13) -> 4 | H13: =G13/$B$5 -> 0.033613445 | J13: argumentative judgment | K13: =SUM(Coding!AD2:AD120) -> 32 | L13: =K13/$B$5 -> 0.26890756
A14: Knowledge/context provision | B14: =COUNTIFS(Coding!$E$2:$E$120,A14) -> 0 | C14: =SUM(Coding!V2:V120) -> 62 | D14: =C14/$B$5 -> 0.5210084 | J14: genre/writing expertise | K14: =SUM(Coding!AE2:AE120) -> 66 | L14: =K14/$B$5 -> 0.55462185
A15: Selection/Rejection | B15: =COUNTIFS(Coding!$E$2:$E$120,A15) -> 2 | C15: =SUM(Coding!W2:W120) -> 2 | D15: =C15/$B$5 -> 0.016806723 | F15: Positive expertise evidence | G15: =$B$5-SUM(Coding!AF2:AF120) -> 105 | J15: none | K15: =SUM(Coding!AF2:AF120) -> 14 | L15: =K15/$B$5 -> 0.11764706
A16: Deliberation | B16: =COUNTIFS(Coding!$E$2:$E$120,A16) -> 4 | C16: =SUM(Coding!X2:X120) -> 4 | D16: =C16/$B$5 -> 0.033613445 | F16: Share with evidence | G16: =G15/$B$5 -> 0.88235294
A19: Phase | B19: First prompt | C19: Last prompt | D19: Prompts | E19: Delegative | F19: Directive | G19: Evaluative | H19: Critical | I19: Deliberative
A20: Conceptual framing and model | B20: 1 | C20: 25 | D20: =COUNTIFS(Coding!$C$2:$C$120,A20) -> 25 | E20: =COUNTIFS(Coding!$C$2:$C$120,$A20,Coding!$G$2:$G$120,"Delegative") -> 1 | F20: =COUNTIFS(Coding!$C$2:$C$120,$A20,Coding!$G$2:$G$120,"Directive") -> 15 | G20: =COUNTIFS(Coding!$C$2:$C$120,$A20,Coding!$G$2:$G$120,"Evaluative") -> 5 | H20: =COUNTIFS(Coding!$C$2:$C$120,$A20,Coding!$G$2:$G$120,"Critical") -> 4 | I20: =COUNTIFS(Coding!$C$2:$C$120,$A20,Coding!$G$2:$G$120,"Deliberative") -> 0
A21: Structure and research design | B21: 26 | C21: 45 | D21: =COUNTIFS(Coding!$C$2:$C$120,A21) -> 20 | E21: =COUNTIFS(Coding!$C$2:$C$120,$A21,Coding!$G$2:$G$120,"Delegative") -> 1 | F21: =COUNTIFS(Coding!$C$2:$C$120,$A21,Coding!$G$2:$G$120,"Directive") -> 13 | G21: =COUNTIFS(Coding!$C$2:$C$120,$A21,Coding!$G$2:$G$120,"Evaluative") -> 1 | H21: =COUNTIFS(Coding!$C$2:$C$120,$A21,Coding!$G$2:$G$120,"Critical") -> 5 | I21: =COUNTIFS(Coding!$C$2:$C$120,$A21,Coding!$G$2:$G$120,"Deliberative") -> 0
A22: Diagnosis, model and reforms | B22: 46 | C22: 82 | D22: =COUNTIFS(Coding!$C$2:$C$120,A22) -> 37 | E22: =COUNTIFS(Coding!$C$2:$C$120,$A22,Coding!$G$2:$G$120,"Delegative") -> 0 | F22: =COUNTIFS(Coding!$C$2:$C$120,$A22,Coding!$G$2:$G$120,"Directive") -> 20 | G22: =COUNTIFS(Coding!$C$2:$C$120,$A22,Coding!$G$2:$G$120,"Evaluative") -> 7 | H22: =COUNTIFS(Coding!$C$2:$C$120,$A22,Coding!$G$2:$G$120,"Critical") -> 9 | I22: =COUNTIFS(Coding!$C$2:$C$120,$A22,Coding!$G$2:$G$120,"Deliberative") -> 1
A23: Review and submission preparation | B23: 83 | C23: 117 | D23: =COUNTIFS(Coding!$C$2:$C$120,A23) -> 35 | E23: =COUNTIFS(Coding!$C$2:$C$120,$A23,Coding!$G$2:$G$120,"Delegative") -> 0 | F23: =COUNTIFS(Coding!$C$2:$C$120,$A23,Coding!$G$2:$G$120,"Directive") -> 20 | G23: =COUNTIFS(Coding!$C$2:$C$120,$A23,Coding!$G$2:$G$120,"Evaluative") -> 5 | H23: =COUNTIFS(Coding!$C$2:$C$120,$A23,Coding!$G$2:$G$120,"Critical") -> 7 | I23: =COUNTIFS(Coding!$C$2:$C$120,$A23,Coding!$G$2:$G$120,"Deliberative") -> 3
A24: Follow-on paper planning | B24: 118 | C24: 119 | D24: =COUNTIFS(Coding!$C$2:$C$120,A24) -> 2 | E24: =COUNTIFS(Coding!$C$2:$C$120,$A24,Coding!$G$2:$G$120,"Delegative") -> 0 | F24: =COUNTIFS(Coding!$C$2:$C$120,$A24,Coding!$G$2:$G$120,"Directive") -> 1 | G24: =COUNTIFS(Coding!$C$2:$C$120,$A24,Coding!$G$2:$G$120,"Evaluative") -> 0 | H24: =COUNTIFS(Coding!$C$2:$C$120,$A24,Coding!$G$2:$G$120,"Critical") -> 1 | I24: =COUNTIFS(Coding!$C$2:$C$120,$A24,Coding!$G$2:$G$120,"Deliberative") -> 0
A28: Key coding patterns and limits
A29: Directed delegation occurs in 81/119 prompts (68.1%); knowledge injection in 62 (52.1%). The researcher frequently supplies the substance and constrains AI drafting.
A30: Critical agency occurs in 26 prompts (21.8%). Challenges cover causal-loop terminology (25,119), study scope (29), survey omission (40), report relevance (103–107) and wording.
A31: Positive expertise evidence is coded in 105/119 prompts (88.2%); genre/writing in 66, argumentative judgment in 32, conceptual discrimination in 28, evidence judgment in 29.
A32: The model develops through researcher-supplied categories, arrows and mechanisms (5,10,24–25,60,66,93,116). Technical corrections recur alongside manuscript editing.
A33: Evidence control appears in source chronology (48–50), survey design/findings (32,40–42,53), and challenges to older or irrelevant reports (99–104,112).
A34: Two prompts after reported submission (118–119) develop a generic model paper. They are retained but separately labelled for manuscript-only comparisons.
A35: The converted Word export needs careful boundary interpretation. These 119 text-bearing prompts do not establish completeness of the original chat.

Sheet Coding
A1: Prompt ID | B1: Sequence | C1: Phase | D1: Prompt excerpt | E1: Primary interaction type | F1: Additional interaction types | G1: Agency mode | H1: Expertise evidence | I1: Coding rationale | J1: Observed outcome / notes | K1: Prompt provenance | L1: Response provenance | M1: Attachment / contextual material | N1: Response availability | O1: Coding caution | P1: Interaction codes | Q1: Type: Delegation | R1: Type: Directed delegation | S1: Type: Evaluation | T1: Type: Correction/Challenge | U1: Type: Redirection | V1: Type: Knowledge injection | W1: Type: Selection/Rejection | X1: Type: Deliberation | Y1: Expertise codes | Z1: Expertise: domain correction | AA1: Expertise: conceptual discrimination | AB1: Expertise: evidence judgment | AC1: Expertise: methodological judgment | AD1: Expertise: argumentative judgment | AE1: Expertise: genre/writing expertise | AF1: Expertise: none
A2: HE-001 | B2: 1 | C2: Conceptual framing and model | D2: paper idea: Azərbaycanımızın Təhsil Sisteminin Sistemli İslahat və İnkişafı üçün Birinci Addım: Sistemin Praqmatik və Diaqnostik Analizi a "macro"-systems analysis (country level) ---------------- -use insights from https://en.wikipedia.org/wiki/Education_in_Azerbaijan when releavant in my paperlook here https://projects.worldbank.org/en/projects-operations/project-detail/P102117 it was a major project called "Second… | E2: Directed delegation | F2: Knowledge injection; Evaluation | G2: Directive | H2: methodological judgment; evidence judgment; argumentative judgment | I2: Frames a macro diagnostic study, supplies report findings and requests checking the model/materials. | J2: AI proposes a systems analysis and interprets supplied reports; access and evidence claims remain unverified. | K2: DOCX body elements 7–15 | L2: DOCX body elements 18–212 | M2: URL(s) supplied in prompt; File/context references in prompt; inspect full text; Extended draft/quoted context; researcher-origin judgment distinguished in rationale | N2: Visible next AI response | O2: Converted DOCX: textbox continuations joined; AI completion/source-check claims are unverified. | P2: =SUM(Q2:X2) -> 3 | Q2: =IF(OR(E2="Delegation",ISNUMBER(SEARCH("; Delegation; ","; "&F2&"; "))),1,0) -> 0 | R2: =IF(OR(E2="Directed delegation",ISNUMBER(SEARCH("; Directed delegation; ","; "&F2&"; "))),1,0) -> 1 | S2: =IF(OR(E2="Evaluation",ISNUMBER(SEARCH("; Evaluation; ","; "&F2&"; "))),1,0) -> 1 | T2: =IF(OR(E2="Correction/Challenge",ISNUMBER(SEARCH("; Correction/Challenge; ","; "&F2&"; "))),1,0) -> 0 | U2: =IF(OR(E2="Redirection",ISNUMBER(SEARCH("; Redirection; ","; "&F2&"; "))),1,0) -> 0 | V2: =IF(OR(E2="Knowledge injection",ISNUMBER(SEARCH("; Knowledge injection; ","; "&F2&"; "))),1,0) -> 1 | W2: =IF(OR(E2="Selection/Rejection",ISNUMBER(SEARCH("; Selection/Rejection; ","; "&F2&"; "))),1,0) -> 0 | X2: =IF(OR(E2="Deliberation",ISNUMBER(SEARCH("; Deliberation; ","; "&F2&"; "))),1,0) -> 0 | Y2: =SUM(Z2:AE2) -> 3 | Z2: =IF(ISNUMBER(SEARCH("; domain correction; ","; "&H2&"; ")),1,0) -> 0 | AA2: =IF(ISNUMBER(SEARCH("; conceptual discrimination; ","; "&H2&"; ")),1,0) -> 0 | AB2: =IF(ISNUMBER(SEARCH("; evidence judgment; ","; "&H2&"; ")),1,0) -> 1 | AC2: =IF(ISNUMBER(SEARCH("; methodological judgment; ","; "&H2&"; ")),1,0) -> 1 | AD2: =IF(ISNUMBER(SEARCH("; argumentative judgment; ","; "&H2&"; ")),1,0) -> 1 | AE2: =IF(ISNUMBER(SEARCH("; genre/writing expertise; ","; "&H2&"; ")),1,0) -> 0 | AF2: =IF(ISNUMBER(SEARCH("; none; ","; "&H2&"; ")),1,0) -> 0
A3: HE-002 | B3: 2 | C3: Conceptual framing and model | D3: max paper legnth is 8000. target: https://www.as-journal.edu.az/instruction_az ... also, I still prefer my title: Azərbaycanımızın Təhsil Sisteminin Sistemli İslahat və İnkişafı üçün Birinci Addım: Sistemin Praqmatik və Diaqnostik Analizi --- since I need to keep the title soft (not too critical, or they will not like it, it can upset many people in AZ!) | E3: Directed delegation | F3: Redirection; Knowledge injection | G3: Directive | H3: genre/writing expertise; argumentative judgment | I3: Sets length and audience constraints and moderates a potentially confrontational title. | J3: AI proposes softer titles and a paper structure. | K3: DOCX body elements 213–213 | L3: DOCX body elements 216–717 | M3: URL(s) supplied in prompt | N3: Visible next AI response | O3: Converted DOCX: textbox continuations joined; AI completion/source-check claims are unverified. | P3: =SUM(Q3:X3) -> 3 | Q3: =IF(OR(E3="Delegation",ISNUMBER(SEARCH("; Delegation; ","; "&F3&"; "))),1,0) -> 0 | R3: =IF(OR(E3="Directed delegation",ISNUMBER(SEARCH("; Directed delegation; ","; "&F3&"; "))),1,0) -> 1 | S3: =IF(OR(E3="Evaluation",ISNUMBER(SEARCH("; Evaluation; ","; "&F3&"; "))),1,0) -> 0 | T3: =IF(OR(E3="Correction/Challenge",ISNUMBER(SEARCH("; Correction/Challenge; ","; "&F3&"; "))),1,0) -> 0 | U3: =IF(OR(E3="Redirection",ISNUMBER(SEARCH("; Redirection; ","; "&F3&"; "))),1,0) -> 1 | V3: =IF(OR(E3="Knowledge injection",ISNUMBER(SEARCH("; Knowledge injection; ","; "&F3&"; "))),1,0) -> 1 | W3: =IF(OR(E3="Selection/Rejection",ISNUMBER(SEARCH("; Selection/Rejection; ","; "&F3&"; "))),1,0) -> 0 | X3: =IF(OR(E3="Deliberation",ISNUMBER(SEARCH("; Deliberation; ","; "&F3&"; "))),1,0) -> 0 | Y3: =SUM(Z3:AE3) -> 2 | Z3: =IF(ISNUMBER(SEARCH("; domain correction; ","; "&H3&"; ")),1,0) -> 0 | AA3: =IF(ISNUMBER(SEARCH("; conceptual discrimination; ","; "&H3&"; ")),1,0) -> 0 | AB3: =IF(ISNUMBER(SEARCH("; evidence judgment; ","; "&H3&"; ")),1,0) -> 0 | AC3: =IF(ISNUMBER(SEARCH("; methodological judgment; ","; "&H3&"; ")),1,0) -> 0 | AD3: =IF(ISNUMBER(SEARCH("; argumentative judgment; ","; "&H3&"; ")),1,0) -> 1 | AE3: =IF(ISNUMBER(SEARCH("; genre/writing expertise; ","; "&H3&"; ")),1,0) -> 1 | AF3: =IF(ISNUMBER(SEARCH("; none; ","; "&H3&"; ")),1,0) -> 0
A4: HE-003 | B4: 3 | C4: Conceptual framing and model | D4: I also put the longer file pdf in the folder : "Implementation Completion and Results Report" .... read it . lots of it is about the financial transactions, of course. Ignore them completely, but some of its discussions are about the, you know, performance and technical performance. Okay. Non financials. So, yeah, use those ideas as well. By the way, you have too many sections and subsections. You need to reduce them… | E4: Directed delegation | F4: Knowledge injection; Redirection; Correction/Challenge | G4: Directive | H4: evidence judgment; genre/writing expertise | I4: Adds a report and directs nonfinancial emphasis and fewer headings. | J4: AI begins a revised plan; response is interrupted in the record. | K4: DOCX body elements 718–718 | L4: DOCX body elements 722–726 | N4: Visible next AI response | O4: Converted DOCX: textbox continuations joined; AI completion/source-check claims are unverified. | P4: =SUM(Q4:X4) -> 4 | Q4: =IF(OR(E4="Delegation",ISNUMBER(SEARCH("; Delegation; ","; "&F4&"; "))),1,0) -> 0 | R4: =IF(OR(E4="Directed delegation",ISNUMBER(SEARCH("; Directed delegation; ","; "&F4&"; "))),1,0) -> 1 | S4: =IF(OR(E4="Evaluation",ISNUMBER(SEARCH("; Evaluation; ","; "&F4&"; "))),1,0) -> 0 | T4: =IF(OR(E4="Correction/Challenge",ISNUMBER(SEARCH("; Correction/Challenge; ","; "&F4&"; "))),1,0) -> 1 | U4: =IF(OR(E4="Redirection",ISNUMBER(SEARCH("; Redirection; ","; "&F4&"; "))),1,0) -> 1 | V4: =IF(OR(E4="Knowledge injection",ISNUMBER(SEARCH("; Knowledge injection; ","; "&F4&"; "))),1,0) -> 1 | W4: =IF(OR(E4="Selection/Rejection",ISNUMBER(SEARCH("; Selection/Rejection; ","; "&F4&"; "))),1,0) -> 0 | X4: =IF(OR(E4="Deliberation",ISNUMBER(SEARCH("; Deliberation; ","; "&F4&"; "))),1,0) -> 0 | Y4: =SUM(Z4:AE4) -> 2 | Z4: =IF(ISNUMBER(SEARCH("; domain correction; ","; "&H4&"; ")),1,0) -> 0 | AA4: =IF(ISNUMBER(SEARCH("; conceptual discrimination; ","; "&H4&"; ")),1,0) -> 0 | AB4: =IF(ISNUMBER(SEARCH("; evidence judgment; ","; "&H4&"; ")),1,0) -> 1 | AC4: =IF(ISNUMBER(SEARCH("; methodological judgment; ","; "&H4&"; ")),1,0) -> 0 | AD4: =IF(ISNUMBER(SEARCH("; argumentative judgment; ","; "&H4&"; ")),1,0) -> 0 | AE4: =IF(ISNUMBER(SEARCH("; genre/writing expertise; ","; "&H4&"; ")),1,0) -> 1 | AF4: =IF(ISNUMBER(SEARCH("; none; ","; "&H4&"; ")),1,0) -> 0
A5: HE-004 | B5: 4 | C5: Conceptual framing and model | D5: Don't focus too much on that World Bank thing because I gave you several other data points. So I don't want one of them come across as the main one. The other one, um, I think, yeah, the PISA. So PISA and that world thing, uh, should be two main things. I also put the longer file pdf in the folder : "Implementation Completion and Results Report" read it . lots of it is about thefinancial transactions, of course. Igno… | E5: Redirection | F5: Directed delegation; Knowledge injection | G5: Directive | H5: evidence judgment; argumentative judgment; genre/writing expertise | I5: Rebalances the evidence sources and repeats structural constraints. | J5: AI revises emphasis and structure. | K5: DOCX body elements 728–728 | L5: DOCX body elements 731–999 | N5: Visible next AI response | O5: Converted DOCX: textbox continuations joined; AI completion/source-check claims are unverified. | P5: =SUM(Q5:X5) -> 3 | Q5: =IF(OR(E5="Delegation",ISNUMBER(SEARCH("; Delegation; ","; "&F5&"; "))),1,0) -> 0 | R5: =IF(OR(E5="Directed delegation",ISNUMBER(SEARCH("; Directed delegation; ","; "&F5&"; "))),1,0) -> 1 | S5: =IF(OR(E5="Evaluation",ISNUMBER(SEARCH("; Evaluation; ","; "&F5&"; "))),1,0) -> 0 | T5: =IF(OR(E5="Correction/Challenge",ISNUMBER(SEARCH("; Correction/Challenge; ","; "&F5&"; "))),1,0) -> 0 | U5: =IF(OR(E5="Redirection",ISNUMBER(SEARCH("; Redirection; ","; "&F5&"; "))),1,0) -> 1 | V5: =IF(OR(E5="Knowledge injection",ISNUMBER(SEARCH("; Knowledge injection; ","; "&F5&"; "))),1,0) -> 1 | W5: =IF(OR(E5="Selection/Rejection",ISNUMBER(SEARCH("; Selection/Rejection; ","; "&F5&"; "))),1,0) -> 0 | X5: =IF(OR(E5="Deliberation",ISNUMBER(SEARCH("; Deliberation; ","; "&F5&"; "))),1,0) -> 0 | Y5: =SUM(Z5:AE5) -> 3 | Z5: =IF(ISNUMBER(SEARCH("; domain correction; ","; "&H5&"; ")),1,0) -> 0 | AA5: =IF(ISNUMBER(SEARCH("; conceptual discrimination; ","; "&H5&"; ")),1,0) -> 0 | AB5: =IF(ISNUMBER(SEARCH("; evidence judgment; ","; "&H5&"; ")),1,0) -> 1 | AC5: =IF(ISNUMBER(SEARCH("; methodological judgment; ","; "&H5&"; ")),1,0) -> 0 | AD5: =IF(ISNUMBER(SEARCH("; argumentative judgment; ","; "&H5&"; ")),1,0) -> 1 | AE5: =IF(ISNUMBER(SEARCH("; genre/writing expertise; ","; "&H5&"; ")),1,0) -> 1 | AF5: =IF(ISNUMBER(SEARCH("; none; ","; "&H5&"; ")),1,0) -> 0
A6: HE-005 | B6: 5 | C6: Conceptual framing and model | D6: I want this paper design. different than yours: 2-related work 3-Diaqnostik and weakness analysis PISA results , and the worldbank project: "Second Education Sector Development Project for Azerbaijan" do not include ANY finacial data / budget discussions 4-Causal loop diagram (Systems model): focus on higer ed, AZ universities factors: motivation of lecturers (muellimler), intrinsic motivation , extrinsic motivation … | E6: Knowledge injection | F6: Directed delegation; Redirection | G6: Directive | H6: methodological judgment; argumentative judgment | I6: Supplies the proposed paper structure and causal model actors. | J6: AI develops the structure around the researcher’s model. | K6: DOCX body elements 1000–1000 | L6: DOCX body elements 1003–1144 | N6: Visible next AI response | O6: Converted DOCX: textbox continuations joined; AI completion/source-check claims are unverified. | P6: =SUM(Q6:X6) -> 3 | Q6: =IF(OR(E6="Delegation",ISNUMBER(SEARCH("; Delegation; ","; "&F6&"; "))),1,0) -> 0 | R6: =IF(OR(E6="Directed delegation",ISNUMBER(SEARCH("; Directed delegation; ","; "&F6&"; "))),1,0) -> 1 | S6: =IF(OR(E6="Evaluation",ISNUMBER(SEARCH("; Evaluation; ","; "&F6&"; "))),1,0) -> 0 | T6: =IF(OR(E6="Correction/Challenge",ISNUMBER(SEARCH("; Correction/Challenge; ","; "&F6&"; "))),1,0) -> 0 | U6: =IF(OR(E6="Redirection",ISNUMBER(SEARCH("; Redirection; ","; "&F6&"; "))),1,0) -> 1 | V6: =IF(OR(E6="Knowledge injection",ISNUMBER(SEARCH("; Knowledge injection; ","; "&F6&"; "))),1,0) -> 1 | W6: =IF(OR(E6="Selection/Rejection",ISNUMBER(SEARCH("; Selection/Rejection; ","; "&F6&"; "))),1,0) -> 0 | X6: =IF(OR(E6="Deliberation",ISNUMBER(SEARCH("; Deliberation; ","; "&F6&"; "))),1,0) -> 0 | Y6: =SUM(Z6:AE6) -> 2 | Z6: =IF(ISNUMBER(SEARCH("; domain correction; ","; "&H6&"; ")),1,0) -> 0 | AA6: =IF(ISNUMBER(SEARCH("; conceptual discrimination; ","; "&H6&"; ")),1,0) -> 0 | AB6: =IF(ISNUMBER(SEARCH("; evidence judgment; ","; "&H6&"; ")),1,0) -> 0 | AC6: =IF(ISNUMBER(SEARCH("; methodological judgment; ","; "&H6&"; ")),1,0) -> 1 | AD6: =IF(ISNUMBER(SEARCH("; argumentative judgment; ","; "&H6&"; ")),1,0) -> 1 | AE6: =IF(ISNUMBER(SEARCH("; genre/writing expertise; ","; "&H6&"; ")),1,0) -> 0 | AF6: =IF(ISNUMBER(SEARCH("; none; ","; "&H6&"; ")),1,0) -> 0
A7: HE-006 | B7: 6 | C7: Conceptual framing and model | D7: remove H1 and H2 labels use more solid azerbaijani writing include as : 1.1 Tədqiqatçının Mövqeliyi and credentials: 25 İl Qərb Universitetlerinde Təcrübəsi və Daxili-Xarici Perspektivi 26 il: Kanada, Türkiyə, Böyük Britaniya also I have been doing Kurikulumun Müasirləşdirilməsi of the AzTU İTT faculty , and capaity buiolding, coaching / mentoring of academic staff. "teaching the teachers". I also taught Fənn-"Akadem… | E7: Redirection | F7: Directed delegation; Knowledge injection | G7: Directive | H7: methodological judgment; genre/writing expertise | I7: Rejects hypothesis labels, specifies Azerbaijani prose and supplies positional experience. | J7: AI revises the outline and merges sections. | K7: DOCX body elements 1145–1145 | L7: DOCX body elements 1148–1440 | N7: Visible next AI response | O7: Converted DOCX: textbox continuations joined; AI completion/source-check claims are unverified. | P7: =SUM(Q7:X7) -> 3 | Q7: =IF(OR(E7="Delegation",ISNUMBER(SEARCH("; Delegation; ","; "&F7&"; "))),1,0) -> 0 | R7: =IF(OR(E7="Directed delegation",ISNUMBER(SEARCH("; Directed delegation; ","; "&F7&"; "))),1,0) -> 1 | S7: =IF(OR(E7="Evaluation",ISNUMBER(SEARCH("; Evaluation; ","; "&F7&"; "))),1,0) -> 0 | T7: =IF(OR(E7="Correction/Challenge",ISNUMBER(SEARCH("; Correction/Challenge; ","; "&F7&"; "))),1,0) -> 0 | U7: =IF(OR(E7="Redirection",ISNUMBER(SEARCH("; Redirection; ","; "&F7&"; "))),1,0) -> 1 | V7: =IF(OR(E7="Knowledge injection",ISNUMBER(SEARCH("; Knowledge injection; ","; "&F7&"; "))),1,0) -> 1 | W7: =IF(OR(E7="Selection/Rejection",ISNUMBER(SEARCH("; Selection/Rejection; ","; "&F7&"; "))),1,0) -> 0 | X7: =IF(OR(E7="Deliberation",ISNUMBER(SEARCH("; Deliberation; ","; "&F7&"; "))),1,0) -> 0 | Y7: =SUM(Z7:AE7) -> 2 | Z7: =IF(ISNUMBER(SEARCH("; domain correction; ","; "&H7&"; ")),1,0) -> 0 | AA7: =IF(ISNUMBER(SEARCH("; conceptual discrimination; ","; "&H7&"; ")),1,0) -> 0 | AB7: =IF(ISNUMBER(SEARCH("; evidence judgment; ","; "&H7&"; ")),1,0) -> 0 | AC7: =IF(ISNUMBER(SEARCH("; methodological judgment; ","; "&H7&"; ")),1,0) -> 1 | AD7: =IF(ISNUMBER(SEARCH("; argumentative judgment; ","; "&H7&"; ")),1,0) -> 0 | AE7: =IF(ISNUMBER(SEARCH("; genre/writing expertise; ","; "&H7&"; ")),1,0) -> 1 | AF7: =IF(ISNUMBER(SEARCH("; none; ","; "&H7&"; ")),1,0) -> 0
A8: HE-007 | B8: 7 | C8: Conceptual framing and model | D8: what u meant by: Fərqin Məzənnələrinin Məhdud Məzənnə Dəyişikliyi??? | E8: Correction/Challenge | G8: Critical | H8: genre/writing expertise | I8: Questions an apparently garbled Azerbaijani phrase. | J8: AI acknowledges a wording error and replaces it. | K8: DOCX body elements 1441–1441 | L8: DOCX body elements 1444–1452 | N8: Visible next AI response | O8: Converted DOCX: textbox continuations joined; AI completion/source-check claims are unverified. | P8: =SUM(Q8:X8) -> 1 | Q8: =IF(OR(E8="Delegation",ISNUMBER(SEARCH("; Delegation; ","; "&F8&"; "))),1,0) -> 0 | R8: =IF(OR(E8="Directed delegation",ISNUMBER(SEARCH("; Directed delegation; ","; "&F8&"; "))),1,0) -> 0 | S8: =IF(OR(E8="Evaluation",ISNUMBER(SEARCH("; Evaluation; ","; "&F8&"; "))),1,0) -> 0 | T8: =IF(OR(E8="Correction/Challenge",ISNUMBER(SEARCH("; Correction/Challenge; ","; "&F8&"; "))),1,0) -> 1 | U8: =IF(OR(E8="Redirection",ISNUMBER(SEARCH("; Redirection; ","; "&F8&"; "))),1,0) -> 0 | V8: =IF(OR(E8="Knowledge injection",ISNUMBER(SEARCH("; Knowledge injection; ","; "&F8&"; "))),1,0) -> 0 | W8: =IF(OR(E8="Selection/Rejection",ISNUMBER(SEARCH("; Selection/Rejection; ","; "&F8&"; "))),1,0) -> 0 | X8: =IF(OR(E8="Deliberation",ISNUMBER(SEARCH("; Deliberation; ","; "&F8&"; "))),1,0) -> 0 | Y8: =SUM(Z8:AE8) -> 1 | Z8: =IF(ISNUMBER(SEARCH("; domain correction; ","; "&H8&"; ")),1,0) -> 0 | AA8: =IF(ISNUMBER(SEARCH("; conceptual discrimination; ","; "&H8&"; ")),1,0) -> 0 | AB8: =IF(ISNUMBER(SEARCH("; evidence judgment; ","; "&H8&"; ")),1,0) -> 0 | AC8: =IF(ISNUMBER(SEARCH("; methodological judgment; ","; "&H8&"; ")),1,0) -> 0 | AD8: =IF(ISNUMBER(SEARCH("; argumentative judgment; ","; "&H8&"; ")),1,0) -> 0 | AE8: =IF(ISNUMBER(SEARCH("; genre/writing expertise; ","; "&H8&"; ")),1,0) -> 1 | AF8: =IF(ISNUMBER(SEARCH("; none; ","; "&H8&"; ")),1,0) -> 0
A9: HE-008 | B9: 8 | C9: Conceptual framing and model | D9: regenerate the full TOC | E9: Directed delegation | G9: Directive | H9: none | I9: Requests regeneration of the table of contents without adding a substantive criterion. | J9: AI supplies a revised contents list. | K9: DOCX body elements 1453–1453 | L9: DOCX body elements 1456–1704 | N9: Visible next AI response | O9: Converted DOCX: textbox continuations joined; AI completion/source-check claims are unverified. | P9: =SUM(Q9:X9) -> 1 | Q9: =IF(OR(E9="Delegation",ISNUMBER(SEARCH("; Delegation; ","; "&F9&"; "))),1,0) -> 0 | R9: =IF(OR(E9="Directed delegation",ISNUMBER(SEARCH("; Directed delegation; ","; "&F9&"; "))),1,0) -> 1 | S9: =IF(OR(E9="Evaluation",ISNUMBER(SEARCH("; Evaluation; ","; "&F9&"; "))),1,0) -> 0 | T9: =IF(OR(E9="Correction/Challenge",ISNUMBER(SEARCH("; Correction/Challenge; ","; "&F9&"; "))),1,0) -> 0 | U9: =IF(OR(E9="Redirection",ISNUMBER(SEARCH("; Redirection; ","; "&F9&"; "))),1,0) -> 0 | V9: =IF(OR(E9="Knowledge injection",ISNUMBER(SEARCH("; Knowledge injection; ","; "&F9&"; "))),1,0) -> 0 | W9: =IF(OR(E9="Selection/Rejection",ISNUMBER(SEARCH("; Selection/Rejection; ","; "&F9&"; "))),1,0) -> 0 | X9: =IF(OR(E9="Deliberation",ISNUMBER(SEARCH("; Deliberation; ","; "&F9&"; "))),1,0) -> 0 | Y9: =SUM(Z9:AE9) -> 0 | Z9: =IF(ISNUMBER(SEARCH("; domain correction; ","; "&H9&"; ")),1,0) -> 0 | AA9: =IF(ISNUMBER(SEARCH("; conceptual discrimination; ","; "&H9&"; ")),1,0) -> 0 | AB9: =IF(ISNUMBER(SEARCH("; evidence judgment; ","; "&H9&"; ")),1,0) -> 0 | AC9: =IF(ISNUMBER(SEARCH("; methodological judgment; ","; "&H9&"; ")),1,0) -> 0 | AD9: =IF(ISNUMBER(SEARCH("; argumentative judgment; ","; "&H9&"; ")),1,0) -> 0 | AE9: =IF(ISNUMBER(SEARCH("; genre/writing expertise; ","; "&H9&"; ")),1,0) -> 0 | AF9: =IF(ISNUMBER(SEARCH("; none; ","; "&H9&"; ")),1,0) -> 1
A10: HE-009 | B10: 9 | C10: Conceptual framing and model | D10: proof heading : 3.2 Dünya Bankı terefinden Azərbaycanin Təhsil Sektorunun İnkişafı maliyelesdirieln Layihəsi (2008-2016) | E10: Directed delegation | F10: Knowledge injection | G10: Directive | H10: none | I10: Supplies a heading for proofreading without explaining a substantive judgment. | J10: AI edits the heading. | K10: DOCX body elements 1705–1705 | L10: DOCX body elements 1708–1719 | N10: Visible next AI response | O10: Converted DOCX: textbox continuations joined; AI completion/source-check claims are unverified. | P10: =SUM(Q10:X10) -> 2 | Q10: =IF(OR(E10="Delegation",ISNUMBER(SEARCH("; Delegation; ","; "&F10&"; "))),1,0) -> 0 | R10: =IF(OR(E10="Directed delegation",ISNUMBER(SEARCH("; Directed delegation; ","; "&F10&"; "))),1,0) -> 1 | S10: =IF(OR(E10="Evaluation",ISNUMBER(SEARCH("; Evaluation; ","; "&F10&"; "))),1,0) -> 0 | T10: =IF(OR(E10="Correction/Challenge",ISNUMBER(SEARCH("; Correction/Challenge; ","; "&F10&"; "))),1,0) -> 0 | U10: =IF(OR(E10="Redirection",ISNUMBER(SEARCH("; Redirection; ","; "&F10&"; "))),1,0) -> 0 | V10: =IF(OR(E10="Knowledge injection",ISNUMBER(SEARCH("; Knowledge injection; ","; "&F10&"; "))),1,0) -> 1 | W10: =IF(OR(E10="Selection/Rejection",ISNUMBER(SEARCH("; Selection/Rejection; ","; "&F10&"; "))),1,0) -> 0 | X10: =IF(OR(E10="Deliberation",ISNUMBER(SEARCH("; Deliberation; ","; "&F10&"; "))),1,0) -> 0 | Y10: =SUM(Z10:AE10) -> 0 | Z10: =IF(ISNUMBER(SEARCH("; domain correction; ","; "&H10&"; ")),1,0) -> 0 | AA10: =IF(ISNUMBER(SEARCH("; conceptual discrimination; ","; "&H10&"; ")),1,0) -> 0 | AB10: =IF(ISNUMBER(SEARCH("; evidence judgment; ","; "&H10&"; ")),1,0) -> 0 | AC10: =IF(ISNUMBER(SEARCH("; methodological judgment; ","; "&H10&"; ")),1,0) -> 0 | AD10: =IF(ISNUMBER(SEARCH("; argumentative judgment; ","; "&H10&"; ")),1,0) -> 0 | AE10: =IF(ISNUMBER(SEARCH("; genre/writing expertise; ","; "&H10&"; ")),1,0) -> 0 | AF10: =IF(ISNUMBER(SEARCH("; none; ","; "&H10&"; ")),1,0) -> 1
A11: HE-010 | B11: 10 | C11: Conceptual framing and model | D11: İ revised the factors... here is the draft... suggest improvements / additions: (SUGGEST A GROUP NAME)- EXTERNAL?: Sovet mirası: dominant düşüncə tərzi, iş və təhsil mədəniyyəti, vs. İNSTİTUSİONAL/STRUKTUR AMİLLƏR Vəzifə/təyinat siyasətləri — irəliləyiş meyarları (araşdırma nəşri, tədris keyfiyyəti) Karyera irəliləyişi meyarı — liyaqət vs. qıdəm Sənaye-akademiya əməkdaşlığı mədəniyyəti AKADEMİK HEYƏT AMİLLƏRİ (Human … | E11: Knowledge injection | F11: Directed delegation; Redirection | G11: Directive | H11: conceptual discrimination; methodological judgment; argumentative judgment | I11: Supplies factor groups and a revised causal explanation. | J11: AI organizes and elaborates the proposed categories. | K11: DOCX body elements 1720–1720 | L11: DOCX body elements 1723–1789 | N11: Visible next AI response | O11: Converted DOCX: textbox continuations joined; AI completion/source-check claims are unverified. | P11: =SUM(Q11:X11) -> 3 | Q11: =IF(OR(E11="Delegation",ISNUMBER(SEARCH("; Delegation; ","; "&F11&"; "))),1,0) -> 0 | R11: =IF(OR(E11="Directed delegation",ISNUMBER(SEARCH("; Directed delegation; ","; "&F11&"; "))),1,0) -> 1 | S11: =IF(OR(E11="Evaluation",ISNUMBER(SEARCH("; Evaluation; ","; "&F11&"; "))),1,0) -> 0 | T11: =IF(OR(E11="Correction/Challenge",ISNUMBER(SEARCH("; Correction/Challenge; ","; "&F11&"; "))),1,0) -> 0 | U11: =IF(OR(E11="Redirection",ISNUMBER(SEARCH("; Redirection; ","; "&F11&"; "))),1,0) -> 1 | V11: =IF(OR(E11="Knowledge injection",ISNUMBER(SEARCH("; Knowledge injection; ","; "&F11&"; "))),1,0) -> 1 | W11: =IF(OR(E11="Selection/Rejection",ISNUMBER(SEARCH("; Selection/Rejection; ","; "&F11&"; "))),1,0) -> 0 | X11: =IF(OR(E11="Deliberation",ISNUMBER(SEARCH("; Deliberation; ","; "&F11&"; "))),1,0) -> 0 | Y11: =SUM(Z11:AE11) -> 3 | Z11: =IF(ISNUMBER(SEARCH("; domain correction; ","; "&H11&"; ")),1,0) -> 0 | AA11: =IF(ISNUMBER(SEARCH("; conceptual discrimination; ","; "&H11&"; ")),1,0) -> 1 | AB11: =IF(ISNUMBER(SEARCH("; evidence judgment; ","; "&H11&"; ")),1,0) -> 0 | AC11: =IF(ISNUMBER(SEARCH("; methodological judgment; ","; "&H11&"; ")),1,0) -> 1 | AD11: =IF(ISNUMBER(SEARCH("; argumentative judgment; ","; "&H11&"; ")),1,0) -> 1 | AE11: =IF(ISNUMBER(SEARCH("; genre/writing expertise; ","; "&H11&"; ")),1,0) -> 0 | AF11: =IF(ISNUMBER(SEARCH("; none; ","; "&H11&"; ")),1,0) -> 0
A12: HE-011 | B12: 11 | C12: Conceptual framing and model | D12: How would those impact the education and other factors? What kind of impacts do you think? | E12: Evaluation | G12: Evaluative | H12: none | I12: Asks AI to explain causal impacts; the question itself supplies no explicit judgment. | J12: AI explains proposed causal pathways. | K12: DOCX body elements 1792–1792 | L12: DOCX body elements 1796–1831 | N12: Visible next AI response | O12: Converted DOCX: textbox continuations joined; AI completion/source-check claims are unverified. | P12: =SUM(Q12:X12) -> 1 | Q12: =IF(OR(E12="Delegation",ISNUMBER(SEARCH("; Delegation; ","; "&F12&"; "))),1,0) -> 0 | R12: =IF(OR(E12="Directed delegation",ISNUMBER(SEARCH("; Directed delegation; ","; "&F12&"; "))),1,0) -> 0 | S12: =IF(OR(E12="Evaluation",ISNUMBER(SEARCH("; Evaluation; ","; "&F12&"; "))),1,0) -> 1 | T12: =IF(OR(E12="Correction/Challenge",ISNUMBER(SEARCH("; Correction/Challenge; ","; "&F12&"; "))),1,0) -> 0 | U12: =IF(OR(E12="Redirection",ISNUMBER(SEARCH("; Redirection; ","; "&F12&"; "))),1,0) -> 0 | V12: =IF(OR(E12="Knowledge injection",ISNUMBER(SEARCH("; Knowledge injection; ","; "&F12&"; "))),1,0) -> 0 | W12: =IF(OR(E12="Selection/Rejection",ISNUMBER(SEARCH("; Selection/Rejection; ","; "&F12&"; "))),1,0) -> 0 | X12: =IF(OR(E12="Deliberation",ISNUMBER(SEARCH("; Deliberation; ","; "&F12&"; "))),1,0) -> 0 | Y12: =SUM(Z12:AE12) -> 0 | Z12: =IF(ISNUMBER(SEARCH("; domain correction; ","; "&H12&"; ")),1,0) -> 0 | AA12: =IF(ISNUMBER(SEARCH("; conceptual discrimination; ","; "&H12&"; ")),1,0) -> 0 | AB12: =IF(ISNUMBER(SEARCH("; evidence judgment; ","; "&H12&"; ")),1,0) -> 0 | AC12: =IF(ISNUMBER(SEARCH("; methodological judgment; ","; "&H12&"; ")),1,0) -> 0 | AD12: =IF(ISNUMBER(SEARCH("; argumentative judgment; ","; "&H12&"; ")),1,0) -> 0 | AE12: =IF(ISNUMBER(SEARCH("; genre/writing expertise; ","; "&H12&"; ")),1,0) -> 0 | AF12: =IF(ISNUMBER(SEARCH("; none; ","; "&H12&"; ")),1,0) -> 1
A13: HE-012 | B13: 12 | C13: Conceptual framing and model | D13: shall ve add: Əmək bazarının ehtiyaclari, sahələr?? | E13: Knowledge injection | F13: Directed delegation | G13: Directive | H13: domain correction; conceptual discrimination | I13: Identifies labour-market needs as a missing factor. | J13: AI adds labour-market alignment. | K13: DOCX body elements 1832–1832 | L13: DOCX body elements 1835–1868 | N13: Visible next AI response | O13: Converted DOCX: textbox continuations joined; AI completion/source-check claims are unverified. | P13: =SUM(Q13:X13) -> 2 | Q13: =IF(OR(E13="Delegation",ISNUMBER(SEARCH("; Delegation; ","; "&F13&"; "))),1,0) -> 0 | R13: =IF(OR(E13="Directed delegation",ISNUMBER(SEARCH("; Directed delegation; ","; "&F13&"; "))),1,0) -> 1 | S13: =IF(OR(E13="Evaluation",ISNUMBER(SEARCH("; Evaluation; ","; "&F13&"; "))),1,0) -> 0 | T13: =IF(OR(E13="Correction/Challenge",ISNUMBER(SEARCH("; Correction/Challenge; ","; "&F13&"; "))),1,0) -> 0 | U13: =IF(OR(E13="Redirection",ISNUMBER(SEARCH("; Redirection; ","; "&F13&"; "))),1,0) -> 0 | V13: =IF(OR(E13="Knowledge injection",ISNUMBER(SEARCH("; Knowledge injection; ","; "&F13&"; "))),1,0) -> 1 | W13: =IF(OR(E13="Selection/Rejection",ISNUMBER(SEARCH("; Selection/Rejection; ","; "&F13&"; "))),1,0) -> 0 | X13: =IF(OR(E13="Deliberation",ISNUMBER(SEARCH("; Deliberation; ","; "&F13&"; "))),1,0) -> 0 | Y13: =SUM(Z13:AE13) -> 2 | Z13: =IF(ISNUMBER(SEARCH("; domain correction; ","; "&H13&"; ")),1,0) -> 1 | AA13: =IF(ISNUMBER(SEARCH("; conceptual discrimination; ","; "&H13&"; ")),1,0) -> 1 | AB13: =IF(ISNUMBER(SEARCH("; evidence judgment; ","; "&H13&"; ")),1,0) -> 0 | AC13: =IF(ISNUMBER(SEARCH("; methodological judgment; ","; "&H13&"; ")),1,0) -> 0 | AD13: =IF(ISNUMBER(SEARCH("; argumentative judgment; ","; "&H13&"; ")),1,0) -> 0 | AE13: =IF(ISNUMBER(SEARCH("; genre/writing expertise; ","; "&H13&"; ")),1,0) -> 0 | AF13: =IF(ISNUMBER(SEARCH("; none; ","; "&H13&"; ")),1,0) -> 0
A14: HE-013 | B14: 13 | C14: Conceptual framing and model | D14: explained this a little with what kind of impacts from that. | E14: Delegation | G14: Delegative | H14: none | I14: Requests further explanation without stating an independent substantive criterion. | J14: AI explains the mechanism. | K14: DOCX body elements 1871–1871 | L14: DOCX body elements 1875–1912 | N14: Visible next AI response | O14: Converted DOCX: textbox continuations joined; AI completion/source-check claims are unverified. | P14: =SUM(Q14:X14) -> 1 | Q14: =IF(OR(E14="Delegation",ISNUMBER(SEARCH("; Delegation; ","; "&F14&"; "))),1,0) -> 1 | R14: =IF(OR(E14="Directed delegation",ISNUMBER(SEARCH("; Directed delegation; ","; "&F14&"; "))),1,0) -> 0 | S14: =IF(OR(E14="Evaluation",ISNUMBER(SEARCH("; Evaluation; ","; "&F14&"; "))),1,0) -> 0 | T14: =IF(OR(E14="Correction/Challenge",ISNUMBER(SEARCH("; Correction/Challenge; ","; "&F14&"; "))),1,0) -> 0 | U14: =IF(OR(E14="Redirection",ISNUMBER(SEARCH("; Redirection; ","; "&F14&"; "))),1,0) -> 0 | V14: =IF(OR(E14="Knowledge injection",ISNUMBER(SEARCH("; Knowledge injection; ","; "&F14&"; "))),1,0) -> 0 | W14: =IF(OR(E14="Selection/Rejection",ISNUMBER(SEARCH("; Selection/Rejection; ","; "&F14&"; "))),1,0) -> 0 | X14: =IF(OR(E14="Deliberation",ISNUMBER(SEARCH("; Deliberation; ","; "&F14&"; "))),1,0) -> 0 | Y14: =SUM(Z14:AE14) -> 0 | Z14: =IF(ISNUMBER(SEARCH("; domain correction; ","; "&H14&"; ")),1,0) -> 0 | AA14: =IF(ISNUMBER(SEARCH("; conceptual discrimination; ","; "&H14&"; ")),1,0) -> 0 | AB14: =IF(ISNUMBER(SEARCH("; evidence judgment; ","; "&H14&"; ")),1,0) -> 0 | AC14: =IF(ISNUMBER(SEARCH("; methodological judgment; ","; "&H14&"; ")),1,0) -> 0 | AD14: =IF(ISNUMBER(SEARCH("; argumentative judgment; ","; "&H14&"; ")),1,0) -> 0 | AE14: =IF(ISNUMBER(SEARCH("; genre/writing expertise; ","; "&H14&"; ")),1,0) -> 0 | AF14: =IF(ISNUMBER(SEARCH("; none; ","; "&H14&"; ")),1,0) -> 1
A15: HE-014 | B15: 14 | C15: Conceptual framing and model | D15: Now I see what you mean. Uh, put the two extremes of it, the terminology. Um, give me better phrases. Perhaps something you can say, shallow versus in-depth and, uh, resolved to even something like that, uh, as the goals are accurate station and, uh, quality assurance. | E15: Directed delegation | F15: Knowledge injection | G15: Directive | H15: conceptual discrimination; genre/writing expertise | I15: Specifies shallow/deep endpoints for the model’s wording. | J15: AI proposes contrasting labels. | K15: DOCX body elements 1915–1915 | L15: DOCX body elements 1919–1956 | N15: Visible next AI response | O15: Converted DOCX: textbox continuations joined; AI completion/source-check claims are unverified. | P15: =SUM(Q15:X15) -> 2 | Q15: =IF(OR(E15="Delegation",ISNUMBER(SEARCH("; Delegation; ","; "&F15&"; "))),1,0) -> 0 | R15: =IF(OR(E15="Directed delegation",ISNUMBER(SEARCH("; Directed delegation; ","; "&F15&"; "))),1,0) -> 1 | S15: =IF(OR(E15="Evaluation",ISNUMBER(SEARCH("; Evaluation; ","; "&F15&"; "))),1,0) -> 0 | T15: =IF(OR(E15="Correction/Challenge",ISNUMBER(SEARCH("; Correction/Challenge; ","; "&F15&"; "))),1,0) -> 0 | U15: =IF(OR(E15="Redirection",ISNUMBER(SEARCH("; Redirection; ","; "&F15&"; "))),1,0) -> 0 | V15: =IF(OR(E15="Knowledge injection",ISNUMBER(SEARCH("; Knowledge injection; ","; "&F15&"; "))),1,0) -> 1 | W15: =IF(OR(E15="Selection/Rejection",ISNUMBER(SEARCH("; Selection/Rejection; ","; "&F15&"; "))),1,0) -> 0 | X15: =IF(OR(E15="Deliberation",ISNUMBER(SEARCH("; Deliberation; ","; "&F15&"; "))),1,0) -> 0 | Y15: =SUM(Z15:AE15) -> 2 | Z15: =IF(ISNUMBER(SEARCH("; domain correction; ","; "&H15&"; ")),1,0) -> 0 | AA15: =IF(ISNUMBER(SEARCH("; conceptual discrimination; ","; "&H15&"; ")),1,0) -> 1 | AB15: =IF(ISNUMBER(SEARCH("; evidence judgment; ","; "&H15&"; ")),1,0) -> 0 | AC15: =IF(ISNUMBER(SEARCH("; methodological judgment; ","; "&H15&"; ")),1,0) -> 0 | AD15: =IF(ISNUMBER(SEARCH("; argumentative judgment; ","; "&H15&"; ")),1,0) -> 0 | AE15: =IF(ISNUMBER(SEARCH("; genre/writing expertise; ","; "&H15&"; ")),1,0) -> 1 | AF15: =IF(ISNUMBER(SEARCH("; none; ","; "&H15&"; ")),1,0) -> 0
A16: HE-015 | B16: 15 | C16: Conceptual framing and model | D16: Bürokratik yük — inzibati işlərin akademik vaxtı nə qədər "yeyməsi" or "yeməsi"? | E16: Correction/Challenge | G16: Critical | H16: genre/writing expertise | I16: Identifies an Azerbaijani spelling choice requiring correction. | J16: AI corrects the spelling. | K16: DOCX body elements 1957–1957 | L16: DOCX body elements 1960–1970 | N16: Visible next AI response | O16: Converted DOCX: textbox continuations joined; AI completion/source-check claims are unverified. | P16: =SUM(Q16:X16) -> 1 | Q16: =IF(OR(E16="Delegation",ISNUMBER(SEARCH("; Delegation; ","; "&F16&"; "))),1,0) -> 0 | R16: =IF(OR(E16="Directed delegation",ISNUMBER(SEARCH("; Directed delegation; ","; "&F16&"; "))),1,0) -> 0 | S16: =IF(OR(E16="Evaluation",ISNUMBER(SEARCH("; Evaluation; ","; "&F16&"; "))),1,0) -> 0 | T16: =IF(OR(E16="Correction/Challenge",ISNUMBER(SEARCH("; Correction/Challenge; ","; "&F16&"; "))),1,0) -> 1 | U16: =IF(OR(E16="Redirection",ISNUMBER(SEARCH("; Redirection; ","; "&F16&"; "))),1,0) -> 0 | V16: =IF(OR(E16="Knowledge injection",ISNUMBER(SEARCH("; Knowledge injection; ","; "&F16&"; "))),1,0) -> 0 | W16: =IF(OR(E16="Selection/Rejection",ISNUMBER(SEARCH("; Selection/Rejection; ","; "&F16&"; "))),1,0) -> 0 | X16: =IF(OR(E16="Deliberation",ISNUMBER(SEARCH("; Deliberation; ","; "&F16&"; "))),1,0) -> 0 | Y16: =SUM(Z16:AE16) -> 1 | Z16: =IF(ISNUMBER(SEARCH("; domain correction; ","; "&H16&"; ")),1,0) -> 0 | AA16: =IF(ISNUMBER(SEARCH("; conceptual discrimination; ","; "&H16&"; ")),1,0) -> 0 | AB16: =IF(ISNUMBER(SEARCH("; evidence judgment; ","; "&H16&"; ")),1,0) -> 0 | AC16: =IF(ISNUMBER(SEARCH("; methodological judgment; ","; "&H16&"; ")),1,0) -> 0 | AD16: =IF(ISNUMBER(SEARCH("; argumentative judgment; ","; "&H16&"; ")),1,0) -> 0 | AE16: =IF(ISNUMBER(SEARCH("; genre/writing expertise; ","; "&H16&"; ")),1,0) -> 1 | AF16: =IF(ISNUMBER(SEARCH("; none; ","; "&H16&"; ")),1,0) -> 0
A17: HE-016 | B17: 16 | C17: Conceptual framing and model | D17: İngilis dili səriştəsi — beynəlxalq elmi ədəbiyyata çıxış və əməkdaşlıq üçün açar amilNotethat in this paper we focus on education quality and not research quality. So in English, yeah, language knowledge is good, but it will help in, uh, to help an academic, uh, read the latest information and follow them. So not about the research, but about his, uh, domain knowledge, uh, getting updated | E17: Correction/Challenge | F17: Redirection; Knowledge injection | G17: Critical | H17: domain correction; conceptual discrimination; argumentative judgment | I17: Distinguishes educational from research quality and supplies the knowledge-access mechanism. | J17: AI refocuses the explanation on teaching and current knowledge. | K17: DOCX body elements 1971–1971 | L17: DOCX body elements 1974–1999 | N17: Visible next AI response | O17: Converted DOCX: textbox continuations joined; AI completion/source-check claims are unverified. | P17: =SUM(Q17:X17) -> 3 | Q17: =IF(OR(E17="Delegation",ISNUMBER(SEARCH("; Delegation; ","; "&F17&"; "))),1,0) -> 0 | R17: =IF(OR(E17="Directed delegation",ISNUMBER(SEARCH("; Directed delegation; ","; "&F17&"; "))),1,0) -> 0 | S17: =IF(OR(E17="Evaluation",ISNUMBER(SEARCH("; Evaluation; ","; "&F17&"; "))),1,0) -> 0 | T17: =IF(OR(E17="Correction/Challenge",ISNUMBER(SEARCH("; Correction/Challenge; ","; "&F17&"; "))),1,0) -> 1 | U17: =IF(OR(E17="Redirection",ISNUMBER(SEARCH("; Redirection; ","; "&F17&"; "))),1,0) -> 1 | V17: =IF(OR(E17="Knowledge injection",ISNUMBER(SEARCH("; Knowledge injection; ","; "&F17&"; "))),1,0) -> 1 | W17: =IF(OR(E17="Selection/Rejection",ISNUMBER(SEARCH("; Selection/Rejection; ","; "&F17&"; "))),1,0) -> 0 | X17: =IF(OR(E17="Deliberation",ISNUMBER(SEARCH("; Deliberation; ","; "&F17&"; "))),1,0) -> 0 | Y17: =SUM(Z17:AE17) -> 3 | Z17: =IF(ISNUMBER(SEARCH("; domain correction; ","; "&H17&"; ")),1,0) -> 1 | AA17: =IF(ISNUMBER(SEARCH("; conceptual discrimination; ","; "&H17&"; ")),1,0) -> 1 | AB17: =IF(ISNUMBER(SEARCH("; evidence judgment; ","; "&H17&"; ")),1,0) -> 0 | AC17: =IF(ISNUMBER(SEARCH("; methodological judgment; ","; "&H17&"; ")),1,0) -> 0 | AD17: =IF(ISNUMBER(SEARCH("; argumentative judgment; ","; "&H17&"; ")),1,0) -> 1 | AE17: =IF(ISNUMBER(SEARCH("; genre/writing expertise; ","; "&H17&"; ")),1,0) -> 0 | AF17: =IF(ISNUMBER(SEARCH("; none; ","; "&H17&"; ")),1,0) -> 0
A18: HE-017 | B18: 17 | C18: Conceptual framing and model | D18: Ailə/sosial-iqtisadi arxa plan (təhsilə çıxış bərabərsizliyi)- Why is this important? - | E18: Evaluation | G18: Evaluative | H18: conceptual discrimination | I18: Questions the causal relevance of family background. | J18: AI explains potential mechanisms. | K18: DOCX body elements 2000–2000 | L18: DOCX body elements 2003–2032 | N18: Visible next AI response | O18: Converted DOCX: textbox continuations joined; AI completion/source-check claims are unverified. | P18: =SUM(Q18:X18) -> 1 | Q18: =IF(OR(E18="Delegation",ISNUMBER(SEARCH("; Delegation; ","; "&F18&"; "))),1,0) -> 0 | R18: =IF(OR(E18="Directed delegation",ISNUMBER(SEARCH("; Directed delegation; ","; "&F18&"; "))),1,0) -> 0 | S18: =IF(OR(E18="Evaluation",ISNUMBER(SEARCH("; Evaluation; ","; "&F18&"; "))),1,0) -> 1 | T18: =IF(OR(E18="Correction/Challenge",ISNUMBER(SEARCH("; Correction/Challenge; ","; "&F18&"; "))),1,0) -> 0 | U18: =IF(OR(E18="Redirection",ISNUMBER(SEARCH("; Redirection; ","; "&F18&"; "))),1,0) -> 0 | V18: =IF(OR(E18="Knowledge injection",ISNUMBER(SEARCH("; Knowledge injection; ","; "&F18&"; "))),1,0) -> 0 | W18: =IF(OR(E18="Selection/Rejection",ISNUMBER(SEARCH("; Selection/Rejection; ","; "&F18&"; "))),1,0) -> 0 | X18: =IF(OR(E18="Deliberation",ISNUMBER(SEARCH("; Deliberation; ","; "&F18&"; "))),1,0) -> 0 | Y18: =SUM(Z18:AE18) -> 1 | Z18: =IF(ISNUMBER(SEARCH("; domain correction; ","; "&H18&"; ")),1,0) -> 0 | AA18: =IF(ISNUMBER(SEARCH("; conceptual discrimination; ","; "&H18&"; ")),1,0) -> 1 | AB18: =IF(ISNUMBER(SEARCH("; evidence judgment; ","; "&H18&"; ")),1,0) -> 0 | AC18: =IF(ISNUMBER(SEARCH("; methodological judgment; ","; "&H18&"; ")),1,0) -> 0 | AD18: =IF(ISNUMBER(SEARCH("; argumentative judgment; ","; "&H18&"; ")),1,0) -> 0 | AE18: =IF(ISNUMBER(SEARCH("; genre/writing expertise; ","; "&H18&"; ")),1,0) -> 0 | AF18: =IF(ISNUMBER(SEARCH("; none; ","; "&H18&"; ")),1,0) -> 0
A19: HE-018 | B19: 18 | C19: Conceptual framing and model | D19: better vay of saying this: Ailə/sosial-iqtisadi arxa plan (təhsilə çıxış bərabərsizliyi) | E19: Directed delegation | G19: Directive | H19: genre/writing expertise | I19: Requests a better phrase for family background. | J19: AI proposes alternatives. | K19: DOCX body elements 2033–2033 | L19: DOCX body elements 2036–2056 | N19: Visible next AI response | O19: Converted DOCX: textbox continuations joined; AI completion/source-check claims are unverified. | P19: =SUM(Q19:X19) -> 1 | Q19: =IF(OR(E19="Delegation",ISNUMBER(SEARCH("; Delegation; ","; "&F19&"; "))),1,0) -> 0 | R19: =IF(OR(E19="Directed delegation",ISNUMBER(SEARCH("; Directed delegation; ","; "&F19&"; "))),1,0) -> 1 | S19: =IF(OR(E19="Evaluation",ISNUMBER(SEARCH("; Evaluation; ","; "&F19&"; "))),1,0) -> 0 | T19: =IF(OR(E19="Correction/Challenge",ISNUMBER(SEARCH("; Correction/Challenge; ","; "&F19&"; "))),1,0) -> 0 | U19: =IF(OR(E19="Redirection",ISNUMBER(SEARCH("; Redirection; ","; "&F19&"; "))),1,0) -> 0 | V19: =IF(OR(E19="Knowledge injection",ISNUMBER(SEARCH("; Knowledge injection; ","; "&F19&"; "))),1,0) -> 0 | W19: =IF(OR(E19="Selection/Rejection",ISNUMBER(SEARCH("; Selection/Rejection; ","; "&F19&"; "))),1,0) -> 0 | X19: =IF(OR(E19="Deliberation",ISNUMBER(SEARCH("; Deliberation; ","; "&F19&"; "))),1,0) -> 0 | Y19: =SUM(Z19:AE19) -> 1 | Z19: =IF(ISNUMBER(SEARCH("; domain correction; ","; "&H19&"; ")),1,0) -> 0 | AA19: =IF(ISNUMBER(SEARCH("; conceptual discrimination; ","; "&H19&"; ")),1,0) -> 0 | AB19: =IF(ISNUMBER(SEARCH("; evidence judgment; ","; "&H19&"; ")),1,0) -> 0 | AC19: =IF(ISNUMBER(SEARCH("; methodological judgment; ","; "&H19&"; ")),1,0) -> 0 | AD19: =IF(ISNUMBER(SEARCH("; argumentative judgment; ","; "&H19&"; ")),1,0) -> 0 | AE19: =IF(ISNUMBER(SEARCH("; genre/writing expertise; ","; "&H19&"; ")),1,0) -> 1 | AF19: =IF(ISNUMBER(SEARCH("; none; ","; "&H19&"; ")),1,0) -> 0
A20: HE-019 | B20: 19 | C20: Conceptual framing and model | D20: So just, uh, another phrase for this--- VASİTƏÇİ/YARANMA AMİLLƏRİ (Mediating) | E20: Evaluation | G20: Evaluative | H20: conceptual discrimination; genre/writing expertise | I20: Seeks an alternative category name for mediating factors. | J20: AI offers terminology options. | K20: DOCX body elements 2057–2057 | L20: DOCX body elements 2060–2081 | N20: Visible next AI response | O20: Converted DOCX: textbox continuations joined; AI completion/source-check claims are unverified. | P20: =SUM(Q20:X20) -> 1 | Q20: =IF(OR(E20="Delegation",ISNUMBER(SEARCH("; Delegation; ","; "&F20&"; "))),1,0) -> 0 | R20: =IF(OR(E20="Directed delegation",ISNUMBER(SEARCH("; Directed delegation; ","; "&F20&"; "))),1,0) -> 0 | S20: =IF(OR(E20="Evaluation",ISNUMBER(SEARCH("; Evaluation; ","; "&F20&"; "))),1,0) -> 1 | T20: =IF(OR(E20="Correction/Challenge",ISNUMBER(SEARCH("; Correction/Challenge; ","; "&F20&"; "))),1,0) -> 0 | U20: =IF(OR(E20="Redirection",ISNUMBER(SEARCH("; Redirection; ","; "&F20&"; "))),1,0) -> 0 | V20: =IF(OR(E20="Knowledge injection",ISNUMBER(SEARCH("; Knowledge injection; ","; "&F20&"; "))),1,0) -> 0 | W20: =IF(OR(E20="Selection/Rejection",ISNUMBER(SEARCH("; Selection/Rejection; ","; "&F20&"; "))),1,0) -> 0 | X20: =IF(OR(E20="Deliberation",ISNUMBER(SEARCH("; Deliberation; ","; "&F20&"; "))),1,0) -> 0 | Y20: =SUM(Z20:AE20) -> 2 | Z20: =IF(ISNUMBER(SEARCH("; domain correction; ","; "&H20&"; ")),1,0) -> 0 | AA20: =IF(ISNUMBER(SEARCH("; conceptual discrimination; ","; "&H20&"; ")),1,0) -> 1 | AB20: =IF(ISNUMBER(SEARCH("; evidence judgment; ","; "&H20&"; ")),1,0) -> 0 | AC20: =IF(ISNUMBER(SEARCH("; methodological judgment; ","; "&H20&"; ")),1,0) -> 0 | AD20: =IF(ISNUMBER(SEARCH("; argumentative judgment; ","; "&H20&"; ")),1,0) -> 0 | AE20: =IF(ISNUMBER(SEARCH("; genre/writing expertise; ","; "&H20&"; ")),1,0) -> 1 | AF20: =IF(ISNUMBER(SEARCH("; none; ","; "&H20&"; ")),1,0) -> 0
A21: HE-020 | B21: 20 | C21: Conceptual framing and model | D21: Any term that is better for every regular person to understand. | E21: Redirection | F21: Directed delegation | G21: Directive | H21: genre/writing expertise | I21: Prioritizes a term understandable to lay readers. | J21: AI suggests accessible wording. | K21: DOCX body elements 2082–2082 | L21: DOCX body elements 2085–2117 | N21: Visible next AI response | O21: Converted DOCX: textbox continuations joined; AI completion/source-check claims are unverified. | P21: =SUM(Q21:X21) -> 2 | Q21: =IF(OR(E21="Delegation",ISNUMBER(SEARCH("; Delegation; ","; "&F21&"; "))),1,0) -> 0 | R21: =IF(OR(E21="Directed delegation",ISNUMBER(SEARCH("; Directed delegation; ","; "&F21&"; "))),1,0) -> 1 | S21: =IF(OR(E21="Evaluation",ISNUMBER(SEARCH("; Evaluation; ","; "&F21&"; "))),1,0) -> 0 | T21: =IF(OR(E21="Correction/Challenge",ISNUMBER(SEARCH("; Correction/Challenge; ","; "&F21&"; "))),1,0) -> 0 | U21: =IF(OR(E21="Redirection",ISNUMBER(SEARCH("; Redirection; ","; "&F21&"; "))),1,0) -> 1 | V21: =IF(OR(E21="Knowledge injection",ISNUMBER(SEARCH("; Knowledge injection; ","; "&F21&"; "))),1,0) -> 0 | W21: =IF(OR(E21="Selection/Rejection",ISNUMBER(SEARCH("; Selection/Rejection; ","; "&F21&"; "))),1,0) -> 0 | X21: =IF(OR(E21="Deliberation",ISNUMBER(SEARCH("; Deliberation; ","; "&F21&"; "))),1,0) -> 0 | Y21: =SUM(Z21:AE21) -> 1 | Z21: =IF(ISNUMBER(SEARCH("; domain correction; ","; "&H21&"; ")),1,0) -> 0 | AA21: =IF(ISNUMBER(SEARCH("; conceptual discrimination; ","; "&H21&"; ")),1,0) -> 0 | AB21: =IF(ISNUMBER(SEARCH("; evidence judgment; ","; "&H21&"; ")),1,0) -> 0 | AC21: =IF(ISNUMBER(SEARCH("; methodological judgment; ","; "&H21&"; ")),1,0) -> 0 | AD21: =IF(ISNUMBER(SEARCH("; argumentative judgment; ","; "&H21&"; ")),1,0) -> 0 | AE21: =IF(ISNUMBER(SEARCH("; genre/writing expertise; ","; "&H21&"; ")),1,0) -> 1 | AF21: =IF(ISNUMBER(SEARCH("; none; ","; "&H21&"; ")),1,0) -> 0
A22: HE-021 | B22: 21 | C22: Conceptual framing and model | D22: Explain why this one is related to our context and what impacts. Geosiyasi kontekst: qonşu ölkələrlə (Türkiyə, Rusiya, İran) tarixi əlaqələr — təhsil və akademik istiqamətlərinə təsirləri | E22: Evaluation | G22: Evaluative | H22: conceptual discrimination; argumentative judgment | I22: Questions geopolitical factors’ relevance and effects. | J22: AI explains their proposed place in the model. | K22: DOCX body elements 2118–2118 | L22: DOCX body elements 2121–2160 | N22: Visible next AI response | O22: Converted DOCX: textbox continuations joined; AI completion/source-check claims are unverified. | P22: =SUM(Q22:X22) -> 1 | Q22: =IF(OR(E22="Delegation",ISNUMBER(SEARCH("; Delegation; ","; "&F22&"; "))),1,0) -> 0 | R22: =IF(OR(E22="Directed delegation",ISNUMBER(SEARCH("; Directed delegation; ","; "&F22&"; "))),1,0) -> 0 | S22: =IF(OR(E22="Evaluation",ISNUMBER(SEARCH("; Evaluation; ","; "&F22&"; "))),1,0) -> 1 | T22: =IF(OR(E22="Correction/Challenge",ISNUMBER(SEARCH("; Correction/Challenge; ","; "&F22&"; "))),1,0) -> 0 | U22: =IF(OR(E22="Redirection",ISNUMBER(SEARCH("; Redirection; ","; "&F22&"; "))),1,0) -> 0 | V22: =IF(OR(E22="Knowledge injection",ISNUMBER(SEARCH("; Knowledge injection; ","; "&F22&"; "))),1,0) -> 0 | W22: =IF(OR(E22="Selection/Rejection",ISNUMBER(SEARCH("; Selection/Rejection; ","; "&F22&"; "))),1,0) -> 0 | X22: =IF(OR(E22="Deliberation",ISNUMBER(SEARCH("; Deliberation; ","; "&F22&"; "))),1,0) -> 0 | Y22: =SUM(Z22:AE22) -> 2 | Z22: =IF(ISNUMBER(SEARCH("; domain correction; ","; "&H22&"; ")),1,0) -> 0 | AA22: =IF(ISNUMBER(SEARCH("; conceptual discrimination; ","; "&H22&"; ")),1,0) -> 1 | AB22: =IF(ISNUMBER(SEARCH("; evidence judgment; ","; "&H22&"; ")),1,0) -> 0 | AC22: =IF(ISNUMBER(SEARCH("; methodological judgment; ","; "&H22&"; ")),1,0) -> 0 | AD22: =IF(ISNUMBER(SEARCH("; argumentative judgment; ","; "&H22&"; ")),1,0) -> 1 | AE22: =IF(ISNUMBER(SEARCH("; genre/writing expertise; ","; "&H22&"; ")),1,0) -> 0 | AF22: =IF(ISNUMBER(SEARCH("; none; ","; "&H22&"; ")),1,0) -> 0
A23: HE-022 | B23: 22 | C23: Conceptual framing and model | D23: give a slightly expanded prhase for the diagramç:? Dinamik akademik mühit (NE demək ?) | E23: Directed delegation | G23: Directive | H23: genre/writing expertise | I23: Requests expansion of a short academic-environment label. | J23: AI supplies fuller wording. | K23: DOCX body elements 2162–2162 | L23: DOCX body elements 2165–2187 | N23: Visible next AI response | O23: Converted DOCX: textbox continuations joined; AI completion/source-check claims are unverified. | P23: =SUM(Q23:X23) -> 1 | Q23: =IF(OR(E23="Delegation",ISNUMBER(SEARCH("; Delegation; ","; "&F23&"; "))),1,0) -> 0 | R23: =IF(OR(E23="Directed delegation",ISNUMBER(SEARCH("; Directed delegation; ","; "&F23&"; "))),1,0) -> 1 | S23: =IF(OR(E23="Evaluation",ISNUMBER(SEARCH("; Evaluation; ","; "&F23&"; "))),1,0) -> 0 | T23: =IF(OR(E23="Correction/Challenge",ISNUMBER(SEARCH("; Correction/Challenge; ","; "&F23&"; "))),1,0) -> 0 | U23: =IF(OR(E23="Redirection",ISNUMBER(SEARCH("; Redirection; ","; "&F23&"; "))),1,0) -> 0 | V23: =IF(OR(E23="Knowledge injection",ISNUMBER(SEARCH("; Knowledge injection; ","; "&F23&"; "))),1,0) -> 0 | W23: =IF(OR(E23="Selection/Rejection",ISNUMBER(SEARCH("; Selection/Rejection; ","; "&F23&"; "))),1,0) -> 0 | X23: =IF(OR(E23="Deliberation",ISNUMBER(SEARCH("; Deliberation; ","; "&F23&"; "))),1,0) -> 0 | Y23: =SUM(Z23:AE23) -> 1 | Z23: =IF(ISNUMBER(SEARCH("; domain correction; ","; "&H23&"; ")),1,0) -> 0 | AA23: =IF(ISNUMBER(SEARCH("; conceptual discrimination; ","; "&H23&"; ")),1,0) -> 0 | AB23: =IF(ISNUMBER(SEARCH("; evidence judgment; ","; "&H23&"; ")),1,0) -> 0 | AC23: =IF(ISNUMBER(SEARCH("; methodological judgment; ","; "&H23&"; ")),1,0) -> 0 | AD23: =IF(ISNUMBER(SEARCH("; argumentative judgment; ","; "&H23&"; ")),1,0) -> 0 | AE23: =IF(ISNUMBER(SEARCH("; genre/writing expertise; ","; "&H23&"; ")),1,0) -> 1 | AF23: =IF(ISNUMBER(SEARCH("; none; ","; "&H23&"; ")),1,0) -> 0
A24: HE-023 | B24: 23 | C24: Conceptual framing and model | D24: trans to AZ: Employability of graduates | E24: Directed delegation | G24: Directive | H24: none | I24: Requests translation of a term without substantive elaboration. | J24: AI translates graduate employability. | K24: DOCX body elements 2188–2188 | L24: DOCX body elements 2191–2201 | N24: Visible next AI response | O24: Converted DOCX: textbox continuations joined; AI completion/source-check claims are unverified. | P24: =SUM(Q24:X24) -> 1 | Q24: =IF(OR(E24="Delegation",ISNUMBER(SEARCH("; Delegation; ","; "&F24&"; "))),1,0) -> 0 | R24: =IF(OR(E24="Directed delegation",ISNUMBER(SEARCH("; Directed delegation; ","; "&F24&"; "))),1,0) -> 1 | S24: =IF(OR(E24="Evaluation",ISNUMBER(SEARCH("; Evaluation; ","; "&F24&"; "))),1,0) -> 0 | T24: =IF(OR(E24="Correction/Challenge",ISNUMBER(SEARCH("; Correction/Challenge; ","; "&F24&"; "))),1,0) -> 0 | U24: =IF(OR(E24="Redirection",ISNUMBER(SEARCH("; Redirection; ","; "&F24&"; "))),1,0) -> 0 | V24: =IF(OR(E24="Knowledge injection",ISNUMBER(SEARCH("; Knowledge injection; ","; "&F24&"; "))),1,0) -> 0 | W24: =IF(OR(E24="Selection/Rejection",ISNUMBER(SEARCH("; Selection/Rejection; ","; "&F24&"; "))),1,0) -> 0 | X24: =IF(OR(E24="Deliberation",ISNUMBER(SEARCH("; Deliberation; ","; "&F24&"; "))),1,0) -> 0 | Y24: =SUM(Z24:AE24) -> 0 | Z24: =IF(ISNUMBER(SEARCH("; domain correction; ","; "&H24&"; ")),1,0) -> 0 | AA24: =IF(ISNUMBER(SEARCH("; conceptual discrimination; ","; "&H24&"; ")),1,0) -> 0 | AB24: =IF(ISNUMBER(SEARCH("; evidence judgment; ","; "&H24&"; ")),1,0) -> 0 | AC24: =IF(ISNUMBER(SEARCH("; methodological judgment; ","; "&H24&"; ")),1,0) -> 0 | AD24: =IF(ISNUMBER(SEARCH("; argumentative judgment; ","; "&H24&"; ")),1,0) -> 0 | AE24: =IF(ISNUMBER(SEARCH("; genre/writing expertise; ","; "&H24&"; ")),1,0) -> 0 | AF24: =IF(ISNUMBER(SEARCH("; none; ","; "&H24&"; ")),1,0) -> 1
A25: HE-024 | B25: 24 | C25: Conceptual framing and model | D25: İ designed the model.. reviev it | E25: Evaluation | F25: Knowledge injection | G25: Evaluative | H25: methodological judgment | I25: Supplies the researcher’s model for assessment. | J25: AI reviews the model and recommends refinements. | K25: DOCX body elements 2204–2204 | L25: DOCX body elements 2208–2245 | N25: Visible next AI response | O25: Converted DOCX: textbox continuations joined; AI completion/source-check claims are unverified. | P25: =SUM(Q25:X25) -> 2 | Q25: =IF(OR(E25="Delegation",ISNUMBER(SEARCH("; Delegation; ","; "&F25&"; "))),1,0) -> 0 | R25: =IF(OR(E25="Directed delegation",ISNUMBER(SEARCH("; Directed delegation; ","; "&F25&"; "))),1,0) -> 0 | S25: =IF(OR(E25="Evaluation",ISNUMBER(SEARCH("; Evaluation; ","; "&F25&"; "))),1,0) -> 1 | T25: =IF(OR(E25="Correction/Challenge",ISNUMBER(SEARCH("; Correction/Challenge; ","; "&F25&"; "))),1,0) -> 0 | U25: =IF(OR(E25="Redirection",ISNUMBER(SEARCH("; Redirection; ","; "&F25&"; "))),1,0) -> 0 | V25: =IF(OR(E25="Knowledge injection",ISNUMBER(SEARCH("; Knowledge injection; ","; "&F25&"; "))),1,0) -> 1 | W25: =IF(OR(E25="Selection/Rejection",ISNUMBER(SEARCH("; Selection/Rejection; ","; "&F25&"; "))),1,0) -> 0 | X25: =IF(OR(E25="Deliberation",ISNUMBER(SEARCH("; Deliberation; ","; "&F25&"; "))),1,0) -> 0 | Y25: =SUM(Z25:AE25) -> 1 | Z25: =IF(ISNUMBER(SEARCH("; domain correction; ","; "&H25&"; ")),1,0) -> 0 | AA25: =IF(ISNUMBER(SEARCH("; conceptual discrimination; ","; "&H25&"; ")),1,0) -> 0 | AB25: =IF(ISNUMBER(SEARCH("; evidence judgment; ","; "&H25&"; ")),1,0) -> 0 | AC25: =IF(ISNUMBER(SEARCH("; methodological judgment; ","; "&H25&"; ")),1,0) -> 1 | AD25: =IF(ISNUMBER(SEARCH("; argumentative judgment; ","; "&H25&"; ")),1,0) -> 0 | AE25: =IF(ISNUMBER(SEARCH("; genre/writing expertise; ","; "&H25&"; ")),1,0) -> 0 | AF25: =IF(ISNUMBER(SEARCH("; none; ","; "&H25&"; ")),1,0) -> 0
A26: HE-025 | B26: 25 | C26: Conceptual framing and model | D26: In this paper I don't want to focus on the feedbacks, my goal is just to identify cause and effect, so what impacts what. And, of course, I'm not showing all of them arrows because it's a bit too crowded. I'm showing the main ones. | E26: Correction/Challenge | F26: Redirection; Knowledge injection | G26: Critical | H26: domain correction; conceptual discrimination; methodological judgment | I26: Distinguishes directional cause–effect arrows from feedback loops and specifies representation. | J26: AI acknowledges the distinction and revises the model description. | K26: DOCX body elements 2248–2248 | L26: DOCX body elements 2252–2305 | N26: Visible next AI response | O26: Converted DOCX: textbox continuations joined; AI completion/source-check claims are unverified. | P26: =SUM(Q26:X26) -> 3 | Q26: =IF(OR(E26="Delegation",ISNUMBER(SEARCH("; Delegation; ","; "&F26&"; "))),1,0) -> 0 | R26: =IF(OR(E26="Directed delegation",ISNUMBER(SEARCH("; Directed delegation; ","; "&F26&"; "))),1,0) -> 0 | S26: =IF(OR(E26="Evaluation",ISNUMBER(SEARCH("; Evaluation; ","; "&F26&"; "))),1,0) -> 0 | T26: =IF(OR(E26="Correction/Challenge",ISNUMBER(SEARCH("; Correction/Challenge; ","; "&F26&"; "))),1,0) -> 1 | U26: =IF(OR(E26="Redirection",ISNUMBER(SEARCH("; Redirection; ","; "&F26&"; "))),1,0) -> 1 | V26: =IF(OR(E26="Knowledge injection",ISNUMBER(SEARCH("; Knowledge injection; ","; "&F26&"; "))),1,0) -> 1 | W26: =IF(OR(E26="Selection/Rejection",ISNUMBER(SEARCH("; Selection/Rejection; ","; "&F26&"; "))),1,0) -> 0 | X26: =IF(OR(E26="Deliberation",ISNUMBER(SEARCH("; Deliberation; ","; "&F26&"; "))),1,0) -> 0 | Y26: =SUM(Z26:AE26) -> 3 | Z26: =IF(ISNUMBER(SEARCH("; domain correction; ","; "&H26&"; ")),1,0) -> 1 | AA26: =IF(ISNUMBER(SEARCH("; conceptual discrimination; ","; "&H26&"; ")),1,0) -> 1 | AB26: =IF(ISNUMBER(SEARCH("; evidence judgment; ","; "&H26&"; ")),1,0) -> 0 | AC26: =IF(ISNUMBER(SEARCH("; methodological judgment; ","; "&H26&"; ")),1,0) -> 1 | AD26: =IF(ISNUMBER(SEARCH("; argumentative judgment; ","; "&H26&"; ")),1,0) -> 0 | AE26: =IF(ISNUMBER(SEARCH("; genre/writing expertise; ","; "&H26&"; ")),1,0) -> 0 | AF26: =IF(ISNUMBER(SEARCH("; none; ","; "&H26&"; ")),1,0) -> 0
A27: HE-026 | B27: 26 | C27: Structure and research design | D27: give 1.1 | E27: Delegation | G27: Delegative | H27: none | I27: Requests Section 1.1 without additional substantive constraints. | J27: AI drafts the subsection. | K27: DOCX body elements 2306–2306 | L27: DOCX body elements 2309–2316 | N27: Visible next AI response | O27: Converted DOCX: textbox continuations joined; AI completion/source-check claims are unverified. | P27: =SUM(Q27:X27) -> 1 | Q27: =IF(OR(E27="Delegation",ISNUMBER(SEARCH("; Delegation; ","; "&F27&"; "))),1,0) -> 1 | R27: =IF(OR(E27="Directed delegation",ISNUMBER(SEARCH("; Directed delegation; ","; "&F27&"; "))),1,0) -> 0 | S27: =IF(OR(E27="Evaluation",ISNUMBER(SEARCH("; Evaluation; ","; "&F27&"; "))),1,0) -> 0 | T27: =IF(OR(E27="Correction/Challenge",ISNUMBER(SEARCH("; Correction/Challenge; ","; "&F27&"; "))),1,0) -> 0 | U27: =IF(OR(E27="Redirection",ISNUMBER(SEARCH("; Redirection; ","; "&F27&"; "))),1,0) -> 0 | V27: =IF(OR(E27="Knowledge injection",ISNUMBER(SEARCH("; Knowledge injection; ","; "&F27&"; "))),1,0) -> 0 | W27: =IF(OR(E27="Selection/Rejection",ISNUMBER(SEARCH("; Selection/Rejection; ","; "&F27&"; "))),1,0) -> 0 | X27: =IF(OR(E27="Deliberation",ISNUMBER(SEARCH("; Deliberation; ","; "&F27&"; "))),1,0) -> 0 | Y27: =SUM(Z27:AE27) -> 0 | Z27: =IF(ISNUMBER(SEARCH("; domain correction; ","; "&H27&"; ")),1,0) -> 0 | AA27: =IF(ISNUMBER(SEARCH("; conceptual discrimination; ","; "&H27&"; ")),1,0) -> 0 | AB27: =IF(ISNUMBER(SEARCH("; evidence judgment; ","; "&H27&"; ")),1,0) -> 0 | AC27: =IF(ISNUMBER(SEARCH("; methodological judgment; ","; "&H27&"; ")),1,0) -> 0 | AD27: =IF(ISNUMBER(SEARCH("; argumentative judgment; ","; "&H27&"; ")),1,0) -> 0 | AE27: =IF(ISNUMBER(SEARCH("; genre/writing expertise; ","; "&H27&"; ")),1,0) -> 0 | AF27: =IF(ISNUMBER(SEARCH("; none; ","; "&H27&"; ")),1,0) -> 1
A28: HE-027 | B28: 27 | C28: Structure and research design | D28: i structure sec 5 as follows. this is better: [5 Sistemin Praqmatik Təhlili və İslahat Təklifləri 6] (#_Toc234664129) [5.1 Makro / Kontekstual Amillərinin Təhlili və İslahatı 6](#_Toc234664130) [5.2 İnstitusional/Struktur Amillərinin Təhlili və İslahatı 6](#_Toc234664131) [5.3 Akademik Heyət Amillərinin Təhlili və İslahatı 6](#_Toc234664132) [5.4 Tələbə Amillərinin Təhlili və İslahatı 6] (#_Toc234664133) [5.5 Vasitəç… | E28: Knowledge injection | F28: Directed delegation | G28: Directive | H28: methodological judgment; genre/writing expertise | I28: Supplies a section structure aligned with the model’s factor groups. | J28: AI reorganizes the section accordingly. | K28: DOCX body elements 2317–2317 | L28: DOCX body elements 2320–2337 | N28: Visible next AI response | O28: Converted DOCX: textbox continuations joined; AI completion/source-check claims are unverified. | P28: =SUM(Q28:X28) -> 2 | Q28: =IF(OR(E28="Delegation",ISNUMBER(SEARCH("; Delegation; ","; "&F28&"; "))),1,0) -> 0 | R28: =IF(OR(E28="Directed delegation",ISNUMBER(SEARCH("; Directed delegation; ","; "&F28&"; "))),1,0) -> 1 | S28: =IF(OR(E28="Evaluation",ISNUMBER(SEARCH("; Evaluation; ","; "&F28&"; "))),1,0) -> 0 | T28: =IF(OR(E28="Correction/Challenge",ISNUMBER(SEARCH("; Correction/Challenge; ","; "&F28&"; "))),1,0) -> 0 | U28: =IF(OR(E28="Redirection",ISNUMBER(SEARCH("; Redirection; ","; "&F28&"; "))),1,0) -> 0 | V28: =IF(OR(E28="Knowledge injection",ISNUMBER(SEARCH("; Knowledge injection; ","; "&F28&"; "))),1,0) -> 1 | W28: =IF(OR(E28="Selection/Rejection",ISNUMBER(SEARCH("; Selection/Rejection; ","; "&F28&"; "))),1,0) -> 0 | X28: =IF(OR(E28="Deliberation",ISNUMBER(SEARCH("; Deliberation; ","; "&F28&"; "))),1,0) -> 0 | Y28: =SUM(Z28:AE28) -> 2 | Z28: =IF(ISNUMBER(SEARCH("; domain correction; ","; "&H28&"; ")),1,0) -> 0 | AA28: =IF(ISNUMBER(SEARCH("; conceptual discrimination; ","; "&H28&"; ")),1,0) -> 0 | AB28: =IF(ISNUMBER(SEARCH("; evidence judgment; ","; "&H28&"; ")),1,0) -> 0 | AC28: =IF(ISNUMBER(SEARCH("; methodological judgment; ","; "&H28&"; ")),1,0) -> 1 | AD28: =IF(ISNUMBER(SEARCH("; argumentative judgment; ","; "&H28&"; ")),1,0) -> 0 | AE28: =IF(ISNUMBER(SEARCH("; genre/writing expertise; ","; "&H28&"; ")),1,0) -> 1 | AF28: =IF(ISNUMBER(SEARCH("; none; ","; "&H28&"; ")),1,0) -> 0
A29: HE-028 | B29: 28 | C29: Structure and research design | D29: Uh, what I have there, that's the personal industry academia interest and actual activities of each professor. And we don't have it in "Vasitəçi Amillər". We have it in the "İnstitusional/Struktur Amillər" means that if the system actually supports and encourages those collaboration. | E29: Correction/Challenge | F29: Knowledge injection | G29: Critical | H29: domain correction; conceptual discrimination | I29: Distinguishes personal industry interest from institutional support. | J29: AI separates the mechanisms. | K29: DOCX body elements 2340–2340 | L29: DOCX body elements 2344–2354 | N29: Visible next AI response | O29: Converted DOCX: textbox continuations joined; AI completion/source-check claims are unverified. | P29: =SUM(Q29:X29) -> 2 | Q29: =IF(OR(E29="Delegation",ISNUMBER(SEARCH("; Delegation; ","; "&F29&"; "))),1,0) -> 0 | R29: =IF(OR(E29="Directed delegation",ISNUMBER(SEARCH("; Directed delegation; ","; "&F29&"; "))),1,0) -> 0 | S29: =IF(OR(E29="Evaluation",ISNUMBER(SEARCH("; Evaluation; ","; "&F29&"; "))),1,0) -> 0 | T29: =IF(OR(E29="Correction/Challenge",ISNUMBER(SEARCH("; Correction/Challenge; ","; "&F29&"; "))),1,0) -> 1 | U29: =IF(OR(E29="Redirection",ISNUMBER(SEARCH("; Redirection; ","; "&F29&"; "))),1,0) -> 0 | V29: =IF(OR(E29="Knowledge injection",ISNUMBER(SEARCH("; Knowledge injection; ","; "&F29&"; "))),1,0) -> 1 | W29: =IF(OR(E29="Selection/Rejection",ISNUMBER(SEARCH("; Selection/Rejection; ","; "&F29&"; "))),1,0) -> 0 | X29: =IF(OR(E29="Deliberation",ISNUMBER(SEARCH("; Deliberation; ","; "&F29&"; "))),1,0) -> 0 | Y29: =SUM(Z29:AE29) -> 2 | Z29: =IF(ISNUMBER(SEARCH("; domain correction; ","; "&H29&"; ")),1,0) -> 1 | AA29: =IF(ISNUMBER(SEARCH("; conceptual discrimination; ","; "&H29&"; ")),1,0) -> 1 | AB29: =IF(ISNUMBER(SEARCH("; evidence judgment; ","; "&H29&"; ")),1,0) -> 0 | AC29: =IF(ISNUMBER(SEARCH("; methodological judgment; ","; "&H29&"; ")),1,0) -> 0 | AD29: =IF(ISNUMBER(SEARCH("; argumentative judgment; ","; "&H29&"; ")),1,0) -> 0 | AE29: =IF(ISNUMBER(SEARCH("; genre/writing expertise; ","; "&H29&"; ")),1,0) -> 0 | AF29: =IF(ISNUMBER(SEARCH("; none; ","; "&H29&"; ")),1,0) -> 0
A30: HE-029 | B30: 29 | C30: Structure and research design | D30: nowhere in the paper used the k12 because that's the American or the Western terminology used the following term: "ümumi təhsil". Also, in the last paragraph of one point one, say... don't say that we focus on all the education system. We focus at the higher ed, but we consider that students, of course, come to the higher ed from "ümumi təhsil". see the AZ overall ed system levels. regen 1.1 | E30: Correction/Challenge | F30: Redirection; Directed delegation | G30: Critical | H30: domain correction; conceptual discrimination; genre/writing expertise | I30: Rejects K–12 terminology and corrects the study’s scope to higher education. | J30: AI changes terminology and scope. | K30: DOCX body elements 2357–2357 | L30: DOCX body elements 2361–2368 | N30: Visible next AI response | O30: Converted DOCX: textbox continuations joined; AI completion/source-check claims are unverified. | P30: =SUM(Q30:X30) -> 3 | Q30: =IF(OR(E30="Delegation",ISNUMBER(SEARCH("; Delegation; ","; "&F30&"; "))),1,0) -> 0 | R30: =IF(OR(E30="Directed delegation",ISNUMBER(SEARCH("; Directed delegation; ","; "&F30&"; "))),1,0) -> 1 | S30: =IF(OR(E30="Evaluation",ISNUMBER(SEARCH("; Evaluation; ","; "&F30&"; "))),1,0) -> 0 | T30: =IF(OR(E30="Correction/Challenge",ISNUMBER(SEARCH("; Correction/Challenge; ","; "&F30&"; "))),1,0) -> 1 | U30: =IF(OR(E30="Redirection",ISNUMBER(SEARCH("; Redirection; ","; "&F30&"; "))),1,0) -> 1 | V30: =IF(OR(E30="Knowledge injection",ISNUMBER(SEARCH("; Knowledge injection; ","; "&F30&"; "))),1,0) -> 0 | W30: =IF(OR(E30="Selection/Rejection",ISNUMBER(SEARCH("; Selection/Rejection; ","; "&F30&"; "))),1,0) -> 0 | X30: =IF(OR(E30="Deliberation",ISNUMBER(SEARCH("; Deliberation; ","; "&F30&"; "))),1,0) -> 0 | Y30: =SUM(Z30:AE30) -> 3 | Z30: =IF(ISNUMBER(SEARCH("; domain correction; ","; "&H30&"; ")),1,0) -> 1 | AA30: =IF(ISNUMBER(SEARCH("; conceptual discrimination; ","; "&H30&"; ")),1,0) -> 1 | AB30: =IF(ISNUMBER(SEARCH("; evidence judgment; ","; "&H30&"; ")),1,0) -> 0 | AC30: =IF(ISNUMBER(SEARCH("; methodological judgment; ","; "&H30&"; ")),1,0) -> 0 | AD30: =IF(ISNUMBER(SEARCH("; argumentative judgment; ","; "&H30&"; ")),1,0) -> 0 | AE30: =IF(ISNUMBER(SEARCH("; genre/writing expertise; ","; "&H30&"; ")),1,0) -> 1 | AF30: =IF(ISNUMBER(SEARCH("; none; ","; "&H30&"; ")),1,0) -> 0
A31: HE-030 | B31: 30 | C31: Structure and research design | D31: Shall that paragraph go in the opening of section one? | E31: Directed delegation | F31: Knowledge injection | G31: Directive | H31: genre/writing expertise | I31: Specifies the placement of a paragraph in the introduction. | J31: AI proposes introductory placement and wording. | K31: DOCX body elements 2371–2371 | L31: DOCX body elements 2373–2394 | N31: Visible next AI response | O31: Converted DOCX: textbox continuations joined; AI completion/source-check claims are unverified. | P31: =SUM(Q31:X31) -> 2 | Q31: =IF(OR(E31="Delegation",ISNUMBER(SEARCH("; Delegation; ","; "&F31&"; "))),1,0) -> 0 | R31: =IF(OR(E31="Directed delegation",ISNUMBER(SEARCH("; Directed delegation; ","; "&F31&"; "))),1,0) -> 1 | S31: =IF(OR(E31="Evaluation",ISNUMBER(SEARCH("; Evaluation; ","; "&F31&"; "))),1,0) -> 0 | T31: =IF(OR(E31="Correction/Challenge",ISNUMBER(SEARCH("; Correction/Challenge; ","; "&F31&"; "))),1,0) -> 0 | U31: =IF(OR(E31="Redirection",ISNUMBER(SEARCH("; Redirection; ","; "&F31&"; "))),1,0) -> 0 | V31: =IF(OR(E31="Knowledge injection",ISNUMBER(SEARCH("; Knowledge injection; ","; "&F31&"; "))),1,0) -> 1 | W31: =IF(OR(E31="Selection/Rejection",ISNUMBER(SEARCH("; Selection/Rejection; ","; "&F31&"; "))),1,0) -> 0 | X31: =IF(OR(E31="Deliberation",ISNUMBER(SEARCH("; Deliberation; ","; "&F31&"; "))),1,0) -> 0 | Y31: =SUM(Z31:AE31) -> 1 | Z31: =IF(ISNUMBER(SEARCH("; domain correction; ","; "&H31&"; ")),1,0) -> 0 | AA31: =IF(ISNUMBER(SEARCH("; conceptual discrimination; ","; "&H31&"; ")),1,0) -> 0 | AB31: =IF(ISNUMBER(SEARCH("; evidence judgment; ","; "&H31&"; ")),1,0) -> 0 | AC31: =IF(ISNUMBER(SEARCH("; methodological judgment; ","; "&H31&"; ")),1,0) -> 0 | AD31: =IF(ISNUMBER(SEARCH("; argumentative judgment; ","; "&H31&"; ")),1,0) -> 0 | AE31: =IF(ISNUMBER(SEARCH("; genre/writing expertise; ","; "&H31&"; ")),1,0) -> 1 | AF31: =IF(ISNUMBER(SEARCH("; none; ","; "&H31&"; ")),1,0) -> 0
A32: HE-031 | B32: 31 | C32: Structure and research design | D32: I added a new section, too, about research design. I think that's a better design way. | E32: Knowledge injection | F32: Directed delegation | G32: Directive | H32: methodological judgment | I32: Supplies the research-design structure. | J32: AI develops the methods section. | K32: DOCX body elements 2397–2397 | L32: DOCX body elements 2401–2428 | N32: Visible next AI response | O32: Converted DOCX: textbox continuations joined; AI completion/source-check claims are unverified. | P32: =SUM(Q32:X32) -> 2 | Q32: =IF(OR(E32="Delegation",ISNUMBER(SEARCH("; Delegation; ","; "&F32&"; "))),1,0) -> 0 | R32: =IF(OR(E32="Directed delegation",ISNUMBER(SEARCH("; Directed delegation; ","; "&F32&"; "))),1,0) -> 1 | S32: =IF(OR(E32="Evaluation",ISNUMBER(SEARCH("; Evaluation; ","; "&F32&"; "))),1,0) -> 0 | T32: =IF(OR(E32="Correction/Challenge",ISNUMBER(SEARCH("; Correction/Challenge; ","; "&F32&"; "))),1,0) -> 0 | U32: =IF(OR(E32="Redirection",ISNUMBER(SEARCH("; Redirection; ","; "&F32&"; "))),1,0) -> 0 | V32: =IF(OR(E32="Knowledge injection",ISNUMBER(SEARCH("; Knowledge injection; ","; "&F32&"; "))),1,0) -> 1 | W32: =IF(OR(E32="Selection/Rejection",ISNUMBER(SEARCH("; Selection/Rejection; ","; "&F32&"; "))),1,0) -> 0 | X32: =IF(OR(E32="Deliberation",ISNUMBER(SEARCH("; Deliberation; ","; "&F32&"; "))),1,0) -> 0 | Y32: =SUM(Z32:AE32) -> 1 | Z32: =IF(ISNUMBER(SEARCH("; domain correction; ","; "&H32&"; ")),1,0) -> 0 | AA32: =IF(ISNUMBER(SEARCH("; conceptual discrimination; ","; "&H32&"; ")),1,0) -> 0 | AB32: =IF(ISNUMBER(SEARCH("; evidence judgment; ","; "&H32&"; ")),1,0) -> 0 | AC32: =IF(ISNUMBER(SEARCH("; methodological judgment; ","; "&H32&"; ")),1,0) -> 1 | AD32: =IF(ISNUMBER(SEARCH("; argumentative judgment; ","; "&H32&"; ")),1,0) -> 0 | AE32: =IF(ISNUMBER(SEARCH("; genre/writing expertise; ","; "&H32&"; ")),1,0) -> 0 | AF32: =IF(ISNUMBER(SEARCH("; none; ","; "&H32&"; ")),1,0) -> 0
A33: HE-032 | B33: 32 | C33: Structure and research design | D33: For research methods, I'd... yeah. Well, you suggest what should we do. We'd say that, you know, we are gonna... I'm thinking of, like, mentioning the data sources and data collection. So I've done a student survey also using my own expertise and observations and field studies and related work. This... the research pay... the research method is that we will design a causation model and then use that to do pragmatic s… | E33: Knowledge injection | F33: Directed delegation | G33: Directive | H33: methodological judgment; evidence judgment | I33: Specifies a student survey, observations and experience as distinct inputs to causal modeling. | J33: AI incorporates the proposed methodological grounding. | K33: DOCX body elements 2431–2431 | L33: DOCX body elements 2435–2449 | N33: Visible next AI response | O33: Converted DOCX: textbox continuations joined; AI completion/source-check claims are unverified. | P33: =SUM(Q33:X33) -> 2 | Q33: =IF(OR(E33="Delegation",ISNUMBER(SEARCH("; Delegation; ","; "&F33&"; "))),1,0) -> 0 | R33: =IF(OR(E33="Directed delegation",ISNUMBER(SEARCH("; Directed delegation; ","; "&F33&"; "))),1,0) -> 1 | S33: =IF(OR(E33="Evaluation",ISNUMBER(SEARCH("; Evaluation; ","; "&F33&"; "))),1,0) -> 0 | T33: =IF(OR(E33="Correction/Challenge",ISNUMBER(SEARCH("; Correction/Challenge; ","; "&F33&"; "))),1,0) -> 0 | U33: =IF(OR(E33="Redirection",ISNUMBER(SEARCH("; Redirection; ","; "&F33&"; "))),1,0) -> 0 | V33: =IF(OR(E33="Knowledge injection",ISNUMBER(SEARCH("; Knowledge injection; ","; "&F33&"; "))),1,0) -> 1 | W33: =IF(OR(E33="Selection/Rejection",ISNUMBER(SEARCH("; Selection/Rejection; ","; "&F33&"; "))),1,0) -> 0 | X33: =IF(OR(E33="Deliberation",ISNUMBER(SEARCH("; Deliberation; ","; "&F33&"; "))),1,0) -> 0 | Y33: =SUM(Z33:AE33) -> 2 | Z33: =IF(ISNUMBER(SEARCH("; domain correction; ","; "&H33&"; ")),1,0) -> 0 | AA33: =IF(ISNUMBER(SEARCH("; conceptual discrimination; ","; "&H33&"; ")),1,0) -> 0 | AB33: =IF(ISNUMBER(SEARCH("; evidence judgment; ","; "&H33&"; ")),1,0) -> 1 | AC33: =IF(ISNUMBER(SEARCH("; methodological judgment; ","; "&H33&"; ")),1,0) -> 1 | AD33: =IF(ISNUMBER(SEARCH("; argumentative judgment; ","; "&H33&"; ")),1,0) -> 0 | AE33: =IF(ISNUMBER(SEARCH("; genre/writing expertise; ","; "&H33&"; ")),1,0) -> 0 | AF33: =IF(ISNUMBER(SEARCH("; none; ","; "&H33&"; ")),1,0) -> 0
A34: HE-033 | B34: 33 | C34: Structure and research design | D34: : Give two opening paragraphs for section one and also give one point one.Notes: --Donot use the Harari style of writing. use standard academic writing. --give text in chat area, not Word file --be very concise / minimalistic in text of each part. paper 's length shall be 8000 words max. keep a count of how much we have written so far. --ensure no overlap of the new text that you give, with other parts of the paper. … | E34: Directed delegation | G34: Directive | H34: evidence judgment; genre/writing expertise | I34: Sets academic style, length and reference-verification constraints for the introduction. | J34: AI drafts the introduction and supplies references; checks are not independently verified. | K34: DOCX body elements 2450–2450 | L34: DOCX body elements 2453–2483 | N34: Visible next AI response | O34: Converted DOCX: textbox continuations joined; AI completion/source-check claims are unverified. | P34: =SUM(Q34:X34) -> 1 | Q34: =IF(OR(E34="Delegation",ISNUMBER(SEARCH("; Delegation; ","; "&F34&"; "))),1,0) -> 0 | R34: =IF(OR(E34="Directed delegation",ISNUMBER(SEARCH("; Directed delegation; ","; "&F34&"; "))),1,0) -> 1 | S34: =IF(OR(E34="Evaluation",ISNUMBER(SEARCH("; Evaluation; ","; "&F34&"; "))),1,0) -> 0 | T34: =IF(OR(E34="Correction/Challenge",ISNUMBER(SEARCH("; Correction/Challenge; ","; "&F34&"; "))),1,0) -> 0 | U34: =IF(OR(E34="Redirection",ISNUMBER(SEARCH("; Redirection; ","; "&F34&"; "))),1,0) -> 0 | V34: =IF(OR(E34="Knowledge injection",ISNUMBER(SEARCH("; Knowledge injection; ","; "&F34&"; "))),1,0) -> 0 | W34: =IF(OR(E34="Selection/Rejection",ISNUMBER(SEARCH("; Selection/Rejection; ","; "&F34&"; "))),1,0) -> 0 | X34: =IF(OR(E34="Deliberation",ISNUMBER(SEARCH("; Deliberation; ","; "&F34&"; "))),1,0) -> 0 | Y34: =SUM(Z34:AE34) -> 2 | Z34: =IF(ISNUMBER(SEARCH("; domain correction; ","; "&H34&"; ")),1,0) -> 0 | AA34: =IF(ISNUMBER(SEARCH("; conceptual discrimination; ","; "&H34&"; ")),1,0) -> 0 | AB34: =IF(ISNUMBER(SEARCH("; evidence judgment; ","; "&H34&"; ")),1,0) -> 1 | AC34: =IF(ISNUMBER(SEARCH("; methodological judgment; ","; "&H34&"; ")),1,0) -> 0 | AD34: =IF(ISNUMBER(SEARCH("; argumentative judgment; ","; "&H34&"; ")),1,0) -> 0 | AE34: =IF(ISNUMBER(SEARCH("; genre/writing expertise; ","; "&H34&"; ")),1,0) -> 1 | AF34: =IF(ISNUMBER(SEARCH("; none; ","; "&H34&"; ")),1,0) -> 0
A35: HE-034 | B35: 34 | C35: Structure and research design | D35: ? | E35: Evaluation | G35: Evaluative | H35: none | I35: A question mark signals uncertainty but does not identify a substantive basis. | J35: AI interprets the cue as a wording question; coding is provisional. | K35: DOCX body elements 2485–2485 | L35: DOCX body elements 2489–2506 | N35: Visible next AI response | O35: Converted DOCX: textbox continuations joined; AI completion/source-check claims are unverified. Ambiguous question-mark cue; provisional interpretation. | P35: =SUM(Q35:X35) -> 1 | Q35: =IF(OR(E35="Delegation",ISNUMBER(SEARCH("; Delegation; ","; "&F35&"; "))),1,0) -> 0 | R35: =IF(OR(E35="Directed delegation",ISNUMBER(SEARCH("; Directed delegation; ","; "&F35&"; "))),1,0) -> 0 | S35: =IF(OR(E35="Evaluation",ISNUMBER(SEARCH("; Evaluation; ","; "&F35&"; "))),1,0) -> 1 | T35: =IF(OR(E35="Correction/Challenge",ISNUMBER(SEARCH("; Correction/Challenge; ","; "&F35&"; "))),1,0) -> 0 | U35: =IF(OR(E35="Redirection",ISNUMBER(SEARCH("; Redirection; ","; "&F35&"; "))),1,0) -> 0 | V35: =IF(OR(E35="Knowledge injection",ISNUMBER(SEARCH("; Knowledge injection; ","; "&F35&"; "))),1,0) -> 0 | W35: =IF(OR(E35="Selection/Rejection",ISNUMBER(SEARCH("; Selection/Rejection; ","; "&F35&"; "))),1,0) -> 0 | X35: =IF(OR(E35="Deliberation",ISNUMBER(SEARCH("; Deliberation; ","; "&F35&"; "))),1,0) -> 0 | Y35: =SUM(Z35:AE35) -> 0 | Z35: =IF(ISNUMBER(SEARCH("; domain correction; ","; "&H35&"; ")),1,0) -> 0 | AA35: =IF(ISNUMBER(SEARCH("; conceptual discrimination; ","; "&H35&"; ")),1,0) -> 0 | AB35: =IF(ISNUMBER(SEARCH("; evidence judgment; ","; "&H35&"; ")),1,0) -> 0 | AC35: =IF(ISNUMBER(SEARCH("; methodological judgment; ","; "&H35&"; ")),1,0) -> 0 | AD35: =IF(ISNUMBER(SEARCH("; argumentative judgment; ","; "&H35&"; ")),1,0) -> 0 | AE35: =IF(ISNUMBER(SEARCH("; genre/writing expertise; ","; "&H35&"; ")),1,0) -> 0 | AF35: =IF(ISNUMBER(SEARCH("; none; ","; "&H35&"; ")),1,0) -> 1
A36: HE-035 | B36: 35 | C36: Structure and research design | D36: using my hints below (if any), give text of: 1.2 Məqalənin Məqsədi və töhfələrNotes: --Donot use the Harari style of writing. use standard academic writing. --give text in chat area, not Word file --be very concise / minimalistic in text of each part. paper 's length shall be 8000 words max. keep a count of how much we have written so far. --ensure no overlap of the new text that you give, with other parts of the pap… | E36: Directed delegation | G36: Directive | H36: genre/writing expertise | I36: Requests a constrained draft of Section 1.2. | J36: AI drafts the subsection. | K36: DOCX body elements 2507–2507 | L36: DOCX body elements 2510–2530 | N36: Visible next AI response | O36: Converted DOCX: textbox continuations joined; AI completion/source-check claims are unverified. | P36: =SUM(Q36:X36) -> 1 | Q36: =IF(OR(E36="Delegation",ISNUMBER(SEARCH("; Delegation; ","; "&F36&"; "))),1,0) -> 0 | R36: =IF(OR(E36="Directed delegation",ISNUMBER(SEARCH("; Directed delegation; ","; "&F36&"; "))),1,0) -> 1 | S36: =IF(OR(E36="Evaluation",ISNUMBER(SEARCH("; Evaluation; ","; "&F36&"; "))),1,0) -> 0 | T36: =IF(OR(E36="Correction/Challenge",ISNUMBER(SEARCH("; Correction/Challenge; ","; "&F36&"; "))),1,0) -> 0 | U36: =IF(OR(E36="Redirection",ISNUMBER(SEARCH("; Redirection; ","; "&F36&"; "))),1,0) -> 0 | V36: =IF(OR(E36="Knowledge injection",ISNUMBER(SEARCH("; Knowledge injection; ","; "&F36&"; "))),1,0) -> 0 | W36: =IF(OR(E36="Selection/Rejection",ISNUMBER(SEARCH("; Selection/Rejection; ","; "&F36&"; "))),1,0) -> 0 | X36: =IF(OR(E36="Deliberation",ISNUMBER(SEARCH("; Deliberation; ","; "&F36&"; "))),1,0) -> 0 | Y36: =SUM(Z36:AE36) -> 1 | Z36: =IF(ISNUMBER(SEARCH("; domain correction; ","; "&H36&"; ")),1,0) -> 0 | AA36: =IF(ISNUMBER(SEARCH("; conceptual discrimination; ","; "&H36&"; ")),1,0) -> 0 | AB36: =IF(ISNUMBER(SEARCH("; evidence judgment; ","; "&H36&"; ")),1,0) -> 0 | AC36: =IF(ISNUMBER(SEARCH("; methodological judgment; ","; "&H36&"; ")),1,0) -> 0 | AD36: =IF(ISNUMBER(SEARCH("; argumentative judgment; ","; "&H36&"; ")),1,0) -> 0 | AE36: =IF(ISNUMBER(SEARCH("; genre/writing expertise; ","; "&H36&"; ")),1,0) -> 1 | AF36: =IF(ISNUMBER(SEARCH("; none; ","; "&H36&"; ")),1,0) -> 0
A37: HE-036 | B37: 36 | C37: Structure and research design | D37: İ changed it to 1.2 Məqalənin Məqsədi, Yanaşması və töhfələri. regen | E37: Redirection | F37: Directed delegation | G37: Directive | H37: genre/writing expertise | I37: Changes the heading to include the approach and requests regeneration. | J37: AI revises the heading and subsection. | K37: DOCX body elements 2532–2532 | L37: DOCX body elements 2535–2556 | N37: Visible next AI response | O37: Converted DOCX: textbox continuations joined; AI completion/source-check claims are unverified. | P37: =SUM(Q37:X37) -> 2 | Q37: =IF(OR(E37="Delegation",ISNUMBER(SEARCH("; Delegation; ","; "&F37&"; "))),1,0) -> 0 | R37: =IF(OR(E37="Directed delegation",ISNUMBER(SEARCH("; Directed delegation; ","; "&F37&"; "))),1,0) -> 1 | S37: =IF(OR(E37="Evaluation",ISNUMBER(SEARCH("; Evaluation; ","; "&F37&"; "))),1,0) -> 0 | T37: =IF(OR(E37="Correction/Challenge",ISNUMBER(SEARCH("; Correction/Challenge; ","; "&F37&"; "))),1,0) -> 0 | U37: =IF(OR(E37="Redirection",ISNUMBER(SEARCH("; Redirection; ","; "&F37&"; "))),1,0) -> 1 | V37: =IF(OR(E37="Knowledge injection",ISNUMBER(SEARCH("; Knowledge injection; ","; "&F37&"; "))),1,0) -> 0 | W37: =IF(OR(E37="Selection/Rejection",ISNUMBER(SEARCH("; Selection/Rejection; ","; "&F37&"; "))),1,0) -> 0 | X37: =IF(OR(E37="Deliberation",ISNUMBER(SEARCH("; Deliberation; ","; "&F37&"; "))),1,0) -> 0 | Y37: =SUM(Z37:AE37) -> 1 | Z37: =IF(ISNUMBER(SEARCH("; domain correction; ","; "&H37&"; ")),1,0) -> 0 | AA37: =IF(ISNUMBER(SEARCH("; conceptual discrimination; ","; "&H37&"; ")),1,0) -> 0 | AB37: =IF(ISNUMBER(SEARCH("; evidence judgment; ","; "&H37&"; ")),1,0) -> 0 | AC37: =IF(ISNUMBER(SEARCH("; methodological judgment; ","; "&H37&"; ")),1,0) -> 0 | AD37: =IF(ISNUMBER(SEARCH("; argumentative judgment; ","; "&H37&"; ")),1,0) -> 0 | AE37: =IF(ISNUMBER(SEARCH("; genre/writing expertise; ","; "&H37&"; ")),1,0) -> 1 | AF37: =IF(ISNUMBER(SEARCH("; none; ","; "&H37&"; ")),1,0) -> 0
A38: HE-037 | B38: 37 | C38: Structure and research design | D38: Is this the best design for section two?2 TƏDQİQATIN DİZAYNI A parag 2.1 Tədqiqat Metodu2.2 Tədqiqatçının Mövqeliyi, Mövzudakı Etibarlılığı və Daxili-Xarici Perspektivi • Qərb Universitetlərində 26 İl Akademik Təcrübəsi (Kanada, Türkiyə, Böyük Britaniya) • Since 2022, he is deeply integrated into AZ higher education system. A part-time invited prof in AZTU • AzTU İTT Fakültəsində Kurikulumun Müasirləşdirilməsi Layihə… | E38: Knowledge injection | F38: Directed delegation | G38: Directive | H38: methodological judgment | I38: Supplies credentials and positionality for the methods structure. | J38: AI develops the methodology and positionality account. | K38: DOCX body elements 2557–2557 | L38: DOCX body elements 2560–2573 | N38: Visible next AI response | O38: Converted DOCX: textbox continuations joined; AI completion/source-check claims are unverified. | P38: =SUM(Q38:X38) -> 2 | Q38: =IF(OR(E38="Delegation",ISNUMBER(SEARCH("; Delegation; ","; "&F38&"; "))),1,0) -> 0 | R38: =IF(OR(E38="Directed delegation",ISNUMBER(SEARCH("; Directed delegation; ","; "&F38&"; "))),1,0) -> 1 | S38: =IF(OR(E38="Evaluation",ISNUMBER(SEARCH("; Evaluation; ","; "&F38&"; "))),1,0) -> 0 | T38: =IF(OR(E38="Correction/Challenge",ISNUMBER(SEARCH("; Correction/Challenge; ","; "&F38&"; "))),1,0) -> 0 | U38: =IF(OR(E38="Redirection",ISNUMBER(SEARCH("; Redirection; ","; "&F38&"; "))),1,0) -> 0 | V38: =IF(OR(E38="Knowledge injection",ISNUMBER(SEARCH("; Knowledge injection; ","; "&F38&"; "))),1,0) -> 1 | W38: =IF(OR(E38="Selection/Rejection",ISNUMBER(SEARCH("; Selection/Rejection; ","; "&F38&"; "))),1,0) -> 0 | X38: =IF(OR(E38="Deliberation",ISNUMBER(SEARCH("; Deliberation; ","; "&F38&"; "))),1,0) -> 0 | Y38: =SUM(Z38:AE38) -> 1 | Z38: =IF(ISNUMBER(SEARCH("; domain correction; ","; "&H38&"; ")),1,0) -> 0 | AA38: =IF(ISNUMBER(SEARCH("; conceptual discrimination; ","; "&H38&"; ")),1,0) -> 0 | AB38: =IF(ISNUMBER(SEARCH("; evidence judgment; ","; "&H38&"; ")),1,0) -> 0 | AC38: =IF(ISNUMBER(SEARCH("; methodological judgment; ","; "&H38&"; ")),1,0) -> 1 | AD38: =IF(ISNUMBER(SEARCH("; argumentative judgment; ","; "&H38&"; ")),1,0) -> 0 | AE38: =IF(ISNUMBER(SEARCH("; genre/writing expertise; ","; "&H38&"; ")),1,0) -> 0 | AF38: =IF(ISNUMBER(SEARCH("; none; ","; "&H38&"; ")),1,0) -> 0
A39: HE-038 | B39: 38 | C39: Structure and research design | D39: No. Those are, uh, those are just the hints that I wanted to give to you. Right? I have, um, those are not ready, um, tasks. Those were just the hints for you. | E39: Correction/Challenge | F39: Redirection | G39: Critical | H39: methodological judgment | I39: Clarifies that supplied hints describe intended work rather than completed tasks. | J39: AI revises the tense and methodological framing. | K39: DOCX body elements 2574–2574 | L39: DOCX body elements 2574–2592 | N39: Visible next AI response | O39: Converted DOCX: textbox continuations joined; AI completion/source-check claims are unverified. | P39: =SUM(Q39:X39) -> 2 | Q39: =IF(OR(E39="Delegation",ISNUMBER(SEARCH("; Delegation; ","; "&F39&"; "))),1,0) -> 0 | R39: =IF(OR(E39="Directed delegation",ISNUMBER(SEARCH("; Directed delegation; ","; "&F39&"; "))),1,0) -> 0 | S39: =IF(OR(E39="Evaluation",ISNUMBER(SEARCH("; Evaluation; ","; "&F39&"; "))),1,0) -> 0 | T39: =IF(OR(E39="Correction/Challenge",ISNUMBER(SEARCH("; Correction/Challenge; ","; "&F39&"; "))),1,0) -> 1 | U39: =IF(OR(E39="Redirection",ISNUMBER(SEARCH("; Redirection; ","; "&F39&"; "))),1,0) -> 1 | V39: =IF(OR(E39="Knowledge injection",ISNUMBER(SEARCH("; Knowledge injection; ","; "&F39&"; "))),1,0) -> 0 | W39: =IF(OR(E39="Selection/Rejection",ISNUMBER(SEARCH("; Selection/Rejection; ","; "&F39&"; "))),1,0) -> 0 | X39: =IF(OR(E39="Deliberation",ISNUMBER(SEARCH("; Deliberation; ","; "&F39&"; "))),1,0) -> 0 | Y39: =SUM(Z39:AE39) -> 1 | Z39: =IF(ISNUMBER(SEARCH("; domain correction; ","; "&H39&"; ")),1,0) -> 0 | AA39: =IF(ISNUMBER(SEARCH("; conceptual discrimination; ","; "&H39&"; ")),1,0) -> 0 | AB39: =IF(ISNUMBER(SEARCH("; evidence judgment; ","; "&H39&"; ")),1,0) -> 0 | AC39: =IF(ISNUMBER(SEARCH("; methodological judgment; ","; "&H39&"; ")),1,0) -> 1 | AD39: =IF(ISNUMBER(SEARCH("; argumentative judgment; ","; "&H39&"; ")),1,0) -> 0 | AE39: =IF(ISNUMBER(SEARCH("; genre/writing expertise; ","; "&H39&"; ")),1,0) -> 0 | AF39: =IF(ISNUMBER(SEARCH("; none; ","; "&H39&"; ")),1,0) -> 0
A40: HE-039 | B40: 39 | C40: Structure and research design | D40: using my hints below (if any), give text of: 2 TƏDQİQATIN DİZAYNI A parag 2.1 Tədqiqat Metodu2.2 Tədqiqatçının Mövqeliyi, Mövzudakı Etibarlılığı və Daxili-Xarici Perspektivi • • Define Daxili-Xarici Tədqiqat (insider outsider research) – BTÜ, İ vill cite “The space between: On being an insider-outsider in qualitative Research”, SC Dwyer, JL Buckle - International journal of qualitative …, 2009 - journals.sagepub.com … | E40: Directed delegation | F40: Knowledge injection | G40: Directive | H40: methodological judgment; evidence judgment; genre/writing expertise | I40: Provides insider/outsider experience and reference requirements for research-design prose. | J40: AI drafts the research design and positionality discussion. | K40: DOCX body elements 2593–2595 | L40: DOCX body elements 2598–2629 | M40: Extended draft/quoted context; researcher-origin judgment distinguished in rationale | N40: Visible next AI response | O40: Converted DOCX: textbox continuations joined; AI completion/source-check claims are unverified. | P40: =SUM(Q40:X40) -> 2 | Q40: =IF(OR(E40="Delegation",ISNUMBER(SEARCH("; Delegation; ","; "&F40&"; "))),1,0) -> 0 | R40: =IF(OR(E40="Directed delegation",ISNUMBER(SEARCH("; Directed delegation; ","; "&F40&"; "))),1,0) -> 1 | S40: =IF(OR(E40="Evaluation",ISNUMBER(SEARCH("; Evaluation; ","; "&F40&"; "))),1,0) -> 0 | T40: =IF(OR(E40="Correction/Challenge",ISNUMBER(SEARCH("; Correction/Challenge; ","; "&F40&"; "))),1,0) -> 0 | U40: =IF(OR(E40="Redirection",ISNUMBER(SEARCH("; Redirection; ","; "&F40&"; "))),1,0) -> 0 | V40: =IF(OR(E40="Knowledge injection",ISNUMBER(SEARCH("; Knowledge injection; ","; "&F40&"; "))),1,0) -> 1 | W40: =IF(OR(E40="Selection/Rejection",ISNUMBER(SEARCH("; Selection/Rejection; ","; "&F40&"; "))),1,0) -> 0 | X40: =IF(OR(E40="Deliberation",ISNUMBER(SEARCH("; Deliberation; ","; "&F40&"; "))),1,0) -> 0 | Y40: =SUM(Z40:AE40) -> 3 | Z40: =IF(ISNUMBER(SEARCH("; domain correction; ","; "&H40&"; ")),1,0) -> 0 | AA40: =IF(ISNUMBER(SEARCH("; conceptual discrimination; ","; "&H40&"; ")),1,0) -> 0 | AB40: =IF(ISNUMBER(SEARCH("; evidence judgment; ","; "&H40&"; ")),1,0) -> 1 | AC40: =IF(ISNUMBER(SEARCH("; methodological judgment; ","; "&H40&"; ")),1,0) -> 1 | AD40: =IF(ISNUMBER(SEARCH("; argumentative judgment; ","; "&H40&"; ")),1,0) -> 0 | AE40: =IF(ISNUMBER(SEARCH("; genre/writing expertise; ","; "&H40&"; ")),1,0) -> 1 | AF40: =IF(ISNUMBER(SEARCH("; none; ","; "&H40&"; ")),1,0) -> 0
A41: HE-040 | B41: 40 | C41: Structure and research design | D41: vhat about the student survey that ve designed and i hjave done? | E41: Correction/Challenge | F41: Knowledge injection | G41: Critical | H41: methodological judgment | I41: Detects omission of the planned student survey. | J41: AI adds the survey to the methods account. | K41: DOCX body elements 2631–2631 | L41: DOCX body elements 2635–2641 | N41: Visible next AI response | O41: Converted DOCX: textbox continuations joined; AI completion/source-check claims are unverified. | P41: =SUM(Q41:X41) -> 2 | Q41: =IF(OR(E41="Delegation",ISNUMBER(SEARCH("; Delegation; ","; "&F41&"; "))),1,0) -> 0 | R41: =IF(OR(E41="Directed delegation",ISNUMBER(SEARCH("; Directed delegation; ","; "&F41&"; "))),1,0) -> 0 | S41: =IF(OR(E41="Evaluation",ISNUMBER(SEARCH("; Evaluation; ","; "&F41&"; "))),1,0) -> 0 | T41: =IF(OR(E41="Correction/Challenge",ISNUMBER(SEARCH("; Correction/Challenge; ","; "&F41&"; "))),1,0) -> 1 | U41: =IF(OR(E41="Redirection",ISNUMBER(SEARCH("; Redirection; ","; "&F41&"; "))),1,0) -> 0 | V41: =IF(OR(E41="Knowledge injection",ISNUMBER(SEARCH("; Knowledge injection; ","; "&F41&"; "))),1,0) -> 1 | W41: =IF(OR(E41="Selection/Rejection",ISNUMBER(SEARCH("; Selection/Rejection; ","; "&F41&"; "))),1,0) -> 0 | X41: =IF(OR(E41="Deliberation",ISNUMBER(SEARCH("; Deliberation; ","; "&F41&"; "))),1,0) -> 0 | Y41: =SUM(Z41:AE41) -> 1 | Z41: =IF(ISNUMBER(SEARCH("; domain correction; ","; "&H41&"; ")),1,0) -> 0 | AA41: =IF(ISNUMBER(SEARCH("; conceptual discrimination; ","; "&H41&"; ")),1,0) -> 0 | AB41: =IF(ISNUMBER(SEARCH("; evidence judgment; ","; "&H41&"; ")),1,0) -> 0 | AC41: =IF(ISNUMBER(SEARCH("; methodological judgment; ","; "&H41&"; ")),1,0) -> 1 | AD41: =IF(ISNUMBER(SEARCH("; argumentative judgment; ","; "&H41&"; ")),1,0) -> 0 | AE41: =IF(ISNUMBER(SEARCH("; genre/writing expertise; ","; "&H41&"; ")),1,0) -> 0 | AF41: =IF(ISNUMBER(SEARCH("; none; ","; "&H41&"; ")),1,0) -> 0
A42: HE-041 | B42: 41 | C42: Structure and research design | D42: data were collected during june-july 2026. 53 student completed it | E42: Knowledge injection | F42: Directed delegation | G42: Directive | H42: methodological judgment; evidence judgment | I42: Supplies survey timing and sample size of 53. | J42: AI integrates the survey details. | K42: DOCX body elements 2644–2644 | L42: DOCX body elements 2648–2679 | N42: Visible next AI response | O42: Converted DOCX: textbox continuations joined; AI completion/source-check claims are unverified. | P42: =SUM(Q42:X42) -> 2 | Q42: =IF(OR(E42="Delegation",ISNUMBER(SEARCH("; Delegation; ","; "&F42&"; "))),1,0) -> 0 | R42: =IF(OR(E42="Directed delegation",ISNUMBER(SEARCH("; Directed delegation; ","; "&F42&"; "))),1,0) -> 1 | S42: =IF(OR(E42="Evaluation",ISNUMBER(SEARCH("; Evaluation; ","; "&F42&"; "))),1,0) -> 0 | T42: =IF(OR(E42="Correction/Challenge",ISNUMBER(SEARCH("; Correction/Challenge; ","; "&F42&"; "))),1,0) -> 0 | U42: =IF(OR(E42="Redirection",ISNUMBER(SEARCH("; Redirection; ","; "&F42&"; "))),1,0) -> 0 | V42: =IF(OR(E42="Knowledge injection",ISNUMBER(SEARCH("; Knowledge injection; ","; "&F42&"; "))),1,0) -> 1 | W42: =IF(OR(E42="Selection/Rejection",ISNUMBER(SEARCH("; Selection/Rejection; ","; "&F42&"; "))),1,0) -> 0 | X42: =IF(OR(E42="Deliberation",ISNUMBER(SEARCH("; Deliberation; ","; "&F42&"; "))),1,0) -> 0 | Y42: =SUM(Z42:AE42) -> 2 | Z42: =IF(ISNUMBER(SEARCH("; domain correction; ","; "&H42&"; ")),1,0) -> 0 | AA42: =IF(ISNUMBER(SEARCH("; conceptual discrimination; ","; "&H42&"; ")),1,0) -> 0 | AB42: =IF(ISNUMBER(SEARCH("; evidence judgment; ","; "&H42&"; ")),1,0) -> 1 | AC42: =IF(ISNUMBER(SEARCH("; methodological judgment; ","; "&H42&"; ")),1,0) -> 1 | AD42: =IF(ISNUMBER(SEARCH("; argumentative judgment; ","; "&H42&"; ")),1,0) -> 0 | AE42: =IF(ISNUMBER(SEARCH("; genre/writing expertise; ","; "&H42&"; ")),1,0) -> 0 | AF42: =IF(ISNUMBER(SEARCH("; none; ","; "&H42&"; ")),1,0) -> 0
A43: HE-042 | B43: 42 | C43: Structure and research design | D43: give a sentence that all the questions of the survey can be found in an online supplementary material (URL) | E43: Knowledge injection | F43: Directed delegation | G43: Directive | H43: evidence judgment | I43: Supplies a survey URL for the account. | J43: AI adds the link and contextual prose; access is not independently confirmed. | K43: DOCX body elements 2680–2680 | L43: DOCX body elements 2684–2692 | N43: Visible next AI response | O43: Converted DOCX: textbox continuations joined; AI completion/source-check claims are unverified. | P43: =SUM(Q43:X43) -> 2 | Q43: =IF(OR(E43="Delegation",ISNUMBER(SEARCH("; Delegation; ","; "&F43&"; "))),1,0) -> 0 | R43: =IF(OR(E43="Directed delegation",ISNUMBER(SEARCH("; Directed delegation; ","; "&F43&"; "))),1,0) -> 1 | S43: =IF(OR(E43="Evaluation",ISNUMBER(SEARCH("; Evaluation; ","; "&F43&"; "))),1,0) -> 0 | T43: =IF(OR(E43="Correction/Challenge",ISNUMBER(SEARCH("; Correction/Challenge; ","; "&F43&"; "))),1,0) -> 0 | U43: =IF(OR(E43="Redirection",ISNUMBER(SEARCH("; Redirection; ","; "&F43&"; "))),1,0) -> 0 | V43: =IF(OR(E43="Knowledge injection",ISNUMBER(SEARCH("; Knowledge injection; ","; "&F43&"; "))),1,0) -> 1 | W43: =IF(OR(E43="Selection/Rejection",ISNUMBER(SEARCH("; Selection/Rejection; ","; "&F43&"; "))),1,0) -> 0 | X43: =IF(OR(E43="Deliberation",ISNUMBER(SEARCH("; Deliberation; ","; "&F43&"; "))),1,0) -> 0 | Y43: =SUM(Z43:AE43) -> 1 | Z43: =IF(ISNUMBER(SEARCH("; domain correction; ","; "&H43&"; ")),1,0) -> 0 | AA43: =IF(ISNUMBER(SEARCH("; conceptual discrimination; ","; "&H43&"; ")),1,0) -> 0 | AB43: =IF(ISNUMBER(SEARCH("; evidence judgment; ","; "&H43&"; ")),1,0) -> 1 | AC43: =IF(ISNUMBER(SEARCH("; methodological judgment; ","; "&H43&"; ")),1,0) -> 0 | AD43: =IF(ISNUMBER(SEARCH("; argumentative judgment; ","; "&H43&"; ")),1,0) -> 0 | AE43: =IF(ISNUMBER(SEARCH("; genre/writing expertise; ","; "&H43&"; ")),1,0) -> 0 | AF43: =IF(ISNUMBER(SEARCH("; none; ","; "&H43&"; ")),1,0) -> 0
A44: HE-043 | B44: 43 | C44: Structure and research design | D44: using my hints below (if any), give text of: 3.1 Azərbaycanın Təhsil Sistemi Haqqında Əvvəlki Tədqiqatlar UNICEF Azərbaycan Təhsil Hesabatı (2010) CITE in APA style, and very briefly discuss THESE PAPERS • Abasova, S. H. q. (2024). Competitiveness of Higher Education in Azerbaijan: Comparative Analysis with Former USSR’ Countries. Journal of Psychological Science and Research, 4(3), 1–8. • Aliyev, M., & Aliyeva, S. (… | E44: Directed delegation | F44: Knowledge injection | G44: Directive | H44: evidence judgment; genre/writing expertise | I44: Supplies a source pool and requires related-work synthesis and citation checks. | J44: AI drafts related work; bibliographic accuracy is not independently checked here. | K44: DOCX body elements 2694–2702 | L44: DOCX body elements 2705–2754 | M44: URL(s) supplied in prompt; Extended draft/quoted context; researcher-origin judgment distinguished in rationale | N44: Visible next AI response | O44: Converted DOCX: textbox continuations joined; AI completion/source-check claims are unverified. | P44: =SUM(Q44:X44) -> 2 | Q44: =IF(OR(E44="Delegation",ISNUMBER(SEARCH("; Delegation; ","; "&F44&"; "))),1,0) -> 0 | R44: =IF(OR(E44="Directed delegation",ISNUMBER(SEARCH("; Directed delegation; ","; "&F44&"; "))),1,0) -> 1 | S44: =IF(OR(E44="Evaluation",ISNUMBER(SEARCH("; Evaluation; ","; "&F44&"; "))),1,0) -> 0 | T44: =IF(OR(E44="Correction/Challenge",ISNUMBER(SEARCH("; Correction/Challenge; ","; "&F44&"; "))),1,0) -> 0 | U44: =IF(OR(E44="Redirection",ISNUMBER(SEARCH("; Redirection; ","; "&F44&"; "))),1,0) -> 0 | V44: =IF(OR(E44="Knowledge injection",ISNUMBER(SEARCH("; Knowledge injection; ","; "&F44&"; "))),1,0) -> 1 | W44: =IF(OR(E44="Selection/Rejection",ISNUMBER(SEARCH("; Selection/Rejection; ","; "&F44&"; "))),1,0) -> 0 | X44: =IF(OR(E44="Deliberation",ISNUMBER(SEARCH("; Deliberation; ","; "&F44&"; "))),1,0) -> 0 | Y44: =SUM(Z44:AE44) -> 2 | Z44: =IF(ISNUMBER(SEARCH("; domain correction; ","; "&H44&"; ")),1,0) -> 0 | AA44: =IF(ISNUMBER(SEARCH("; conceptual discrimination; ","; "&H44&"; ")),1,0) -> 0 | AB44: =IF(ISNUMBER(SEARCH("; evidence judgment; ","; "&H44&"; ")),1,0) -> 1 | AC44: =IF(ISNUMBER(SEARCH("; methodological judgment; ","; "&H44&"; ")),1,0) -> 0 | AD44: =IF(ISNUMBER(SEARCH("; argumentative judgment; ","; "&H44&"; ")),1,0) -> 0 | AE44: =IF(ISNUMBER(SEARCH("; genre/writing expertise; ","; "&H44&"; ")),1,0) -> 1 | AF44: =IF(ISNUMBER(SEARCH("; none; ","; "&H44&"; ")),1,0) -> 0
A45: HE-044 | B45: 44 | C45: Structure and research design | D45: here it is https://www.journalser.com/jser/article/view/130 -- and its Abstract In the modern era, higher education institutions are not only organizations that perform teaching functions but also strategic academic centers that play a crucial role in the creation, dissemination, and application of scientific knowledge. Strengthening the research potential of universities is one of the key prerequisites for the devel… | E45: Correction/Challenge | F45: Knowledge injection | G45: Critical | H45: evidence judgment | I45: Supplies a URL and abstract to counter AI’s doubts about a source. | J45: AI accepts the supplied source and revises its treatment. | K45: DOCX body elements 2759–2759 | L45: DOCX body elements 2763–2775 | M45: URL(s) supplied in prompt; Extended draft/quoted context; researcher-origin judgment distinguished in rationale | N45: Visible next AI response | O45: Converted DOCX: textbox continuations joined; AI completion/source-check claims are unverified. | P45: =SUM(Q45:X45) -> 2 | Q45: =IF(OR(E45="Delegation",ISNUMBER(SEARCH("; Delegation; ","; "&F45&"; "))),1,0) -> 0 | R45: =IF(OR(E45="Directed delegation",ISNUMBER(SEARCH("; Directed delegation; ","; "&F45&"; "))),1,0) -> 0 | S45: =IF(OR(E45="Evaluation",ISNUMBER(SEARCH("; Evaluation; ","; "&F45&"; "))),1,0) -> 0 | T45: =IF(OR(E45="Correction/Challenge",ISNUMBER(SEARCH("; Correction/Challenge; ","; "&F45&"; "))),1,0) -> 1 | U45: =IF(OR(E45="Redirection",ISNUMBER(SEARCH("; Redirection; ","; "&F45&"; "))),1,0) -> 0 | V45: =IF(OR(E45="Knowledge injection",ISNUMBER(SEARCH("; Knowledge injection; ","; "&F45&"; "))),1,0) -> 1 | W45: =IF(OR(E45="Selection/Rejection",ISNUMBER(SEARCH("; Selection/Rejection; ","; "&F45&"; "))),1,0) -> 0 | X45: =IF(OR(E45="Deliberation",ISNUMBER(SEARCH("; Deliberation; ","; "&F45&"; "))),1,0) -> 0 | Y45: =SUM(Z45:AE45) -> 1 | Z45: =IF(ISNUMBER(SEARCH("; domain correction; ","; "&H45&"; ")),1,0) -> 0 | AA45: =IF(ISNUMBER(SEARCH("; conceptual discrimination; ","; "&H45&"; ")),1,0) -> 0 | AB45: =IF(ISNUMBER(SEARCH("; evidence judgment; ","; "&H45&"; ")),1,0) -> 1 | AC45: =IF(ISNUMBER(SEARCH("; methodological judgment; ","; "&H45&"; ")),1,0) -> 0 | AD45: =IF(ISNUMBER(SEARCH("; argumentative judgment; ","; "&H45&"; ")),1,0) -> 0 | AE45: =IF(ISNUMBER(SEARCH("; genre/writing expertise; ","; "&H45&"; ")),1,0) -> 0 | AF45: =IF(ISNUMBER(SEARCH("; none; ","; "&H45&"; ")),1,0) -> 0
A46: HE-045 | B46: 45 | C46: Structure and research design | D46: regen 3.1 | E46: Directed delegation | G46: Directive | H46: none | I46: Requests regeneration of a named subsection without new substantive specification. | J46: AI rewrites Section 3.1. | K46: DOCX body elements 2777–2777 | L46: DOCX body elements 2780–2819 | N46: Visible next AI response | O46: Converted DOCX: textbox continuations joined; AI completion/source-check claims are unverified. | P46: =SUM(Q46:X46) -> 1 | Q46: =IF(OR(E46="Delegation",ISNUMBER(SEARCH("; Delegation; ","; "&F46&"; "))),1,0) -> 0 | R46: =IF(OR(E46="Directed delegation",ISNUMBER(SEARCH("; Directed delegation; ","; "&F46&"; "))),1,0) -> 1 | S46: =IF(OR(E46="Evaluation",ISNUMBER(SEARCH("; Evaluation; ","; "&F46&"; "))),1,0) -> 0 | T46: =IF(OR(E46="Correction/Challenge",ISNUMBER(SEARCH("; Correction/Challenge; ","; "&F46&"; "))),1,0) -> 0 | U46: =IF(OR(E46="Redirection",ISNUMBER(SEARCH("; Redirection; ","; "&F46&"; "))),1,0) -> 0 | V46: =IF(OR(E46="Knowledge injection",ISNUMBER(SEARCH("; Knowledge injection; ","; "&F46&"; "))),1,0) -> 0 | W46: =IF(OR(E46="Selection/Rejection",ISNUMBER(SEARCH("; Selection/Rejection; ","; "&F46&"; "))),1,0) -> 0 | X46: =IF(OR(E46="Deliberation",ISNUMBER(SEARCH("; Deliberation; ","; "&F46&"; "))),1,0) -> 0 | Y46: =SUM(Z46:AE46) -> 0 | Z46: =IF(ISNUMBER(SEARCH("; domain correction; ","; "&H46&"; ")),1,0) -> 0 | AA46: =IF(ISNUMBER(SEARCH("; conceptual discrimination; ","; "&H46&"; ")),1,0) -> 0 | AB46: =IF(ISNUMBER(SEARCH("; evidence judgment; ","; "&H46&"; ")),1,0) -> 0 | AC46: =IF(ISNUMBER(SEARCH("; methodological judgment; ","; "&H46&"; ")),1,0) -> 0 | AD46: =IF(ISNUMBER(SEARCH("; argumentative judgment; ","; "&H46&"; ")),1,0) -> 0 | AE46: =IF(ISNUMBER(SEARCH("; genre/writing expertise; ","; "&H46&"; ")),1,0) -> 0 | AF46: =IF(ISNUMBER(SEARCH("; none; ","; "&H46&"; ")),1,0) -> 1
A47: HE-046 | B47: 46 | C47: Diagnosis, model and reforms | D47: using my hints below (if any), give text of: 4 DİAQNOSTİK ANALİZ VƏ ÇATIŞMAZLIQLARIN MÜƏYYƏNLƏŞDİRİLMƏSİ Opening parag... vhat ve vill cover in sec 4 4.1 PISA Nəticələri: Ümumi Təhsil Təməlinin Zəifliyindən Ali Təhsilə Ötürülmə (OECD, 2023) • PİSA is OECD’nin tanınmış Beynəlxalq Tələbə Qiymətləndirmə Proqramının (İngiliscə: Program for International Student Assessment • global evaluation of 15-year-olds' math, readin… | E47: Directed delegation | F47: Knowledge injection | G47: Directive | H47: evidence judgment; argumentative judgment; genre/writing expertise | I47: Supplies PISA-based diagnostic content and specifies interpretation and drafting constraints. | J47: AI drafts the diagnosis and comparison. | K47: DOCX body elements 2822–2825 | L47: DOCX body elements 2828–2864 | M47: Extended draft/quoted context; researcher-origin judgment distinguished in rationale | N47: Visible next AI response | O47: Converted DOCX: textbox continuations joined; AI completion/source-check claims are unverified. | P47: =SUM(Q47:X47) -> 2 | Q47: =IF(OR(E47="Delegation",ISNUMBER(SEARCH("; Delegation; ","; "&F47&"; "))),1,0) -> 0 | R47: =IF(OR(E47="Directed delegation",ISNUMBER(SEARCH("; Directed delegation; ","; "&F47&"; "))),1,0) -> 1 | S47: =IF(OR(E47="Evaluation",ISNUMBER(SEARCH("; Evaluation; ","; "&F47&"; "))),1,0) -> 0 | T47: =IF(OR(E47="Correction/Challenge",ISNUMBER(SEARCH("; Correction/Challenge; ","; "&F47&"; "))),1,0) -> 0 | U47: =IF(OR(E47="Redirection",ISNUMBER(SEARCH("; Redirection; ","; "&F47&"; "))),1,0) -> 0 | V47: =IF(OR(E47="Knowledge injection",ISNUMBER(SEARCH("; Knowledge injection; ","; "&F47&"; "))),1,0) -> 1 | W47: =IF(OR(E47="Selection/Rejection",ISNUMBER(SEARCH("; Selection/Rejection; ","; "&F47&"; "))),1,0) -> 0 | X47: =IF(OR(E47="Deliberation",ISNUMBER(SEARCH("; Deliberation; ","; "&F47&"; "))),1,0) -> 0 | Y47: =SUM(Z47:AE47) -> 3 | Z47: =IF(ISNUMBER(SEARCH("; domain correction; ","; "&H47&"; ")),1,0) -> 0 | AA47: =IF(ISNUMBER(SEARCH("; conceptual discrimination; ","; "&H47&"; ")),1,0) -> 0 | AB47: =IF(ISNUMBER(SEARCH("; evidence judgment; ","; "&H47&"; ")),1,0) -> 1 | AC47: =IF(ISNUMBER(SEARCH("; methodological judgment; ","; "&H47&"; ")),1,0) -> 0 | AD47: =IF(ISNUMBER(SEARCH("; argumentative judgment; ","; "&H47&"; ")),1,0) -> 1 | AE47: =IF(ISNUMBER(SEARCH("; genre/writing expertise; ","; "&H47&"; ")),1,0) -> 1 | AF47: =IF(ISNUMBER(SEARCH("; none; ","; "&H47&"; ")),1,0) -> 0
A48: HE-047 | B48: 47 | C48: Diagnosis, model and reforms | D48: what are TIMSS və PIRLS? | E48: Evaluation | G48: Evaluative | H48: none | I48: Requests definitions of TIMSS and PIRLS without displaying a judgment. | J48: AI explains the assessments. | K48: DOCX body elements 2865–2865 | L48: DOCX body elements 2868–2891 | N48: Visible next AI response | O48: Converted DOCX: textbox continuations joined; AI completion/source-check claims are unverified. | P48: =SUM(Q48:X48) -> 1 | Q48: =IF(OR(E48="Delegation",ISNUMBER(SEARCH("; Delegation; ","; "&F48&"; "))),1,0) -> 0 | R48: =IF(OR(E48="Directed delegation",ISNUMBER(SEARCH("; Directed delegation; ","; "&F48&"; "))),1,0) -> 0 | S48: =IF(OR(E48="Evaluation",ISNUMBER(SEARCH("; Evaluation; ","; "&F48&"; "))),1,0) -> 1 | T48: =IF(OR(E48="Correction/Challenge",ISNUMBER(SEARCH("; Correction/Challenge; ","; "&F48&"; "))),1,0) -> 0 | U48: =IF(OR(E48="Redirection",ISNUMBER(SEARCH("; Redirection; ","; "&F48&"; "))),1,0) -> 0 | V48: =IF(OR(E48="Knowledge injection",ISNUMBER(SEARCH("; Knowledge injection; ","; "&F48&"; "))),1,0) -> 0 | W48: =IF(OR(E48="Selection/Rejection",ISNUMBER(SEARCH("; Selection/Rejection; ","; "&F48&"; "))),1,0) -> 0 | X48: =IF(OR(E48="Deliberation",ISNUMBER(SEARCH("; Deliberation; ","; "&F48&"; "))),1,0) -> 0 | Y48: =SUM(Z48:AE48) -> 0 | Z48: =IF(ISNUMBER(SEARCH("; domain correction; ","; "&H48&"; ")),1,0) -> 0 | AA48: =IF(ISNUMBER(SEARCH("; conceptual discrimination; ","; "&H48&"; ")),1,0) -> 0 | AB48: =IF(ISNUMBER(SEARCH("; evidence judgment; ","; "&H48&"; ")),1,0) -> 0 | AC48: =IF(ISNUMBER(SEARCH("; methodological judgment; ","; "&H48&"; ")),1,0) -> 0 | AD48: =IF(ISNUMBER(SEARCH("; argumentative judgment; ","; "&H48&"; ")),1,0) -> 0 | AE48: =IF(ISNUMBER(SEARCH("; genre/writing expertise; ","; "&H48&"; ")),1,0) -> 0 | AF48: =IF(ISNUMBER(SEARCH("; none; ","; "&H48&"; ")),1,0) -> 1
A49: HE-048 | B49: 48 | C49: Diagnosis, model and reforms | D49: find PISA 2012 Results of azerbaijan | E49: Directed delegation | G49: Directive | H49: evidence judgment | I49: Requests retrieval of a specific assessment-year result. | J49: AI discusses PISA 2012 participation/results; retrieval claim is unverified. | K49: DOCX body elements 2892–2892 | L49: DOCX body elements 2897–2919 | N49: Visible next AI response | O49: Converted DOCX: textbox continuations joined; AI completion/source-check claims are unverified. | P49: =SUM(Q49:X49) -> 1 | Q49: =IF(OR(E49="Delegation",ISNUMBER(SEARCH("; Delegation; ","; "&F49&"; "))),1,0) -> 0 | R49: =IF(OR(E49="Directed delegation",ISNUMBER(SEARCH("; Directed delegation; ","; "&F49&"; "))),1,0) -> 1 | S49: =IF(OR(E49="Evaluation",ISNUMBER(SEARCH("; Evaluation; ","; "&F49&"; "))),1,0) -> 0 | T49: =IF(OR(E49="Correction/Challenge",ISNUMBER(SEARCH("; Correction/Challenge; ","; "&F49&"; "))),1,0) -> 0 | U49: =IF(OR(E49="Redirection",ISNUMBER(SEARCH("; Redirection; ","; "&F49&"; "))),1,0) -> 0 | V49: =IF(OR(E49="Knowledge injection",ISNUMBER(SEARCH("; Knowledge injection; ","; "&F49&"; "))),1,0) -> 0 | W49: =IF(OR(E49="Selection/Rejection",ISNUMBER(SEARCH("; Selection/Rejection; ","; "&F49&"; "))),1,0) -> 0 | X49: =IF(OR(E49="Deliberation",ISNUMBER(SEARCH("; Deliberation; ","; "&F49&"; "))),1,0) -> 0 | Y49: =SUM(Z49:AE49) -> 1 | Z49: =IF(ISNUMBER(SEARCH("; domain correction; ","; "&H49&"; ")),1,0) -> 0 | AA49: =IF(ISNUMBER(SEARCH("; conceptual discrimination; ","; "&H49&"; ")),1,0) -> 0 | AB49: =IF(ISNUMBER(SEARCH("; evidence judgment; ","; "&H49&"; ")),1,0) -> 1 | AC49: =IF(ISNUMBER(SEARCH("; methodological judgment; ","; "&H49&"; ")),1,0) -> 0 | AD49: =IF(ISNUMBER(SEARCH("; argumentative judgment; ","; "&H49&"; ")),1,0) -> 0 | AE49: =IF(ISNUMBER(SEARCH("; genre/writing expertise; ","; "&H49&"; ")),1,0) -> 0 | AF49: =IF(ISNUMBER(SEARCH("; none; ","; "&H49&"; ")),1,0) -> 0
A50: HE-049 | B50: 49 | C50: Diagnosis, model and reforms | D50: find PISA 2015 Results of azerbaijan | E50: Directed delegation | G50: Directive | H50: evidence judgment | I50: Requests retrieval of another assessment-year result. | J50: AI discusses PISA 2015 participation/results; retrieval claim is unverified. | K50: DOCX body elements 2920–2920 | L50: DOCX body elements 2925–2944 | N50: Visible next AI response | O50: Converted DOCX: textbox continuations joined; AI completion/source-check claims are unverified. | P50: =SUM(Q50:X50) -> 1 | Q50: =IF(OR(E50="Delegation",ISNUMBER(SEARCH("; Delegation; ","; "&F50&"; "))),1,0) -> 0 | R50: =IF(OR(E50="Directed delegation",ISNUMBER(SEARCH("; Directed delegation; ","; "&F50&"; "))),1,0) -> 1 | S50: =IF(OR(E50="Evaluation",ISNUMBER(SEARCH("; Evaluation; ","; "&F50&"; "))),1,0) -> 0 | T50: =IF(OR(E50="Correction/Challenge",ISNUMBER(SEARCH("; Correction/Challenge; ","; "&F50&"; "))),1,0) -> 0 | U50: =IF(OR(E50="Redirection",ISNUMBER(SEARCH("; Redirection; ","; "&F50&"; "))),1,0) -> 0 | V50: =IF(OR(E50="Knowledge injection",ISNUMBER(SEARCH("; Knowledge injection; ","; "&F50&"; "))),1,0) -> 0 | W50: =IF(OR(E50="Selection/Rejection",ISNUMBER(SEARCH("; Selection/Rejection; ","; "&F50&"; "))),1,0) -> 0 | X50: =IF(OR(E50="Deliberation",ISNUMBER(SEARCH("; Deliberation; ","; "&F50&"; "))),1,0) -> 0 | Y50: =SUM(Z50:AE50) -> 1 | Z50: =IF(ISNUMBER(SEARCH("; domain correction; ","; "&H50&"; ")),1,0) -> 0 | AA50: =IF(ISNUMBER(SEARCH("; conceptual discrimination; ","; "&H50&"; ")),1,0) -> 0 | AB50: =IF(ISNUMBER(SEARCH("; evidence judgment; ","; "&H50&"; ")),1,0) -> 1 | AC50: =IF(ISNUMBER(SEARCH("; methodological judgment; ","; "&H50&"; ")),1,0) -> 0 | AD50: =IF(ISNUMBER(SEARCH("; argumentative judgment; ","; "&H50&"; ")),1,0) -> 0 | AE50: =IF(ISNUMBER(SEARCH("; genre/writing expertise; ","; "&H50&"; ")),1,0) -> 0 | AF50: =IF(ISNUMBER(SEARCH("; none; ","; "&H50&"; ")),1,0) -> 0
A51: HE-050 | B51: 50 | C51: Diagnosis, model and reforms | D51: regen text of 4.1 with this update: • Azərbaycan first entered the assessment in 2009, 65 ölkə arasında sondan ikinci yerdə qərarlaşdı -Azərbaycan 2012 ve 2015-ci il PISA-da İştirak Etmədi | E51: Correction/Challenge | F51: Knowledge injection; Directed delegation | G51: Critical | H51: evidence judgment; domain correction | I51: Corrects participation chronology using the reported 2009 entry and absence in 2012/2015. | J51: AI revises Section 4.1. | K51: DOCX body elements 2945–2945 | L51: DOCX body elements 2948–2973 | N51: Visible next AI response | O51: Converted DOCX: textbox continuations joined; AI completion/source-check claims are unverified. | P51: =SUM(Q51:X51) -> 3 | Q51: =IF(OR(E51="Delegation",ISNUMBER(SEARCH("; Delegation; ","; "&F51&"; "))),1,0) -> 0 | R51: =IF(OR(E51="Directed delegation",ISNUMBER(SEARCH("; Directed delegation; ","; "&F51&"; "))),1,0) -> 1 | S51: =IF(OR(E51="Evaluation",ISNUMBER(SEARCH("; Evaluation; ","; "&F51&"; "))),1,0) -> 0 | T51: =IF(OR(E51="Correction/Challenge",ISNUMBER(SEARCH("; Correction/Challenge; ","; "&F51&"; "))),1,0) -> 1 | U51: =IF(OR(E51="Redirection",ISNUMBER(SEARCH("; Redirection; ","; "&F51&"; "))),1,0) -> 0 | V51: =IF(OR(E51="Knowledge injection",ISNUMBER(SEARCH("; Knowledge injection; ","; "&F51&"; "))),1,0) -> 1 | W51: =IF(OR(E51="Selection/Rejection",ISNUMBER(SEARCH("; Selection/Rejection; ","; "&F51&"; "))),1,0) -> 0 | X51: =IF(OR(E51="Deliberation",ISNUMBER(SEARCH("; Deliberation; ","; "&F51&"; "))),1,0) -> 0 | Y51: =SUM(Z51:AE51) -> 2 | Z51: =IF(ISNUMBER(SEARCH("; domain correction; ","; "&H51&"; ")),1,0) -> 1 | AA51: =IF(ISNUMBER(SEARCH("; conceptual discrimination; ","; "&H51&"; ")),1,0) -> 0 | AB51: =IF(ISNUMBER(SEARCH("; evidence judgment; ","; "&H51&"; ")),1,0) -> 1 | AC51: =IF(ISNUMBER(SEARCH("; methodological judgment; ","; "&H51&"; ")),1,0) -> 0 | AD51: =IF(ISNUMBER(SEARCH("; argumentative judgment; ","; "&H51&"; ")),1,0) -> 0 | AE51: =IF(ISNUMBER(SEARCH("; genre/writing expertise; ","; "&H51&"; ")),1,0) -> 0 | AF51: =IF(ISNUMBER(SEARCH("; none; ","; "&H51&"; ")),1,0) -> 0
A52: HE-051 | B52: 51 | C52: Diagnosis, model and reforms | D52: see the attached paper file in progressit 2838 vords already/ using my hints below (if any), give text of: 4.2 Dünya Bankının Dəstəklədiyi Azərbaycanın Təhsil İnkişafı Layihəsi (2008-2016) Nəticələr, Dərslər və Ali Təhsilə Aidiyyəti • Layihənin məqsədi: Ümumi Təhsildə, tədris keyfiyyətinin artırılması, akademik heyətin hazırlığı, kurikulum islahatı • Əsas nəticələr: o 145,000-dən çox müəllimin təhsil xidmətinə cəlb e… | E52: Directed delegation | F52: Knowledge injection | G52: Directive | H52: evidence judgment; argumentative judgment; genre/writing expertise | I52: Supplies World Bank findings and directs their diagnostic interpretation. | J52: AI drafts a report-based diagnostic subsection. | K52: DOCX body elements 2978–2980 | L52: DOCX body elements 2986–3008 | M52: File/context references in prompt; inspect full text; Extended draft/quoted context; researcher-origin judgment distinguished in rationale | N52: Visible next AI response | O52: Converted DOCX: textbox continuations joined; AI completion/source-check claims are unverified. | P52: =SUM(Q52:X52) -> 2 | Q52: =IF(OR(E52="Delegation",ISNUMBER(SEARCH("; Delegation; ","; "&F52&"; "))),1,0) -> 0 | R52: =IF(OR(E52="Directed delegation",ISNUMBER(SEARCH("; Directed delegation; ","; "&F52&"; "))),1,0) -> 1 | S52: =IF(OR(E52="Evaluation",ISNUMBER(SEARCH("; Evaluation; ","; "&F52&"; "))),1,0) -> 0 | T52: =IF(OR(E52="Correction/Challenge",ISNUMBER(SEARCH("; Correction/Challenge; ","; "&F52&"; "))),1,0) -> 0 | U52: =IF(OR(E52="Redirection",ISNUMBER(SEARCH("; Redirection; ","; "&F52&"; "))),1,0) -> 0 | V52: =IF(OR(E52="Knowledge injection",ISNUMBER(SEARCH("; Knowledge injection; ","; "&F52&"; "))),1,0) -> 1 | W52: =IF(OR(E52="Selection/Rejection",ISNUMBER(SEARCH("; Selection/Rejection; ","; "&F52&"; "))),1,0) -> 0 | X52: =IF(OR(E52="Deliberation",ISNUMBER(SEARCH("; Deliberation; ","; "&F52&"; "))),1,0) -> 0 | Y52: =SUM(Z52:AE52) -> 3 | Z52: =IF(ISNUMBER(SEARCH("; domain correction; ","; "&H52&"; ")),1,0) -> 0 | AA52: =IF(ISNUMBER(SEARCH("; conceptual discrimination; ","; "&H52&"; ")),1,0) -> 0 | AB52: =IF(ISNUMBER(SEARCH("; evidence judgment; ","; "&H52&"; ")),1,0) -> 1 | AC52: =IF(ISNUMBER(SEARCH("; methodological judgment; ","; "&H52&"; ")),1,0) -> 0 | AD52: =IF(ISNUMBER(SEARCH("; argumentative judgment; ","; "&H52&"; ")),1,0) -> 1 | AE52: =IF(ISNUMBER(SEARCH("; genre/writing expertise; ","; "&H52&"; ")),1,0) -> 1 | AF52: =IF(ISNUMBER(SEARCH("; none; ","; "&H52&"; ")),1,0) -> 0
A53: HE-052 | B53: 52 | C53: Diagnosis, model and reforms | D53: xidmətdaxili təhsilə? | E53: Evaluation | G53: Evaluative | H53: genre/writing expertise | I53: Questions the suitability of an Azerbaijani training term. | J53: AI explains or replaces the term. | K53: DOCX body elements 3009–3009 | L53: DOCX body elements 3012–3025 | N53: Visible next AI response | O53: Converted DOCX: textbox continuations joined; AI completion/source-check claims are unverified. | P53: =SUM(Q53:X53) -> 1 | Q53: =IF(OR(E53="Delegation",ISNUMBER(SEARCH("; Delegation; ","; "&F53&"; "))),1,0) -> 0 | R53: =IF(OR(E53="Directed delegation",ISNUMBER(SEARCH("; Directed delegation; ","; "&F53&"; "))),1,0) -> 0 | S53: =IF(OR(E53="Evaluation",ISNUMBER(SEARCH("; Evaluation; ","; "&F53&"; "))),1,0) -> 1 | T53: =IF(OR(E53="Correction/Challenge",ISNUMBER(SEARCH("; Correction/Challenge; ","; "&F53&"; "))),1,0) -> 0 | U53: =IF(OR(E53="Redirection",ISNUMBER(SEARCH("; Redirection; ","; "&F53&"; "))),1,0) -> 0 | V53: =IF(OR(E53="Knowledge injection",ISNUMBER(SEARCH("; Knowledge injection; ","; "&F53&"; "))),1,0) -> 0 | W53: =IF(OR(E53="Selection/Rejection",ISNUMBER(SEARCH("; Selection/Rejection; ","; "&F53&"; "))),1,0) -> 0 | X53: =IF(OR(E53="Deliberation",ISNUMBER(SEARCH("; Deliberation; ","; "&F53&"; "))),1,0) -> 0 | Y53: =SUM(Z53:AE53) -> 1 | Z53: =IF(ISNUMBER(SEARCH("; domain correction; ","; "&H53&"; ")),1,0) -> 0 | AA53: =IF(ISNUMBER(SEARCH("; conceptual discrimination; ","; "&H53&"; ")),1,0) -> 0 | AB53: =IF(ISNUMBER(SEARCH("; evidence judgment; ","; "&H53&"; ")),1,0) -> 0 | AC53: =IF(ISNUMBER(SEARCH("; methodological judgment; ","; "&H53&"; ")),1,0) -> 0 | AD53: =IF(ISNUMBER(SEARCH("; argumentative judgment; ","; "&H53&"; ")),1,0) -> 0 | AE53: =IF(ISNUMBER(SEARCH("; genre/writing expertise; ","; "&H53&"; ")),1,0) -> 1 | AF53: =IF(ISNUMBER(SEARCH("; none; ","; "&H53&"; ")),1,0) -> 0
A54: HE-053 | B54: 53 | C54: Diagnosis, model and reforms | D54: using my hints below (if any), give text of: 4.3 Onlayn Anket Sorğudan Gələn Tələbələrin Rəyləri Say why we did the Anket Sorğu// to further augment our analysis and inform bjulding the model in sec 5 53 cavabdeh (hazırda ali təhsil və ya texniki peşə təhsili alan, yaxud bu təhsili bitirmiş gənclər) -Notes: --Do not use the Harari style of writing. use standard academic writing. --give text in chat area, not Word fil… | E54: Directed delegation | F54: Knowledge injection | G54: Directive | H54: methodological judgment; evidence judgment; argumentative judgment; genre/writing expertise | I54: Supplies the 53-student survey findings and directs analysis and quotation use. | J54: AI drafts the survey findings and interpretation. | K54: DOCX body elements 3027–3030 | L54: DOCX body elements 3034–3057 | M54: Extended draft/quoted context; researcher-origin judgment distinguished in rationale | N54: Visible next AI response | O54: Converted DOCX: textbox continuations joined; AI completion/source-check claims are unverified. | P54: =SUM(Q54:X54) -> 2 | Q54: =IF(OR(E54="Delegation",ISNUMBER(SEARCH("; Delegation; ","; "&F54&"; "))),1,0) -> 0 | R54: =IF(OR(E54="Directed delegation",ISNUMBER(SEARCH("; Directed delegation; ","; "&F54&"; "))),1,0) -> 1 | S54: =IF(OR(E54="Evaluation",ISNUMBER(SEARCH("; Evaluation; ","; "&F54&"; "))),1,0) -> 0 | T54: =IF(OR(E54="Correction/Challenge",ISNUMBER(SEARCH("; Correction/Challenge; ","; "&F54&"; "))),1,0) -> 0 | U54: =IF(OR(E54="Redirection",ISNUMBER(SEARCH("; Redirection; ","; "&F54&"; "))),1,0) -> 0 | V54: =IF(OR(E54="Knowledge injection",ISNUMBER(SEARCH("; Knowledge injection; ","; "&F54&"; "))),1,0) -> 1 | W54: =IF(OR(E54="Selection/Rejection",ISNUMBER(SEARCH("; Selection/Rejection; ","; "&F54&"; "))),1,0) -> 0 | X54: =IF(OR(E54="Deliberation",ISNUMBER(SEARCH("; Deliberation; ","; "&F54&"; "))),1,0) -> 0 | Y54: =SUM(Z54:AE54) -> 4 | Z54: =IF(ISNUMBER(SEARCH("; domain correction; ","; "&H54&"; ")),1,0) -> 0 | AA54: =IF(ISNUMBER(SEARCH("; conceptual discrimination; ","; "&H54&"; ")),1,0) -> 0 | AB54: =IF(ISNUMBER(SEARCH("; evidence judgment; ","; "&H54&"; ")),1,0) -> 1 | AC54: =IF(ISNUMBER(SEARCH("; methodological judgment; ","; "&H54&"; ")),1,0) -> 1 | AD54: =IF(ISNUMBER(SEARCH("; argumentative judgment; ","; "&H54&"; ")),1,0) -> 1 | AE54: =IF(ISNUMBER(SEARCH("; genre/writing expertise; ","; "&H54&"; ")),1,0) -> 1 | AF54: =IF(ISNUMBER(SEARCH("; none; ","; "&H54&"; ")),1,0) -> 0
A55: HE-054 | B55: 54 | C55: Diagnosis, model and reforms | D55: DO WE really need this subsec: 4.4 Ümumi Təhsildə Hazırlığın Tələbələrin Ali Təhsildəki Performanslarına Təsirləri? that issue has been discuss a a few times? | E55: Correction/Challenge | F55: Redirection | G55: Critical | H55: argumentative judgment; genre/writing expertise | I55: Identifies redundancy with the earlier general-preparation discussion. | J55: AI recommends reducing or reorganizing the subsection. | K55: DOCX body elements 3058–3058 | L55: DOCX body elements 3061–3084 | N55: Visible next AI response | O55: Converted DOCX: textbox continuations joined; AI completion/source-check claims are unverified. | P55: =SUM(Q55:X55) -> 2 | Q55: =IF(OR(E55="Delegation",ISNUMBER(SEARCH("; Delegation; ","; "&F55&"; "))),1,0) -> 0 | R55: =IF(OR(E55="Directed delegation",ISNUMBER(SEARCH("; Directed delegation; ","; "&F55&"; "))),1,0) -> 0 | S55: =IF(OR(E55="Evaluation",ISNUMBER(SEARCH("; Evaluation; ","; "&F55&"; "))),1,0) -> 0 | T55: =IF(OR(E55="Correction/Challenge",ISNUMBER(SEARCH("; Correction/Challenge; ","; "&F55&"; "))),1,0) -> 1 | U55: =IF(OR(E55="Redirection",ISNUMBER(SEARCH("; Redirection; ","; "&F55&"; "))),1,0) -> 1 | V55: =IF(OR(E55="Knowledge injection",ISNUMBER(SEARCH("; Knowledge injection; ","; "&F55&"; "))),1,0) -> 0 | W55: =IF(OR(E55="Selection/Rejection",ISNUMBER(SEARCH("; Selection/Rejection; ","; "&F55&"; "))),1,0) -> 0 | X55: =IF(OR(E55="Deliberation",ISNUMBER(SEARCH("; Deliberation; ","; "&F55&"; "))),1,0) -> 0 | Y55: =SUM(Z55:AE55) -> 2 | Z55: =IF(ISNUMBER(SEARCH("; domain correction; ","; "&H55&"; ")),1,0) -> 0 | AA55: =IF(ISNUMBER(SEARCH("; conceptual discrimination; ","; "&H55&"; ")),1,0) -> 0 | AB55: =IF(ISNUMBER(SEARCH("; evidence judgment; ","; "&H55&"; ")),1,0) -> 0 | AC55: =IF(ISNUMBER(SEARCH("; methodological judgment; ","; "&H55&"; ")),1,0) -> 0 | AD55: =IF(ISNUMBER(SEARCH("; argumentative judgment; ","; "&H55&"; ")),1,0) -> 1 | AE55: =IF(ISNUMBER(SEARCH("; genre/writing expertise; ","; "&H55&"; ")),1,0) -> 1 | AF55: =IF(ISNUMBER(SEARCH("; none; ","; "&H55&"; ")),1,0) -> 0
A56: HE-055 | B56: 55 | C56: Diagnosis, model and reforms | D56: using my hints below (if any), give text of: 4.4 Mövcud Səylər: TKTA, TİF, və Ali Təhsildə Beynəlxalq Akkreditasiyalar Fəaliyyətləri – include in heading: teqdire layiq, but we need to do more Educatin QA has recieved more awareness in AZ in recent years teqdire layiq, but we need to do more Establishment of Təhsildə Keyfiyyət Təminatı Agentliyi (TKTA) in 2019 under the MOSE embassy https://tkta.edu.az/ ... they do P… | E56: Directed delegation | F56: Knowledge injection | G56: Directive | H56: evidence judgment; argumentative judgment; genre/writing expertise | I56: Supplies quality-assurance initiatives and requires a balanced interpretation. | J56: AI drafts the initiatives subsection with supporting references. | K56: DOCX body elements 3086–3095 | L56: DOCX body elements 3099–3126 | M56: URL(s) supplied in prompt; Extended draft/quoted context; researcher-origin judgment distinguished in rationale | N56: Visible next AI response | O56: Converted DOCX: textbox continuations joined; AI completion/source-check claims are unverified. | P56: =SUM(Q56:X56) -> 2 | Q56: =IF(OR(E56="Delegation",ISNUMBER(SEARCH("; Delegation; ","; "&F56&"; "))),1,0) -> 0 | R56: =IF(OR(E56="Directed delegation",ISNUMBER(SEARCH("; Directed delegation; ","; "&F56&"; "))),1,0) -> 1 | S56: =IF(OR(E56="Evaluation",ISNUMBER(SEARCH("; Evaluation; ","; "&F56&"; "))),1,0) -> 0 | T56: =IF(OR(E56="Correction/Challenge",ISNUMBER(SEARCH("; Correction/Challenge; ","; "&F56&"; "))),1,0) -> 0 | U56: =IF(OR(E56="Redirection",ISNUMBER(SEARCH("; Redirection; ","; "&F56&"; "))),1,0) -> 0 | V56: =IF(OR(E56="Knowledge injection",ISNUMBER(SEARCH("; Knowledge injection; ","; "&F56&"; "))),1,0) -> 1 | W56: =IF(OR(E56="Selection/Rejection",ISNUMBER(SEARCH("; Selection/Rejection; ","; "&F56&"; "))),1,0) -> 0 | X56: =IF(OR(E56="Deliberation",ISNUMBER(SEARCH("; Deliberation; ","; "&F56&"; "))),1,0) -> 0 | Y56: =SUM(Z56:AE56) -> 3 | Z56: =IF(ISNUMBER(SEARCH("; domain correction; ","; "&H56&"; ")),1,0) -> 0 | AA56: =IF(ISNUMBER(SEARCH("; conceptual discrimination; ","; "&H56&"; ")),1,0) -> 0 | AB56: =IF(ISNUMBER(SEARCH("; evidence judgment; ","; "&H56&"; ")),1,0) -> 1 | AC56: =IF(ISNUMBER(SEARCH("; methodological judgment; ","; "&H56&"; ")),1,0) -> 0 | AD56: =IF(ISNUMBER(SEARCH("; argumentative judgment; ","; "&H56&"; ")),1,0) -> 1 | AE56: =IF(ISNUMBER(SEARCH("; genre/writing expertise; ","; "&H56&"; ")),1,0) -> 1 | AF56: =IF(ISNUMBER(SEARCH("; none; ","; "&H56&"; ")),1,0) -> 0
A57: HE-056 | B57: 56 | C57: Diagnosis, model and reforms | D57: yetkinləşməmiş? | E57: Evaluation | G57: Evaluative | H57: genre/writing expertise | I57: Questions an Azerbaijani word’s appropriateness. | J57: AI explains and proposes alternatives. | K57: DOCX body elements 3127–3127 | L57: DOCX body elements 3130–3151 | N57: Visible next AI response | O57: Converted DOCX: textbox continuations joined; AI completion/source-check claims are unverified. | P57: =SUM(Q57:X57) -> 1 | Q57: =IF(OR(E57="Delegation",ISNUMBER(SEARCH("; Delegation; ","; "&F57&"; "))),1,0) -> 0 | R57: =IF(OR(E57="Directed delegation",ISNUMBER(SEARCH("; Directed delegation; ","; "&F57&"; "))),1,0) -> 0 | S57: =IF(OR(E57="Evaluation",ISNUMBER(SEARCH("; Evaluation; ","; "&F57&"; "))),1,0) -> 1 | T57: =IF(OR(E57="Correction/Challenge",ISNUMBER(SEARCH("; Correction/Challenge; ","; "&F57&"; "))),1,0) -> 0 | U57: =IF(OR(E57="Redirection",ISNUMBER(SEARCH("; Redirection; ","; "&F57&"; "))),1,0) -> 0 | V57: =IF(OR(E57="Knowledge injection",ISNUMBER(SEARCH("; Knowledge injection; ","; "&F57&"; "))),1,0) -> 0 | W57: =IF(OR(E57="Selection/Rejection",ISNUMBER(SEARCH("; Selection/Rejection; ","; "&F57&"; "))),1,0) -> 0 | X57: =IF(OR(E57="Deliberation",ISNUMBER(SEARCH("; Deliberation; ","; "&F57&"; "))),1,0) -> 0 | Y57: =SUM(Z57:AE57) -> 1 | Z57: =IF(ISNUMBER(SEARCH("; domain correction; ","; "&H57&"; ")),1,0) -> 0 | AA57: =IF(ISNUMBER(SEARCH("; conceptual discrimination; ","; "&H57&"; ")),1,0) -> 0 | AB57: =IF(ISNUMBER(SEARCH("; evidence judgment; ","; "&H57&"; ")),1,0) -> 0 | AC57: =IF(ISNUMBER(SEARCH("; methodological judgment; ","; "&H57&"; ")),1,0) -> 0 | AD57: =IF(ISNUMBER(SEARCH("; argumentative judgment; ","; "&H57&"; ")),1,0) -> 0 | AE57: =IF(ISNUMBER(SEARCH("; genre/writing expertise; ","; "&H57&"; ")),1,0) -> 1 | AF57: =IF(ISNUMBER(SEARCH("; none; ","; "&H57&"; ")),1,0) -> 0
A58: HE-057 | B58: 57 | C58: Diagnosis, model and reforms | D58: Now let's move to section five. Is this the best structure that we can have for that section? | E58: Evaluation | G58: Evaluative | H58: genre/writing expertise | I58: Requests assessment of the Section 5 structure. | J58: AI evaluates and refines the structure. | K58: DOCX body elements 3154–3154 | L58: DOCX body elements 3158–3197 | N58: Visible next AI response | O58: Converted DOCX: textbox continuations joined; AI completion/source-check claims are unverified. | P58: =SUM(Q58:X58) -> 1 | Q58: =IF(OR(E58="Delegation",ISNUMBER(SEARCH("; Delegation; ","; "&F58&"; "))),1,0) -> 0 | R58: =IF(OR(E58="Directed delegation",ISNUMBER(SEARCH("; Directed delegation; ","; "&F58&"; "))),1,0) -> 0 | S58: =IF(OR(E58="Evaluation",ISNUMBER(SEARCH("; Evaluation; ","; "&F58&"; "))),1,0) -> 1 | T58: =IF(OR(E58="Correction/Challenge",ISNUMBER(SEARCH("; Correction/Challenge; ","; "&F58&"; "))),1,0) -> 0 | U58: =IF(OR(E58="Redirection",ISNUMBER(SEARCH("; Redirection; ","; "&F58&"; "))),1,0) -> 0 | V58: =IF(OR(E58="Knowledge injection",ISNUMBER(SEARCH("; Knowledge injection; ","; "&F58&"; "))),1,0) -> 0 | W58: =IF(OR(E58="Selection/Rejection",ISNUMBER(SEARCH("; Selection/Rejection; ","; "&F58&"; "))),1,0) -> 0 | X58: =IF(OR(E58="Deliberation",ISNUMBER(SEARCH("; Deliberation; ","; "&F58&"; "))),1,0) -> 0 | Y58: =SUM(Z58:AE58) -> 1 | Z58: =IF(ISNUMBER(SEARCH("; domain correction; ","; "&H58&"; ")),1,0) -> 0 | AA58: =IF(ISNUMBER(SEARCH("; conceptual discrimination; ","; "&H58&"; ")),1,0) -> 0 | AB58: =IF(ISNUMBER(SEARCH("; evidence judgment; ","; "&H58&"; ")),1,0) -> 0 | AC58: =IF(ISNUMBER(SEARCH("; methodological judgment; ","; "&H58&"; ")),1,0) -> 0 | AD58: =IF(ISNUMBER(SEARCH("; argumentative judgment; ","; "&H58&"; ")),1,0) -> 0 | AE58: =IF(ISNUMBER(SEARCH("; genre/writing expertise; ","; "&H58&"; ")),1,0) -> 1 | AF58: =IF(ISNUMBER(SEARCH("; none; ","; "&H58&"; ")),1,0) -> 0
A59: HE-058 | B59: 58 | C59: Diagnosis, model and reforms | D59: 5.2 Modelin Dizaynı: Kateqoriyalar və Səbəb-Nəticə əlaqələri? | E59: Knowledge injection | F59: Directed delegation | G59: Directive | H59: methodological judgment; genre/writing expertise | I59: Proposes a model-development heading. | J59: AI refines the heading. | K59: DOCX body elements 3198–3198 | L59: DOCX body elements 3201–3208 | N59: Visible next AI response | O59: Converted DOCX: textbox continuations joined; AI completion/source-check claims are unverified. | P59: =SUM(Q59:X59) -> 2 | Q59: =IF(OR(E59="Delegation",ISNUMBER(SEARCH("; Delegation; ","; "&F59&"; "))),1,0) -> 0 | R59: =IF(OR(E59="Directed delegation",ISNUMBER(SEARCH("; Directed delegation; ","; "&F59&"; "))),1,0) -> 1 | S59: =IF(OR(E59="Evaluation",ISNUMBER(SEARCH("; Evaluation; ","; "&F59&"; "))),1,0) -> 0 | T59: =IF(OR(E59="Correction/Challenge",ISNUMBER(SEARCH("; Correction/Challenge; ","; "&F59&"; "))),1,0) -> 0 | U59: =IF(OR(E59="Redirection",ISNUMBER(SEARCH("; Redirection; ","; "&F59&"; "))),1,0) -> 0 | V59: =IF(OR(E59="Knowledge injection",ISNUMBER(SEARCH("; Knowledge injection; ","; "&F59&"; "))),1,0) -> 1 | W59: =IF(OR(E59="Selection/Rejection",ISNUMBER(SEARCH("; Selection/Rejection; ","; "&F59&"; "))),1,0) -> 0 | X59: =IF(OR(E59="Deliberation",ISNUMBER(SEARCH("; Deliberation; ","; "&F59&"; "))),1,0) -> 0 | Y59: =SUM(Z59:AE59) -> 2 | Z59: =IF(ISNUMBER(SEARCH("; domain correction; ","; "&H59&"; ")),1,0) -> 0 | AA59: =IF(ISNUMBER(SEARCH("; conceptual discrimination; ","; "&H59&"; ")),1,0) -> 0 | AB59: =IF(ISNUMBER(SEARCH("; evidence judgment; ","; "&H59&"; ")),1,0) -> 0 | AC59: =IF(ISNUMBER(SEARCH("; methodological judgment; ","; "&H59&"; ")),1,0) -> 1 | AD59: =IF(ISNUMBER(SEARCH("; argumentative judgment; ","; "&H59&"; ")),1,0) -> 0 | AE59: =IF(ISNUMBER(SEARCH("; genre/writing expertise; ","; "&H59&"; ")),1,0) -> 1 | AF59: =IF(ISNUMBER(SEARCH("; none; ","; "&H59&"; ")),1,0) -> 0
A60: HE-059 | B60: 59 | C60: Diagnosis, model and reforms | D60: caption for Şəkil 1-Azərbaycanın Ali Təhsil Sisteminin Keyfiyyətinə Spesifik Dizayn Olmuş Səbəb-Nəticə Modeli? | E60: Directed delegation | F60: Knowledge injection | G60: Directive | H60: genre/writing expertise | I60: Supplies a figure and requests its caption. | J60: The visible response begins with factor descriptions; the requested caption is not clearly recoverable. | K60: DOCX body elements 3209–3209 | L60: DOCX body elements 3209–3254 | N60: Visible next AI response | O60: Converted DOCX: textbox continuations joined; AI completion/source-check claims are unverified. Interpret response/intent in context; see rationale and notes. | P60: =SUM(Q60:X60) -> 2 | Q60: =IF(OR(E60="Delegation",ISNUMBER(SEARCH("; Delegation; ","; "&F60&"; "))),1,0) -> 0 | R60: =IF(OR(E60="Directed delegation",ISNUMBER(SEARCH("; Directed delegation; ","; "&F60&"; "))),1,0) -> 1 | S60: =IF(OR(E60="Evaluation",ISNUMBER(SEARCH("; Evaluation; ","; "&F60&"; "))),1,0) -> 0 | T60: =IF(OR(E60="Correction/Challenge",ISNUMBER(SEARCH("; Correction/Challenge; ","; "&F60&"; "))),1,0) -> 0 | U60: =IF(OR(E60="Redirection",ISNUMBER(SEARCH("; Redirection; ","; "&F60&"; "))),1,0) -> 0 | V60: =IF(OR(E60="Knowledge injection",ISNUMBER(SEARCH("; Knowledge injection; ","; "&F60&"; "))),1,0) -> 1 | W60: =IF(OR(E60="Selection/Rejection",ISNUMBER(SEARCH("; Selection/Rejection; ","; "&F60&"; "))),1,0) -> 0 | X60: =IF(OR(E60="Deliberation",ISNUMBER(SEARCH("; Deliberation; ","; "&F60&"; "))),1,0) -> 0 | Y60: =SUM(Z60:AE60) -> 1 | Z60: =IF(ISNUMBER(SEARCH("; domain correction; ","; "&H60&"; ")),1,0) -> 0 | AA60: =IF(ISNUMBER(SEARCH("; conceptual discrimination; ","; "&H60&"; ")),1,0) -> 0 | AB60: =IF(ISNUMBER(SEARCH("; evidence judgment; ","; "&H60&"; ")),1,0) -> 0 | AC60: =IF(ISNUMBER(SEARCH("; methodological judgment; ","; "&H60&"; ")),1,0) -> 0 | AD60: =IF(ISNUMBER(SEARCH("; argumentative judgment; ","; "&H60&"; ")),1,0) -> 0 | AE60: =IF(ISNUMBER(SEARCH("; genre/writing expertise; ","; "&H60&"; ")),1,0) -> 1 | AF60: =IF(ISNUMBER(SEARCH("; none; ","; "&H60&"; ")),1,0) -> 0
A61: HE-060 | B61: 60 | C61: Diagnosis, model and reforms | D61: using my hints below (if any), give text of: 5 SİSTEMİN KÖK-SƏBƏB-NƏTİCƏ MODELLƏŞDİRİLMƏSİ [Açılış paraqrafı — metodun əsaslandırılması] niyə səbəb-nəticə modelləşdirmə bu kontekst üçün faydalıdır 5.1 Sistemdəki Kök-Səbəb və Nəticə Amillərini Təyin Etmək [Amillərin siyahısı + hər birinin qısa empirik/nəzəri əsası]-Notes: --Do not use the Harari style of writing. use standard academic writing. --give text inchat area,… | E61: Directed delegation | F61: Knowledge injection | G61: Directive | H61: methodological judgment; argumentative judgment; genre/writing expertise | I61: Specifies model development, factor-selection justification and drafting constraints. | J61: AI drafts the model-development account. | K61: DOCX body elements 3257–3257 | L61: DOCX body elements 3261–3293 | N61: Visible next AI response | O61: Converted DOCX: textbox continuations joined; AI completion/source-check claims are unverified. | P61: =SUM(Q61:X61) -> 2 | Q61: =IF(OR(E61="Delegation",ISNUMBER(SEARCH("; Delegation; ","; "&F61&"; "))),1,0) -> 0 | R61: =IF(OR(E61="Directed delegation",ISNUMBER(SEARCH("; Directed delegation; ","; "&F61&"; "))),1,0) -> 1 | S61: =IF(OR(E61="Evaluation",ISNUMBER(SEARCH("; Evaluation; ","; "&F61&"; "))),1,0) -> 0 | T61: =IF(OR(E61="Correction/Challenge",ISNUMBER(SEARCH("; Correction/Challenge; ","; "&F61&"; "))),1,0) -> 0 | U61: =IF(OR(E61="Redirection",ISNUMBER(SEARCH("; Redirection; ","; "&F61&"; "))),1,0) -> 0 | V61: =IF(OR(E61="Knowledge injection",ISNUMBER(SEARCH("; Knowledge injection; ","; "&F61&"; "))),1,0) -> 1 | W61: =IF(OR(E61="Selection/Rejection",ISNUMBER(SEARCH("; Selection/Rejection; ","; "&F61&"; "))),1,0) -> 0 | X61: =IF(OR(E61="Deliberation",ISNUMBER(SEARCH("; Deliberation; ","; "&F61&"; "))),1,0) -> 0 | Y61: =SUM(Z61:AE61) -> 3 | Z61: =IF(ISNUMBER(SEARCH("; domain correction; ","; "&H61&"; ")),1,0) -> 0 | AA61: =IF(ISNUMBER(SEARCH("; conceptual discrimination; ","; "&H61&"; ")),1,0) -> 0 | AB61: =IF(ISNUMBER(SEARCH("; evidence judgment; ","; "&H61&"; ")),1,0) -> 0 | AC61: =IF(ISNUMBER(SEARCH("; methodological judgment; ","; "&H61&"; ")),1,0) -> 1 | AD61: =IF(ISNUMBER(SEARCH("; argumentative judgment; ","; "&H61&"; ")),1,0) -> 1 | AE61: =IF(ISNUMBER(SEARCH("; genre/writing expertise; ","; "&H61&"; ")),1,0) -> 1 | AF61: =IF(ISNUMBER(SEARCH("; none; ","; "&H61&"; ")),1,0) -> 0
A62: HE-061 | B62: 61 | C62: Diagnosis, model and reforms | D62: it Seems we have not cited the following three papers. Right? in the opening paragraph of section five, you can say that system dynamic modeling has been used actually for higher education systems analysis and cite the following three papers very brieflyCruz-Bohorquez, J. M., Adams, S. G., & Bravo, F. A. (2024). The Academic System Influence on Instructional Change: A Conceptual Systems Dynamics Model of Faculty Moti… | E62: Correction/Challenge | F62: Knowledge injection; Directed delegation | G62: Critical | H62: evidence judgment; methodological judgment | I62: Identifies omitted systems-dynamics papers and supplies references for integration. | J62: AI integrates the named comparison studies. | K62: DOCX body elements 3294–3294 | L62: DOCX body elements 3297–3330 | M62: URL(s) supplied in prompt | N62: Visible next AI response | O62: Converted DOCX: textbox continuations joined; AI completion/source-check claims are unverified. | P62: =SUM(Q62:X62) -> 3 | Q62: =IF(OR(E62="Delegation",ISNUMBER(SEARCH("; Delegation; ","; "&F62&"; "))),1,0) -> 0 | R62: =IF(OR(E62="Directed delegation",ISNUMBER(SEARCH("; Directed delegation; ","; "&F62&"; "))),1,0) -> 1 | S62: =IF(OR(E62="Evaluation",ISNUMBER(SEARCH("; Evaluation; ","; "&F62&"; "))),1,0) -> 0 | T62: =IF(OR(E62="Correction/Challenge",ISNUMBER(SEARCH("; Correction/Challenge; ","; "&F62&"; "))),1,0) -> 1 | U62: =IF(OR(E62="Redirection",ISNUMBER(SEARCH("; Redirection; ","; "&F62&"; "))),1,0) -> 0 | V62: =IF(OR(E62="Knowledge injection",ISNUMBER(SEARCH("; Knowledge injection; ","; "&F62&"; "))),1,0) -> 1 | W62: =IF(OR(E62="Selection/Rejection",ISNUMBER(SEARCH("; Selection/Rejection; ","; "&F62&"; "))),1,0) -> 0 | X62: =IF(OR(E62="Deliberation",ISNUMBER(SEARCH("; Deliberation; ","; "&F62&"; "))),1,0) -> 0 | Y62: =SUM(Z62:AE62) -> 2 | Z62: =IF(ISNUMBER(SEARCH("; domain correction; ","; "&H62&"; ")),1,0) -> 0 | AA62: =IF(ISNUMBER(SEARCH("; conceptual discrimination; ","; "&H62&"; ")),1,0) -> 0 | AB62: =IF(ISNUMBER(SEARCH("; evidence judgment; ","; "&H62&"; ")),1,0) -> 1 | AC62: =IF(ISNUMBER(SEARCH("; methodological judgment; ","; "&H62&"; ")),1,0) -> 1 | AD62: =IF(ISNUMBER(SEARCH("; argumentative judgment; ","; "&H62&"; ")),1,0) -> 0 | AE62: =IF(ISNUMBER(SEARCH("; genre/writing expertise; ","; "&H62&"; ")),1,0) -> 0 | AF62: =IF(ISNUMBER(SEARCH("; none; ","; "&H62&"; ")),1,0) -> 0
A63: HE-062 | B63: 62 | C63: Diagnosis, model and reforms | D63: in sec five point one you already did the classifications . do we need five point two or do we need to merge those two? I'm not sure. | E63: Redirection | F63: Directed delegation | G63: Directive | H63: conceptual discrimination; genre/writing expertise | I63: Identifies overlap between factor classification and model explanation and requests merging. | J63: AI combines the sections. | K63: DOCX body elements 3331–3331 | L63: DOCX body elements 3334–3367 | N63: Visible next AI response | O63: Converted DOCX: textbox continuations joined; AI completion/source-check claims are unverified. | P63: =SUM(Q63:X63) -> 2 | Q63: =IF(OR(E63="Delegation",ISNUMBER(SEARCH("; Delegation; ","; "&F63&"; "))),1,0) -> 0 | R63: =IF(OR(E63="Directed delegation",ISNUMBER(SEARCH("; Directed delegation; ","; "&F63&"; "))),1,0) -> 1 | S63: =IF(OR(E63="Evaluation",ISNUMBER(SEARCH("; Evaluation; ","; "&F63&"; "))),1,0) -> 0 | T63: =IF(OR(E63="Correction/Challenge",ISNUMBER(SEARCH("; Correction/Challenge; ","; "&F63&"; "))),1,0) -> 0 | U63: =IF(OR(E63="Redirection",ISNUMBER(SEARCH("; Redirection; ","; "&F63&"; "))),1,0) -> 1 | V63: =IF(OR(E63="Knowledge injection",ISNUMBER(SEARCH("; Knowledge injection; ","; "&F63&"; "))),1,0) -> 0 | W63: =IF(OR(E63="Selection/Rejection",ISNUMBER(SEARCH("; Selection/Rejection; ","; "&F63&"; "))),1,0) -> 0 | X63: =IF(OR(E63="Deliberation",ISNUMBER(SEARCH("; Deliberation; ","; "&F63&"; "))),1,0) -> 0 | Y63: =SUM(Z63:AE63) -> 2 | Z63: =IF(ISNUMBER(SEARCH("; domain correction; ","; "&H63&"; ")),1,0) -> 0 | AA63: =IF(ISNUMBER(SEARCH("; conceptual discrimination; ","; "&H63&"; ")),1,0) -> 1 | AB63: =IF(ISNUMBER(SEARCH("; evidence judgment; ","; "&H63&"; ")),1,0) -> 0 | AC63: =IF(ISNUMBER(SEARCH("; methodological judgment; ","; "&H63&"; ")),1,0) -> 0 | AD63: =IF(ISNUMBER(SEARCH("; argumentative judgment; ","; "&H63&"; ")),1,0) -> 0 | AE63: =IF(ISNUMBER(SEARCH("; genre/writing expertise; ","; "&H63&"; ")),1,0) -> 1 | AF63: =IF(ISNUMBER(SEARCH("; none; ","; "&H63&"; ")),1,0) -> 0
A64: HE-063 | B64: 63 | C64: Diagnosis, model and reforms | D64: but then vhat about 5.3 Modelin Təfsir və İnterpretasiyası... vhat shall üe have there? | E64: Deliberation | F64: Evaluation | G64: Deliberative | H64: argumentative judgment; genre/writing expertise | I64: Asks what interpretation should add to the model presentation. | J64: AI distinguishes interpretation from description and recommendations. | K64: DOCX body elements 3368–3368 | L64: DOCX body elements 3371–3399 | N64: Visible next AI response | O64: Converted DOCX: textbox continuations joined; AI completion/source-check claims are unverified. | P64: =SUM(Q64:X64) -> 2 | Q64: =IF(OR(E64="Delegation",ISNUMBER(SEARCH("; Delegation; ","; "&F64&"; "))),1,0) -> 0 | R64: =IF(OR(E64="Directed delegation",ISNUMBER(SEARCH("; Directed delegation; ","; "&F64&"; "))),1,0) -> 0 | S64: =IF(OR(E64="Evaluation",ISNUMBER(SEARCH("; Evaluation; ","; "&F64&"; "))),1,0) -> 1 | T64: =IF(OR(E64="Correction/Challenge",ISNUMBER(SEARCH("; Correction/Challenge; ","; "&F64&"; "))),1,0) -> 0 | U64: =IF(OR(E64="Redirection",ISNUMBER(SEARCH("; Redirection; ","; "&F64&"; "))),1,0) -> 0 | V64: =IF(OR(E64="Knowledge injection",ISNUMBER(SEARCH("; Knowledge injection; ","; "&F64&"; "))),1,0) -> 0 | W64: =IF(OR(E64="Selection/Rejection",ISNUMBER(SEARCH("; Selection/Rejection; ","; "&F64&"; "))),1,0) -> 0 | X64: =IF(OR(E64="Deliberation",ISNUMBER(SEARCH("; Deliberation; ","; "&F64&"; "))),1,0) -> 1 | Y64: =SUM(Z64:AE64) -> 2 | Z64: =IF(ISNUMBER(SEARCH("; domain correction; ","; "&H64&"; ")),1,0) -> 0 | AA64: =IF(ISNUMBER(SEARCH("; conceptual discrimination; ","; "&H64&"; ")),1,0) -> 0 | AB64: =IF(ISNUMBER(SEARCH("; evidence judgment; ","; "&H64&"; ")),1,0) -> 0 | AC64: =IF(ISNUMBER(SEARCH("; methodological judgment; ","; "&H64&"; ")),1,0) -> 0 | AD64: =IF(ISNUMBER(SEARCH("; argumentative judgment; ","; "&H64&"; ")),1,0) -> 1 | AE64: =IF(ISNUMBER(SEARCH("; genre/writing expertise; ","; "&H64&"; ")),1,0) -> 1 | AF64: =IF(ISNUMBER(SEARCH("; none; ","; "&H64&"; ")),1,0) -> 0
A65: HE-064 | B65: 64 | C65: Diagnosis, model and reforms | D65: give text of those tvo subsecs | E65: Directed delegation | G65: Directive | H65: none | I65: Requests the two previously discussed subsections without adding a criterion. | J65: AI drafts them. | K65: DOCX body elements 3402–3402 | L65: DOCX body elements 3406–3413 | N65: Visible next AI response | O65: Converted DOCX: textbox continuations joined; AI completion/source-check claims are unverified. | P65: =SUM(Q65:X65) -> 1 | Q65: =IF(OR(E65="Delegation",ISNUMBER(SEARCH("; Delegation; ","; "&F65&"; "))),1,0) -> 0 | R65: =IF(OR(E65="Directed delegation",ISNUMBER(SEARCH("; Directed delegation; ","; "&F65&"; "))),1,0) -> 1 | S65: =IF(OR(E65="Evaluation",ISNUMBER(SEARCH("; Evaluation; ","; "&F65&"; "))),1,0) -> 0 | T65: =IF(OR(E65="Correction/Challenge",ISNUMBER(SEARCH("; Correction/Challenge; ","; "&F65&"; "))),1,0) -> 0 | U65: =IF(OR(E65="Redirection",ISNUMBER(SEARCH("; Redirection; ","; "&F65&"; "))),1,0) -> 0 | V65: =IF(OR(E65="Knowledge injection",ISNUMBER(SEARCH("; Knowledge injection; ","; "&F65&"; "))),1,0) -> 0 | W65: =IF(OR(E65="Selection/Rejection",ISNUMBER(SEARCH("; Selection/Rejection; ","; "&F65&"; "))),1,0) -> 0 | X65: =IF(OR(E65="Deliberation",ISNUMBER(SEARCH("; Deliberation; ","; "&F65&"; "))),1,0) -> 0 | Y65: =SUM(Z65:AE65) -> 0 | Z65: =IF(ISNUMBER(SEARCH("; domain correction; ","; "&H65&"; ")),1,0) -> 0 | AA65: =IF(ISNUMBER(SEARCH("; conceptual discrimination; ","; "&H65&"; ")),1,0) -> 0 | AB65: =IF(ISNUMBER(SEARCH("; evidence judgment; ","; "&H65&"; ")),1,0) -> 0 | AC65: =IF(ISNUMBER(SEARCH("; methodological judgment; ","; "&H65&"; ")),1,0) -> 0 | AD65: =IF(ISNUMBER(SEARCH("; argumentative judgment; ","; "&H65&"; ")),1,0) -> 0 | AE65: =IF(ISNUMBER(SEARCH("; genre/writing expertise; ","; "&H65&"; ")),1,0) -> 0 | AF65: =IF(ISNUMBER(SEARCH("; none; ","; "&H65&"; ")),1,0) -> 1
A66: HE-065 | B66: 65 | C66: Diagnosis, model and reforms | D66: vhich six? not a good vay to start if you have not discussed those 6 | E66: Correction/Challenge | G66: Critical | H66: conceptual discrimination; genre/writing expertise | I66: Challenges an undefined reference to six categories. | J66: AI clarifies the categories and their introduction. | K66: DOCX body elements 3416–3416 | L66: DOCX body elements 3420–3432 | N66: Visible next AI response | O66: Converted DOCX: textbox continuations joined; AI completion/source-check claims are unverified. | P66: =SUM(Q66:X66) -> 1 | Q66: =IF(OR(E66="Delegation",ISNUMBER(SEARCH("; Delegation; ","; "&F66&"; "))),1,0) -> 0 | R66: =IF(OR(E66="Directed delegation",ISNUMBER(SEARCH("; Directed delegation; ","; "&F66&"; "))),1,0) -> 0 | S66: =IF(OR(E66="Evaluation",ISNUMBER(SEARCH("; Evaluation; ","; "&F66&"; "))),1,0) -> 0 | T66: =IF(OR(E66="Correction/Challenge",ISNUMBER(SEARCH("; Correction/Challenge; ","; "&F66&"; "))),1,0) -> 1 | U66: =IF(OR(E66="Redirection",ISNUMBER(SEARCH("; Redirection; ","; "&F66&"; "))),1,0) -> 0 | V66: =IF(OR(E66="Knowledge injection",ISNUMBER(SEARCH("; Knowledge injection; ","; "&F66&"; "))),1,0) -> 0 | W66: =IF(OR(E66="Selection/Rejection",ISNUMBER(SEARCH("; Selection/Rejection; ","; "&F66&"; "))),1,0) -> 0 | X66: =IF(OR(E66="Deliberation",ISNUMBER(SEARCH("; Deliberation; ","; "&F66&"; "))),1,0) -> 0 | Y66: =SUM(Z66:AE66) -> 2 | Z66: =IF(ISNUMBER(SEARCH("; domain correction; ","; "&H66&"; ")),1,0) -> 0 | AA66: =IF(ISNUMBER(SEARCH("; conceptual discrimination; ","; "&H66&"; ")),1,0) -> 1 | AB66: =IF(ISNUMBER(SEARCH("; evidence judgment; ","; "&H66&"; ")),1,0) -> 0 | AC66: =IF(ISNUMBER(SEARCH("; methodological judgment; ","; "&H66&"; ")),1,0) -> 0 | AD66: =IF(ISNUMBER(SEARCH("; argumentative judgment; ","; "&H66&"; ")),1,0) -> 0 | AE66: =IF(ISNUMBER(SEARCH("; genre/writing expertise; ","; "&H66&"; ")),1,0) -> 1 | AF66: =IF(ISNUMBER(SEARCH("; none; ","; "&H66&"; ")),1,0) -> 0
A67: HE-066 | B67: 66 | C67: Diagnosis, model and reforms | D67: Here is figure one, not that I have not put all the possible impact, uh, the relationships and, uh, arrows and edges there, just not to overload, um, them. I have put the most important one and, of course, as you can see for the student factors, uh, I treat them as a kind of, uh, let's say, composite node means that all the four factors, understand factors, I put, like, an, uh, a box and around them and so that all o… | E67: Knowledge injection | F67: Directed delegation | G67: Directive | H67: conceptual discrimination; methodological judgment; argumentative judgment | I67: Explains representative arrows and a composite student node, directing model interpretation. | J67: AI revises the explanation of the model’s simplifications. | K67: DOCX body elements 3435–3435 | L67: DOCX body elements 3439–3443 | N67: Visible next AI response | O67: Converted DOCX: textbox continuations joined; AI completion/source-check claims are unverified. | P67: =SUM(Q67:X67) -> 2 | Q67: =IF(OR(E67="Delegation",ISNUMBER(SEARCH("; Delegation; ","; "&F67&"; "))),1,0) -> 0 | R67: =IF(OR(E67="Directed delegation",ISNUMBER(SEARCH("; Directed delegation; ","; "&F67&"; "))),1,0) -> 1 | S67: =IF(OR(E67="Evaluation",ISNUMBER(SEARCH("; Evaluation; ","; "&F67&"; "))),1,0) -> 0 | T67: =IF(OR(E67="Correction/Challenge",ISNUMBER(SEARCH("; Correction/Challenge; ","; "&F67&"; "))),1,0) -> 0 | U67: =IF(OR(E67="Redirection",ISNUMBER(SEARCH("; Redirection; ","; "&F67&"; "))),1,0) -> 0 | V67: =IF(OR(E67="Knowledge injection",ISNUMBER(SEARCH("; Knowledge injection; ","; "&F67&"; "))),1,0) -> 1 | W67: =IF(OR(E67="Selection/Rejection",ISNUMBER(SEARCH("; Selection/Rejection; ","; "&F67&"; "))),1,0) -> 0 | X67: =IF(OR(E67="Deliberation",ISNUMBER(SEARCH("; Deliberation; ","; "&F67&"; "))),1,0) -> 0 | Y67: =SUM(Z67:AE67) -> 3 | Z67: =IF(ISNUMBER(SEARCH("; domain correction; ","; "&H67&"; ")),1,0) -> 0 | AA67: =IF(ISNUMBER(SEARCH("; conceptual discrimination; ","; "&H67&"; ")),1,0) -> 1 | AB67: =IF(ISNUMBER(SEARCH("; evidence judgment; ","; "&H67&"; ")),1,0) -> 0 | AC67: =IF(ISNUMBER(SEARCH("; methodological judgment; ","; "&H67&"; ")),1,0) -> 1 | AD67: =IF(ISNUMBER(SEARCH("; argumentative judgment; ","; "&H67&"; ")),1,0) -> 1 | AE67: =IF(ISNUMBER(SEARCH("; genre/writing expertise; ","; "&H67&"; ")),1,0) -> 0 | AF67: =IF(ISNUMBER(SEARCH("; none; ","; "&H67&"; ")),1,0) -> 0
A68: HE-067 | B68: 67 | C68: Diagnosis, model and reforms | D68: give 5.2 | E68: Directed delegation | G68: Directive | H68: none | I68: Names a subsection to generate without new substantive specification. | J68: AI drafts the subsection. | K68: DOCX body elements 3445–3445 | L68: DOCX body elements 3448–3471 | N68: Visible next AI response | O68: Converted DOCX: textbox continuations joined; AI completion/source-check claims are unverified. | P68: =SUM(Q68:X68) -> 1 | Q68: =IF(OR(E68="Delegation",ISNUMBER(SEARCH("; Delegation; ","; "&F68&"; "))),1,0) -> 0 | R68: =IF(OR(E68="Directed delegation",ISNUMBER(SEARCH("; Directed delegation; ","; "&F68&"; "))),1,0) -> 1 | S68: =IF(OR(E68="Evaluation",ISNUMBER(SEARCH("; Evaluation; ","; "&F68&"; "))),1,0) -> 0 | T68: =IF(OR(E68="Correction/Challenge",ISNUMBER(SEARCH("; Correction/Challenge; ","; "&F68&"; "))),1,0) -> 0 | U68: =IF(OR(E68="Redirection",ISNUMBER(SEARCH("; Redirection; ","; "&F68&"; "))),1,0) -> 0 | V68: =IF(OR(E68="Knowledge injection",ISNUMBER(SEARCH("; Knowledge injection; ","; "&F68&"; "))),1,0) -> 0 | W68: =IF(OR(E68="Selection/Rejection",ISNUMBER(SEARCH("; Selection/Rejection; ","; "&F68&"; "))),1,0) -> 0 | X68: =IF(OR(E68="Deliberation",ISNUMBER(SEARCH("; Deliberation; ","; "&F68&"; "))),1,0) -> 0 | Y68: =SUM(Z68:AE68) -> 0 | Z68: =IF(ISNUMBER(SEARCH("; domain correction; ","; "&H68&"; ")),1,0) -> 0 | AA68: =IF(ISNUMBER(SEARCH("; conceptual discrimination; ","; "&H68&"; ")),1,0) -> 0 | AB68: =IF(ISNUMBER(SEARCH("; evidence judgment; ","; "&H68&"; ")),1,0) -> 0 | AC68: =IF(ISNUMBER(SEARCH("; methodological judgment; ","; "&H68&"; ")),1,0) -> 0 | AD68: =IF(ISNUMBER(SEARCH("; argumentative judgment; ","; "&H68&"; ")),1,0) -> 0 | AE68: =IF(ISNUMBER(SEARCH("; genre/writing expertise; ","; "&H68&"; ")),1,0) -> 0 | AF68: =IF(ISNUMBER(SEARCH("; none; ","; "&H68&"; ")),1,0) -> 1
A69: HE-068 | B69: 68 | C69: Diagnosis, model and reforms | D69: I feel that five point two is is is going to converge and have similar text as section six in which we will analyze and propose some suggestions. How should we remove this overlap? shall Modelin Təfsir və İnterpretasiyası be much shorter and higher level? | E69: Correction/Challenge | F69: Redirection; Directed delegation | G69: Critical | H69: argumentative judgment; genre/writing expertise | I69: Identifies overlap with recommendations and requires a shorter, higher-level interpretation. | J69: AI shortens and refocuses the interpretation. | K69: DOCX body elements 3472–3472 | L69: DOCX body elements 3475–3511 | N69: Visible next AI response | O69: Converted DOCX: textbox continuations joined; AI completion/source-check claims are unverified. | P69: =SUM(Q69:X69) -> 3 | Q69: =IF(OR(E69="Delegation",ISNUMBER(SEARCH("; Delegation; ","; "&F69&"; "))),1,0) -> 0 | R69: =IF(OR(E69="Directed delegation",ISNUMBER(SEARCH("; Directed delegation; ","; "&F69&"; "))),1,0) -> 1 | S69: =IF(OR(E69="Evaluation",ISNUMBER(SEARCH("; Evaluation; ","; "&F69&"; "))),1,0) -> 0 | T69: =IF(OR(E69="Correction/Challenge",ISNUMBER(SEARCH("; Correction/Challenge; ","; "&F69&"; "))),1,0) -> 1 | U69: =IF(OR(E69="Redirection",ISNUMBER(SEARCH("; Redirection; ","; "&F69&"; "))),1,0) -> 1 | V69: =IF(OR(E69="Knowledge injection",ISNUMBER(SEARCH("; Knowledge injection; ","; "&F69&"; "))),1,0) -> 0 | W69: =IF(OR(E69="Selection/Rejection",ISNUMBER(SEARCH("; Selection/Rejection; ","; "&F69&"; "))),1,0) -> 0 | X69: =IF(OR(E69="Deliberation",ISNUMBER(SEARCH("; Deliberation; ","; "&F69&"; "))),1,0) -> 0 | Y69: =SUM(Z69:AE69) -> 2 | Z69: =IF(ISNUMBER(SEARCH("; domain correction; ","; "&H69&"; ")),1,0) -> 0 | AA69: =IF(ISNUMBER(SEARCH("; conceptual discrimination; ","; "&H69&"; ")),1,0) -> 0 | AB69: =IF(ISNUMBER(SEARCH("; evidence judgment; ","; "&H69&"; ")),1,0) -> 0 | AC69: =IF(ISNUMBER(SEARCH("; methodological judgment; ","; "&H69&"; ")),1,0) -> 0 | AD69: =IF(ISNUMBER(SEARCH("; argumentative judgment; ","; "&H69&"; ")),1,0) -> 1 | AE69: =IF(ISNUMBER(SEARCH("; genre/writing expertise; ","; "&H69&"; ")),1,0) -> 1 | AF69: =IF(ISNUMBER(SEARCH("; none; ","; "&H69&"; ")),1,0) -> 0
A70: HE-069 | B70: 69 | C70: Diagnosis, model and reforms | D70: What do you mean by those three? | E70: Correction/Challenge | G70: Critical | H70: conceptual discrimination | I70: Challenges an imprecise reference to three levels. | J70: AI acknowledges imprecision and clarifies the intended categories. | K70: DOCX body elements 3514–3514 | L70: DOCX body elements 3518–3540 | N70: Visible next AI response | O70: Converted DOCX: textbox continuations joined; AI completion/source-check claims are unverified. | P70: =SUM(Q70:X70) -> 1 | Q70: =IF(OR(E70="Delegation",ISNUMBER(SEARCH("; Delegation; ","; "&F70&"; "))),1,0) -> 0 | R70: =IF(OR(E70="Directed delegation",ISNUMBER(SEARCH("; Directed delegation; ","; "&F70&"; "))),1,0) -> 0 | S70: =IF(OR(E70="Evaluation",ISNUMBER(SEARCH("; Evaluation; ","; "&F70&"; "))),1,0) -> 0 | T70: =IF(OR(E70="Correction/Challenge",ISNUMBER(SEARCH("; Correction/Challenge; ","; "&F70&"; "))),1,0) -> 1 | U70: =IF(OR(E70="Redirection",ISNUMBER(SEARCH("; Redirection; ","; "&F70&"; "))),1,0) -> 0 | V70: =IF(OR(E70="Knowledge injection",ISNUMBER(SEARCH("; Knowledge injection; ","; "&F70&"; "))),1,0) -> 0 | W70: =IF(OR(E70="Selection/Rejection",ISNUMBER(SEARCH("; Selection/Rejection; ","; "&F70&"; "))),1,0) -> 0 | X70: =IF(OR(E70="Deliberation",ISNUMBER(SEARCH("; Deliberation; ","; "&F70&"; "))),1,0) -> 0 | Y70: =SUM(Z70:AE70) -> 1 | Z70: =IF(ISNUMBER(SEARCH("; domain correction; ","; "&H70&"; ")),1,0) -> 0 | AA70: =IF(ISNUMBER(SEARCH("; conceptual discrimination; ","; "&H70&"; ")),1,0) -> 1 | AB70: =IF(ISNUMBER(SEARCH("; evidence judgment; ","; "&H70&"; ")),1,0) -> 0 | AC70: =IF(ISNUMBER(SEARCH("; methodological judgment; ","; "&H70&"; ")),1,0) -> 0 | AD70: =IF(ISNUMBER(SEARCH("; argumentative judgment; ","; "&H70&"; ")),1,0) -> 0 | AE70: =IF(ISNUMBER(SEARCH("; genre/writing expertise; ","; "&H70&"; ")),1,0) -> 0 | AF70: =IF(ISNUMBER(SEARCH("; none; ","; "&H70&"; ")),1,0) -> 0
A71: HE-070 | B71: 70 | C71: Diagnosis, model and reforms | D71: Is this the best structure for section six? I also would like to include the term "road map" in the headings. Is that a good idea? | E71: Redirection | F71: Directed delegation | G71: Directive | H71: genre/writing expertise | I71: Adds a roadmap to the reform section structure. | J71: AI revises the section plan. | K71: DOCX body elements 3543–3543 | L71: DOCX body elements 3547–3593 | N71: Visible next AI response | O71: Converted DOCX: textbox continuations joined; AI completion/source-check claims are unverified. | P71: =SUM(Q71:X71) -> 2 | Q71: =IF(OR(E71="Delegation",ISNUMBER(SEARCH("; Delegation; ","; "&F71&"; "))),1,0) -> 0 | R71: =IF(OR(E71="Directed delegation",ISNUMBER(SEARCH("; Directed delegation; ","; "&F71&"; "))),1,0) -> 1 | S71: =IF(OR(E71="Evaluation",ISNUMBER(SEARCH("; Evaluation; ","; "&F71&"; "))),1,0) -> 0 | T71: =IF(OR(E71="Correction/Challenge",ISNUMBER(SEARCH("; Correction/Challenge; ","; "&F71&"; "))),1,0) -> 0 | U71: =IF(OR(E71="Redirection",ISNUMBER(SEARCH("; Redirection; ","; "&F71&"; "))),1,0) -> 1 | V71: =IF(OR(E71="Knowledge injection",ISNUMBER(SEARCH("; Knowledge injection; ","; "&F71&"; "))),1,0) -> 0 | W71: =IF(OR(E71="Selection/Rejection",ISNUMBER(SEARCH("; Selection/Rejection; ","; "&F71&"; "))),1,0) -> 0 | X71: =IF(OR(E71="Deliberation",ISNUMBER(SEARCH("; Deliberation; ","; "&F71&"; "))),1,0) -> 0 | Y71: =SUM(Z71:AE71) -> 1 | Z71: =IF(ISNUMBER(SEARCH("; domain correction; ","; "&H71&"; ")),1,0) -> 0 | AA71: =IF(ISNUMBER(SEARCH("; conceptual discrimination; ","; "&H71&"; ")),1,0) -> 0 | AB71: =IF(ISNUMBER(SEARCH("; evidence judgment; ","; "&H71&"; ")),1,0) -> 0 | AC71: =IF(ISNUMBER(SEARCH("; methodological judgment; ","; "&H71&"; ")),1,0) -> 0 | AD71: =IF(ISNUMBER(SEARCH("; argumentative judgment; ","; "&H71&"; ")),1,0) -> 0 | AE71: =IF(ISNUMBER(SEARCH("; genre/writing expertise; ","; "&H71&"; ")),1,0) -> 1 | AF71: =IF(ISNUMBER(SEARCH("; none; ","; "&H71&"; ")),1,0) -> 0
A72: HE-071 | B72: 71 | C72: Diagnosis, model and reforms | D72: using my hints below (if any), give text of: 6 SİSTEMİN PRAQMATİK TƏHLİLİ VƏ İSLAHAT TƏKLİFLƏRİ Opening parag 6.1 Makro / Kontekstual Amillərinin Təhlili və İslahatı Not much can be done Sovet mirası: dominant düşüncə tərzi, iş və təhsil mədəniyyəti, vs. – it is what it is. We cannot change the past, we can just deal with and improve it Əmək bazarının strukturu: dövlət sektorunun dominantlığı, özəl sektorun zəifliyi … | E72: Directed delegation | F72: Knowledge injection | G72: Directive | H72: conceptual discrimination; argumentative judgment; genre/writing expertise | I72: Explains that contextual factors differ in changeability and supplies reform-writing constraints. | J72: AI drafts contextual recommendations. | K72: DOCX body elements 3595–3597 | L72: DOCX body elements 3600–3630 | M72: Extended draft/quoted context; researcher-origin judgment distinguished in rationale | N72: Visible next AI response | O72: Converted DOCX: textbox continuations joined; AI completion/source-check claims are unverified. | P72: =SUM(Q72:X72) -> 2 | Q72: =IF(OR(E72="Delegation",ISNUMBER(SEARCH("; Delegation; ","; "&F72&"; "))),1,0) -> 0 | R72: =IF(OR(E72="Directed delegation",ISNUMBER(SEARCH("; Directed delegation; ","; "&F72&"; "))),1,0) -> 1 | S72: =IF(OR(E72="Evaluation",ISNUMBER(SEARCH("; Evaluation; ","; "&F72&"; "))),1,0) -> 0 | T72: =IF(OR(E72="Correction/Challenge",ISNUMBER(SEARCH("; Correction/Challenge; ","; "&F72&"; "))),1,0) -> 0 | U72: =IF(OR(E72="Redirection",ISNUMBER(SEARCH("; Redirection; ","; "&F72&"; "))),1,0) -> 0 | V72: =IF(OR(E72="Knowledge injection",ISNUMBER(SEARCH("; Knowledge injection; ","; "&F72&"; "))),1,0) -> 1 | W72: =IF(OR(E72="Selection/Rejection",ISNUMBER(SEARCH("; Selection/Rejection; ","; "&F72&"; "))),1,0) -> 0 | X72: =IF(OR(E72="Deliberation",ISNUMBER(SEARCH("; Deliberation; ","; "&F72&"; "))),1,0) -> 0 | Y72: =SUM(Z72:AE72) -> 3 | Z72: =IF(ISNUMBER(SEARCH("; domain correction; ","; "&H72&"; ")),1,0) -> 0 | AA72: =IF(ISNUMBER(SEARCH("; conceptual discrimination; ","; "&H72&"; ")),1,0) -> 1 | AB72: =IF(ISNUMBER(SEARCH("; evidence judgment; ","; "&H72&"; ")),1,0) -> 0 | AC72: =IF(ISNUMBER(SEARCH("; methodological judgment; ","; "&H72&"; ")),1,0) -> 0 | AD72: =IF(ISNUMBER(SEARCH("; argumentative judgment; ","; "&H72&"; ")),1,0) -> 1 | AE72: =IF(ISNUMBER(SEARCH("; genre/writing expertise; ","; "&H72&"; ")),1,0) -> 1 | AF72: =IF(ISNUMBER(SEARCH("; none; ","; "&H72&"; ")),1,0) -> 0
A73: HE-072 | B73: 72 | C73: Diagnosis, model and reforms | D73: "qıdəm-əsaslı: proper AZ term? | E73: Correction/Challenge | G73: Critical | H73: genre/writing expertise | I73: Questions a nonstandard Azerbaijani seniority term. | J73: AI acknowledges a translation problem and proposes a replacement. | K73: DOCX body elements 3631–3631 | L73: DOCX body elements 3634–3657 | N73: Visible next AI response | O73: Converted DOCX: textbox continuations joined; AI completion/source-check claims are unverified. | P73: =SUM(Q73:X73) -> 1 | Q73: =IF(OR(E73="Delegation",ISNUMBER(SEARCH("; Delegation; ","; "&F73&"; "))),1,0) -> 0 | R73: =IF(OR(E73="Directed delegation",ISNUMBER(SEARCH("; Directed delegation; ","; "&F73&"; "))),1,0) -> 0 | S73: =IF(OR(E73="Evaluation",ISNUMBER(SEARCH("; Evaluation; ","; "&F73&"; "))),1,0) -> 0 | T73: =IF(OR(E73="Correction/Challenge",ISNUMBER(SEARCH("; Correction/Challenge; ","; "&F73&"; "))),1,0) -> 1 | U73: =IF(OR(E73="Redirection",ISNUMBER(SEARCH("; Redirection; ","; "&F73&"; "))),1,0) -> 0 | V73: =IF(OR(E73="Knowledge injection",ISNUMBER(SEARCH("; Knowledge injection; ","; "&F73&"; "))),1,0) -> 0 | W73: =IF(OR(E73="Selection/Rejection",ISNUMBER(SEARCH("; Selection/Rejection; ","; "&F73&"; "))),1,0) -> 0 | X73: =IF(OR(E73="Deliberation",ISNUMBER(SEARCH("; Deliberation; ","; "&F73&"; "))),1,0) -> 0 | Y73: =SUM(Z73:AE73) -> 1 | Z73: =IF(ISNUMBER(SEARCH("; domain correction; ","; "&H73&"; ")),1,0) -> 0 | AA73: =IF(ISNUMBER(SEARCH("; conceptual discrimination; ","; "&H73&"; ")),1,0) -> 0 | AB73: =IF(ISNUMBER(SEARCH("; evidence judgment; ","; "&H73&"; ")),1,0) -> 0 | AC73: =IF(ISNUMBER(SEARCH("; methodological judgment; ","; "&H73&"; ")),1,0) -> 0 | AD73: =IF(ISNUMBER(SEARCH("; argumentative judgment; ","; "&H73&"; ")),1,0) -> 0 | AE73: =IF(ISNUMBER(SEARCH("; genre/writing expertise; ","; "&H73&"; ")),1,0) -> 1 | AF73: =IF(ISNUMBER(SEARCH("; none; ","; "&H73&"; ")),1,0) -> 0
A74: HE-073 | B74: 73 | C74: Diagnosis, model and reforms | D74: using my hints below (if any), give text of: 6.2 İnstitusional/Struktur Amillərinin Təhlili və İslahatı Give pragmatic improvement suggestions for: Universitet muxtariyyəti səviyyəsi (mərkəzi nəzarət ↔ institusional sərbəstlik) Akademik Heyət Vəzifə/təyinat siyasətləri, Karyera irəliləyişi meyarı (tədris keyfiyyəti, araşdırma nəşri) Universitet səviyyəsində Akademiya-Sənaye əməkdaşlığı mədəniyyəti və təşviq olub olma… | E74: Directed delegation | F74: Knowledge injection | G74: Directive | H74: evidence judgment; argumentative judgment; genre/writing expertise | I74: Supplies academic-staff reform mechanisms and an ÖYP comparator, emphasizing staff centrality. | J74: AI drafts institutional and staff reforms with sources. | K74: DOCX body elements 3659–3662 | L74: DOCX body elements 3666–3716 | M74: URL(s) supplied in prompt; File/context references in prompt; inspect full text; Extended draft/quoted context; researcher-origin judgment distinguished in rationale | N74: Visible next AI response | O74: Converted DOCX: textbox continuations joined; AI completion/source-check claims are unverified. | P74: =SUM(Q74:X74) -> 2 | Q74: =IF(OR(E74="Delegation",ISNUMBER(SEARCH("; Delegation; ","; "&F74&"; "))),1,0) -> 0 | R74: =IF(OR(E74="Directed delegation",ISNUMBER(SEARCH("; Directed delegation; ","; "&F74&"; "))),1,0) -> 1 | S74: =IF(OR(E74="Evaluation",ISNUMBER(SEARCH("; Evaluation; ","; "&F74&"; "))),1,0) -> 0 | T74: =IF(OR(E74="Correction/Challenge",ISNUMBER(SEARCH("; Correction/Challenge; ","; "&F74&"; "))),1,0) -> 0 | U74: =IF(OR(E74="Redirection",ISNUMBER(SEARCH("; Redirection; ","; "&F74&"; "))),1,0) -> 0 | V74: =IF(OR(E74="Knowledge injection",ISNUMBER(SEARCH("; Knowledge injection; ","; "&F74&"; "))),1,0) -> 1 | W74: =IF(OR(E74="Selection/Rejection",ISNUMBER(SEARCH("; Selection/Rejection; ","; "&F74&"; "))),1,0) -> 0 | X74: =IF(OR(E74="Deliberation",ISNUMBER(SEARCH("; Deliberation; ","; "&F74&"; "))),1,0) -> 0 | Y74: =SUM(Z74:AE74) -> 3 | Z74: =IF(ISNUMBER(SEARCH("; domain correction; ","; "&H74&"; ")),1,0) -> 0 | AA74: =IF(ISNUMBER(SEARCH("; conceptual discrimination; ","; "&H74&"; ")),1,0) -> 0 | AB74: =IF(ISNUMBER(SEARCH("; evidence judgment; ","; "&H74&"; ")),1,0) -> 1 | AC74: =IF(ISNUMBER(SEARCH("; methodological judgment; ","; "&H74&"; ")),1,0) -> 0 | AD74: =IF(ISNUMBER(SEARCH("; argumentative judgment; ","; "&H74&"; ")),1,0) -> 1 | AE74: =IF(ISNUMBER(SEARCH("; genre/writing expertise; ","; "&H74&"; ")),1,0) -> 1 | AF74: =IF(ISNUMBER(SEARCH("; none; ","; "&H74&"; ")),1,0) -> 0
A75: HE-074 | B75: 74 | C75: Diagnosis, model and reforms | D75: I think we have not said that changing and improving knowledge of existing and established faculty members are not important, is not easy, and most of these suggestions should be considered for training of new faculty members and young, uh, assistant professors. And, really, separate project and effort and paper can be spent on each of the above, um, factors in six point three. give me 1-2 parags to add to end of 6.3 | E75: Knowledge injection | F75: Redirection; Directed delegation | G75: Directive | H75: domain correction; conceptual discrimination; argumentative judgment | I75: Distinguishes reform prospects for established staff from new hires. | J75: AI adds differentiated recommendations. | K75: DOCX body elements 3719–3719 | L75: DOCX body elements 3723–3740 | N75: Visible next AI response | O75: Converted DOCX: textbox continuations joined; AI completion/source-check claims are unverified. | P75: =SUM(Q75:X75) -> 3 | Q75: =IF(OR(E75="Delegation",ISNUMBER(SEARCH("; Delegation; ","; "&F75&"; "))),1,0) -> 0 | R75: =IF(OR(E75="Directed delegation",ISNUMBER(SEARCH("; Directed delegation; ","; "&F75&"; "))),1,0) -> 1 | S75: =IF(OR(E75="Evaluation",ISNUMBER(SEARCH("; Evaluation; ","; "&F75&"; "))),1,0) -> 0 | T75: =IF(OR(E75="Correction/Challenge",ISNUMBER(SEARCH("; Correction/Challenge; ","; "&F75&"; "))),1,0) -> 0 | U75: =IF(OR(E75="Redirection",ISNUMBER(SEARCH("; Redirection; ","; "&F75&"; "))),1,0) -> 1 | V75: =IF(OR(E75="Knowledge injection",ISNUMBER(SEARCH("; Knowledge injection; ","; "&F75&"; "))),1,0) -> 1 | W75: =IF(OR(E75="Selection/Rejection",ISNUMBER(SEARCH("; Selection/Rejection; ","; "&F75&"; "))),1,0) -> 0 | X75: =IF(OR(E75="Deliberation",ISNUMBER(SEARCH("; Deliberation; ","; "&F75&"; "))),1,0) -> 0 | Y75: =SUM(Z75:AE75) -> 3 | Z75: =IF(ISNUMBER(SEARCH("; domain correction; ","; "&H75&"; ")),1,0) -> 1 | AA75: =IF(ISNUMBER(SEARCH("; conceptual discrimination; ","; "&H75&"; ")),1,0) -> 1 | AB75: =IF(ISNUMBER(SEARCH("; evidence judgment; ","; "&H75&"; ")),1,0) -> 0 | AC75: =IF(ISNUMBER(SEARCH("; methodological judgment; ","; "&H75&"; ")),1,0) -> 0 | AD75: =IF(ISNUMBER(SEARCH("; argumentative judgment; ","; "&H75&"; ")),1,0) -> 1 | AE75: =IF(ISNUMBER(SEARCH("; genre/writing expertise; ","; "&H75&"; ")),1,0) -> 0 | AF75: =IF(ISNUMBER(SEARCH("; none; ","; "&H75&"; ")),1,0) -> 0
A76: HE-075 | B76: 75 | C76: Diagnosis, model and reforms | D76: təcrübəli-yeni akademik heyət tandemləri? | E76: Evaluation | G76: Evaluative | H76: genre/writing expertise | I76: Questions the proposed wording for experienced/new-staff tandems. | J76: AI explains and revises the term. | K76: DOCX body elements 3741–3741 | L76: DOCX body elements 3744–3771 | N76: Visible next AI response | O76: Converted DOCX: textbox continuations joined; AI completion/source-check claims are unverified. | P76: =SUM(Q76:X76) -> 1 | Q76: =IF(OR(E76="Delegation",ISNUMBER(SEARCH("; Delegation; ","; "&F76&"; "))),1,0) -> 0 | R76: =IF(OR(E76="Directed delegation",ISNUMBER(SEARCH("; Directed delegation; ","; "&F76&"; "))),1,0) -> 0 | S76: =IF(OR(E76="Evaluation",ISNUMBER(SEARCH("; Evaluation; ","; "&F76&"; "))),1,0) -> 1 | T76: =IF(OR(E76="Correction/Challenge",ISNUMBER(SEARCH("; Correction/Challenge; ","; "&F76&"; "))),1,0) -> 0 | U76: =IF(OR(E76="Redirection",ISNUMBER(SEARCH("; Redirection; ","; "&F76&"; "))),1,0) -> 0 | V76: =IF(OR(E76="Knowledge injection",ISNUMBER(SEARCH("; Knowledge injection; ","; "&F76&"; "))),1,0) -> 0 | W76: =IF(OR(E76="Selection/Rejection",ISNUMBER(SEARCH("; Selection/Rejection; ","; "&F76&"; "))),1,0) -> 0 | X76: =IF(OR(E76="Deliberation",ISNUMBER(SEARCH("; Deliberation; ","; "&F76&"; "))),1,0) -> 0 | Y76: =SUM(Z76:AE76) -> 1 | Z76: =IF(ISNUMBER(SEARCH("; domain correction; ","; "&H76&"; ")),1,0) -> 0 | AA76: =IF(ISNUMBER(SEARCH("; conceptual discrimination; ","; "&H76&"; ")),1,0) -> 0 | AB76: =IF(ISNUMBER(SEARCH("; evidence judgment; ","; "&H76&"; ")),1,0) -> 0 | AC76: =IF(ISNUMBER(SEARCH("; methodological judgment; ","; "&H76&"; ")),1,0) -> 0 | AD76: =IF(ISNUMBER(SEARCH("; argumentative judgment; ","; "&H76&"; ")),1,0) -> 0 | AE76: =IF(ISNUMBER(SEARCH("; genre/writing expertise; ","; "&H76&"; ")),1,0) -> 1 | AF76: =IF(ISNUMBER(SEARCH("; none; ","; "&H76&"; ")),1,0) -> 0
A77: HE-076 | B77: 76 | C77: Diagnosis, model and reforms | D77: using my hints below (if any), give text of: 6.4 Tələbə Amillərinin Təhlili və İslahatı Give pragmatic improvement suggestions for: Ümumi təhsildən gələn Bilik, Bacarıq hazırlıq səviyyəsi (a separate study / paper shall be done on Ümumi təhsild quality QA. We focused on AZ high ed in this paper) Motivasiya / həvəs səviyyəsi— daxili (Sinek "Niyə?") Motivasiya / həvəs səviyyəsi xarici (gələcək karyera, maaş) Ailəsinin … | E77: Directed delegation | F77: Knowledge injection | G77: Directive | H77: conceptual discrimination; argumentative judgment; genre/writing expertise | I77: Supplies student, mediating-factor and outcome reform ideas with drafting constraints. | J77: AI drafts the proposed reform subsections. | K77: DOCX body elements 3773–3776 | L77: DOCX body elements 3782–3831 | M77: URL(s) supplied in prompt; Extended draft/quoted context; researcher-origin judgment distinguished in rationale | N77: Visible next AI response | O77: Converted DOCX: textbox continuations joined; AI completion/source-check claims are unverified. | P77: =SUM(Q77:X77) -> 2 | Q77: =IF(OR(E77="Delegation",ISNUMBER(SEARCH("; Delegation; ","; "&F77&"; "))),1,0) -> 0 | R77: =IF(OR(E77="Directed delegation",ISNUMBER(SEARCH("; Directed delegation; ","; "&F77&"; "))),1,0) -> 1 | S77: =IF(OR(E77="Evaluation",ISNUMBER(SEARCH("; Evaluation; ","; "&F77&"; "))),1,0) -> 0 | T77: =IF(OR(E77="Correction/Challenge",ISNUMBER(SEARCH("; Correction/Challenge; ","; "&F77&"; "))),1,0) -> 0 | U77: =IF(OR(E77="Redirection",ISNUMBER(SEARCH("; Redirection; ","; "&F77&"; "))),1,0) -> 0 | V77: =IF(OR(E77="Knowledge injection",ISNUMBER(SEARCH("; Knowledge injection; ","; "&F77&"; "))),1,0) -> 1 | W77: =IF(OR(E77="Selection/Rejection",ISNUMBER(SEARCH("; Selection/Rejection; ","; "&F77&"; "))),1,0) -> 0 | X77: =IF(OR(E77="Deliberation",ISNUMBER(SEARCH("; Deliberation; ","; "&F77&"; "))),1,0) -> 0 | Y77: =SUM(Z77:AE77) -> 3 | Z77: =IF(ISNUMBER(SEARCH("; domain correction; ","; "&H77&"; ")),1,0) -> 0 | AA77: =IF(ISNUMBER(SEARCH("; conceptual discrimination; ","; "&H77&"; ")),1,0) -> 1 | AB77: =IF(ISNUMBER(SEARCH("; evidence judgment; ","; "&H77&"; ")),1,0) -> 0 | AC77: =IF(ISNUMBER(SEARCH("; methodological judgment; ","; "&H77&"; ")),1,0) -> 0 | AD77: =IF(ISNUMBER(SEARCH("; argumentative judgment; ","; "&H77&"; ")),1,0) -> 1 | AE77: =IF(ISNUMBER(SEARCH("; genre/writing expertise; ","; "&H77&"; ")),1,0) -> 1 | AF77: =IF(ISNUMBER(SEARCH("; none; ","; "&H77&"; ")),1,0) -> 0
A78: HE-077 | B78: 77 | C78: Diagnosis, model and reforms | D78: as paper title İ have: Azərbaycanın Ali Təhsil Sisteminin Sistemli İslahat və İnkişafı üçün Birinci Addım: Sistem Keyfiyyətinin Praqmatik və Diaqnostik Təhliligive me better suggestions | E78: Evaluation | F78: Directed delegation; Knowledge injection | G78: Evaluative | H78: genre/writing expertise | I78: Supplies the current title and requests alternatives. | J78: AI proposes revised titles. | K78: DOCX body elements 3832–3832 | L78: DOCX body elements 3835–3864 | N78: Visible next AI response | O78: Converted DOCX: textbox continuations joined; AI completion/source-check claims are unverified. | P78: =SUM(Q78:X78) -> 3 | Q78: =IF(OR(E78="Delegation",ISNUMBER(SEARCH("; Delegation; ","; "&F78&"; "))),1,0) -> 0 | R78: =IF(OR(E78="Directed delegation",ISNUMBER(SEARCH("; Directed delegation; ","; "&F78&"; "))),1,0) -> 1 | S78: =IF(OR(E78="Evaluation",ISNUMBER(SEARCH("; Evaluation; ","; "&F78&"; "))),1,0) -> 1 | T78: =IF(OR(E78="Correction/Challenge",ISNUMBER(SEARCH("; Correction/Challenge; ","; "&F78&"; "))),1,0) -> 0 | U78: =IF(OR(E78="Redirection",ISNUMBER(SEARCH("; Redirection; ","; "&F78&"; "))),1,0) -> 0 | V78: =IF(OR(E78="Knowledge injection",ISNUMBER(SEARCH("; Knowledge injection; ","; "&F78&"; "))),1,0) -> 1 | W78: =IF(OR(E78="Selection/Rejection",ISNUMBER(SEARCH("; Selection/Rejection; ","; "&F78&"; "))),1,0) -> 0 | X78: =IF(OR(E78="Deliberation",ISNUMBER(SEARCH("; Deliberation; ","; "&F78&"; "))),1,0) -> 0 | Y78: =SUM(Z78:AE78) -> 1 | Z78: =IF(ISNUMBER(SEARCH("; domain correction; ","; "&H78&"; ")),1,0) -> 0 | AA78: =IF(ISNUMBER(SEARCH("; conceptual discrimination; ","; "&H78&"; ")),1,0) -> 0 | AB78: =IF(ISNUMBER(SEARCH("; evidence judgment; ","; "&H78&"; ")),1,0) -> 0 | AC78: =IF(ISNUMBER(SEARCH("; methodological judgment; ","; "&H78&"; ")),1,0) -> 0 | AD78: =IF(ISNUMBER(SEARCH("; argumentative judgment; ","; "&H78&"; ")),1,0) -> 0 | AE78: =IF(ISNUMBER(SEARCH("; genre/writing expertise; ","; "&H78&"; ")),1,0) -> 1 | AF78: =IF(ISNUMBER(SEARCH("; none; ","; "&H78&"; ")),1,0) -> 0
A79: HE-078 | B79: 78 | C79: Diagnosis, model and reforms | D79: Praqmatik və Diaqnostik Bir Model və Təhlil? | E79: Knowledge injection | F79: Evaluation | G79: Evaluative | H79: genre/writing expertise | I79: Proposes a title emphasizing model and analysis. | J79: AI assesses and refines the title. | K79: DOCX body elements 3865–3865 | L79: DOCX body elements 3868–3895 | N79: Visible next AI response | O79: Converted DOCX: textbox continuations joined; AI completion/source-check claims are unverified. | P79: =SUM(Q79:X79) -> 2 | Q79: =IF(OR(E79="Delegation",ISNUMBER(SEARCH("; Delegation; ","; "&F79&"; "))),1,0) -> 0 | R79: =IF(OR(E79="Directed delegation",ISNUMBER(SEARCH("; Directed delegation; ","; "&F79&"; "))),1,0) -> 0 | S79: =IF(OR(E79="Evaluation",ISNUMBER(SEARCH("; Evaluation; ","; "&F79&"; "))),1,0) -> 1 | T79: =IF(OR(E79="Correction/Challenge",ISNUMBER(SEARCH("; Correction/Challenge; ","; "&F79&"; "))),1,0) -> 0 | U79: =IF(OR(E79="Redirection",ISNUMBER(SEARCH("; Redirection; ","; "&F79&"; "))),1,0) -> 0 | V79: =IF(OR(E79="Knowledge injection",ISNUMBER(SEARCH("; Knowledge injection; ","; "&F79&"; "))),1,0) -> 1 | W79: =IF(OR(E79="Selection/Rejection",ISNUMBER(SEARCH("; Selection/Rejection; ","; "&F79&"; "))),1,0) -> 0 | X79: =IF(OR(E79="Deliberation",ISNUMBER(SEARCH("; Deliberation; ","; "&F79&"; "))),1,0) -> 0 | Y79: =SUM(Z79:AE79) -> 1 | Z79: =IF(ISNUMBER(SEARCH("; domain correction; ","; "&H79&"; ")),1,0) -> 0 | AA79: =IF(ISNUMBER(SEARCH("; conceptual discrimination; ","; "&H79&"; ")),1,0) -> 0 | AB79: =IF(ISNUMBER(SEARCH("; evidence judgment; ","; "&H79&"; ")),1,0) -> 0 | AC79: =IF(ISNUMBER(SEARCH("; methodological judgment; ","; "&H79&"; ")),1,0) -> 0 | AD79: =IF(ISNUMBER(SEARCH("; argumentative judgment; ","; "&H79&"; ")),1,0) -> 0 | AE79: =IF(ISNUMBER(SEARCH("; genre/writing expertise; ","; "&H79&"; ")),1,0) -> 1 | AF79: =IF(ISNUMBER(SEARCH("; none; ","; "&H79&"; ")),1,0) -> 0
A80: HE-079 | B80: 79 | C80: Diagnosis, model and reforms | D80: but "Keyfiyyət" is not there | E80: Correction/Challenge | G80: Critical | H80: genre/writing expertise | I80: Detects omission of educational quality from the title. | J80: AI restores the quality focus. | K80: DOCX body elements 3898–3898 | L80: DOCX body elements 3902–3924 | N80: Visible next AI response | O80: Converted DOCX: textbox continuations joined; AI completion/source-check claims are unverified. | P80: =SUM(Q80:X80) -> 1 | Q80: =IF(OR(E80="Delegation",ISNUMBER(SEARCH("; Delegation; ","; "&F80&"; "))),1,0) -> 0 | R80: =IF(OR(E80="Directed delegation",ISNUMBER(SEARCH("; Directed delegation; ","; "&F80&"; "))),1,0) -> 0 | S80: =IF(OR(E80="Evaluation",ISNUMBER(SEARCH("; Evaluation; ","; "&F80&"; "))),1,0) -> 0 | T80: =IF(OR(E80="Correction/Challenge",ISNUMBER(SEARCH("; Correction/Challenge; ","; "&F80&"; "))),1,0) -> 1 | U80: =IF(OR(E80="Redirection",ISNUMBER(SEARCH("; Redirection; ","; "&F80&"; "))),1,0) -> 0 | V80: =IF(OR(E80="Knowledge injection",ISNUMBER(SEARCH("; Knowledge injection; ","; "&F80&"; "))),1,0) -> 0 | W80: =IF(OR(E80="Selection/Rejection",ISNUMBER(SEARCH("; Selection/Rejection; ","; "&F80&"; "))),1,0) -> 0 | X80: =IF(OR(E80="Deliberation",ISNUMBER(SEARCH("; Deliberation; ","; "&F80&"; "))),1,0) -> 0 | Y80: =SUM(Z80:AE80) -> 1 | Z80: =IF(ISNUMBER(SEARCH("; domain correction; ","; "&H80&"; ")),1,0) -> 0 | AA80: =IF(ISNUMBER(SEARCH("; conceptual discrimination; ","; "&H80&"; ")),1,0) -> 0 | AB80: =IF(ISNUMBER(SEARCH("; evidence judgment; ","; "&H80&"; ")),1,0) -> 0 | AC80: =IF(ISNUMBER(SEARCH("; methodological judgment; ","; "&H80&"; ")),1,0) -> 0 | AD80: =IF(ISNUMBER(SEARCH("; argumentative judgment; ","; "&H80&"; ")),1,0) -> 0 | AE80: =IF(ISNUMBER(SEARCH("; genre/writing expertise; ","; "&H80&"; ")),1,0) -> 1 | AF80: =IF(ISNUMBER(SEARCH("; none; ","; "&H80&"; ")),1,0) -> 0
A81: HE-080 | B81: 80 | C81: Diagnosis, model and reforms | D81: rephrase | E81: Directed delegation | G81: Directive | H81: none | I81: Requests rephrasing without specifying a substantive criterion. | J81: AI supplies alternatives. | K81: DOCX body elements 3927–3927 | L81: DOCX body elements 3931–3948 | N81: Visible next AI response | O81: Converted DOCX: textbox continuations joined; AI completion/source-check claims are unverified. | P81: =SUM(Q81:X81) -> 1 | Q81: =IF(OR(E81="Delegation",ISNUMBER(SEARCH("; Delegation; ","; "&F81&"; "))),1,0) -> 0 | R81: =IF(OR(E81="Directed delegation",ISNUMBER(SEARCH("; Directed delegation; ","; "&F81&"; "))),1,0) -> 1 | S81: =IF(OR(E81="Evaluation",ISNUMBER(SEARCH("; Evaluation; ","; "&F81&"; "))),1,0) -> 0 | T81: =IF(OR(E81="Correction/Challenge",ISNUMBER(SEARCH("; Correction/Challenge; ","; "&F81&"; "))),1,0) -> 0 | U81: =IF(OR(E81="Redirection",ISNUMBER(SEARCH("; Redirection; ","; "&F81&"; "))),1,0) -> 0 | V81: =IF(OR(E81="Knowledge injection",ISNUMBER(SEARCH("; Knowledge injection; ","; "&F81&"; "))),1,0) -> 0 | W81: =IF(OR(E81="Selection/Rejection",ISNUMBER(SEARCH("; Selection/Rejection; ","; "&F81&"; "))),1,0) -> 0 | X81: =IF(OR(E81="Deliberation",ISNUMBER(SEARCH("; Deliberation; ","; "&F81&"; "))),1,0) -> 0 | Y81: =SUM(Z81:AE81) -> 0 | Z81: =IF(ISNUMBER(SEARCH("; domain correction; ","; "&H81&"; ")),1,0) -> 0 | AA81: =IF(ISNUMBER(SEARCH("; conceptual discrimination; ","; "&H81&"; ")),1,0) -> 0 | AB81: =IF(ISNUMBER(SEARCH("; evidence judgment; ","; "&H81&"; ")),1,0) -> 0 | AC81: =IF(ISNUMBER(SEARCH("; methodological judgment; ","; "&H81&"; ")),1,0) -> 0 | AD81: =IF(ISNUMBER(SEARCH("; argumentative judgment; ","; "&H81&"; ")),1,0) -> 0 | AE81: =IF(ISNUMBER(SEARCH("; genre/writing expertise; ","; "&H81&"; ")),1,0) -> 0 | AF81: =IF(ISNUMBER(SEARCH("; none; ","; "&H81&"; ")),1,0) -> 1
A82: HE-081 | B82: 81 | C82: Diagnosis, model and reforms | D82: preparatoriya: AZ vord? | E82: Correction/Challenge | G82: Critical | H82: genre/writing expertise | I82: Questions a calque used for preparatory education. | J82: AI replaces the problematic term. | K82: DOCX body elements 3949–3949 | L82: DOCX body elements 3952–3971 | N82: Visible next AI response | O82: Converted DOCX: textbox continuations joined; AI completion/source-check claims are unverified. | P82: =SUM(Q82:X82) -> 1 | Q82: =IF(OR(E82="Delegation",ISNUMBER(SEARCH("; Delegation; ","; "&F82&"; "))),1,0) -> 0 | R82: =IF(OR(E82="Directed delegation",ISNUMBER(SEARCH("; Directed delegation; ","; "&F82&"; "))),1,0) -> 0 | S82: =IF(OR(E82="Evaluation",ISNUMBER(SEARCH("; Evaluation; ","; "&F82&"; "))),1,0) -> 0 | T82: =IF(OR(E82="Correction/Challenge",ISNUMBER(SEARCH("; Correction/Challenge; ","; "&F82&"; "))),1,0) -> 1 | U82: =IF(OR(E82="Redirection",ISNUMBER(SEARCH("; Redirection; ","; "&F82&"; "))),1,0) -> 0 | V82: =IF(OR(E82="Knowledge injection",ISNUMBER(SEARCH("; Knowledge injection; ","; "&F82&"; "))),1,0) -> 0 | W82: =IF(OR(E82="Selection/Rejection",ISNUMBER(SEARCH("; Selection/Rejection; ","; "&F82&"; "))),1,0) -> 0 | X82: =IF(OR(E82="Deliberation",ISNUMBER(SEARCH("; Deliberation; ","; "&F82&"; "))),1,0) -> 0 | Y82: =SUM(Z82:AE82) -> 1 | Z82: =IF(ISNUMBER(SEARCH("; domain correction; ","; "&H82&"; ")),1,0) -> 0 | AA82: =IF(ISNUMBER(SEARCH("; conceptual discrimination; ","; "&H82&"; ")),1,0) -> 0 | AB82: =IF(ISNUMBER(SEARCH("; evidence judgment; ","; "&H82&"; ")),1,0) -> 0 | AC82: =IF(ISNUMBER(SEARCH("; methodological judgment; ","; "&H82&"; ")),1,0) -> 0 | AD82: =IF(ISNUMBER(SEARCH("; argumentative judgment; ","; "&H82&"; ")),1,0) -> 0 | AE82: =IF(ISNUMBER(SEARCH("; genre/writing expertise; ","; "&H82&"; ")),1,0) -> 1 | AF82: =IF(ISNUMBER(SEARCH("; none; ","; "&H82&"; ")),1,0) -> 0
A83: HE-082 | B83: 82 | C83: Diagnosis, model and reforms | D83: using my hints below (if any), give text of: 7 NƏTİCƏ: PRAQMATİK YANAŞMA VƏ İRƏLİYƏ DOĞRU YOL We do not indent to provide a details Yol Xəritəsi, since if that work is to be done, it shall be done jointly with MOSE and other stakeholders. A centralized, controlled and pragmatic roadmap on eadch of the suggestiosn in sec 6 is encouraged 7.1 Yekun Mülahizə Azərbaycanın ali təhsil sistemində əsas çatışmazlıq təkcə maliy… | E83: Directed delegation | F83: Knowledge injection; Redirection | G83: Directive | H83: argumentative judgment; genre/writing expertise | I83: Directs a conclusion emphasizing collaboration without repeating the full roadmap. | J83: AI drafts the conclusion. | K83: DOCX body elements 3972–3974 | L83: DOCX body elements 3977–4006 | M83: Extended draft/quoted context; researcher-origin judgment distinguished in rationale | N83: Visible next AI response | O83: Converted DOCX: textbox continuations joined; AI completion/source-check claims are unverified. | P83: =SUM(Q83:X83) -> 3 | Q83: =IF(OR(E83="Delegation",ISNUMBER(SEARCH("; Delegation; ","; "&F83&"; "))),1,0) -> 0 | R83: =IF(OR(E83="Directed delegation",ISNUMBER(SEARCH("; Directed delegation; ","; "&F83&"; "))),1,0) -> 1 | S83: =IF(OR(E83="Evaluation",ISNUMBER(SEARCH("; Evaluation; ","; "&F83&"; "))),1,0) -> 0 | T83: =IF(OR(E83="Correction/Challenge",ISNUMBER(SEARCH("; Correction/Challenge; ","; "&F83&"; "))),1,0) -> 0 | U83: =IF(OR(E83="Redirection",ISNUMBER(SEARCH("; Redirection; ","; "&F83&"; "))),1,0) -> 1 | V83: =IF(OR(E83="Knowledge injection",ISNUMBER(SEARCH("; Knowledge injection; ","; "&F83&"; "))),1,0) -> 1 | W83: =IF(OR(E83="Selection/Rejection",ISNUMBER(SEARCH("; Selection/Rejection; ","; "&F83&"; "))),1,0) -> 0 | X83: =IF(OR(E83="Deliberation",ISNUMBER(SEARCH("; Deliberation; ","; "&F83&"; "))),1,0) -> 0 | Y83: =SUM(Z83:AE83) -> 2 | Z83: =IF(ISNUMBER(SEARCH("; domain correction; ","; "&H83&"; ")),1,0) -> 0 | AA83: =IF(ISNUMBER(SEARCH("; conceptual discrimination; ","; "&H83&"; ")),1,0) -> 0 | AB83: =IF(ISNUMBER(SEARCH("; evidence judgment; ","; "&H83&"; ")),1,0) -> 0 | AC83: =IF(ISNUMBER(SEARCH("; methodological judgment; ","; "&H83&"; ")),1,0) -> 0 | AD83: =IF(ISNUMBER(SEARCH("; argumentative judgment; ","; "&H83&"; ")),1,0) -> 1 | AE83: =IF(ISNUMBER(SEARCH("; genre/writing expertise; ","; "&H83&"; ")),1,0) -> 1 | AF83: =IF(ISNUMBER(SEARCH("; none; ","; "&H83&"; ")),1,0) -> 0
A84: HE-083 | B84: 83 | C84: Review and submission preparation | D84: proof: Təşəkkürlər Muellim 2022 ilden etibran vetenimiz Azerbaycan ile uzaq da da yasasa da, activ isbirilig edib. Bütöv deyerli hemkarlar ve meslekdaslar ki bu meqalede yazılan mövzularda muellim ki muzakire ve fikir mubadiklesi edibler, tesekkur edir. | E84: Directed delegation | F84: Knowledge injection | G84: Directive | H84: none | I84: Supplies an acknowledgments draft for proofreading. | J84: AI edits the acknowledgments. | K84: DOCX body elements 4007–4007 | L84: DOCX body elements 4010–4032 | N84: Visible next AI response | O84: Converted DOCX: textbox continuations joined; AI completion/source-check claims are unverified. | P84: =SUM(Q84:X84) -> 2 | Q84: =IF(OR(E84="Delegation",ISNUMBER(SEARCH("; Delegation; ","; "&F84&"; "))),1,0) -> 0 | R84: =IF(OR(E84="Directed delegation",ISNUMBER(SEARCH("; Directed delegation; ","; "&F84&"; "))),1,0) -> 1 | S84: =IF(OR(E84="Evaluation",ISNUMBER(SEARCH("; Evaluation; ","; "&F84&"; "))),1,0) -> 0 | T84: =IF(OR(E84="Correction/Challenge",ISNUMBER(SEARCH("; Correction/Challenge; ","; "&F84&"; "))),1,0) -> 0 | U84: =IF(OR(E84="Redirection",ISNUMBER(SEARCH("; Redirection; ","; "&F84&"; "))),1,0) -> 0 | V84: =IF(OR(E84="Knowledge injection",ISNUMBER(SEARCH("; Knowledge injection; ","; "&F84&"; "))),1,0) -> 1 | W84: =IF(OR(E84="Selection/Rejection",ISNUMBER(SEARCH("; Selection/Rejection; ","; "&F84&"; "))),1,0) -> 0 | X84: =IF(OR(E84="Deliberation",ISNUMBER(SEARCH("; Deliberation; ","; "&F84&"; "))),1,0) -> 0 | Y84: =SUM(Z84:AE84) -> 0 | Z84: =IF(ISNUMBER(SEARCH("; domain correction; ","; "&H84&"; ")),1,0) -> 0 | AA84: =IF(ISNUMBER(SEARCH("; conceptual discrimination; ","; "&H84&"; ")),1,0) -> 0 | AB84: =IF(ISNUMBER(SEARCH("; evidence judgment; ","; "&H84&"; ")),1,0) -> 0 | AC84: =IF(ISNUMBER(SEARCH("; methodological judgment; ","; "&H84&"; ")),1,0) -> 0 | AD84: =IF(ISNUMBER(SEARCH("; argumentative judgment; ","; "&H84&"; ")),1,0) -> 0 | AE84: =IF(ISNUMBER(SEARCH("; genre/writing expertise; ","; "&H84&"; ")),1,0) -> 0 | AF84: =IF(ISNUMBER(SEARCH("; none; ","; "&H84&"; ")),1,0) -> 1
A85: HE-084 | B85: 84 | C85: Review and submission preparation | D85: expand 2 fold | E85: Directed delegation | G85: Directive | H85: genre/writing expertise | I85: Requests a twofold expansion without identifying the passage in the short prompt. | J85: AI expands the conclusion; the preceding acknowledgments context makes the target ambiguous. | K85: DOCX body elements 4037–4037 | L85: DOCX body elements 4040–4058 | N85: Visible next AI response | O85: Converted DOCX: textbox continuations joined; AI completion/source-check claims are unverified. Interpret response/intent in context; see rationale and notes. | P85: =SUM(Q85:X85) -> 1 | Q85: =IF(OR(E85="Delegation",ISNUMBER(SEARCH("; Delegation; ","; "&F85&"; "))),1,0) -> 0 | R85: =IF(OR(E85="Directed delegation",ISNUMBER(SEARCH("; Directed delegation; ","; "&F85&"; "))),1,0) -> 1 | S85: =IF(OR(E85="Evaluation",ISNUMBER(SEARCH("; Evaluation; ","; "&F85&"; "))),1,0) -> 0 | T85: =IF(OR(E85="Correction/Challenge",ISNUMBER(SEARCH("; Correction/Challenge; ","; "&F85&"; "))),1,0) -> 0 | U85: =IF(OR(E85="Redirection",ISNUMBER(SEARCH("; Redirection; ","; "&F85&"; "))),1,0) -> 0 | V85: =IF(OR(E85="Knowledge injection",ISNUMBER(SEARCH("; Knowledge injection; ","; "&F85&"; "))),1,0) -> 0 | W85: =IF(OR(E85="Selection/Rejection",ISNUMBER(SEARCH("; Selection/Rejection; ","; "&F85&"; "))),1,0) -> 0 | X85: =IF(OR(E85="Deliberation",ISNUMBER(SEARCH("; Deliberation; ","; "&F85&"; "))),1,0) -> 0 | Y85: =SUM(Z85:AE85) -> 1 | Z85: =IF(ISNUMBER(SEARCH("; domain correction; ","; "&H85&"; ")),1,0) -> 0 | AA85: =IF(ISNUMBER(SEARCH("; conceptual discrimination; ","; "&H85&"; ")),1,0) -> 0 | AB85: =IF(ISNUMBER(SEARCH("; evidence judgment; ","; "&H85&"; ")),1,0) -> 0 | AC85: =IF(ISNUMBER(SEARCH("; methodological judgment; ","; "&H85&"; ")),1,0) -> 0 | AD85: =IF(ISNUMBER(SEARCH("; argumentative judgment; ","; "&H85&"; ")),1,0) -> 0 | AE85: =IF(ISNUMBER(SEARCH("; genre/writing expertise; ","; "&H85&"; ")),1,0) -> 1 | AF85: =IF(ISNUMBER(SEARCH("; none; ","; "&H85&"; ")),1,0) -> 0
A86: HE-085 | B86: 85 | C86: Review and submission preparation | D86: Review the draft paper. I need an abstract and keyword from you. And, also, uh, titled in English and also abstracting keyword in English as well. | E86: Evaluation | F86: Directed delegation | G86: Evaluative | H86: genre/writing expertise | I86: Requests manuscript review, abstract, keywords and bilingual title work. | J86: AI reviews and drafts the requested front matter. | K86: DOCX body elements 4061–4061 | L86: DOCX body elements 4066–4095 | N86: Visible next AI response | O86: Converted DOCX: textbox continuations joined; AI completion/source-check claims are unverified. | P86: =SUM(Q86:X86) -> 2 | Q86: =IF(OR(E86="Delegation",ISNUMBER(SEARCH("; Delegation; ","; "&F86&"; "))),1,0) -> 0 | R86: =IF(OR(E86="Directed delegation",ISNUMBER(SEARCH("; Directed delegation; ","; "&F86&"; "))),1,0) -> 1 | S86: =IF(OR(E86="Evaluation",ISNUMBER(SEARCH("; Evaluation; ","; "&F86&"; "))),1,0) -> 1 | T86: =IF(OR(E86="Correction/Challenge",ISNUMBER(SEARCH("; Correction/Challenge; ","; "&F86&"; "))),1,0) -> 0 | U86: =IF(OR(E86="Redirection",ISNUMBER(SEARCH("; Redirection; ","; "&F86&"; "))),1,0) -> 0 | V86: =IF(OR(E86="Knowledge injection",ISNUMBER(SEARCH("; Knowledge injection; ","; "&F86&"; "))),1,0) -> 0 | W86: =IF(OR(E86="Selection/Rejection",ISNUMBER(SEARCH("; Selection/Rejection; ","; "&F86&"; "))),1,0) -> 0 | X86: =IF(OR(E86="Deliberation",ISNUMBER(SEARCH("; Deliberation; ","; "&F86&"; "))),1,0) -> 0 | Y86: =SUM(Z86:AE86) -> 1 | Z86: =IF(ISNUMBER(SEARCH("; domain correction; ","; "&H86&"; ")),1,0) -> 0 | AA86: =IF(ISNUMBER(SEARCH("; conceptual discrimination; ","; "&H86&"; ")),1,0) -> 0 | AB86: =IF(ISNUMBER(SEARCH("; evidence judgment; ","; "&H86&"; ")),1,0) -> 0 | AC86: =IF(ISNUMBER(SEARCH("; methodological judgment; ","; "&H86&"; ")),1,0) -> 0 | AD86: =IF(ISNUMBER(SEARCH("; argumentative judgment; ","; "&H86&"; ")),1,0) -> 0 | AE86: =IF(ISNUMBER(SEARCH("; genre/writing expertise; ","; "&H86&"; ")),1,0) -> 1 | AF86: =IF(ISNUMBER(SEARCH("; none; ","; "&H86&"; ")),1,0) -> 0
A87: HE-086 | B87: 86 | C87: Review and submission preparation | D87: remove all old versions of this paper that you have in your memory. and then review this latest version. provide feedback for improvement . if there are problems tell me exactly where and how i should change it | E87: Correction/Challenge | F87: Directed delegation | G87: Critical | H87: evidence judgment; genre/writing expertise | I87: Requires use of only the latest version and precise, actionable review. | J87: AI gives a detailed review and specific changes. | K87: DOCX body elements 4100–4100 | L87: DOCX body elements 4105–4188 | N87: Visible next AI response | O87: Converted DOCX: textbox continuations joined; AI completion/source-check claims are unverified. | P87: =SUM(Q87:X87) -> 2 | Q87: =IF(OR(E87="Delegation",ISNUMBER(SEARCH("; Delegation; ","; "&F87&"; "))),1,0) -> 0 | R87: =IF(OR(E87="Directed delegation",ISNUMBER(SEARCH("; Directed delegation; ","; "&F87&"; "))),1,0) -> 1 | S87: =IF(OR(E87="Evaluation",ISNUMBER(SEARCH("; Evaluation; ","; "&F87&"; "))),1,0) -> 0 | T87: =IF(OR(E87="Correction/Challenge",ISNUMBER(SEARCH("; Correction/Challenge; ","; "&F87&"; "))),1,0) -> 1 | U87: =IF(OR(E87="Redirection",ISNUMBER(SEARCH("; Redirection; ","; "&F87&"; "))),1,0) -> 0 | V87: =IF(OR(E87="Knowledge injection",ISNUMBER(SEARCH("; Knowledge injection; ","; "&F87&"; "))),1,0) -> 0 | W87: =IF(OR(E87="Selection/Rejection",ISNUMBER(SEARCH("; Selection/Rejection; ","; "&F87&"; "))),1,0) -> 0 | X87: =IF(OR(E87="Deliberation",ISNUMBER(SEARCH("; Deliberation; ","; "&F87&"; "))),1,0) -> 0 | Y87: =SUM(Z87:AE87) -> 2 | Z87: =IF(ISNUMBER(SEARCH("; domain correction; ","; "&H87&"; ")),1,0) -> 0 | AA87: =IF(ISNUMBER(SEARCH("; conceptual discrimination; ","; "&H87&"; ")),1,0) -> 0 | AB87: =IF(ISNUMBER(SEARCH("; evidence judgment; ","; "&H87&"; ")),1,0) -> 1 | AC87: =IF(ISNUMBER(SEARCH("; methodological judgment; ","; "&H87&"; ")),1,0) -> 0 | AD87: =IF(ISNUMBER(SEARCH("; argumentative judgment; ","; "&H87&"; ")),1,0) -> 0 | AE87: =IF(ISNUMBER(SEARCH("; genre/writing expertise; ","; "&H87&"; ")),1,0) -> 1 | AF87: =IF(ISNUMBER(SEARCH("; none; ","; "&H87&"; ")),1,0) -> 0
A88: HE-087 | B88: 87 | C88: Review and submission preparation | D88: Write a short professional email in az to Arzu Soltan (Baş redaktor) https://www.as-journal.edu.az/editorial-boardsay that I would like to submit this Əlyazma (Manuscript) totheir journal, by the way, that's the sign of submission. They don't have an onlinesystem. | E88: Directed delegation | F88: Knowledge injection | G88: Directive | H88: genre/writing expertise | I88: Sets a short Azerbaijani submission email and provides the intended editor/journal. | J88: AI drafts the email; no sending is recorded. | K88: DOCX body elements 4189–4189 | L88: DOCX body elements 4193–4212 | M88: URL(s) supplied in prompt | N88: Visible next AI response | O88: Converted DOCX: textbox continuations joined; AI completion/source-check claims are unverified. | P88: =SUM(Q88:X88) -> 2 | Q88: =IF(OR(E88="Delegation",ISNUMBER(SEARCH("; Delegation; ","; "&F88&"; "))),1,0) -> 0 | R88: =IF(OR(E88="Directed delegation",ISNUMBER(SEARCH("; Directed delegation; ","; "&F88&"; "))),1,0) -> 1 | S88: =IF(OR(E88="Evaluation",ISNUMBER(SEARCH("; Evaluation; ","; "&F88&"; "))),1,0) -> 0 | T88: =IF(OR(E88="Correction/Challenge",ISNUMBER(SEARCH("; Correction/Challenge; ","; "&F88&"; "))),1,0) -> 0 | U88: =IF(OR(E88="Redirection",ISNUMBER(SEARCH("; Redirection; ","; "&F88&"; "))),1,0) -> 0 | V88: =IF(OR(E88="Knowledge injection",ISNUMBER(SEARCH("; Knowledge injection; ","; "&F88&"; "))),1,0) -> 1 | W88: =IF(OR(E88="Selection/Rejection",ISNUMBER(SEARCH("; Selection/Rejection; ","; "&F88&"; "))),1,0) -> 0 | X88: =IF(OR(E88="Deliberation",ISNUMBER(SEARCH("; Deliberation; ","; "&F88&"; "))),1,0) -> 0 | Y88: =SUM(Z88:AE88) -> 1 | Z88: =IF(ISNUMBER(SEARCH("; domain correction; ","; "&H88&"; ")),1,0) -> 0 | AA88: =IF(ISNUMBER(SEARCH("; conceptual discrimination; ","; "&H88&"; ")),1,0) -> 0 | AB88: =IF(ISNUMBER(SEARCH("; evidence judgment; ","; "&H88&"; ")),1,0) -> 0 | AC88: =IF(ISNUMBER(SEARCH("; methodological judgment; ","; "&H88&"; ")),1,0) -> 0 | AD88: =IF(ISNUMBER(SEARCH("; argumentative judgment; ","; "&H88&"; ")),1,0) -> 0 | AE88: =IF(ISNUMBER(SEARCH("; genre/writing expertise; ","; "&H88&"; ")),1,0) -> 1 | AF88: =IF(ISNUMBER(SEARCH("; none; ","; "&H88&"; ")),1,0) -> 0
A89: HE-088 | B89: 88 | C89: Review and submission preparation | D89: Because of the following phrase on their website "Bu sistemdə həm müəlliflərin, həm də rəyçilərin kimliyi anonim saxlanılır", say that I have removed... I have not included my, um, name and affiliation in the first page, but they are in a separate file. also, thank her and the rəyçilərin in advance | E89: Directed delegation | F89: Knowledge injection | G89: Directive | H89: genre/writing expertise | I89: Supplies anonymous-submission rules and requests title-page guidance. | J89: AI explains the required submission materials. | K89: DOCX body elements 4213–4213 | L89: DOCX body elements 4216–4236 | N89: Visible next AI response | O89: Converted DOCX: textbox continuations joined; AI completion/source-check claims are unverified. | P89: =SUM(Q89:X89) -> 2 | Q89: =IF(OR(E89="Delegation",ISNUMBER(SEARCH("; Delegation; ","; "&F89&"; "))),1,0) -> 0 | R89: =IF(OR(E89="Directed delegation",ISNUMBER(SEARCH("; Directed delegation; ","; "&F89&"; "))),1,0) -> 1 | S89: =IF(OR(E89="Evaluation",ISNUMBER(SEARCH("; Evaluation; ","; "&F89&"; "))),1,0) -> 0 | T89: =IF(OR(E89="Correction/Challenge",ISNUMBER(SEARCH("; Correction/Challenge; ","; "&F89&"; "))),1,0) -> 0 | U89: =IF(OR(E89="Redirection",ISNUMBER(SEARCH("; Redirection; ","; "&F89&"; "))),1,0) -> 0 | V89: =IF(OR(E89="Knowledge injection",ISNUMBER(SEARCH("; Knowledge injection; ","; "&F89&"; "))),1,0) -> 1 | W89: =IF(OR(E89="Selection/Rejection",ISNUMBER(SEARCH("; Selection/Rejection; ","; "&F89&"; "))),1,0) -> 0 | X89: =IF(OR(E89="Deliberation",ISNUMBER(SEARCH("; Deliberation; ","; "&F89&"; "))),1,0) -> 0 | Y89: =SUM(Z89:AE89) -> 1 | Z89: =IF(ISNUMBER(SEARCH("; domain correction; ","; "&H89&"; ")),1,0) -> 0 | AA89: =IF(ISNUMBER(SEARCH("; conceptual discrimination; ","; "&H89&"; ")),1,0) -> 0 | AB89: =IF(ISNUMBER(SEARCH("; evidence judgment; ","; "&H89&"; ")),1,0) -> 0 | AC89: =IF(ISNUMBER(SEARCH("; methodological judgment; ","; "&H89&"; ")),1,0) -> 0 | AD89: =IF(ISNUMBER(SEARCH("; argumentative judgment; ","; "&H89&"; ")),1,0) -> 0 | AE89: =IF(ISNUMBER(SEARCH("; genre/writing expertise; ","; "&H89&"; ")),1,0) -> 1 | AF89: =IF(ISNUMBER(SEARCH("; none; ","; "&H89&"; ")),1,0) -> 0
A90: HE-089 | B90: 89 | C90: Review and submission preparation | D90: Əhəmiyyətli dövlət investisiyalarına baxmayaraq, Azərbaycanın ali təhsil sistemi keyfiyyət çatışmazlıqları ilə üzləşir. add after this phrase in the abstract, some examples such as low number of, uh, papers from, uh, top, uh, international journals from AZ researchers, uh, weaknesses of the research, uh, environment, and, uh, relatively lower quality of research profile of many, uh, academic staff. | E90: Knowledge injection | F90: Directed delegation | G90: Directive | H90: argumentative judgment | I90: Proposes adding weak research output to the abstract. | J90: No intervening AI response is visible before the next human prompt. | K90: DOCX body elements 4237–4237 | N90: No intervening AI response visible | O90: Converted DOCX: textbox continuations joined; AI completion/source-check claims are unverified. Interpret response/intent in context; see rationale and notes. | P90: =SUM(Q90:X90) -> 2 | Q90: =IF(OR(E90="Delegation",ISNUMBER(SEARCH("; Delegation; ","; "&F90&"; "))),1,0) -> 0 | R90: =IF(OR(E90="Directed delegation",ISNUMBER(SEARCH("; Directed delegation; ","; "&F90&"; "))),1,0) -> 1 | S90: =IF(OR(E90="Evaluation",ISNUMBER(SEARCH("; Evaluation; ","; "&F90&"; "))),1,0) -> 0 | T90: =IF(OR(E90="Correction/Challenge",ISNUMBER(SEARCH("; Correction/Challenge; ","; "&F90&"; "))),1,0) -> 0 | U90: =IF(OR(E90="Redirection",ISNUMBER(SEARCH("; Redirection; ","; "&F90&"; "))),1,0) -> 0 | V90: =IF(OR(E90="Knowledge injection",ISNUMBER(SEARCH("; Knowledge injection; ","; "&F90&"; "))),1,0) -> 1 | W90: =IF(OR(E90="Selection/Rejection",ISNUMBER(SEARCH("; Selection/Rejection; ","; "&F90&"; "))),1,0) -> 0 | X90: =IF(OR(E90="Deliberation",ISNUMBER(SEARCH("; Deliberation; ","; "&F90&"; "))),1,0) -> 0 | Y90: =SUM(Z90:AE90) -> 1 | Z90: =IF(ISNUMBER(SEARCH("; domain correction; ","; "&H90&"; ")),1,0) -> 0 | AA90: =IF(ISNUMBER(SEARCH("; conceptual discrimination; ","; "&H90&"; ")),1,0) -> 0 | AB90: =IF(ISNUMBER(SEARCH("; evidence judgment; ","; "&H90&"; ")),1,0) -> 0 | AC90: =IF(ISNUMBER(SEARCH("; methodological judgment; ","; "&H90&"; ")),1,0) -> 0 | AD90: =IF(ISNUMBER(SEARCH("; argumentative judgment; ","; "&H90&"; ")),1,0) -> 1 | AE90: =IF(ISNUMBER(SEARCH("; genre/writing expertise; ","; "&H90&"; ")),1,0) -> 0 | AF90: =IF(ISNUMBER(SEARCH("; none; ","; "&H90&"; ")),1,0) -> 0
